Workbook

Sheet README
A1: BSSC Control Library — Recommended Controls
A2: Prepared 2026-10-19 by Blockchain Security Architecture (drafted with Claude). Scope: all organisation profiles — exchange/custodian, protocol/dApp/token issuer, node/validator operator, enterprise baseline.
A4: Source standards (Blockchain Security Standards Council, https://blockchainssc.org/standards/)
A5: NOS — Node Operation Standard, v2 (2026-05-14) — https://specs.blockchainssc.org/nos/
A6: TIS — Token Integration Standard, v1 (2025-05-13) — https://specs.blockchainssc.org/tis/
A7: KMS — Key Management Standard, v1 (2025-05-13) — https://specs.blockchainssc.org/kms/
A8: SCS — Smart Contract Security Standard, v1 (2026-05-14) — https://specs.blockchainssc.org/scs/
A9: GSP — General Security & Privacy Guidelines, v2 (2026-05-14) — https://specs.blockchainssc.org/gsp/
A11: How the library is built
A12: • Comprehensive: one recommended control per normative BSSC requirement (MUST / MUST NOT / SHOULD / SHOULD NOT / MAY), rewritten as an implementable, testable control.
A13: • Verified: requirement anchors for NOS (53), SCS (69) and GSP (56) were cross-checked against the live specs; TIS and KMS were checked heading-by-heading.
A14: • Reference Standard / BSSC Requirement ID: NOS, SCS and GSP use the spec's own req- anchors (Source Link deep-links to them). TIS has only one req- anchor, so other rows cite the spec heading. KMS defines no IDs, so IDs KMS-GEN/KG/KD/KS/KDI/KU/KR/KX-nn were assigned here in document order.
... A31: Disclaimer: this library interprets BSSC standards for implementation planning. It is not an official BSSC conformance assessment; consult the normative specs for audit and compliance claims.

Sheet Summary
A1: BSSC Control Library — Coverage Summary
A2: All counts are live formulas over the 'All Controls' tab; they update as you edit Priority and Implementation Status.
A4: Standard | B4: Name | C4: Version | D4: Critical | E4: High | F4: Medium | G4: Low | H4: Total | I4: Implemented | J4: % Implemented | K4: Not applicable / Risk accepted
A5: NOS | B5: Node Operation Standard | C5: v2 (2026-05-14) | D5: =COUNTIFS('All Controls'!$B$2:$B$326,$A5,'All Controls'!$I$2:$I$326,"Critical") -> 11 | E5: =COUNTIFS('All Controls'!$B$2:$B$326,$A5,'All Controls'!$I$2:$I$326,"High") -> 24 | F5: =COUNTIFS('All Controls'!$B$2:$B$326,$A5,'All Controls'!$I$2:$I$326,"Medium") -> 16 | G5: =COUNTIFS('All Controls'!$B$2:$B$326,$A5,'All Controls'!$I$2:$I$326,"Low") -> 3 | H5: =SUM(D5:G5) -> 54 | I5: =COUNTIFS('All Controls'!$B$2:$B$326,$A5,'All Controls'!$P$2:$P$326,"Implemented") -> 0 | J5: =IF((H5-K5)=0,0,I5/(H5-K5)) -> 0 | K5: =COUNTIFS('All Controls'!$B$2:$B$326,$A5,'All Controls'!$P$2:$P$326,"Not applicable")+COUNTIFS('All Controls'!$B$2:$B$326,$A5,'All Controls'!$P$2:$P$326,"Risk accepted") -> 0
A6: TIS | B6: Token Integration Standard | C6: v1 (2025-05-13) | D6: =COUNTIFS('All Controls'!$B$2:$B$326,$A6,'All Controls'!$I$2:$I$326,"Critical") -> 5 | E6: =COUNTIFS('All Controls'!$B$2:$B$326,$A6,'All Controls'!$I$2:$I$326,"High") -> 20 | F6: =COUNTIFS('All Controls'!$B$2:$B$326,$A6,'All Controls'!$I$2:$I$326,"Medium") -> 18 | G6: =COUNTIFS('All Controls'!$B$2:$B$326,$A6,'All Controls'!$I$2:$I$326,"Low") -> 7 | H6: =SUM(D6:G6) -> 50 | I6: =COUNTIFS('All Controls'!$B$2:$B$326,$A6,'All Controls'!$P$2:$P$326,"Implemented") -> 0 | J6: =IF((H6-K6)=0,0,I6/(H6-K6)) -> 0 | K6: =COUNTIFS('All Controls'!$B$2:$B$326,$A6,'All Controls'!$P$2:$P$326,"Not applicable")+COUNTIFS('All Controls'!$B$2:$B$326,$A6,'All Controls'!$P$2:$P$326,"Risk accepted") -> 0
A7: KMS | B7: Key Management Standard | C7: v1 (2025-05-13) | D7: =COUNTIFS('All Controls'!$B$2:$B$326,$A7,'All Controls'!$I$2:$I$326,"Critical") -> 26 | E7: =COUNTIFS('All Controls'!$B$2:$B$326,$A7,'All Controls'!$I$2:$I$326,"High") -> 48 | F7: =COUNTIFS('All Controls'!$B$2:$B$326,$A7,'All Controls'!$I$2:$I$326,"Medium") -> 19 | G7: =COUNTIFS('All Controls'!$B$2:$B$326,$A7,'All Controls'!$I$2:$I$326,"Low") -> 3 | H7: =SUM(D7:G7) -> 96 | I7: =COUNTIFS('All Controls'!$B$2:$B$326,$A7,'All Controls'!$P$2:$P$326,"Implemented") -> 0 | J7: =IF((H7-K7)=0,0,I7/(H7-K7)) -> 0 | K7: =COUNTIFS('All Controls'!$B$2:$B$326,$A7,'All Controls'!$P$2:$P$326,"Not applicable")+COUNTIFS('All Controls'!$B$2:$B$326,$A7,'All Controls'!$P$2:$P$326,"Risk accepted") -> 0
A8: SCS | B8: Smart Contract Security Standard | C8: v1 (2026-05-14) | D8: =COUNTIFS('All Controls'!$B$2:$B$326,$A8,'All Controls'!$I$2:$I$326,"Critical") -> 10 | E8: =COUNTIFS('All Controls'!$B$2:$B$326,$A8,'All Controls'!$I$2:$I$326,"High") -> 18 | F8: =COUNTIFS('All Controls'!$B$2:$B$326,$A8,'All Controls'!$I$2:$I$326,"Medium") -> 29 | G8: =COUNTIFS('All Controls'!$B$2:$B$326,$A8,'All Controls'!$I$2:$I$326,"Low") -> 12 | H8: =SUM(D8:G8) -> 69 | I8: =COUNTIFS('All Controls'!$B$2:$B$326,$A8,'All Controls'!$P$2:$P$326,"Implemented") -> 0 | J8: =IF((H8-K8)=0,0,I8/(H8-K8)) -> 0 | K8: =COUNTIFS('All Controls'!$B$2:$B$326,$A8,'All Controls'!$P$2:$P$326,"Not applicable")+COUNTIFS('All Controls'!$B$2:$B$326,$A8,'All Controls'!$P$2:$P$326,"Risk accepted") -> 0
A9: GSP | B9: General Security & Privacy Guidelines | C9: v2 (2026-05-14) | D9: =COUNTIFS('All Controls'!$B$2:$B$326,$A9,'All Controls'!$I$2:$I$326,"Critical") -> 3 | E9: =COUNTIFS('All Controls'!$B$2:$B$326,$A9,'All Controls'!$I$2:$I$326,"High") -> 34 | F9: =COUNTIFS('All Controls'!$B$2:$B$326,$A9,'All Controls'!$I$2:$I$326,"Medium") -> 18 | G9: =COUNTIFS('All Controls'!$B$2:$B$326,$A9,'All Controls'!$I$2:$I$326,"Low") -> 1 | H9: =SUM(D9:G9) -> 56 | I9: =COUNTIFS('All Controls'!$B$2:$B$326,$A9,'All Controls'!$P$2:$P$326,"Implemented") -> 0 | J9: =IF((H9-K9)=0,0,I9/(H9-K9)) -> 0 | K9: =COUNTIFS('All Controls'!$B$2:$B$326,$A9,'All Controls'!$P$2:$P$326,"Not applicable")+COUNTIFS('All Controls'!$B$2:$B$326,$A9,'All Controls'!$P$2:$P$326,"Risk accepted") -> 0
A10: Total | D10: =SUM(D5:D9) -> 55 | E10: =SUM(E5:E9) -> 144 | F10: =SUM(F5:F9) -> 100 | G10: =SUM(G5:G9) -> 26 | H10: =SUM(H5:H9) -> 325 | I10: =SUM(I5:I9) -> 0 | J10: =IF((H10-K10)=0,0,I10/(H10-K10)) -> 0 | K10: =SUM(K5:K9) -> 0
A12: By BSSC keyword level
A13: Level | B13: NOS | C13: TIS | D13: KMS | E13: SCS | F13: GSP | G13: Total
A14: MUST | B14: =COUNTIFS('All Controls'!$B$2:$B$326,"NOS",'All Controls'!$H$2:$H$326,$A14) -> 40 | C14: =COUNTIFS('All Controls'!$B$2:$B$326,"TIS",'All Controls'!$H$2:$H$326,$A14) -> 40 | D14: =COUNTIFS('All Controls'!$B$2:$B$326,"KMS",'All Controls'!$H$2:$H$326,$A14) -> 49 | E14: =COUNTIFS('All Controls'!$B$2:$B$326,"SCS",'All Controls'!$H$2:$H$326,$A14) -> 38 | F14: =COUNTIFS('All Controls'!$B$2:$B$326,"GSP",'All Controls'!$H$2:$H$326,$A14) -> 0 | G14: =SUM(B14:F14) -> 167
A15: MUST NOT | B15: =COUNTIFS('All Controls'!$B$2:$B$326,"NOS",'All Controls'!$H$2:$H$326,$A15) -> 0 | C15: =COUNTIFS('All Controls'!$B$2:$B$326,"TIS",'All Controls'!$H$2:$H$326,$A15) -> 2 | D15: =COUNTIFS('All Controls'!$B$2:$B$326,"KMS",'All Controls'!$H$2:$H$326,$A15) -> 1 | E15: =COUNTIFS('All Controls'!$B$2:$B$326,"SCS",'All Controls'!$H$2:$H$326,$A15) -> 0 | F15: =COUNTIFS('All Controls'!$B$2:$B$326,"GSP",'All Controls'!$H$2:$H$326,$A15) -> 0 | G15: =SUM(B15:F15) -> 3
A16: SHOULD | B16: =COUNTIFS('All Controls'!$B$2:$B$326,"NOS",'All Controls'!$H$2:$H$326,$A16) -> 11 | C16: =COUNTIFS('All Controls'!$B$2:$B$326,"TIS",'All Controls'!$H$2:$H$326,$A16) -> 4 | D16: =COUNTIFS('All Controls'!$B$2:$B$326,"KMS",'All Controls'!$H$2:$H$326,$A16) -> 43 | E16: =COUNTIFS('All Controls'!$B$2:$B$326,"SCS",'All Controls'!$H$2:$H$326,$A16) -> 23 | F16: =COUNTIFS('All Controls'!$B$2:$B$326,"GSP",'All Controls'!$H$2:$H$326,$A16) -> 56 | G16: =SUM(B16:F16) -> 137
A17: SHOULD NOT | B17: =COUNTIFS('All Controls'!$B$2:$B$326,"NOS",'All Controls'!$H$2:$H$326,$A17) -> 1 | C17: =COUNTIFS('All Controls'!$B$2:$B$326,"TIS",'All Controls'!$H$2:$H$326,$A17) -> 3 | D17: =COUNTIFS('All Controls'!$B$2:$B$326,"KMS",'All Controls'!$H$2:$H$326,$A17) -> 1 | E17: =COUNTIFS('All Controls'!$B$2:$B$326,"SCS",'All Controls'!$H$2:$H$326,$A17) -> 0 | F17: =COUNTIFS('All Controls'!$B$2:$B$326,"GSP",'All Controls'!$H$2:$H$326,$A17) -> 0 | G17: =SUM(B17:F17) -> 5
A18: MAY | B18: =COUNTIFS('All Controls'!$B$2:$B$326,"NOS",'All Controls'!$H$2:$H$326,$A18) -> 0 | C18: =COUNTIFS('All Controls'!$B$2:$B$326,"TIS",'All Controls'!$H$2:$H$326,$A18) -> 1 | D18: =COUNTIFS('All Controls'!$B$2:$B$326,"KMS",'All Controls'!$H$2:$H$326,$A18) -> 2 | E18: =COUNTIFS('All Controls'!$B$2:$B$326,"SCS",'All Controls'!$H$2:$H$326,$A18) -> 1 | F18: =COUNTIFS('All Controls'!$B$2:$B$326,"GSP",'All Controls'!$H$2:$H$326,$A18) -> 0 | G18: =SUM(B18:F18) -> 4
A19: MUST / SHOULD | B19: =COUNTIFS('All Controls'!$B$2:$B$326,"NOS",'All Controls'!$H$2:$H$326,$A19) -> 1 | C19: =COUNTIFS('All Controls'!$B$2:$B$326,"TIS",'All Controls'!$H$2:$H$326,$A19) -> 0 | D19: =COUNTIFS('All Controls'!$B$2:$B$326,"KMS",'All Controls'!$H$2:$H$326,$A19) -> 0 | E19: =COUNTIFS('All Controls'!$B$2:$B$326,"SCS",'All Controls'!$H$2:$H$326,$A19) -> 0 | F19: =COUNTIFS('All Controls'!$B$2:$B$326,"GSP",'All Controls'!$H$2:$H$326,$A19) -> 0 | G19: =SUM(B19:F19) -> 1
A20: SHOULD / MUST | B20: =COUNTIFS('All Controls'!$B$2:$B$326,"NOS",'All Controls'!$H$2:$H$326,$A20) -> 0 | C20: =COUNTIFS('All Controls'!$B$2:$B$326,"TIS",'All Controls'!$H$2:$H$326,$A20) -> 0 | D20: =COUNTIFS('All Controls'!$B$2:$B$326,"KMS",'All Controls'!$H$2:$H$326,$A20) -> 0 | E20: =COUNTIFS('All Controls'!$B$2:$B$326,"SCS",'All Controls'!$H$2:$H$326,$A20) -> 6 | F20: =COUNTIFS('All Controls'!$B$2:$B$326,"GSP",'All Controls'!$H$2:$H$326,$A20) -> 0 | G20: =SUM(B20:F20) -> 6
A21: SHOULD / MAY | B21: =COUNTIFS('All Controls'!$B$2:$B$326,"NOS",'All Controls'!$H$2:$H$326,$A21) -> 0 | C21: =COUNTIFS('All Controls'!$B$2:$B$326,"TIS",'All Controls'!$H$2:$H$326,$A21) -> 0 | D21: =COUNTIFS('All Controls'!$B$2:$B$326,"KMS",'All Controls'!$H$2:$H$326,$A21) -> 0 | E21: =COUNTIFS('All Controls'!$B$2:$B$326,"SCS",'All Controls'!$H$2:$H$326,$A21) -> 1 | F21: =COUNTIFS('All Controls'!$B$2:$B$326,"GSP",'All Controls'!$H$2:$H$326,$A21) -> 0 | G21: =SUM(B21:F21) -> 1
A22: MUST / MUST NOT | B22: =COUNTIFS('All Controls'!$B$2:$B$326,"NOS",'All Controls'!$H$2:$H$326,$A22) -> 1 | C22: =COUNTIFS('All Controls'!$B$2:$B$326,"TIS",'All Controls'!$H$2:$H$326,$A22) -> 0 | D22: =COUNTIFS('All Controls'!$B$2:$B$326,"KMS",'All Controls'!$H$2:$H$326,$A22) -> 0 | E22: =COUNTIFS('All Controls'!$B$2:$B$326,"SCS",'All Controls'!$H$2:$H$326,$A22) -> 0 | F22: =COUNTIFS('All Controls'!$B$2:$B$326,"GSP",'All Controls'!$H$2:$H$326,$A22) -> 0 | G22: =SUM(B22:F22) -> 1
A23: Total | B23: =SUM(B14:B22) -> 54 | C23: =SUM(C14:C22) -> 50 | D23: =SUM(D14:D22) -> 96 | E23: =SUM(E14:E22) -> 69 | F23: =SUM(F14:F22) -> 56 | G23: =SUM(G14:G22) -> 325
A24: Check: level total equals control total → | G24: =IF(G23=H10,"OK","MISMATCH") -> OK

Sheet All Controls
A1: Control ID | B1: Standard | C1: Domain | D1: Area | E1: Recommended Control | F1: Reference Standard | G1: BSSC Requirement ID | H1: BSSC Level (RFC 2119) | I1: Priority | J1: Applies To | K1: NIST CSF 2.0 | L1: ISO/IEC 27001:2022 | M1: CCSS Aspect (indicative) | N1: Verification Method / Evidence | O1: Source Link | P1: Implementation Status | Q1: Control Owner | R1: Notes
A2: NOS-001 | B2: NOS | C2: 0. Basic Security | D2: Key security | E2: Manage all node, validator, withdrawal and signing keys under the BSSC Key Management Standard (or a documented equivalent); maintain a KMS conformance mapping. | F2: BSSC NOS v2 — 0. Basic Security | G2: req-manage-key-security | H2: MUST | I2: Critical | J2: Node/validator operator; Exchange/Custodian running nodes | K2: PR.AA-01; PR.DS-01 | L2: A.8.24 | M2: 1.01-1.06 | N2: Review KMS conformance matrix; sample key lifecycle records; interview key custodians. | O2: Open spec | P2: Not started
A3: NOS-002 | B3: NOS | C3: 0. Basic Security | D3: Baseline security program | E3: Implement the BSSC General Security & Privacy Guidelines (or ISO 27001 / SOC 2 equivalent) as the baseline security program for node operations. | F3: BSSC NOS v2 — 0. Basic Security | G3: req-implement-basic-security | H3: MUST | I3: High | J3: Node/validator operator; Exchange/Custodian running nodes | K3: GV.PO-01 | L3: A.5.1 | M3: — | N3: Review GSP gap assessment or ISO/SOC 2 report scope covering node infrastructure. | O3: Open spec | P3: Not started
A4: NOS-003 | B4: NOS | C4: 1. Protocol Onboarding | D4: Risk assessment | E4: Run a documented protocol selection and risk analysis (consensus, economics, client maturity, slashing exposure) before onboarding any new network. | F4: BSSC NOS v2 — 1. Protocol Onboarding | G4: req-document-protocol-analysis | H4: MUST | I4: High | J4: Node/validator operator; Exchange/Custodian running nodes | K4: ID.RA-01; GV.RM-03 | L4: A.5.8 | M4: — | N4: Inspect onboarding risk assessments and approval sign-off for each supported protocol. | O4: Open spec | P4: Not started
A5: NOS-004 | B5: NOS | C5: 1. Protocol Onboarding | D5: Risk assessment | E5: Continuously monitor protocol forks, upgrades and governance changes (release feeds, EIPs/BIPs, dev calls) and refresh the protocol risk assessment on each material change. | F5: BSSC NOS v2 — 1. Protocol Onboarding | G5: req-monitor-protocol-changes | H5: MUST | I5: High | J5: Node/validator operator; Exchange/Custodian running nodes | K5: ID.RA-03; ID.RA-07 | L5: A.5.7 | M5: — | N5: Show change-tracking log, subscriptions, and risk-assessment revision history. | O5: Open spec | P5: Not started
A6: NOS-005 | B6: NOS | C6: 1. Protocol Onboarding | D6: Software supply chain | E6: Maintain an SBOM and supply-chain risk analysis for all node components (clients, signers, sidecars, MEV relays, OS images, containers). | F6: BSSC NOS v2 — 1. Protocol Onboarding | G6: req-document-supply-chains | H6: MUST | I6: High | J6: Node/validator operator; Exchange/Custodian running nodes | K6: GV.SC-04; ID.AM-02 | L6: A.5.21 | M6: — | N6: Review SBOMs per node build and supply-chain risk register. | O6: Open spec | P6: Not started
A7: NOS-006 | B7: NOS | C7: 1. Protocol Onboarding | D7: Software supply chain | E7: Obtain node software only from official sources; verify release signatures/checksums and pin versions in build pipelines. | F7: BSSC NOS v2 — 1. Protocol Onboarding | G7: req-use-official-software | H7: MUST | I7: Critical | J7: Node/validator operator; Exchange/Custodian running nodes | K7: PR.PS-02; GV.SC-05 | L7: A.8.19 | M7: — | N7: Inspect build pipeline for signature/hash verification; trace deployed binaries to official releases. | O7: Open spec | P7: Not started
A8: NOS-007 | B8: NOS | C8: 1. Protocol Onboarding | D8: Software supply chain | E8: Define and follow a security assessment procedure (audit status, CVE history, code review) for every new protocol-related software package. | F8: BSSC NOS v2 — 1. Protocol Onboarding | G8: req-document-protocol-software-security | H8: MUST | I8: High | J8: Node/validator operator; Exchange/Custodian running nodes | K8: GV.SC-07; ID.RA-01 | L8: A.5.22 | M8: — | N8: Review completed software assessments for recently added packages. | O8: Open spec | P8: Not started
A9: NOS-008 | B9: NOS | C9: 1. Protocol Onboarding | D9: Protocol assessment | E9: Document technical and non-technical responsibilities to each protocol (duties, SLAs, governance participation, disclosure). | F9: BSSC NOS v2 — 1. Protocol Onboarding | G9: req-document-protocol-responsibilities | H9: MUST | I9: Medium | J9: Node/validator operator; Exchange/Custodian running nodes | K9: GV.RR-02 | L9: A.5.2 | M9: — | N9: Review responsibility matrix (RACI) per protocol. | O9: Open spec | P9: Not started
A10: NOS-009 | B10: NOS | C10: 1. Protocol Onboarding | D10: Protocol assessment | E10: Document protocol mechanics: upgrade path, governance and voting, kill-switches/emergency halts, and operator actions for each. | F10: BSSC NOS v2 — 1. Protocol Onboarding | G10: req-document-protocol-operation | H10: MUST | I10: High | J10: Node/validator operator; Exchange/Custodian running nodes | K10: ID.AM-03 | L10: A.5.37 | M10: — | N10: Review protocol runbooks for upgrade, vote and halt scenarios. | O10: Open spec | P10: Not started
A11: NOS-010 | B11: NOS | C11: 1. Protocol Onboarding | D11: Protocol assessment | E11: Pilot every new protocol and client version on an official/controlled testnet to validate performance, interoperability and security before mainnet. | F11: BSSC NOS v2 — 1. Protocol Onboarding | G11: req-use-testnet | H11: MUST | I11: High | J11: Node/validator operator; Exchange/Custodian running nodes | K11: PR.PS-06; ID.IM-02 | L11: A.8.31; A.8.29 | M11: — | N11: Inspect testnet run evidence (metrics, test reports) preceding each mainnet deployment. | O11: Open spec | P11: Not started
A12: NOS-011 | B12: NOS | C12: 1. Protocol Onboarding | D12: Compliance | E12: Screen counterparties and addresses against applicable AML/sanctions blacklists (e.g., OFAC SDN) where required; document jurisdictional obligations. | F12: BSSC NOS v2 — 1. Protocol Onboarding | G12: req-follow-relevant-regulation | H12: MUST | I12: Critical | J12: Node/validator operator; Exchange/Custodian running nodes | K12: GV.OC-03 | L12: A.5.31 | M12: — | N12: Test screening tooling against known sanctioned addresses; review compliance register. | O12: Open spec | P12: Not started
A13: NOS-012 | B13: NOS | C13: 1. Protocol Onboarding | D13: Cryptographic agility | E13: Maintain a cryptographic inventory per protocol (signature schemes, hash functions, key exchange). | F13: BSSC NOS v2 — 1. Protocol Onboarding | G13: req-document-protocol-crypto | H13: MUST | I13: Medium | J13: Node/validator operator; Exchange/Custodian running nodes | K13: ID.AM-08; PR.DS-01 | L13: A.8.24 | M13: — | N13: Review crypto inventory completeness against protocol specs. | O13: Open spec | P13: Not started
... A326: GSP-056 | B326: GSP | C326: 7. Privacy | D326: PII | E326: Minimise personal data stored on-chain (hashes/commitments, off-chain storage). | F326: BSSC GSP v2 — 7. Privacy | G326: req-minimize-pii-stored | H326: SHOULD | I326: High | J326: All blockchain participants | K326: PR.DS-01 | L326: A.5.34; A.8.11 | M326: — | N326: Design review of on-chain payloads. | O326: Open spec | P326: Not started

Sheet NOS
A1: Control ID | B1: Standard | C1: Domain | D1: Area | E1: Recommended Control | F1: Reference Standard | G1: BSSC Requirement ID | H1: BSSC Level (RFC 2119) | I1: Priority | J1: Applies To | K1: NIST CSF 2.0 | L1: ISO/IEC 27001:2022 | M1: CCSS Aspect (indicative) | N1: Verification Method / Evidence | O1: Source Link | P1: Implementation Status | Q1: Control Owner | R1: Notes
A2: NOS-001 | B2: NOS | C2: 0. Basic Security | D2: Key security | E2: Manage all node, validator, withdrawal and signing keys under the BSSC Key Management Standard (or a documented equivalent); maintain a KMS conformance mapping. | F2: BSSC NOS v2 — 0. Basic Security | G2: req-manage-key-security | H2: MUST | I2: Critical | J2: Node/validator operator; Exchange/Custodian running nodes | K2: PR.AA-01; PR.DS-01 | L2: A.8.24 | M2: 1.01-1.06 | N2: Review KMS conformance matrix; sample key lifecycle records; interview key custodians. | O2: Open spec | P2: Not started
A3: NOS-002 | B3: NOS | C3: 0. Basic Security | D3: Baseline security program | E3: Implement the BSSC General Security & Privacy Guidelines (or ISO 27001 / SOC 2 equivalent) as the baseline security program for node operations. | F3: BSSC NOS v2 — 0. Basic Security | G3: req-implement-basic-security | H3: MUST | I3: High | J3: Node/validator operator; Exchange/Custodian running nodes | K3: GV.PO-01 | L3: A.5.1 | M3: — | N3: Review GSP gap assessment or ISO/SOC 2 report scope covering node infrastructure. | O3: Open spec | P3: Not started
A4: NOS-003 | B4: NOS | C4: 1. Protocol Onboarding | D4: Risk assessment | E4: Run a documented protocol selection and risk analysis (consensus, economics, client maturity, slashing exposure) before onboarding any new network. | F4: BSSC NOS v2 — 1. Protocol Onboarding | G4: req-document-protocol-analysis | H4: MUST | I4: High | J4: Node/validator operator; Exchange/Custodian running nodes | K4: ID.RA-01; GV.RM-03 | L4: A.5.8 | M4: — | N4: Inspect onboarding risk assessments and approval sign-off for each supported protocol. | O4: Open spec | P4: Not started
A5: NOS-004 | B5: NOS | C5: 1. Protocol Onboarding | D5: Risk assessment | E5: Continuously monitor protocol forks, upgrades and governance changes (release feeds, EIPs/BIPs, dev calls) and refresh the protocol risk assessment on each material change. | F5: BSSC NOS v2 — 1. Protocol Onboarding | G5: req-monitor-protocol-changes | H5: MUST | I5: High | J5: Node/validator operator; Exchange/Custodian running nodes | K5: ID.RA-03; ID.RA-07 | L5: A.5.7 | M5: — | N5: Show change-tracking log, subscriptions, and risk-assessment revision history. | O5: Open spec | P5: Not started
A6: NOS-005 | B6: NOS | C6: 1. Protocol Onboarding | D6: Software supply chain | E6: Maintain an SBOM and supply-chain risk analysis for all node components (clients, signers, sidecars, MEV relays, OS images, containers). | F6: BSSC NOS v2 — 1. Protocol Onboarding | G6: req-document-supply-chains | H6: MUST | I6: High | J6: Node/validator operator; Exchange/Custodian running nodes | K6: GV.SC-04; ID.AM-02 | L6: A.5.21 | M6: — | N6: Review SBOMs per node build and supply-chain risk register. | O6: Open spec | P6: Not started
A7: NOS-006 | B7: NOS | C7: 1. Protocol Onboarding | D7: Software supply chain | E7: Obtain node software only from official sources; verify release signatures/checksums and pin versions in build pipelines. | F7: BSSC NOS v2 — 1. Protocol Onboarding | G7: req-use-official-software | H7: MUST | I7: Critical | J7: Node/validator operator; Exchange/Custodian running nodes | K7: PR.PS-02; GV.SC-05 | L7: A.8.19 | M7: — | N7: Inspect build pipeline for signature/hash verification; trace deployed binaries to official releases. | O7: Open spec | P7: Not started
A8: NOS-007 | B8: NOS | C8: 1. Protocol Onboarding | D8: Software supply chain | E8: Define and follow a security assessment procedure (audit status, CVE history, code review) for every new protocol-related software package. | F8: BSSC NOS v2 — 1. Protocol Onboarding | G8: req-document-protocol-software-security | H8: MUST | I8: High | J8: Node/validator operator; Exchange/Custodian running nodes | K8: GV.SC-07; ID.RA-01 | L8: A.5.22 | M8: — | N8: Review completed software assessments for recently added packages. | O8: Open spec | P8: Not started
A9: NOS-008 | B9: NOS | C9: 1. Protocol Onboarding | D9: Protocol assessment | E9: Document technical and non-technical responsibilities to each protocol (duties, SLAs, governance participation, disclosure). | F9: BSSC NOS v2 — 1. Protocol Onboarding | G9: req-document-protocol-responsibilities | H9: MUST | I9: Medium | J9: Node/validator operator; Exchange/Custodian running nodes | K9: GV.RR-02 | L9: A.5.2 | M9: — | N9: Review responsibility matrix (RACI) per protocol. | O9: Open spec | P9: Not started
A10: NOS-009 | B10: NOS | C10: 1. Protocol Onboarding | D10: Protocol assessment | E10: Document protocol mechanics: upgrade path, governance and voting, kill-switches/emergency halts, and operator actions for each. | F10: BSSC NOS v2 — 1. Protocol Onboarding | G10: req-document-protocol-operation | H10: MUST | I10: High | J10: Node/validator operator; Exchange/Custodian running nodes | K10: ID.AM-03 | L10: A.5.37 | M10: — | N10: Review protocol runbooks for upgrade, vote and halt scenarios. | O10: Open spec | P10: Not started
A11: NOS-010 | B11: NOS | C11: 1. Protocol Onboarding | D11: Protocol assessment | E11: Pilot every new protocol and client version on an official/controlled testnet to validate performance, interoperability and security before mainnet. | F11: BSSC NOS v2 — 1. Protocol Onboarding | G11: req-use-testnet | H11: MUST | I11: High | J11: Node/validator operator; Exchange/Custodian running nodes | K11: PR.PS-06; ID.IM-02 | L11: A.8.31; A.8.29 | M11: — | N11: Inspect testnet run evidence (metrics, test reports) preceding each mainnet deployment. | O11: Open spec | P11: Not started
A12: NOS-011 | B12: NOS | C12: 1. Protocol Onboarding | D12: Compliance | E12: Screen counterparties and addresses against applicable AML/sanctions blacklists (e.g., OFAC SDN) where required; document jurisdictional obligations. | F12: BSSC NOS v2 — 1. Protocol Onboarding | G12: req-follow-relevant-regulation | H12: MUST | I12: Critical | J12: Node/validator operator; Exchange/Custodian running nodes | K12: GV.OC-03 | L12: A.5.31 | M12: — | N12: Test screening tooling against known sanctioned addresses; review compliance register. | O12: Open spec | P12: Not started
A13: NOS-012 | B13: NOS | C13: 1. Protocol Onboarding | D13: Cryptographic agility | E13: Maintain a cryptographic inventory per protocol (signature schemes, hash functions, key exchange). | F13: BSSC NOS v2 — 1. Protocol Onboarding | G13: req-document-protocol-crypto | H13: MUST | I13: Medium | J13: Node/validator operator; Exchange/Custodian running nodes | K13: ID.AM-08; PR.DS-01 | L13: A.8.24 | M13: — | N13: Review crypto inventory completeness against protocol specs. | O13: Open spec | P13: Not started
... A55: NOS-054 | B55: NOS | C55: 5. Transparency | D55: Transparency | E55: Disclose governance participation criteria, proposal criteria, voting history (where safe) and conflicts of interest including abstentions. | F55: BSSC NOS v2 — 5. Transparency | G55: req-document-governance-positions | H55: MUST | I55: Low | J55: Node/validator operator; Exchange/Custodian running nodes | K55: GV.OC-02 | L55: A.5.1 | M55: — | N55: Review published governance disclosures. | O55: Open spec | P55: Not started

Sheet TIS
A1: Control ID | B1: Standard | C1: Domain | D1: Area | E1: Recommended Control | F1: Reference Standard | G1: BSSC Requirement ID | H1: BSSC Level (RFC 2119) | I1: Priority | J1: Applies To | K1: NIST CSF 2.0 | L1: ISO/IEC 27001:2022 | M1: CCSS Aspect (indicative) | N1: Verification Method / Evidence | O1: Source Link | P1: Implementation Status | Q1: Control Owner | R1: Notes
A2: TIS-001 | B2: TIS | C2: 1. General Information | D2: Disclosure package | E2: Require a complete token information package from the issuer before integration; block listing until all items are provided. | F2: BSSC TIS v1 — 1. General Information | G2: Heading: General Information (lead-in) | H2: MUST | I2: High | J2: Token issuer (provide); Exchange/Custodian/DeFi integrator (verify at listing) | K2: GV.SC-06 | L2: A.5.19 | M2: — | N2: Listing due-diligence checklist: confirm all General Information items present and signed off. | O2: Open spec | P2: Not started
A3: TIS-002 | B3: TIS | C3: 1. General Information | D3: Disclosure package | E3: Obtain token allocations and vesting schedules; reconcile against on-chain holder distribution. | F3: BSSC TIS v1 — 1. General Information | G3: Heading: Token allocation | H3: MUST | I3: Medium | J3: Token issuer (provide); Exchange/Custodian/DeFi integrator (verify at listing) | K3: GV.SC-06 | L3: A.5.19 | M3: — | N3: Listing due-diligence checklist: compare stated allocation to on-chain top-holder analysis. | O3: Open spec | P3: Not started
A4: TIS-003 | B4: TIS | C4: 1. General Information | D4: Token identity | E4: Verify that disclosed name and symbol exactly match on-chain name() and symbol() return values. | F4: BSSC TIS v1 — 1. General Information | G4: Heading: Name and Symbol | H4: MUST | I4: High | J4: Token issuer (provide); Exchange/Custodian/DeFi integrator (verify at listing) | K4: ID.AM-02 | L4: A.5.9 | M4: — | N4: Call name()/symbol() on each deployment; compare to listing record. | O4: Open spec | P4: Not started
A5: TIS-004 | B5: TIS | C5: 1. General Information | D5: Disclosure package | E5: Obtain and archive a link to the token's technical documentation. | F5: BSSC TIS v1 — 1. General Information | G5: Heading: Technical Documentation | H5: MUST | I5: Low | J5: Token issuer (provide); Exchange/Custodian/DeFi integrator (verify at listing) | K5: GV.SC-06 | L5: A.5.19 | M5: — | N5: Listing due-diligence checklist: archive link and snapshot. | O5: Open spec | P5: Not started
A6: TIS-005 | B6: TIS | C6: 1. General Information | D6: Disclosure package | E6: Record verified contact details for the managing team, including a security contact. | F6: BSSC TIS v1 — 1. General Information | G6: Heading: Contact Information | H6: MUST | I6: Medium | J6: Token issuer (provide); Exchange/Custodian/DeFi integrator (verify at listing) | K6: GV.SC-06 | L6: A.5.5 | M6: — | N6: Test contact channel response. | O6: Open spec | P6: Not started
A7: TIS-006 | B7: TIS | C7: 1. General Information | D7: Token identity | E7: Maintain an allow-listed registry of official contract addresses per chain; reject unregistered contracts. | F7: BSSC TIS v1 — 1. General Information | G7: Heading: Deployment Address | H7: MUST | I7: Critical | J7: Token issuer (provide); Exchange/Custodian/DeFi integrator (verify at listing) | K7: ID.AM-02 | L7: A.5.9 | M7: — | N7: Verify address registry against issuer-signed list and block explorers. | O7: Open spec | P7: Not started
A8: TIS-007 | B8: TIS | C8: 1. General Information | D8: Token identity | E8: Classify each token as native, bridged or wrapped and assess the bridge/wrapper trust model. | F8: BSSC TIS v1 — 1. General Information | G8: Heading: Is it native, bridged, wrapped? | H8: MUST | I8: High | J8: Token issuer (provide); Exchange/Custodian/DeFi integrator (verify at listing) | K8: ID.RA-01 | L8: A.5.19 | M8: — | N8: Review classification and bridge risk assessment. | O8: Open spec | P8: Not started
A9: TIS-008 | B9: TIS | C9: 1. General Information | D9: Token behaviour | E9: Identify rebasing behaviour and adapt ledger/accounting (share-based balances) before integration. | F9: BSSC TIS v1 — 1. General Information | G9: Heading: Token Rebasing | H9: MUST | I9: High | J9: Token issuer (provide); Exchange/Custodian/DeFi integrator (verify at listing) | K9: ID.RA-01 | L9: A.8.25 | M9: — | N9: Test deposits/withdrawals across a rebase event on testnet. | O9: Open spec | P9: Not started
A10: TIS-009 | B10: TIS | C10: 1. General Information | D10: Upgradability | E10: Record whether the contract is upgradeable (proxy pattern, admin) as a listing risk factor. | F10: BSSC TIS v1 — 1. General Information | G10: Heading: Document Upgradability | H10: MUST | I10: High | J10: Token issuer (provide); Exchange/Custodian/DeFi integrator (verify at listing) | K10: ID.RA-01 | L10: A.5.19 | M10: — | N10: Inspect proxy storage slots / admin on-chain. | O10: Open spec | P10: Not started
A11: TIS-010 | B11: TIS | C11: 1. General Information | D11: Market risk | E11: Obtain trading and TVL history since deployment for liquidity and manipulation risk review. | F11: BSSC TIS v1 — 1. General Information | G11: Heading: Trading History | H11: MUST | I11: Medium | J11: Token issuer (provide); Exchange/Custodian/DeFi integrator (verify at listing) | K11: ID.RA-01 | L11: A.5.19 | M11: — | N11: Review market data analysis in listing memo. | O11: Open spec | P11: Not started
A12: TIS-011 | B12: TIS | C12: 1. General Information | D12: Market risk | E12: Where minting/burning is supported, obtain and assess the automated price discovery mechanism. | F12: BSSC TIS v1 — 1. General Information | G12: Heading: Price discovery mechanism | H12: MUST | I12: Medium | J12: Token issuer (provide); Exchange/Custodian/DeFi integrator (verify at listing) | K12: ID.RA-01 | L12: A.5.19 | M12: — | N12: Review economic analysis of price discovery. | O12: Open spec | P12: Not started
A13: TIS-012 | B13: TIS | C13: 1. General Information | D13: Market risk | E13: For stablecoins, obtain and assess stabilisation/backing mechanism and attestations. | F13: BSSC TIS v1 — 1. General Information | G13: Heading: Stablecoin Backing | H13: MUST | I13: High | J13: Token issuer (provide); Exchange/Custodian/DeFi integrator (verify at listing) | K13: ID.RA-01 | L13: A.5.19 | M13: 1.09 | N13: Review reserve attestations and stabilisation mechanism analysis. | O13: Open spec | P13: Not started
... A51: TIS-050 | B51: TIS | C51: 6. Token Behaviors | D51: Blocklist/freeze | E51: Determine whether blocked addresses can receive deposits; prevent customer sends to frozen addresses. | F51: BSSC TIS v1 — 6. Token Behaviors | G51: Heading: Document Whether Blocked Accounts Can Receive Transfers | H51: MUST | I51: Medium | J51: Token issuer (provide); Exchange/Custodian/DeFi integrator (verify at listing) | K51: PR.PS-06 | L51: A.8.29 | M51: — | N51: Review documentation; fork test. | O51: Open spec | P51: Not started

Sheet KMS
A1: Control ID | B1: Standard | C1: Domain | D1: Area | E1: Recommended Control | F1: Reference Standard | G1: BSSC Requirement ID | H1: BSSC Level (RFC 2119) | I1: Priority | J1: Applies To | K1: NIST CSF 2.0 | L1: ISO/IEC 27001:2022 | M1: CCSS Aspect (indicative) | N1: Verification Method / Evidence | O1: Source Link | P1: Implementation Status | Q1: Control Owner | R1: Notes
A2: KMS-001 | B2: KMS | C2: §5 General Requirements | D2: Change management | E2: Enforce a formal change management process for every key management component (HSMs, MPC nodes, policy engines, signing services). | F2: BSSC KMS v1 — §5 General Requirements | G2: KMS-GEN-01 (assigned; spec has no IDs) | H2: MUST | I2: High | J2: All key holders (Custodian/Exchange, Node operator, Protocol/admin keys) | K2: PR.PS-01; ID.IM-03 | L2: A.8.32 | M2: 1.06 | N2: Sample changes: ticket, approval, test evidence. | O2: Open spec | P2: Not started
A3: KMS-002 | B3: KMS | C3: §5 General Requirements | D3: Change management | E3: Keep an audit trail of every change naming proposer and approver(s). | F3: BSSC KMS v1 — §5 General Requirements | G3: KMS-GEN-02 (assigned; spec has no IDs) | H3: MUST | I3: High | J3: All key holders (Custodian/Exchange, Node operator, Protocol/admin keys) | K3: PR.PS-04 | L3: A.8.32; A.8.15 | M3: 1.10 | N3: Inspect change records for proposer/approver identity. | O3: Open spec | P3: Not started
A4: KMS-003 | B4: KMS | C4: §5 General Requirements | D4: Change management | E4: Require at least one proposer and one distinct approver for every change (four-eyes). | F4: BSSC KMS v1 — §5 General Requirements | G4: KMS-GEN-03 (assigned; spec has no IDs) | H4: MUST | I4: Critical | J4: All key holders (Custodian/Exchange, Node operator, Protocol/admin keys) | K4: PR.AA-05 | L4: A.5.3 | M4: 1.06 | N4: Verify tooling blocks self-approval. | O4: Open spec | P4: Not started
A5: KMS-004 | B5: KMS | C5: §5 General Requirements | D5: Separation of duties | E5: Technically enforce that no single individual can cause key misuse or destruction (quorum, MPC thresholds, policy engines). | F5: BSSC KMS v1 — §5 General Requirements | G5: KMS-GEN-04 (assigned; spec has no IDs) | H5: SHOULD | I5: Critical | J5: All key holders (Custodian/Exchange, Node operator, Protocol/admin keys) | K5: PR.AA-05 | L5: A.5.3 | M5: 1.04; 1.06 | N5: Attempt single-actor critical action in test; review threshold configs. | O5: Open spec | P5: Not started
A6: KMS-005 | B6: KMS | C6: §5 General Requirements | D6: Change management | E6: Test all changes in a non-production environment before activation. | F6: BSSC KMS v1 — §5 General Requirements | G6: KMS-GEN-05 (assigned; spec has no IDs) | H6: MUST | I6: High | J6: All key holders (Custodian/Exchange, Node operator, Protocol/admin keys) | K6: PR.PS-06 | L6: A.8.31; A.8.32 | M6: — | N6: Trace changes to test evidence. | O6: Open spec | P6: Not started
A7: KMS-006 | B7: KMS | C7: §5 General Requirements | D7: Auditability | E7: Ensure every key management component is auditable. | F7: BSSC KMS v1 — §5 General Requirements | G7: KMS-GEN-06 (assigned; spec has no IDs) | H7: MUST | I7: High | J7: All key holders (Custodian/Exchange, Node operator, Protocol/admin keys) | K7: PR.PS-04 | L7: A.8.15 | M7: 1.10 | N7: Confirm logging coverage inventory. | O7: Open spec | P7: Not started
A8: KMS-007 | B8: KMS | C8: §5 General Requirements | D8: Auditability | E8: Record when Critical Actions occur and who authorised/executed them. | F8: BSSC KMS v1 — §5 General Requirements | G8: KMS-GEN-07 (assigned; spec has no IDs) | H8: SHOULD | I8: High | J8: All key holders (Custodian/Exchange, Node operator, Protocol/admin keys) | K8: PR.PS-04; DE.CM-03 | L8: A.8.15 | M8: 1.10 | N8: Sample Critical Action log entries. | O8: Open spec | P8: Not started
A9: KMS-008 | B9: KMS | C9: §5 General Requirements | D9: Auditability | E9: Never write key material, seeds, shares or sensitive values to logs; scan logs for secrets. | F9: BSSC KMS v1 — §5 General Requirements | G9: KMS-GEN-08 (assigned; spec has no IDs) | H9: MUST NOT | I9: Critical | J9: All key holders (Custodian/Exchange, Node operator, Protocol/admin keys) | K9: PR.DS-01 | L9: A.8.11; A.8.15 | M9: 1.10 | N9: Secret-scan log stores. | O9: Open spec | P9: Not started
A10: KMS-009 | B10: KMS | C10: §5 General Requirements | D10: Procedures | E10: Document non-digital (ceremony, physical) processes as transparent, repeatable procedures. | F10: BSSC KMS v1 — §5 General Requirements | G10: KMS-GEN-09 (assigned; spec has no IDs) | H10: MUST | I10: Medium | J10: All key holders (Custodian/Exchange, Node operator, Protocol/admin keys) | K10: GV.PO-01 | L10: A.5.37 | M10: 1.01 | N10: Review ceremony scripts. | O10: Open spec | P10: Not started
A11: KMS-010 | B11: KMS | C11: §5 General Requirements | D11: Auditability | E11: Protect audit logs from tampering and unauthorised access (WORM, hash-chaining, RBAC). | F11: BSSC KMS v1 — §5 General Requirements | G11: KMS-GEN-10 (assigned; spec has no IDs) | H11: MUST | I11: High | J11: All key holders (Custodian/Exchange, Node operator, Protocol/admin keys) | K11: PR.PS-04 | L11: A.8.15 | M11: 1.10 | N11: Verify immutability settings and access lists. | O11: Open spec | P11: Not started
A12: KMS-011 | B12: KMS | C12: §5 General Requirements | D12: Monitoring | E12: Monitor and alert on incidents and abnormal behaviour for automated key components. | F12: BSSC KMS v1 — §5 General Requirements | G12: KMS-GEN-11 (assigned; spec has no IDs) | H12: SHOULD | I12: High | J12: All key holders (Custodian/Exchange, Node operator, Protocol/admin keys) | K12: DE.CM-09; DE.AE-02 | L12: A.8.16 | M12: — | N12: Review alert rules and recent alert handling. | O12: Open spec | P12: Not started
A13: KMS-012 | B13: KMS | C13: §5 General Requirements | D13: Access control | E13: Apply least privilege across all key management components. | F13: BSSC KMS v1 — §5 General Requirements | G13: KMS-GEN-12 (assigned; spec has no IDs) | H13: SHOULD | I13: High | J13: All key holders (Custodian/Exchange, Node operator, Protocol/admin keys) | K13: PR.AA-05 | L13: A.8.2; A.5.15 | M13: 1.06 | N13: Access review sample. | O13: Open spec | P13: Not started
... A97: KMS-096 | B97: KMS | C97: §6 Key Destruction | D97: Destruction | E97: Use irreversible destruction (zeroisation, physical hardware destruction). | F97: BSSC KMS v1 — §6 Key Destruction | G97: KMS-KX-04 (assigned; spec has no IDs) | H97: MUST | I97: High | J97: All key holders (Custodian/Exchange, Node operator, Protocol/admin keys) | K97: PR.DS-01 | L97: A.8.10; A.7.14 | M97: 1.08 | N97: Destruction certificates. | O97: Open spec | P97: Not started

Sheet SCS
A1: Control ID | B1: Standard | C1: Domain | D1: Area | E1: Recommended Control | F1: Reference Standard | G1: BSSC Requirement ID | H1: BSSC Level (RFC 2119) | I1: Priority | J1: Applies To | K1: NIST CSF 2.0 | L1: ISO/IEC 27001:2022 | M1: CCSS Aspect (indicative) | N1: Verification Method / Evidence | O1: Source Link | P1: Implementation Status | Q1: Control Owner | R1: Notes
A2: SCS-001 | B2: SCS | C2: 1. Development | D2: Naming conventions | E2: Use clear, self-describing names for contracts, functions and variables. | F2: BSSC SCS v1 — 1. Development | G2: req-use-clear-names | H2: SHOULD | I2: Low | J2: Protocol/dApp/token developer; Exchange/Custodian (own contracts) | K2: PR.PS-06 | L2: A.8.28 | M2: — | N2: Code review checklist. | O2: Open spec | P2: Not started
A3: SCS-002 | B3: SCS | C3: 1. Development | D3: Naming conventions | E3: Maintain a glossary of non-obvious domain terms. | F3: BSSC SCS v1 — 1. Development | G3: req-use-glossary | H3: SHOULD | I3: Low | J3: Protocol/dApp/token developer; Exchange/Custodian (own contracts) | K3: PR.PS-06 | L3: A.8.28 | M3: — | N3: Repo documentation check. | O3: Open spec | P3: Not started
A4: SCS-003 | B4: SCS | C4: 1. Development | D4: Style guides | E4: Follow the language style guide (e.g., Solidity style guide) enforced by linters. | F4: BSSC SCS v1 — 1. Development | G4: req-use-language-styleguide | H4: SHOULD | I4: Low | J4: Protocol/dApp/token developer; Exchange/Custodian (own contracts) | K4: PR.PS-06 | L4: A.8.28 | M4: — | N4: CI linter configuration (solhint/forge fmt). | O4: Open spec | P4: Not started
A5: SCS-004 | B5: SCS | C5: 1. Development | D5: Style guides | E5: Adopt a documented style standard available to all contributors and enforce it in CI. | F5: BSSC SCS v1 — 1. Development | G5: req-use-styleguide | H5: MUST | I5: Medium | J5: Protocol/dApp/token developer; Exchange/Custodian (own contracts) | K5: PR.PS-06 | L5: A.8.28 | M5: — | N5: Style guide + CI gate evidence. | O5: Open spec | P5: Not started
A6: SCS-005 | B6: SCS | C6: 1. Development | D6: Modular design | E6: Build modular, self-contained components with clear interfaces. | F6: BSSC SCS v1 — 1. Development | G6: req-use-modular-code | H6: SHOULD | I6: Medium | J6: Protocol/dApp/token developer; Exchange/Custodian (own contracts) | K6: PR.PS-06 | L6: A.8.27 | M6: — | N6: Architecture review. | O6: Open spec | P6: Not started
A7: SCS-006 | B7: SCS | C7: 1. Development | D7: Modular design | E7: Keep methods concise (≈<100 lines) and single-purpose. | F7: BSSC SCS v1 — 1. Development | G7: req-use-concise-methods | H7: SHOULD | I7: Low | J7: Protocol/dApp/token developer; Exchange/Custodian (own contracts) | K7: PR.PS-06 | L7: A.8.28 | M7: — | N7: Static metrics. | O7: Open spec | P7: Not started
A8: SCS-007 | B8: SCS | C8: 1. Development | D8: Modular design | E8: Document inter-module dependencies. | F8: BSSC SCS v1 — 1. Development | G8: req-document-dependencies | H8: SHOULD / MUST | I8: Medium | J8: Protocol/dApp/token developer; Exchange/Custodian (own contracts) | K8: ID.AM-02 | L8: A.8.27 | M8: — | N8: Dependency diagram. | O8: Open spec | P8: Not started
A9: SCS-008 | B9: SCS | C9: 1. Development | D9: Modular design | E9: Use vetted library code (e.g., audited OpenZeppelin) instead of custom implementations. | F9: BSSC SCS v1 — 1. Development | G9: req-use-open-source | H9: SHOULD | I9: Medium | J9: Protocol/dApp/token developer; Exchange/Custodian (own contracts) | K9: GV.SC-07 | L9: A.8.28 | M9: — | N9: Dependency review. | O9: Open spec | P9: Not started
A10: SCS-009 | B10: SCS | C10: 1. Development | D10: Code operations | E10: Follow consistent operation ordering across functions (validation → effects → interactions). | F10: BSSC SCS v1 — 1. Development | G10: req-use-consistent-steps | H10: SHOULD | I10: Medium | J10: Protocol/dApp/token developer; Exchange/Custodian (own contracts) | K10: PR.PS-06 | L10: A.8.28 | M10: — | N10: Code review. | O10: Open spec | P10: Not started
A11: SCS-010 | B11: SCS | C11: 1. Development | D11: Dependencies | E11: Document all external dependencies (oracles, bridges, protocols, libraries). | F11: BSSC SCS v1 — 1. Development | G11: req-document-external-dependencies | H11: MUST | I11: High | J11: Protocol/dApp/token developer; Exchange/Custodian (own contracts) | K11: ID.AM-02; GV.SC-04 | L11: A.5.21 | M11: — | N11: External dependency register. | O11: Open spec | P11: Not started
A12: SCS-011 | B12: SCS | C12: 1. Development | D12: Dependencies | E12: Manage dependencies and tooling as third-party systems with version pinning and risk review. | F12: BSSC SCS v1 — 1. Development | G12: req-manage-dependencies-externally | H12: SHOULD | I12: Medium | J12: Protocol/dApp/token developer; Exchange/Custodian (own contracts) | K12: GV.SC-07 | L12: A.5.21; A.5.22 | M12: — | N12: Lockfiles; supplier risk review. | O12: Open spec | P12: Not started
A13: SCS-012 | B13: SCS | C13: 1. Development | D13: Dependencies | E13: Design contracts so any oracle can be replaced (governed setter, fallback oracle, staleness checks). | F13: BSSC SCS v1 — 1. Development | G13: req-use-oracles-carefully | H13: MUST | I13: Critical | J13: Protocol/dApp/token developer; Exchange/Custodian (own contracts) | K13: PR.IR-03 | L13: A.8.27 | M13: — | N13: Code review of oracle wiring. | O13: Open spec | P13: Not started
... A70: SCS-069 | B70: SCS | C70: 5. Governance | D70: Privileged roles | E70: Hold entities in privileged roles to appropriate security and compliance standards (KMS for signer keys). | F70: BSSC SCS v1 — 5. Governance | G70: req-secure-privileged-roles | H70: MUST | I70: Critical | J70: Protocol/dApp/token developer; Exchange/Custodian (own contracts) | K70: GV.SC-05; PR.AA-05 | L70: A.5.19; A.8.2 | M70: 1.03; 1.04 | N70: Signer security attestation. | O70: Open spec | P70: Not started

Sheet GSP
A1: Control ID | B1: Standard | C1: Domain | D1: Area | E1: Recommended Control | F1: Reference Standard | G1: BSSC Requirement ID | H1: BSSC Level (RFC 2119) | I1: Priority | J1: Applies To | K1: NIST CSF 2.0 | L1: ISO/IEC 27001:2022 | M1: CCSS Aspect (indicative) | N1: Verification Method / Evidence | O1: Source Link | P1: Implementation Status | Q1: Control Owner | R1: Notes
A2: GSP-001 | B2: GSP | C2: 1. Govern | D2: Risk management | E2: Include blockchain-specific risks (key loss, smart contract, chain, bridge) in enterprise risk management. | F2: BSSC GSP v2 — 1. Govern | G2: req-treat-blockchain-risk | H2: SHOULD | I2: High | J2: All blockchain participants | K2: GV.RM-01; GV.RM-03 | L2: Cl. 6.1; A.5.1 | M2: — | N2: ERM register shows blockchain risk category. | O2: Open spec | P2: Not started
A3: GSP-002 | B3: GSP | C3: 1. Govern | D3: Risk management | E3: Maintain a risk governance framework and risk register reviewed with stakeholders. | F3: BSSC GSP v2 — 1. Govern | G3: req-risk-register | H3: SHOULD | I3: High | J3: All blockchain participants | K3: GV.RM-01; ID.RA-06 | L3: Cl. 6.1.2; Cl. 8.2 | M3: — | N3: Register and review minutes. | O3: Open spec | P3: Not started
A4: GSP-003 | B4: GSP | C4: 1. Govern | D4: Governance resources | E4: Assign dedicated resources and owners for security governance and compliance. | F4: BSSC GSP v2 — 1. Govern | G4: req-assign-governance | H4: SHOULD | I4: Medium | J4: All blockchain participants | K4: GV.RR-03 | L4: Cl. 5.3; A.5.2 | M4: — | N4: Org chart / RACI. | O4: Open spec | P4: Not started
A5: GSP-004 | B5: GSP | C5: 1. Govern | D5: Data classification | E5: Define data classification tiers, criteria, access limits and protections. | F5: BSSC GSP v2 — 1. Govern | G5: req-define-data-risk | H5: SHOULD | I5: Medium | J5: All blockchain participants | K5: ID.AM-07; GV.PO-01 | L5: A.5.12; A.5.13 | M5: — | N5: Classification policy. | O5: Open spec | P5: Not started
A6: GSP-005 | B6: GSP | C6: 1. Govern | D6: Public compliance | E6: Publish a trust centre with compliance documentation and privacy policy. | F6: BSSC GSP v2 — 1. Govern | G6: req-publish-trust-info | H6: SHOULD | I6: Low | J6: All blockchain participants | K6: GV.OC-02 | L6: A.5.34 | M6: — | N6: Trust centre review. | O6: Open spec | P6: Not started
A7: GSP-006 | B7: GSP | C7: 1. Govern | D7: Regulatory monitoring | E7: Track and adapt to evolving regulation (MiCA, Travel Rule, local VASP rules). | F7: BSSC GSP v2 — 1. Govern | G7: req-monitor-regulation | H7: SHOULD | I7: High | J7: All blockchain participants | K7: GV.OC-03 | L7: A.5.31 | M7: — | N7: Regulatory watch log. | O7: Open spec | P7: Not started
A8: GSP-007 | B8: GSP | C8: 1. Govern | D8: Vendor management | E8: Document vendor/third-party risk management (custody, node, oracle, KYT providers). | F8: BSSC GSP v2 — 1. Govern | G8: req-manage-vendors | H8: SHOULD | I8: High | J8: All blockchain participants | K8: GV.SC-01; GV.SC-06 | L8: A.5.19-A.5.22 | M8: — | N8: Vendor inventory and assessments. | O8: Open spec | P8: Not started
A9: GSP-008 | B9: GSP | C9: 1. Govern | D9: Crypto standards | E9: Track cryptographic standards incl. post-quantum guidance in risk management. | F9: BSSC GSP v2 — 1. Govern | G9: req-monitor-crypto | H9: SHOULD | I9: Medium | J9: All blockchain participants | K9: ID.RA-03 | L9: A.8.24 | M9: — | N9: Crypto watch entries in risk register. | O9: Open spec | P9: Not started
A10: GSP-009 | B10: GSP | C10: 2. Identify | D10: Risk assessment | E10: Conduct regular blockchain-specific risk assessments. | F10: BSSC GSP v2 — 2. Identify | G10: req-assess-risks | H10: SHOULD | I10: High | J10: All blockchain participants | K10: ID.RA-01 | L10: Cl. 8.2 | M10: — | N10: Assessment reports. | O10: Open spec | P10: Not started
A11: GSP-010 | B11: GSP | C11: 2. Identify | D11: Customer funds | E11: Document risks to customer funds and keep accessible. | F11: BSSC GSP v2 — 2. Identify | G11: req-document-funds-risks | H11: SHOULD | I11: Critical | J11: Custodian/Exchange; Protocol holding user funds | K11: ID.RA-04 | L11: Cl. 6.1.2 | M11: 1.09 | N11: Customer-funds risk document. | O11: Open spec | P11: Not started
A12: GSP-011 | B12: GSP | C12: 2. Identify | D12: Ecosystem risk | E12: Assess ecosystem/external risks (bridges, L1 health, counterparties, stablecoin depegs). | F12: BSSC GSP v2 — 2. Identify | G12: req-assess-ecosystem-risk | H12: SHOULD | I12: High | J12: All blockchain participants | K12: ID.RA-03; GV.SC-07 | L12: A.5.7 | M12: — | N12: Ecosystem risk assessment. | O12: Open spec | P12: Not started
A13: GSP-012 | B13: GSP | C13: 2. Identify | D13: Threat intelligence | E13: Subscribe to and integrate reputable threat intelligence (Crypto-ISAC, SEAL-ISAC, chain analytics). | F13: BSSC GSP v2 — 2. Identify | G13: req-monitor-threat-intel | H13: SHOULD | I13: High | J13: All blockchain participants | K13: ID.RA-02 | L13: A.5.7 | M13: — | N13: Feed subscriptions and integration. | O13: Open spec | P13: Not started
... A57: GSP-056 | B57: GSP | C57: 7. Privacy | D57: PII | E57: Minimise personal data stored on-chain (hashes/commitments, off-chain storage). | F57: BSSC GSP v2 — 7. Privacy | G57: req-minimize-pii-stored | H57: SHOULD | I57: High | J57: All blockchain participants | K57: PR.DS-01 | L57: A.5.34; A.8.11 | M57: — | N57: Design review of on-chain payloads. | O57: Open spec | P57: Not started
