Workbook

Sheet Overview
A1: Security Hardening & Evergreen Governance Program - Plan v2
A2: Prepared 19 Oct 2026. Yellow cells are inputs. All dated/versioned facts are sourced on the Sources tab.
A4: Program Week 1 start (input) | B4: 46321
A5: Program Week 26 end | B5: =B4+7*26-1 -> 46502
A6: Week 0 (Immediate) start | B6: =B4-7 -> 46314
A8: Goal | B8: Deliver a decision-ready, staffed 26-week security program that (1) hardens OS and containers, (2) hardens security monitoring and response, and (3) installs an evergreen governance model, for an AWS-hosted Ethereum/Solana dApp business pursuing SOC 2.
A9: Timeline | B9: Week 0 = 19-25 Oct 2026 (Immediate actions). Week 1 starts Mon 26 Oct 2026; Week 26 ends Sun 25 Apr 2027. Weeks 9-10 (21 Dec 2026 - 3 Jan 2027) are reduced-capacity with a production change freeze (emergency changes only).
A10: In scope | B10: AWS multi-account org (Control Tower, Organizations, EC2 Linux, EKS, ECS/EC2 containers, data services, network, logging, backup); Microsoft Entra ID (workforce), Azure AD B2C (customers), IAM Identity Center; Splunk SIEM/SOAR, CrowdStrike EDR, MDR; Ethereum Solidity contracts and Solana Rust/Anchor programs, admin multisigs (Safe/Squads), MPC custody vendor oversight, staking-provider oversight; SOC 2 readiness and Type I; policies, TPRM, HR controls, training.
A11: Out of scope | B11: MiCA/DORA/PCI DSS build-out (go/no-go only, D-01); AML/money-transmission programme (contingent on D-01); running own validators; executing the B2C -> External ID migration (roadmap only); ISO 27001 certification (alignment only); Windows workloads; physical security; budget costing (envelope requested at Gate 1).
A13: Headline numbers (live)
A14: Total tasks | B14: =COUNTA('Project Plan'!$A$7:$A$156) -> 150
A15: Immediate actions (with owner + deadline) | B15: =COUNTIF('Project Plan'!$U$7:$U$156,"?*") -> 16
A16: Workstreams | B16: =6 -> 6
A17: Steering gates | B17: =COUNTA(A55:A58) -> 4
A18: Internal program FTE | B18: ='Roles & Skills'!E27 -> 5
A19: Contractor FTE (peak concurrent) | B19: ='Roles & Skills'!E28 -> 6.5
A20: Contractor FTE-weeks | B20: ='Roles & Skills'!H27 -> 133
A21: Partner/firm engagements | B21: ='Roles & Skills'!E29 -> 7
A22: KPIs | B22: =COUNTA(KPIs!A5:A29) -> 25
A23: Decisions in log | B23: =COUNTA('Risks and Decisions'!A30:A46) -> 17
A24: Risks in register | B24: =COUNTA('Risks and Decisions'!A5:A26) -> 22
A25: Review findings logged | B25: =COUNTA('Review Log'!A5:A66) -> 62
A26: Dependency violations (must be 0) | B26: =COUNTIF('Project Plan'!$K$7:$K$156,"VIOLATION") -> 0
A27: Tasks ending after W26 (must be 0) | B27: =COUNTIF('Project Plan'!$L$7:$L$156,"LATE") -> 0
A28: Decision misalignments (must be 0) | B28: =COUNTIF('Risks and Decisions'!J30:J46,"MISALIGNED") -> 0
A29: Role overloads (must be 0) | B29: =COUNTIF('Roles & Skills'!P5:P26,"OVER") -> 0
A31: Assumptions
A32: • Non-EU firm; no EU solicitation of customers; SOC 2 is the primary compliance driver (user-confirmed). Confirmed or overturned by D-01 in W4.
A33: • No cardholder data in scope (user-confirmed); any future card acceptance via hosted iframe/redirect would fall under PCI DSS v4.0.1 SAQ A.
A34: • Amazon Linux 2 workloads remain in the fleet alongside AL2023 (user-confirmed); exact count from HD-01.
A35: • Staking is delegated to a third-party staking provider (no self-run validators); treasury/hot wallets on a third-party MPC custody platform; admin keys in Safe (EVM) and Squads v4 (Solana) multisigs.
A36: • Splunk remains the SIEM (Enterprise Security 8.x, SOAR available); CrowdStrike Falcon covers EC2. Microsoft Sentinel is not adopted, so its Azure-portal retirement (31 Mar 2027) is noted but not actioned.
A37: • Security program team = 5.0 internal FTE plus contractors/partners; platform and application engineering teams implement changes (supporting role, outside program FTE).
A38: • Assumed US-headquartered entity for OFAC/state-law purposes (to be confirmed in D-01).
A39: • Whether the business is custodial for customer funds (withdrawal flows exist) is UNVERIFIED; D-01 answers custodial / FinCEN MSB / state licensing / FTC Safeguards Rule. Any 'yes' triggers a re-plan at Gate 1.
A40: • Weeks 9-10 (21 Dec 2026 - 3 Jan 2027) are a production change freeze; design and non-prod work continues at reduced capacity.
A41: • Capacity rule: each role leads at most round(3 x FTE) concurrent tasks and carries a weighted load (lead 1.0 + support 0.25 per task) of at most 4 x FTE in any week.
A42: • Budget is not costed in this plan; licence uplifts (Entra P2/ID Governance, Security Hub per-resource pricing, EKS extended support, Splunk ingest) are flagged as decisions/risks.
A44: Phases
A45: Phase | B45: Name | C45: Start wk | D45: End wk | E45: Start date | F45: Purpose
A46: P0 | B46: Immediate (pre-program) | C46: 0 | D46: 2 | E46: =$B$4+7*(C46-1) -> 46314 | F46: Close exposures that land before or at the very start of the program
A47: P1 | B47: Mobilize | C47: 1 | D47: 6 | E47: =$B$4+7*(C47-1) -> 46321 | F47: Charter, budget, partner bookings, scope, risk appetite, threat model, baseline
A48: P2 | B48: Assess & Design | C48: 2 | D48: 10 | E48: =$B$4+7*(C48-1) -> 46328 | F48: Gap assessment and ARB-approved designs per workstream
A49: P3 | B49: Build & Harden | C49: 6 | D49: 20 | E49: =$B$4+7*(C49-1) -> 46356 | F49: Guardrails, hardening, identity, telemetry, on-chain controls
A50: P4 | B50: Monitor & Validate | C50: 10 | D50: 22 | E50: =$B$4+7*(C50-1) -> 46384 | F50: Detections, pentest, audit, tabletop, DR test, SOC 2 readiness
A51: P5 | B51: Operationalize & Handover | C51: 14 | D51: 26 | E51: =$B$4+7*(C51-1) -> 46412 | F51: Evergreen model, runbooks, BAU handover, SOC 2 Type I / Type II start
A53: Steering Committee gates (signed)
A54: Gate | B54: Week | C54: Name | D54: Exit criteria | E54: Gate task | F54: Gate date (Fri)
A55: G1 | B55: 6 | C55: Mobilize exit | D55: Charter and interim budget approved; long-lead partners booked; D-01 regulatory scope signed (custodial/MSB answered); risk appetite approved; threat model and CSF 2.0 gap baseline issued; zero EKS 1.31 clusters; agentless AWS detection services in 100% of accounts/Regions; interim 24/7 on-call and paging live; break-glass tested; interim multisig hardening complete. | E55: PM-08 | F55: =$B$4+7*(B55-1)+4 -> 46360
A56: G2 | B56: 15 | C56: Design complete & critical exposures closed | D56: ARB #1 and #2 approvals; org guardrails live in all OUs; Conditional Access enforced with phishing-resistant admin MFA; telemetry sources 100% onboarded; MDR 24/7 live; on-chain monitors live; custody policy engine configured; no AL2 EKS nodes; Inspector CIS baseline captured; policies v1.0 approved; control matrix, TPRM and risk/exception registers live. | E56: PM-10 | F56: =$B$4+7*(B56-1)+4 -> 46423
A57: G3 | B57: 20 | C57: Build complete | D57: 100% upgrade/admin on-chain roles under multisig + timelock (pause guardian per role matrix); detection waves 1-2 in production; pentest executed; smart-contract audit preliminary report received; Kubernetes baseline enforced; all clusters on 1.36; DR restore test passed; SOC 2 readiness assessment complete. | E57: PM-11 | F57: =$B$4+7*(B57-1)+4 -> 46458
A58: G4 | B58: 26 | C58: Program close & BAU acceptance | D58: BAU handover signed; KPIs at target or exceptions approved; SOC 2 Type I fieldwork done; Type II engagement letter signed with period dates and first in-period evidence for every recurring control; IA report reviewed by Board/Audit Committee; bug bounty live; AL2 count 0 or approved exceptions; review-log items closed or formally deferred. | E58: PM-16 | F58: =$B$4+7*(B58-1)+4 -> 46500

Sheet Project Plan
A1: Project Plan - 150 tasks; End wk, dates and checks are formulas; Gantt W0-W26 via conditional formatting
A2: Status column has a dropdown. Dependency check = every dependency ends before this task starts. Weeks 9-10 shaded = production change freeze.
A4: Legend: | B4: HD OS & Container Hardening | C4: ID Identity Hardening | D4: MR Security Monitoring, Response & Resilience | E4: BC Blockchain Security | F4: GC Governance & Compliance | G4: PM Program Management & Sustainment
W5: =Overview!$B$4+7*(W6-1) -> 46314 | X5: =Overview!$B$4+7*(X6-1) -> 46321 | Y5: =Overview!$B$4+7*(Y6-1) -> 46328 | Z5: =Overview!$B$4+7*(Z6-1) -> 46335 | AA5: =Overview!$B$4+7*(AA6-1) -> 46342 | AB5: =Overview!$B$4+7*(AB6-1) -> 46349 | AC5: =Overview!$B$4+7*(AC6-1) -> 46356 | AD5: =Overview!$B$4+7*(AD6-1) -> 46363 | ... AW5: =Overview!$B$4+7*(AW6-1) -> 46496
A6: ID | B6: Phase | C6: Workstream | D6: Task | E6: Key activities | F6: Start wk | G6: Duration (wks) | H6: End wk | I6: Dependencies (IDs) | J6: Latest dependency end | K6: Dependency check | L6: End-week check | M6: Start date | N6: End date | O6: Lead role | P6: Supporting roles | Q6: Skill set required | R6: Deliverable | S6: Benchmark / standard reference | T6: Status | U6: Immediate action (owner / deadline) | V6: Support (delimited) | W6: 0 | X6: 1 | Y6: 2 | Z6: 3 | AA6: 4 | AB6: 5 | AC6: 6 | AD6: 7 | AE6: 8 | AF6: 9 | AG6: 10 | AH6: 11 | AI6: 12 | AJ6: 13 | AK6: 14 | AL6: 15 | AM6: 16 | AN6: 17 | AO6: 18 | AP6: 19 | AQ6: 20 | AR6: 21 | AS6: 22 | AT6: 23 | AU6: 24 | AV6: 25 | AW6: 26
A7: PM-01 | B7: P0 Immediate (pre-program) | C7: PM | D7: Stand up Immediate-actions cell and name owners | E7: Daily 15-min stand-up for Immediate actions; owners/deadlines confirmed by exec sponsor | F7: 0 | G7: 1 | H7: =F7+G7-1 -> 0 | J7: =IF(I7="","",SUMPRODUCT(MAX(ISNUMBER(SEARCH(","&$A$7:$A$156&",",","&SUBSTITUTE(I7," ","")&","))*$H$7:$H$156))) | K7: =IF(I7="","OK",IF(F7>J7,"OK","VIOLATION")) -> OK | L7: =IF(H7<=26,"OK","LATE") -> OK | M7: =Overview!$B$4+7*(F7-1) -> 46314 | N7: =Overview!$B$4+7*(H7-1)+4 -> 46318 | O7: PL | P7: CSE; ISE; BSE; GRC | Q7: Program management | R7: Immediate-actions tracker with owners | S7: NIST CSF 2.0 GV.RR | T7: Not started | U7: Owner PL - Fri 23 Oct 2026 | V7: =";"&SUBSTITUTE(P7," ","")&";" -> ;CSE;ISE;BSE;GRC;
A8: ID-00 | B8: P0 Immediate (pre-program) | C8: ID | D8: Order FIDO2 security keys and signer hardware wallets | E8: Device-bound FIDO2 keys (approved models/AAGUIDs) for break-glass, admins, spares; clear-signing hardware wallets for on-chain signers | F8: 0 | G8: 1 | H8: =F8+G8-1 -> 0 | J8: =IF(I8="","",SUMPRODUCT(MAX(ISNUMBER(SEARCH(","&$A$7:$A$156&",",","&SUBSTITUTE(I8," ","")&","))*$H$7:$H$156))) | K8: =IF(I8="","OK",IF(F8>J8,"OK","VIOLATION")) -> OK | L8: =IF(H8<=26,"OK","LATE") -> OK | M8: =Overview!$B$4+7*(F8-1) -> 46314 | N8: =Overview!$B$4+7*(H8-1)+4 -> 46318 | O8: PL | P8: ISE; BSE | Q8: Procurement | R8: Purchase orders; delivery tracked to W3 | S8: Entra passkey (FIDO2) docs; SEAL Wallet Security | T8: Not started | U8: Owner PL - order by Fri 23 Oct 2026 | V8: =";"&SUBSTITUTE(P8," ","")&";" -> ;ISE;BSE;
A9: GC-01 | B9: P0 Immediate (pre-program) | C9: GC | D9: Regulatory scope go/no-go (D-01) with counsel engaged in W0 | E9: Counsel opinion: MiCA Art 61 reverse solicitation/ESMA guidelines; DORA (only via MiCA authorisation); PCI DSS (no CHD); US: custodial vs non-custodial, FinCEN MSB status, state money-transmission, OFAC, FTC Safeguards Rule, NYDFS; any 'yes' triggers re-plan at Gate 1 | F9: 0 | G9: 5 | H9: =F9+G9-1 -> 4 | J9: =IF(I9="","",SUMPRODUCT(MAX(ISNUMBER(SEARCH(","&$A$7:$A$156&",",","&SUBSTITUTE(I9," ","")&","))*$H$7:$H$156))) | K9: =IF(I9="","OK",IF(F9>J9,"OK","VIOLATION")) -> OK | L9: =IF(H9<=26,"OK","LATE") -> OK | M9: =Overview!$B$4+7*(F9-1) -> 46314 | N9: =Overview!$B$4+7*(H9-1)+4 -> 46346 | O9: GRC | P9: LEG; PL | Q9: Regulatory analysis | R9: Signed regulatory scope memo (D-01) | S9: MiCA Art 61/143; ESMA35-1872330276-2030; DORA Art 2(1)(f); PCI DSS v4.0.1; FinCEN FIN-2019-G001; OFAC VC guidance | T9: Not started | U9: Owner GRC - signed by Steering Fri 20 Nov 2026 (W4) | V9: =";"&SUBSTITUTE(P9," ","")&";" -> ;LEG;PL;
A10: BC-01 | B10: P0 Immediate (pre-program) | C10: BC | D10: Alpenglow readiness confirmation from staking provider (activates 21 Oct 2026) | E10: By Tue 20 Oct: written confirmation of BLS pubkey registration, VAT funding (0.8 SOL burned PER EPOCH above rent-exempt, auto top-up), Agave-4.3.0-based client (Firedancer/Frankendancer unsupported during migration), VAT pass-through in commission; pre-approved re-delegation fallback; verify rewards for epochs 1065-1066 | F10: 0 | G10: 2 | H10: =F10+G10-1 -> 1 | J10: =IF(I10="","",SUMPRODUCT(MAX(ISNUMBER(SEARCH(","&$A$7:$A$156&",",","&SUBSTITUTE(I10," ","")&","))*$H$7:$H$156))) | K10: =IF(I10="","OK",IF(F10>J10,"OK","VIOLATION")) -> OK | L10: =IF(H10<=26,"OK","LATE") -> OK | M10: =Overview!$B$4+7*(F10-1) -> 46314 | N10: =Overview!$B$4+7*(H10-1)+4 -> 46325 | O10: BSE | Q10: Solana staking, vendor management | R10: Provider confirmation + reward-delta check note | S10: solana.com/upgrades/alpenglow; BSSC NOS v2 | T10: Not started | U10: Owner BSE - confirmation Tue 20 Oct 2026; reward check Fri 30 Oct 2026 | V10: =";"&SUBSTITUTE(P10," ","")&";" -> ;;
A11: BC-02 | B11: P0 Immediate (pre-program) | C11: BC | D11: Staking authority inventory and on-chain verification | E11: Every Ethereum validator: credential type (0x00/0x01/0x02) and that 0x01/0x02 point to our custody address; plan 0x00 change signed by us; provider-owned 0x01 -> exit/re-deposit via BC-19; Solana stake withdraw authority = our MPC vault; interim alerts on EIP-7002 requests and authority changes | F11: 0 | G11: 2 | H11: =F11+G11-1 -> 1 | J11: =IF(I11="","",SUMPRODUCT(MAX(ISNUMBER(SEARCH(","&$A$7:$A$156&",",","&SUBSTITUTE(I11," ","")&","))*$H$7:$H$156))) | K11: =IF(I11="","OK",IF(F11>J11,"OK","VIOLATION")) -> OK | L11: =IF(H11<=26,"OK","LATE") -> OK | M11: =Overview!$B$4+7*(F11-1) -> 46314 | N11: =Overview!$B$4+7*(H11-1)+4 -> 46325 | O11: BSE | P11: CSO | Q11: Ethereum/Solana staking internals | R11: Staking authority register (signed) | S11: EIP-7002; EIP-7251; Anza delegate-stake & vote-account docs; CCSS v9 | T11: Not started | U11: Owner BSE - Fri 30 Oct 2026 | V11: =";"&SUBSTITUTE(P11," ","")&";" -> ;CSO;
A12: BC-22 | B12: P0 Immediate (pre-program) | C12: BC | D12: Interim multisig hardening (Drift-pattern exposure) | E12: Raise Safe/Squads thresholds to policy minimum; enable Squads time lock on upgrade authorities; ban durable-nonce/pre-signed admin txs; confirm signer set and devices; emergency CUKC path | F12: 0 | G12: 3 | H12: =F12+G12-1 -> 2 | J12: =IF(I12="","",SUMPRODUCT(MAX(ISNUMBER(SEARCH(","&$A$7:$A$156&",",","&SUBSTITUTE(I12," ","")&","))*$H$7:$H$156))) | K12: =IF(I12="","OK",IF(F12>J12,"OK","VIOLATION")) -> OK | L12: =IF(H12<=26,"OK","LATE") -> OK | M12: =Overview!$B$4+7*(F12-1) -> 46314 | N12: =Overview!$B$4+7*(H12-1)+4 -> 46332 | O12: BSE | P12: CSO | Q12: Safe/Squads operations | R12: Interim multisig hardening record | S12: SEAL Multisig framework; Squads v4 docs | T12: Not started | U12: Owner BSE - Fri 6 Nov 2026 | V12: =";"&SUBSTITUTE(P12," ","")&";" -> ;CSO;
A13: HD-01 | B13: P0 Immediate (pre-program) | C13: HD | D13: EOL inventory: AL2 hosts/AMIs, EKS versions and upgradePolicy (D-10) | E13: Org-wide Config query + SSM inventory + EKS API: AL2 instances/AMIs/launch templates, ECS AMIs, cluster versions (1.31-1.37), node AMI types, per-cluster upgradePolicy (STANDARD auto-upgrades at end of standard support; EXTENDED costs $0.60/cluster-hr); D-10 recommendation | F13: 0 | G13: 2 | H13: =F13+G13-1 -> 1 | J13: =IF(I13="","",SUMPRODUCT(MAX(ISNUMBER(SEARCH(","&$A$7:$A$156&",",","&SUBSTITUTE(I13," ","")&","))*$H$7:$H$156))) | K13: =IF(I13="","OK",IF(F13>J13,"OK","VIOLATION")) -> OK | L13: =IF(H13<=26,"OK","LATE") -> OK | M13: =Overview!$B$4+7*(F13-1) -> 46314 | N13: =Overview!$B$4+7*(H13-1)+4 -> 46325 | O13: CSE | P13: ENG | Q13: AWS Config, EKS | R13: EOL register + D-10 recommendation | S13: AL2 FAQ (EOS 2026-06-30); EKS kubernetes-versions page; SH EKS.2/EKS.9 | T13: Not started | U13: Owner CSE - Fri 30 Oct 2026 | V13: =";"&SUBSTITUTE(P13," ","")&";" -> ;ENG;
A14: MR-01 | B14: P0 Immediate (pre-program) | C14: MR | D14: Enable agentless AWS detection services org-wide (independent of SIEM) | E14: Delegated admin; GuardDuty all accounts/Regions incl. EKS audit-log monitoring, S3 Protection, Malware Protection for EC2; Security Hub CSPM (FSBP + CIS AWS v5.0.0) and Security Hub; Inspector EC2/ECR/Lambda; Access Analyzer external + internal; Config all Regions; org CloudTrail. Runtime agents follow in MR-01B | F14: 0 | G14: 2 | H14: =F14+G14-1 -> 1 | J14: =IF(I14="","",SUMPRODUCT(MAX(ISNUMBER(SEARCH(","&$A$7:$A$156&",",","&SUBSTITUTE(I14," ","")&","))*$H$7:$H$156))) | K14: =IF(I14="","OK",IF(F14>J14,"OK","VIOLATION")) -> OK | L14: =IF(H14<=26,"OK","LATE") -> OK | M14: =Overview!$B$4+7*(F14-1) -> 46314 | N14: =Overview!$B$4+7*(H14-1)+4 -> 46325 | O14: CSE | P14: ISE | Q14: AWS security services | R14: Detection services coverage report | S14: SH GuardDuty.1/.5/.8/.10, Config.1, CloudTrail.1, Inspector.1-.4; CIS AWS v5.0.0 | T14: Not started | U14: Owner CSE - Fri 30 Oct 2026 | V14: =";"&SUBSTITUTE(P14," ","")&";" -> ;ISE;
A15: MR-21 | B15: P0 Immediate (pre-program) | C15: MR | D15: Archive Entra and B2C logs before they expire | E15: Diagnostic settings for Entra (sign-in incl. non-interactive/SP/MI, audit, risk, Graph activity) and B2C (via Azure Lighthouse) to immutable storage; Entra keeps only 30 days on P1/P2 | F15: 0 | G15: 2 | H15: =F15+G15-1 -> 1 | J15: =IF(I15="","",SUMPRODUCT(MAX(ISNUMBER(SEARCH(","&$A$7:$A$156&",",","&SUBSTITUTE(I15," ","")&","))*$H$7:$H$156))) | K15: =IF(I15="","OK",IF(F15>J15,"OK","VIOLATION")) -> OK | L15: =IF(H15<=26,"OK","LATE") -> OK | M15: =Overview!$B$4+7*(F15-1) -> 46314 | N15: =Overview!$B$4+7*(H15-1)+4 -> 46325 | O15: CSE | P15: ISE | Q15: Azure Monitor | R15: Log archive live (evidence preserved) | S15: Entra data-retention reference; B2C Azure Monitor docs | T15: Not started | U15: Owner CSE - Fri 30 Oct 2026 | V15: =";"&SUBSTITUTE(P15," ","")&";" -> ;ISE;
A16: MR-00 | B16: P0 Immediate (pre-program) | C16: MR | D16: Interim 24/7 coverage until MDR is live | E16: On-call rota incl. holiday weeks; paging tool; GuardDuty/Security Hub/Falcon high-severity alerts via EventBridge/SNS to pager; interim IR runbook (severity, contacts, SEAL 911, counsel) | F16: 0 | G16: 2 | H16: =F16+G16-1 -> 1 | J16: =IF(I16="","",SUMPRODUCT(MAX(ISNUMBER(SEARCH(","&$A$7:$A$156&",",","&SUBSTITUTE(I16," ","")&","))*$H$7:$H$156))) | K16: =IF(I16="","OK",IF(F16>J16,"OK","VIOLATION")) -> OK | L16: =IF(H16<=26,"OK","LATE") -> OK | M16: =Overview!$B$4+7*(F16-1) -> 46314 | N16: =Overview!$B$4+7*(H16-1)+4 -> 46325 | O16: ISE | P16: BSE | Q16: SOC operations | R16: On-call rota + paging + interim runbook | S16: NIST SP 800-61r3; CSF 2.0 DE.CM/RS.MA | T16: Not started | U16: Owner ISE - Fri 30 Oct 2026 | V16: =";"&SUBSTITUTE(P16," ","")&";" -> ;BSE;
A17: ID-01 | B17: P0 Immediate (pre-program) | C17: ID | D17: Break-glass accounts before any Conditional Access change | E17: 2 cloud-only permanent Global Admins with FIDO2/certificate auth distinct from admins; excluded from blocking CA; Sev-0 sign-in alert via Log Analytics to pager until Splunk; AWS break-glass: management-account root (2 FIDO2) + emergency role with alarm; test every 90 days | F17: 0 | G17: 2 | H17: =F17+G17-1 -> 1 | J17: =IF(I17="","",SUMPRODUCT(MAX(ISNUMBER(SEARCH(","&$A$7:$A$156&",",","&SUBSTITUTE(I17," ","")&","))*$H$7:$H$156))) | K17: =IF(I17="","OK",IF(F17>J17,"OK","VIOLATION")) -> OK | L17: =IF(H17<=26,"OK","LATE") -> OK | M17: =Overview!$B$4+7*(F17-1) -> 46314 | N17: =Overview!$B$4+7*(H17-1)+4 -> 46325 | O17: ISE | Q17: Entra ID, AWS IAM | R17: Break-glass runbook + test record | S17: Microsoft emergency-access guidance; mandatory Azure MFA; SH IAM.4/IAM.6 | T17: Not started | U17: Owner ISE - Fri 30 Oct 2026 | V17: =";"&SUBSTITUTE(P17," ","")&";" -> ;;
A18: ID-02 | B18: P0 Immediate (pre-program) | C18: ID | D18: Azure MFA Phase 2 (enforced): move user-run automation to workload identities | E18: Find CLI/PowerShell/IaC/SDK automation running as users (breaking now); migrate to managed identities/service principals with federated credentials (exempt) | F18: 0 | G18: 3 | H18: =F18+G18-1 -> 2 | J18: =IF(I18="","",SUMPRODUCT(MAX(ISNUMBER(SEARCH(","&$A$7:$A$156&",",","&SUBSTITUTE(I18," ","")&","))*$H$7:$H$156))) | K18: =IF(I18="","OK",IF(F18>J18,"OK","VIOLATION")) -> OK | L18: =IF(H18<=26,"OK","LATE") -> OK | M18: =Overview!$B$4+7*(F18-1) -> 46314 | N18: =Overview!$B$4+7*(H18-1)+4 -> 46332 | O18: ISE | P18: ENG | Q18: Entra workload identities | R18: Automation identity register; remediated pipelines | S18: Microsoft mandatory MFA (Phase 2) | T18: Not started | U18: Owner ISE - Fri 6 Nov 2026 | V18: =";"&SUBSTITUTE(P18," ","")&";" -> ;ENG;
A19: PM-02 | B19: P1 Mobilize | C19: PM | D19: Program charter, scope, success criteria and Steering ToR | E19: Charter; scope/out-of-scope; Steering membership and decision rights | F19: 1 | G19: 1 | H19: =F19+G19-1 -> 1 | I19: PM-01 | J19: =IF(I19="","",SUMPRODUCT(MAX(ISNUMBER(SEARCH(","&$A$7:$A$156&",",","&SUBSTITUTE(I19," ","")&","))*$H$7:$H$156))) -> 0 | K19: =IF(I19="","OK",IF(F19>J19,"OK","VIOLATION")) -> OK | L19: =IF(H19<=26,"OK","LATE") -> OK | M19: =Overview!$B$4+7*(F19-1) -> 46321 | N19: =Overview!$B$4+7*(H19-1)+4 -> 46325 | O19: PL | P19: GRC; PMC | Q19: Program management | R19: Signed charter | S19: NIST CSF 2.0 GV.OC/GV.RR | T19: Not started | V19: =";"&SUBSTITUTE(P19," ","")&";" -> ;GRC;PMC;
A20: PM-02A | B20: P0 Immediate (pre-program) | C20: PM | D20: Interim budget approval for long-lead commitments (D-17) | E20: CFO approves envelope for partners, 8 contractors (6.5 FTE peak) and licences booked in W1-2 (D-17); full budget at Gate 1 | F20: 0 | G20: 1 | H20: =F20+G20-1 -> 0 | J20: =IF(I20="","",SUMPRODUCT(MAX(ISNUMBER(SEARCH(","&$A$7:$A$156&",",","&SUBSTITUTE(I20," ","")&","))*$H$7:$H$156))) | K20: =IF(I20="","OK",IF(F20>J20,"OK","VIOLATION")) -> OK | L20: =IF(H20<=26,"OK","LATE") -> OK | M20: =Overview!$B$4+7*(F20-1) -> 46314 | N20: =Overview!$B$4+7*(H20-1)+4 -> 46318 | O20: PL | P20: PMC | Q20: Finance | R20: Approved interim budget | S20: NIST CSF 2.0 GV.RR-03 | T20: Not started | V20: =";"&SUBSTITUTE(P20," ","")&";" -> ;PMC;
A21: PM-03 | B21: P1 Mobilize | C21: PM | D21: Book long-lead partners and contractors (weeks 1-2) | E21: Sign: smart-contract auditor (slot W16-W19, sized by nSLOC; >4k nSLOC -> parallel teams), SOC 2 CPA, independent readiness assessor, MDR, pentest (W18), GRC platform trial, contractors (KHE/CPE/DET/IDC/CSO/BSC/GRCC/PMC) | F21: 1 | G21: 2 | H21: =F21+G21-1 -> 2 | I21: PM-01, PM-02A | J21: =IF(I21="","",SUMPRODUCT(MAX(ISNUMBER(SEARCH(","&$A$7:$A$156&",",","&SUBSTITUTE(I21," ","")&","))*$H$7:$H$156))) -> 0 | K21: =IF(I21="","OK",IF(F21>J21,"OK","VIOLATION")) -> OK | L21: =IF(H21<=26,"OK","LATE") -> OK | M21: =Overview!$B$4+7*(F21-1) -> 46321 | N21: =Overview!$B$4+7*(H21-1)+4 -> 46332 | O21: PL | P21: GRC; BSE; ISE; PMC | Q21: Procurement | R21: Signed SOWs / booked slots | S21: NIST CSF 2.0 GV.SC | T21: Not started | V21: =";"&SUBSTITUTE(P21," ","")&";" -> ;GRC;BSE;ISE;PMC;
A22: PM-04 | B22: P1 Mobilize | C22: PM | D22: Risk appetite statement and tolerances (D-14) | E22: On-chain loss tolerance, hot-wallet caps, velocity limits, max time-to-pause, patch SLAs, exception limits (max 90 days, one renewal) | F22: 2 | G22: 2 | H22: =F22+G22-1 -> 3 | I22: PM-02 | J22: =IF(I22="","",SUMPRODUCT(MAX(ISNUMBER(SEARCH(","&$A$7:$A$156&",",","&SUBSTITUTE(I22," ","")&","))*$H$7:$H$156))) -> 1 | K22: =IF(I22="","OK",IF(F22>J22,"OK","VIOLATION")) -> OK | L22: =IF(H22<=26,"OK","LATE") -> OK | M22: =Overview!$B$4+7*(F22-1) -> 46328 | N22: =Overview!$B$4+7*(H22-1)+4 -> 46339 | O22: PL | P22: GRC; BSE | Q22: Risk management | R22: Approved risk appetite statement | S22: NIST CSF 2.0 GV.RM; ISO 27001 6.1 | T22: Not started | V22: =";"&SUBSTITUTE(P22," ","")&";" -> ;GRC;BSE;
A23: PM-07 | B23: P1 Mobilize | C23: PM | D23: RACI, RAID log, interim exception log and operating rhythm | E23: RACI; weekly status; RAID log; interim exception log; change calendar incl. W9-W10 freeze | F23: 2 | G23: 1 | H23: =F23+G23-1 -> 2 | I23: PM-02 | J23: =IF(I23="","",SUMPRODUCT(MAX(ISNUMBER(SEARCH(","&$A$7:$A$156&",",","&SUBSTITUTE(I23," ","")&","))*$H$7:$H$156))) -> 1 | K23: =IF(I23="","OK",IF(F23>J23,"OK","VIOLATION")) -> OK | L23: =IF(H23<=26,"OK","LATE") -> OK | M23: =Overview!$B$4+7*(F23-1) -> 46328 | N23: =Overview!$B$4+7*(H23-1)+4 -> 46332 | O23: PMC | P23: PL | Q23: PMO | R23: RACI + RAID + interim exception log | S23: ISO 27001 5.3 | T23: Not started | V23: =";"&SUBSTITUTE(P23," ","")&";" -> ;PL;
A24: PM-05 | B24: P1 Mobilize | C24: PM | D24: Threat model (cloud, identity, on-chain, supply chain, insider) | E24: Signer-UI compromise (Bybit), durable-nonce pre-signing (Drift), EIP-7702 delegation phishing, DPRK IT workers, domain/front-end hijack, CI/CD poisoning, ransomware, B2C account takeover, helpdesk reset fraud | F24: 3 | G24: 3 | H24: =F24+G24-1 -> 5 | I24: PM-02 | J24: =IF(I24="","",SUMPRODUCT(MAX(ISNUMBER(SEARCH(","&$A$7:$A$156&",",","&SUBSTITUTE(I24," ","")&","))*$H$7:$H$156))) -> 1 | K24: =IF(I24="","OK",IF(F24>J24,"OK","VIOLATION")) -> OK | L24: =IF(H24<=26,"OK","LATE") -> OK | M24: =Overview!$B$4+7*(F24-1) -> 46335 | N24: =Overview!$B$4+7*(H24-1)+4 -> 46353 | O24: PL | P24: CSE; ISE; BSE | Q24: Threat modelling | R24: Threat model + prioritised scenarios | S24: MITRE ATT&CK; OWASP SC Top 10 2026; SEAL Frameworks | T24: Not started | V24: =";"&SUBSTITUTE(P24," ","")&";" -> ;CSE;ISE;BSE;
A25: PM-06 | B25: P1 Mobilize | C25: PM | D25: Baseline gap assessment (CSF 2.0 current/target profile) | E25: CSF 2.0 profiles; CIS Controls v8.1 IG1/IG2; Security Hub CSPM baseline; Inspector; identity and on-chain gaps | F25: 3 | G25: 3 | H25: =F25+G25-1 -> 5 | I25: PM-02, MR-01 | J25: =IF(I25="","",SUMPRODUCT(MAX(ISNUMBER(SEARCH(","&$A$7:$A$156&",",","&SUBSTITUTE(I25," ","")&","))*$H$7:$H$156))) -> 1 | K25: =IF(I25="","OK",IF(F25>J25,"OK","VIOLATION")) -> OK | L25: =IF(H25<=26,"OK","LATE") -> OK | M25: =Overview!$B$4+7*(F25-1) -> 46335 | N25: =Overview!$B$4+7*(H25-1)+4 -> 46353 | O25: GRC | Q25: Assessment | R25: Gap assessment + baseline KPIs | S25: NIST CSF 2.0; CIS Controls v8.1 | T25: Not started | V25: =";"&SUBSTITUTE(P25," ","")&";" -> ;;
A26: GC-02 | B26: P1 Mobilize | C26: GC | D26: Governance operating model and forum ToRs | E26: Steering, ARB (fortnightly), CUKC (fortnightly + ad hoc, internal chair), CAB (weekly), IR forum, independent assurance; three lines; decision rights | F26: 3 | G26: 2 | H26: =F26+G26-1 -> 4 | I26: PM-02, PM-07 | J26: =IF(I26="","",SUMPRODUCT(MAX(ISNUMBER(SEARCH(","&$A$7:$A$156&",",","&SUBSTITUTE(I26," ","")&","))*$H$7:$H$156))) -> 2 | K26: =IF(I26="","OK",IF(F26>J26,"OK","VIOLATION")) -> OK | L26: =IF(H26<=26,"OK","LATE") -> OK | M26: =Overview!$B$4+7*(F26-1) -> 46335 | N26: =Overview!$B$4+7*(H26-1)+4 -> 46346 | O26: PL | P26: GRC | Q26: Governance design | R26: Governance model + ToRs | S26: NIST CSF 2.0 GV.RR; ISO 27001 5.1-5.3; IIA Three Lines | T26: Not started | V26: =";"&SUBSTITUTE(P26," ","")&";" -> ;GRC;
A27: MR-02 | B27: P1 Mobilize | C27: MR | D27: MDR selection and contract (D-03) | E27: Falcon Complete Next-Gen MDR vs Splunk-integrated MDR; named 24/7 owner per alert source (incl. Splunk notables); acknowledge/contain SLAs; authority to disable accounts/isolate hosts; escalation to CUKC | F27: 3 | G27: 2 | H27: =F27+G27-1 -> 4 | I27: PM-03 | J27: =IF(I27="","",SUMPRODUCT(MAX(ISNUMBER(SEARCH(","&$A$7:$A$156&",",","&SUBSTITUTE(I27," ","")&","))*$H$7:$H$156))) -> 2 | K27: =IF(I27="","OK",IF(F27>J27,"OK","VIOLATION")) -> OK | L27: =IF(H27<=26,"OK","LATE") -> OK | M27: =Overview!$B$4+7*(F27-1) -> 46335 | N27: =Overview!$B$4+7*(H27-1)+4 -> 46346 | O27: ISE | P27: PL | Q27: SOC operations, vendor evaluation | R27: Signed MDR contract (D-03) | S27: NIST SP 800-61r3; CSF 2.0 DE/RS | T27: Not started | V27: =";"&SUBSTITUTE(P27," ","")&";" -> ;PL;
A28: MR-23 | B28: P1 Mobilize | C28: MR | D28: Security services cost review before trials end (D-15) | E28: Security Hub per-resource pricing, GuardDuty/Inspector, EKS extended support, Splunk ingest sizing; plan selection | F28: 3 | G28: 2 | H28: =F28+G28-1 -> 4 | I28: MR-01 | J28: =IF(I28="","",SUMPRODUCT(MAX(ISNUMBER(SEARCH(","&$A$7:$A$156&",",","&SUBSTITUTE(I28," ","")&","))*$H$7:$H$156))) -> 1 | K28: =IF(I28="","OK",IF(F28>J28,"OK","VIOLATION")) -> OK | L28: =IF(H28<=26,"OK","LATE") -> OK | M28: =Overview!$B$4+7*(F28-1) -> 46335 | N28: =Overview!$B$4+7*(H28-1)+4 -> 46346 | O28: PMC | Q28: Cost analysis | R28: D-15 cost decision | S28: Security Hub pricing; EKS pricing | T28: Not started | V28: =";"&SUBSTITUTE(P28," ","")&";" -> ;;
A29: GC-03 | B29: P1 Mobilize | C29: GC | D29: GRC platform selection (D-04) | E29: Vanta/Drata/Secureframe: AWS, Entra (licence/role needs), GitHub, HRIS integrations; pricing | F29: 3 | G29: 2 | H29: =F29+G29-1 -> 4 | I29: PM-03 | J29: =IF(I29="","",SUMPRODUCT(MAX(ISNUMBER(SEARCH(","&$A$7:$A$156&",",","&SUBSTITUTE(I29," ","")&","))*$H$7:$H$156))) -> 2 | K29: =IF(I29="","OK",IF(F29>J29,"OK","VIOLATION")) -> OK | L29: =IF(H29<=26,"OK","LATE") -> OK | M29: =Overview!$B$4+7*(F29-1) -> 46335 | N29: =Overview!$B$4+7*(H29-1)+4 -> 46346 | O29: GRCC | P29: GRC | Q29: GRC tooling | R29: GRC platform decision (D-04) | S29: AICPA TSC 2017 (2022 PoF) | T29: Not started | V29: =";"&SUBSTITUTE(P29," ","")&";" -> ;GRC;
A30: GC-18 | B30: P1 Mobilize | C30: GC | D30: Business impact analysis (BIA) | E30: Critical services, dependencies (custody, staking, RPC, Splunk), RTO/RPO, tolerable on-chain downtime | F30: 4 | G30: 2 | H30: =F30+G30-1 -> 5 | I30: PM-02 | J30: =IF(I30="","",SUMPRODUCT(MAX(ISNUMBER(SEARCH(","&$A$7:$A$156&",",","&SUBSTITUTE(I30," ","")&","))*$H$7:$H$156))) -> 1 | K30: =IF(I30="","OK",IF(F30>J30,"OK","VIOLATION")) -> OK | L30: =IF(H30<=26,"OK","LATE") -> OK | M30: =Overview!$B$4+7*(F30-1) -> 46342 | N30: =Overview!$B$4+7*(H30-1)+4 -> 46353 | O30: GRC | P30: PL; CSE; BSE | Q30: BC planning | R30: Approved BIA | S30: NIST CSF 2.0 ID.AM/RC; ISO 27001 A.5.30 | T30: Not started | V30: =";"&SUBSTITUTE(P30," ","")&";" -> ;PL;CSE;BSE;
A31: GC-20 | B31: P1 Mobilize | C31: GC | D31: Board oversight of cyber risk | E31: Board/Audit Committee terms; quarterly cyber report format; first briefing | F31: 5 | G31: 2 | H31: =F31+G31-1 -> 6 | I31: PM-02 | J31: =IF(I31="","",SUMPRODUCT(MAX(ISNUMBER(SEARCH(","&$A$7:$A$156&",",","&SUBSTITUTE(I31," ","")&","))*$H$7:$H$156))) -> 1 | K31: =IF(I31="","OK",IF(F31>J31,"OK","VIOLATION")) -> OK | L31: =IF(H31<=26,"OK","LATE") -> OK | M31: =Overview!$B$4+7*(F31-1) -> 46349 | N31: =Overview!$B$4+7*(H31-1)+4 -> 46360 | O31: PL | P31: GRC | Q31: Board reporting | R31: Board reporting cadence + first pack | S31: SOC 2 CC1.2; NIST CSF 2.0 GV.OV | T31: Not started | V31: =";"&SUBSTITUTE(P31," ","")&";" -> ;GRC;
A32: GC-08 | B32: P1 Mobilize | C32: GC | D32: Change management / CAB live | E32: CAB ToR; change types; emergency CAB; freeze rules; link to CUKC for on-chain changes | F32: 5 | G32: 2 | H32: =F32+G32-1 -> 6 | I32: GC-02 | J32: =IF(I32="","",SUMPRODUCT(MAX(ISNUMBER(SEARCH(","&$A$7:$A$156&",",","&SUBSTITUTE(I32," ","")&","))*$H$7:$H$156))) -> 4 | K32: =IF(I32="","OK",IF(F32>J32,"OK","VIOLATION")) -> OK | L32: =IF(H32<=26,"OK","LATE") -> OK | M32: =Overview!$B$4+7*(F32-1) -> 46349 | N32: =Overview!$B$4+7*(H32-1)+4 -> 46360 | O32: PMC | P32: PL | Q32: ITSM | R32: CAB procedure live | S32: SOC 2 CC8.1; ISO 27001 A.8.32 | T32: Not started | V32: =";"&SUBSTITUTE(P32," ","")&";" -> ;PL;
A33: PM-08 | B33: P1 Mobilize | C33: PM | D33: Gate 1 - Mobilize exit (Steering, W6) | E33: Criteria in Overview: charter + budget; partners booked; D-01 signed; risk appetite; threat model + gap baseline; 1.31 clusters gone; agentless detection 100% accounts; interim 24/7 live; break-glass tested; interim multisig hardening done | F33: 6 | G33: 1 | H33: =F33+G33-1 -> 6 | I33: PM-02A, PM-03, PM-04, PM-05, PM-06, GC-01, GC-02, HD-02, MR-01, MR-00, ID-01, BC-22 | J33: =IF(I33="","",SUMPRODUCT(MAX(ISNUMBER(SEARCH(","&$A$7:$A$156&",",","&SUBSTITUTE(I33," ","")&","))*$H$7:$H$156))) -> 5 | K33: =IF(I33="","OK",IF(F33>J33,"OK","VIOLATION")) -> OK | L33: =IF(H33<=26,"OK","LATE") -> OK | M33: =Overview!$B$4+7*(F33-1) -> 46356 | N33: =Overview!$B$4+7*(H33-1)+4 -> 46360 | O33: PL | P33: PMC | Q33: Governance | R33: Signed Gate 1 minute | S33: Program governance | T33: Not started | V33: =";"&SUBSTITUTE(P33," ","")&";" -> ;PMC;
A34: HD-04 | B34: P2 Assess & Design | C34: HD | D34: Org guardrail design: SCPs, RCPs, declarative policies, Control Tower controls | E34: SCP: protect CloudTrail/GuardDuty/Config, allow guardduty:SendSecurityTelemetry, region allowlist, block Identity Store writes; RCP data perimeter; declarative: IMDSv2 (hop limit set per launch template: EKS 1, ECS bridge 2), snapshot/AMI BPA, VPC BPA with exclusions, serial console, allowed images (audit mode first); EBS default encryption via Control Tower/Config + automation (not a declarative attribute) | F34: 3 | G34: 3 | H34: =F34+G34-1 -> 5 | I34: HD-01, PM-02 | J34: =IF(I34="","",SUMPRODUCT(MAX(ISNUMBER(SEARCH(","&$A$7:$A$156&",",","&SUBSTITUTE(I34," ","")&","))*$H$7:$H$156))) -> 1 | K34: =IF(I34="","OK",IF(F34>J34,"OK","VIOLATION")) -> OK | L34: =IF(H34<=26,"OK","LATE") -> OK | M34: =Overview!$B$4+7*(F34-1) -> 46335 | N34: =Overview!$B$4+7*(H34-1)+4 -> 46353 | O34: CSE | P34: KHE | Q34: AWS Organizations policy design | R34: Guardrail design (ARB pack) | S34: SH EC2.7/EC2.8/EC2.170/S3.1; CIS AWS v5.0.0; declarative policy docs | T34: Not started | V34: =";"&SUBSTITUTE(P34," ","")&";" -> ;KHE;
A35: HD-05 | B35: P2 Assess & Design | C35: HD | D35: Hardened image standard and EKS node OS decision (D-05) | E35: CIS AL2023 v1.0.0 L1; AL2023 vs Bottlerocket vs EKS Auto Mode for nodes; CIS EKS v2.0.0 / Auto Mode v1.0.0; Inspector CIS is x86_64-oriented and excludes Bottlerocket -> alternate evidence; CrowdStrike AL2023/Bottlerocket support in writing | F35: 2 | G35: 3 | H35: =F35+G35-1 -> 4 | I35: HD-01 | J35: =IF(I35="","",SUMPRODUCT(MAX(ISNUMBER(SEARCH(","&$A$7:$A$156&",",","&SUBSTITUTE(I35," ","")&","))*$H$7:$H$156))) -> 1 | K35: =IF(I35="","OK",IF(F35>J35,"OK","VIOLATION")) -> OK | L35: =IF(H35<=26,"OK","LATE") -> OK | M35: =Overview!$B$4+7*(F35-1) -> 46328 | N35: =Overview!$B$4+7*(H35-1)+4 -> 46346 | O35: KHE | P35: CSE | Q35: CIS benchmarks | R35: Image standard + D-05 | S35: CIS AL2023 v1.0.0; CIS Bottlerocket v1.0.0; CIS EKS v2.0.0 | T35: Not started | V35: =";"&SUBSTITUTE(P35," ","")&";" -> ;CSE;
A36: HD-24 | B36: P2 Assess & Design | C36: HD | D36: EKS upgrade-readiness matrix per version hop | E36: Per hop 1.32->1.36: add-ons, Karpenter/CA, deprecated APIs, cgroup v2, containerd 2.x, ingress controller replacement; rollback limits | F36: 2 | G36: 3 | H36: =F36+G36-1 -> 4 | I36: HD-01 | J36: =IF(I36="","",SUMPRODUCT(MAX(ISNUMBER(SEARCH(","&$A$7:$A$156&",",","&SUBSTITUTE(I36," ","")&","))*$H$7:$H$156))) -> 1 | K36: =IF(I36="","OK",IF(F36>J36,"OK","VIOLATION")) -> OK | L36: =IF(H36<=26,"OK","LATE") -> OK | M36: =Overview!$B$4+7*(F36-1) -> 46328 | N36: =Overview!$B$4+7*(H36-1)+4 -> 46346 | O36: KHE | P36: ENG | Q36: EKS | R36: Upgrade-readiness matrix | S36: EKS kubernetes-versions & upgrade docs | T36: Not started | V36: =";"&SUBSTITUTE(P36," ","")&";" -> ;ENG;
A37: HD-06 | B37: P2 Assess & Design | C37: HD | D37: SSM enrolment fleet-wide (prerequisite for runtime agents, Patch Manager, Inspector CIS) | E37: Instance profiles with AmazonSSMManagedInstanceCore + AmazonInspector2ManagedCisPolicy as primary path; DHMC where no profile (needs IMDSv2); per-instance IMDSv2 conversion where compatible; VPC endpoints | F37: 2 | G37: 5 | H37: =F37+G37-1 -> 6 | I37: HD-01 | J37: =IF(I37="","",SUMPRODUCT(MAX(ISNUMBER(SEARCH(","&$A$7:$A$156&",",","&SUBSTITUTE(I37," ","")&","))*$H$7:$H$156))) -> 1 | K37: =IF(I37="","OK",IF(F37>J37,"OK","VIOLATION")) -> OK | L37: =IF(H37<=26,"OK","LATE") -> OK | M37: =Overview!$B$4+7*(F37-1) -> 46328 | N37: =Overview!$B$4+7*(H37-1)+4 -> 46360 | O37: KHE | P37: ENG | Q37: Systems Manager | R37: >=95% EC2 managed by SSM | S37: SH SSM.1; Inspector CIS prerequisites | T37: Not started | V37: =";"&SUBSTITUTE(P37," ","")&";" -> ;ENG;
A38: HD-22 | B38: P2 Assess & Design | C38: HD | D38: Immutable log archive | E38: Log Archive account; S3 Object Lock; CloudTrail data events (critical S3/KMS/Secrets); log-file validation; KMS encryption; retention by log class | F38: 3 | G38: 3 | H38: =F38+G38-1 -> 5 | I38: MR-01 | J38: =IF(I38="","",SUMPRODUCT(MAX(ISNUMBER(SEARCH(","&$A$7:$A$156&",",","&SUBSTITUTE(I38," ","")&","))*$H$7:$H$156))) -> 1 | K38: =IF(I38="","OK",IF(F38>J38,"OK","VIOLATION")) -> OK | L38: =IF(H38<=26,"OK","LATE") -> OK | M38: =Overview!$B$4+7*(F38-1) -> 46335 | N38: =Overview!$B$4+7*(H38-1)+4 -> 46353 | O38: CPE | Q38: AWS logging | R38: Immutable log archive | S38: SH CloudTrail.2/.4, S3.5; CIS AWS v5.0.0 | T38: Not started | V38: =";"&SUBSTITUTE(P38," ","")&";" -> ;;
A39: HD-02 | B39: P1 Mobilize | C39: HD | D39: EKS end-of-support remediation (1.31 before 26 Nov; 1.34 per D-10 before 2 Dec) | E39: Controlled 1.31->1.32 upgrade (last AL2-AMI version); add-on compatibility; 1.34 clusters upgraded to 1.35 or upgradePolicy set to EXTENDED per D-10; rollback plan | F39: 2 | G39: 4 | H39: =F39+G39-1 -> 5 | I39: HD-01 | J39: =IF(I39="","",SUMPRODUCT(MAX(ISNUMBER(SEARCH(","&$A$7:$A$156&",",","&SUBSTITUTE(I39," ","")&","))*$H$7:$H$156))) -> 1 | K39: =IF(I39="","OK",IF(F39>J39,"OK","VIOLATION")) -> OK | L39: =IF(H39<=26,"OK","LATE") -> OK | M39: =Overview!$B$4+7*(F39-1) -> 46328 | N39: =Overview!$B$4+7*(H39-1)+4 -> 46353 | O39: CSE | P39: KHE; ENG | Q39: EKS upgrades | R39: No 1.31 clusters; 1.34 handled per D-10 | S39: EKS kubernetes-versions page; SH EKS.2/EKS.9 | T39: Not started | U39: Owner CSE - 1.31 upgraded by Fri 20 Nov 2026; 1.34 by Fri 27 Nov 2026 | V39: =";"&SUBSTITUTE(P39," ","")&";" -> ;KHE;ENG;
A40: HD-03 | B40: P1 Mobilize | C40: HD | D40: AL2 containment and migration backlog | E40: Tag/isolate remaining AL2; CrowdStrike prevention policy; restrict SGs; owners/dates per workload; time-boxed exceptions | F40: 2 | G40: 2 | H40: =F40+G40-1 -> 3 | I40: HD-01 | J40: =IF(I40="","",SUMPRODUCT(MAX(ISNUMBER(SEARCH(","&$A$7:$A$156&",",","&SUBSTITUTE(I40," ","")&","))*$H$7:$H$156))) -> 1 | K40: =IF(I40="","OK",IF(F40>J40,"OK","VIOLATION")) -> OK | L40: =IF(H40<=26,"OK","LATE") -> OK | M40: =Overview!$B$4+7*(F40-1) -> 46328 | N40: =Overview!$B$4+7*(H40-1)+4 -> 46339 | O40: CSE | P40: ENG | Q40: Linux ops, CrowdStrike | R40: AL2 backlog + exceptions | S40: AL2 FAQ; CIS Controls v8.1 2.2/7 | T40: Not started | U40: Owner CSE - Fri 6 Nov 2026 | V40: =";"&SUBSTITUTE(P40," ","")&";" -> ;ENG;
A41: HD-07 | B41: P2 Assess & Design | C41: HD | D41: Network baseline design | E41: VPC segmentation, TGW route domains, Network Firewall egress allowlist, NAT, VPC endpoints, WAF managed rules, SG standards, flow logs, Route 53 Resolver DNS Firewall | F41: 6 | G41: 2 | H41: =F41+G41-1 -> 7 | I41: PM-05 | J41: =IF(I41="","",SUMPRODUCT(MAX(ISNUMBER(SEARCH(","&$A$7:$A$156&",",","&SUBSTITUTE(I41," ","")&","))*$H$7:$H$156))) -> 5 | K41: =IF(I41="","OK",IF(F41>J41,"OK","VIOLATION")) -> OK | L41: =IF(H41<=26,"OK","LATE") -> OK | M41: =Overview!$B$4+7*(F41-1) -> 46356 | N41: =Overview!$B$4+7*(H41-1)+4 -> 46367 | O41: KHE | P41: CSE | Q41: AWS networking | R41: Network design (ARB pack) | S41: SH EC2.2/EC2.6/EC2.9/ELB.16/WAF.10/WAF.11/NetworkFirewall.2/.4/.5; CIS Controls 12/13 | T41: Not started | V41: =";"&SUBSTITUTE(P41," ","")&";" -> ;CSE;
A42: HD-08 | B42: P2 Assess & Design | C42: HD | D42: Kubernetes security baseline design (D-11) | E42: PSA restricted; admission policy (ValidatingAdmissionPolicy vs Kyverno) + signature verifier (D-11); NetworkPolicies; private endpoint; access entries; audit logs; KMS secrets encryption (no SH control - custom Config rule); Pod Identity/IRSA | F42: 5 | G42: 2 | H42: =F42+G42-1 -> 6 | I42: HD-05 | J42: =IF(I42="","",SUMPRODUCT(MAX(ISNUMBER(SEARCH(","&$A$7:$A$156&",",","&SUBSTITUTE(I42," ","")&","))*$H$7:$H$156))) -> 4 | K42: =IF(I42="","OK",IF(F42>J42,"OK","VIOLATION")) -> OK | L42: =IF(H42<=26,"OK","LATE") -> OK | M42: =Overview!$B$4+7*(F42-1) -> 46349 | N42: =Overview!$B$4+7*(H42-1)+4 -> 46360 | O42: CSE | P42: KHE | Q42: Kubernetes security | R42: K8s baseline design (ARB pack) | S42: CIS EKS v2.0.0; CIS Kubernetes v2.1.0; SH EKS.1/EKS.8 | T42: Not started | V42: =";"&SUBSTITUTE(P42," ","")&";" -> ;KHE;
A43: HD-09 | B43: P2 Assess & Design | C43: HD | D43: CIS AWS Foundations v7.1.0 delta vs automated v5.0.0 | E43: Map deltas; custom Config rules or manual evidence; feed control matrix | F43: 6 | G43: 2 | H43: =F43+G43-1 -> 7 | I43: PM-06 | J43: =IF(I43="","",SUMPRODUCT(MAX(ISNUMBER(SEARCH(","&$A$7:$A$156&",",","&SUBSTITUTE(I43," ","")&","))*$H$7:$H$156))) -> 5 | K43: =IF(I43="","OK",IF(F43>J43,"OK","VIOLATION")) -> OK | L43: =IF(H43<=26,"OK","LATE") -> OK | M43: =Overview!$B$4+7*(F43-1) -> 46356 | N43: =Overview!$B$4+7*(H43-1)+4 -> 46367 | O43: KHE | P43: GRCC | Q43: CIS benchmarks | R43: CIS v7.1.0 delta register | S43: CIS AWS Foundations v7.1.0; Security Hub CIS docs | T43: Not started | V43: =";"&SUBSTITUTE(P43," ","")&";" -> ;GRCC;
A44: HD-27 | B44: P2 Assess & Design | C44: HD | D44: Control Tower currency, drift and account vending baseline | E44: Landing-zone version; drift remediation; account factory baseline; OU structure for staged guardrails | F44: 6 | G44: 4 | H44: =F44+G44-1 -> 9 | I44: HD-04 | J44: =IF(I44="","",SUMPRODUCT(MAX(ISNUMBER(SEARCH(","&$A$7:$A$156&",",","&SUBSTITUTE(I44," ","")&","))*$H$7:$H$156))) -> 5 | K44: =IF(I44="","OK",IF(F44>J44,"OK","VIOLATION")) -> OK | L44: =IF(H44<=26,"OK","LATE") -> OK | M44: =Overview!$B$4+7*(F44-1) -> 46356 | N44: =Overview!$B$4+7*(H44-1)+4 -> 46381 | O44: CSE | P44: KHE | Q44: Control Tower | R44: Control Tower baseline report | S44: AWS Control Tower docs | T44: Not started | V44: =";"&SUBSTITUTE(P44," ","")&";" -> ;KHE;
A45: ID-03 | B45: P2 Assess & Design | C45: ID | D45: Entra licensing and workforce identity design (D-02) | E45: D-02 covers: P2/ID Governance for admins and for every user in access reviews, P2 for workforce risk-based CA, Workload ID Premium for risky SPs; CA baseline; authentication strengths (device-bound FIDO2, AAGUID allowlist); PIM incl. PIM for Groups | F45: 3 | G45: 3 | H45: =F45+G45-1 -> 5 | I45: ID-01, PM-03 | J45: =IF(I45="","",SUMPRODUCT(MAX(ISNUMBER(SEARCH(","&$A$7:$A$156&",",","&SUBSTITUTE(I45," ","")&","))*$H$7:$H$156))) -> 2 | K45: =IF(I45="","OK",IF(F45>J45,"OK","VIOLATION")) -> OK | L45: =IF(H45<=26,"OK","LATE") -> OK | M45: =Overview!$B$4+7*(F45-1) -> 46335 | N45: =Overview!$B$4+7*(H45-1)+4 -> 46353 | O45: IDC | P45: ISE | Q45: Entra ID architecture | R45: Identity design + D-02 | S45: Entra licensing; authentication strengths; CIS Controls 5/6 | T45: Not started | V45: =";"&SUBSTITUTE(P45," ","")&";" -> ;ISE;
A46: ID-04 | B46: P2 Assess & Design | C46: ID | D46: AWS workforce access design (IAM Identity Center) incl. JIT approach (D-16) | E46: Entra SAML + SCIM (flat groups; 1-yr SCIM token rotation diarised); permission sets; JIT: PIM for Groups via SCIM (accept delay) vs alternative (verify maintenance); SCP blocks Identity Store writes; no IAM users/keys for humans | F46: 3 | G46: 3 | H46: =F46+G46-1 -> 5 | I46: ID-01, HD-01 | J46: =IF(I46="","",SUMPRODUCT(MAX(ISNUMBER(SEARCH(","&$A$7:$A$156&",",","&SUBSTITUTE(I46," ","")&","))*$H$7:$H$156))) -> 1 | K46: =IF(I46="","OK",IF(F46>J46,"OK","VIOLATION")) -> OK | L46: =IF(H46<=26,"OK","LATE") -> OK | M46: =Overview!$B$4+7*(F46-1) -> 46335 | N46: =Overview!$B$4+7*(H46-1)+4 -> 46353 | O46: ISE | P46: CSE | Q46: IAM Identity Center | R46: AWS access design + D-16 | S46: IAM Identity Center Entra/SCIM docs; SH IAM.1/.2/.4/.8/.22 | T46: Not started | V46: =";"&SUBSTITUTE(P46," ","")&";" -> ;CSE;
A47: ID-05 | B47: P2 Assess & Design | C47: ID | D47: Workload identity and secrets design | E47: EKS Pod Identity (IRSA for Fargate/Windows); CI/CD OIDC federation; Secrets Manager rotation; KMS key policies | F47: 6 | G47: 2 | H47: =F47+G47-1 -> 7 | I47: ID-04 | J47: =IF(I47="","",SUMPRODUCT(MAX(ISNUMBER(SEARCH(","&$A$7:$A$156&",",","&SUBSTITUTE(I47," ","")&","))*$H$7:$H$156))) -> 5 | K47: =IF(I47="","OK",IF(F47>J47,"OK","VIOLATION")) -> OK | L47: =IF(H47<=26,"OK","LATE") -> OK | M47: =Overview!$B$4+7*(F47-1) -> 46356 | N47: =Overview!$B$4+7*(H47-1)+4 -> 46367 | O47: ISE | P47: CSE; ENG | Q47: AWS IAM, EKS | R47: Workload identity design | S47: EKS Pod Identity docs; SH SecretsManager.1/.3, KMS.3/.4 | T47: Not started | V47: =";"&SUBSTITUTE(P47," ","")&";" -> ;CSE;ENG;
A48: ID-06 | B48: P2 Assess & Design | C48: ID | D48: Customer identity (Azure AD B2C) assessment and custom-policy security review | E48: Policies in git with CI; policy keys; API-connector auth; redirect URIs; ROPC off; MFA coverage; risk gap after P2 retirement (15 Mar 2026); fraud/bot vendor (D-13); step-up design (acr_values/max_age, server-side auth_time check bound to transaction); External ID options | F48: 4 | G48: 4 | H48: =F48+G48-1 -> 7 | I48: PM-03 | J48: =IF(I48="","",SUMPRODUCT(MAX(ISNUMBER(SEARCH(","&$A$7:$A$156&",",","&SUBSTITUTE(I48," ","")&","))*$H$7:$H$156))) -> 2 | K48: =IF(I48="","OK",IF(F48>J48,"OK","VIOLATION")) -> OK | L48: =IF(H48<=26,"OK","LATE") -> OK | M48: =Overview!$B$4+7*(F48-1) -> 46342 | N48: =Overview!$B$4+7*(H48-1)+4 -> 46367 | O48: IDC | P48: ISE | Q48: B2C/IEF, CIAM | R48: B2C assessment + step-up design + D-13 | S48: B2C FAQ; B2C claim resolvers; External ID supported features; OWASP ASVS | T48: Not started | V48: =";"&SUBSTITUTE(P48," ","")&";" -> ;ISE;
A49: ID-07 | B49: P2 Assess & Design | C49: ID | D49: Wallet sign-in design (SIWE / Sign-In With Solana) | E49: EIP-4361 (Final) verification; nonce/replay store; domain/URI/chain-id binding; EIP-1271 for contract wallets; verifier API from B2C policy or custom OIDC IdP; no EIP-7702 authorisation prompts | F49: 8 | G49: 2 | H49: =F49+G49-1 -> 9 | I49: ID-06 | J49: =IF(I49="","",SUMPRODUCT(MAX(ISNUMBER(SEARCH(","&$A$7:$A$156&",",","&SUBSTITUTE(I49," ","")&","))*$H$7:$H$156))) -> 7 | K49: =IF(I49="","OK",IF(F49>J49,"OK","VIOLATION")) -> OK | L49: =IF(H49<=26,"OK","LATE") -> OK | M49: =Overview!$B$4+7*(F49-1) -> 46370 | N49: =Overview!$B$4+7*(H49-1)+4 -> 46381 | O49: BSE | P49: BSC | Q49: Web3 auth | R49: Wallet sign-in design | S49: EIP-4361; EIP-1271; EIP-7702 security considerations | T49: Not started | V49: =";"&SUBSTITUTE(P49," ","")&";" -> ;BSC;
A50: ID-18 | B50: P2 Assess & Design | C50: ID | D50: App consent and service-principal governance | E50: User consent off; admin-consent workflow; app inventory; SP credential expiry/creation alerts | F50: 6 | G50: 3 | H50: =F50+G50-1 -> 8 | I50: ID-03 | J50: =IF(I50="","",SUMPRODUCT(MAX(ISNUMBER(SEARCH(","&$A$7:$A$156&",",","&SUBSTITUTE(I50," ","")&","))*$H$7:$H$156))) -> 5 | K50: =IF(I50="","OK",IF(F50>J50,"OK","VIOLATION")) -> OK | L50: =IF(H50<=26,"OK","LATE") -> OK | M50: =Overview!$B$4+7*(F50-1) -> 46356 | N50: =Overview!$B$4+7*(H50-1)+4 -> 46374 | O50: ISE | Q50: Entra app governance | R50: App governance baseline | S50: Entra app consent docs; CIS Controls 6 | T50: Not started | V50: =";"&SUBSTITUTE(P50," ","")&";" -> ;;
A51: MR-03 | B51: P2 Assess & Design | C51: MR | D51: Logging and telemetry architecture for Splunk | E51: Splunk Add-on for AWS 8.2.x (CloudTrail/VPC/Config); Splunk Add-on for AWS Security Hub (OCSF via EventBridge->HEC); Entra via Event Hub (MS Cloud Services add-on 6.3.x) incl. NonInteractive/SP/MI sign-ins, risk, Graph activity; B2C (Audit, SignIn) via Lighthouse; CrowdStrike Event Streams; on-chain alert webhooks; retention; volume sizing and filtering | F51: 3 | G51: 3 | H51: =F51+G51-1 -> 5 | I51: MR-01, PM-03 | J51: =IF(I51="","",SUMPRODUCT(MAX(ISNUMBER(SEARCH(","&$A$7:$A$156&",",","&SUBSTITUTE(I51," ","")&","))*$H$7:$H$156))) -> 2 | K51: =IF(I51="","OK",IF(F51>J51,"OK","VIOLATION")) -> OK | L51: =IF(H51<=26,"OK","LATE") -> OK | M51: =Overview!$B$4+7*(F51-1) -> 46335 | N51: =Overview!$B$4+7*(H51-1)+4 -> 46353 | O51: ISE | P51: DET | Q51: Splunk architecture | R51: Telemetry architecture + log source register | S51: Splunkbase 1876/8642/3110/5082; Entra Event Hub docs; B2C Azure Monitor docs | T51: Not started | V51: =";"&SUBSTITUTE(P51," ","")&";" -> ;DET;
A52: MR-04 | B52: P2 Assess & Design | C52: MR | D52: Detection use-case catalogue mapped to threat model and ATT&CK | E52: Identity, control plane, workload, on-chain use cases; ESCU baseline | F52: 6 | G52: 2 | H52: =F52+G52-1 -> 7 | I52: PM-05, MR-03 | J52: =IF(I52="","",SUMPRODUCT(MAX(ISNUMBER(SEARCH(","&$A$7:$A$156&",",","&SUBSTITUTE(I52," ","")&","))*$H$7:$H$156))) -> 5 | K52: =IF(I52="","OK",IF(F52>J52,"OK","VIOLATION")) -> OK | L52: =IF(H52<=26,"OK","LATE") -> OK | M52: =Overview!$B$4+7*(F52-1) -> 46356 | N52: =Overview!$B$4+7*(H52-1)+4 -> 46367 | O52: DET | P52: ISE; BSE | Q52: Detection engineering | R52: Use-case catalogue | S52: MITRE ATT&CK; Splunk ESCU | T52: Not started | V52: =";"&SUBSTITUTE(P52," ","")&";" -> ;ISE;BSE;
A53: MR-05 | B53: P2 Assess & Design | C53: MR | D53: Incident response plan (NIST SP 800-61r3 / CSF 2.0 profile) incl. on-chain | E53: Severity matrix; roles; 24/7 escalation; on-chain incidents (pause/guardian, SEAL 911); notification matrix from D-01 (e.g. FTC Safeguards 30 days if applicable); DORA timelines as benchmark only (4h/24h, +72h, 1 month) | F53: 6 | G53: 3 | H53: =F53+G53-1 -> 8 | I53: GC-01, PM-05 | J53: =IF(I53="","",SUMPRODUCT(MAX(ISNUMBER(SEARCH(","&$A$7:$A$156&",",","&SUBSTITUTE(I53," ","")&","))*$H$7:$H$156))) -> 5 | K53: =IF(I53="","OK",IF(F53>J53,"OK","VIOLATION")) -> OK | L53: =IF(H53<=26,"OK","LATE") -> OK | M53: =Overview!$B$4+7*(F53-1) -> 46356 | N53: =Overview!$B$4+7*(H53-1)+4 -> 46374 | O53: ISE | P53: BSE; GRC; PL | Q53: Incident management | R53: Approved IR plan | S53: NIST SP 800-61r3; SEAL Frameworks; Del. Reg. (EU) 2025/301 | T53: Not started | V53: =";"&SUBSTITUTE(P53," ","")&";" -> ;BSE;GRC;PL;
A54: MR-06 | B54: P2 Assess & Design | C54: MR | D54: Backup and DR design | E54: AWS Backup org policies; logically air-gapped vault (direct for supported types, copy otherwise); Aurora PITR (backtrack MySQL only); EKS backup approach (verify AWS Backup EKS support vs alternative); RTO/RPO from BIA | F54: 6 | G54: 2 | H54: =F54+G54-1 -> 7 | I54: PM-06, GC-18 | J54: =IF(I54="","",SUMPRODUCT(MAX(ISNUMBER(SEARCH(","&$A$7:$A$156&",",","&SUBSTITUTE(I54," ","")&","))*$H$7:$H$156))) -> 5 | K54: =IF(I54="","OK",IF(F54>J54,"OK","VIOLATION")) -> OK | L54: =IF(H54<=26,"OK","LATE") -> OK | M54: =Overview!$B$4+7*(F54-1) -> 46356 | N54: =Overview!$B$4+7*(H54-1)+4 -> 46367 | O54: CSE | P54: ENG | Q54: AWS Backup, Aurora | R54: Backup & DR design | S54: SH Backup.1/RDS.11/RDS.14; CSF 2.0 RC | T54: Not started | V54: =";"&SUBSTITUTE(P54," ","")&";" -> ;ENG;
A55: BC-03 | B55: P2 Assess & Design | C55: BC | D55: Retired-tool sweep: OpenZeppelin Defender (shut down 1 Jul 2026) | E55: Find remaining Defender relayers/monitors/scripts; list on-chain roles still held by old relayer addresses; revoke via multisig | F55: 2 | G55: 1 | H55: =F55+G55-1 -> 2 | J55: =IF(I55="","",SUMPRODUCT(MAX(ISNUMBER(SEARCH(","&$A$7:$A$156&",",","&SUBSTITUTE(I55," ","")&","))*$H$7:$H$156))) | K55: =IF(I55="","OK",IF(F55>J55,"OK","VIOLATION")) -> OK | L55: =IF(H55<=26,"OK","LATE") -> OK | M55: =Overview!$B$4+7*(F55-1) -> 46328 | N55: =Overview!$B$4+7*(H55-1)+4 -> 46332 | O55: BSE | Q55: EVM ops tooling | R55: Retired-tool list + revocation txs | S55: OpenZeppelin Defender phase-out notice | T55: Not started | V55: =";"&SUBSTITUTE(P55," ","")&";" -> ;;
A56: BC-05 | B56: P2 Assess & Design | C56: BC | D56: On-chain asset and privilege inventory; audit scope sizing | E56: All contracts/programs, upgrade authorities, ProxyAdmin/Ownable owners, Safe versions/modules/guards, Squads config authority, spending limits, vault vs multisig authority, Anchor IDL authority; nSLOC per chain for auditor | F56: 2 | G56: 3 | H56: =F56+G56-1 -> 4 | I56: BC-02 | J56: =IF(I56="","",SUMPRODUCT(MAX(ISNUMBER(SEARCH(","&$A$7:$A$156&",",","&SUBSTITUTE(I56," ","")&","))*$H$7:$H$156))) -> 1 | K56: =IF(I56="","OK",IF(F56>J56,"OK","VIOLATION")) -> OK | L56: =IF(H56<=26,"OK","LATE") -> OK | M56: =Overview!$B$4+7*(F56-1) -> 46328 | N56: =Overview!$B$4+7*(H56-1)+4 -> 46346 | O56: BSE | Q56: Ethereum/Solana | R56: Privileged-role register + audit scope | S56: BSSC SCS & KMS; SEAL Multisig framework; Squads v4 | T56: Not started | V56: =";"&SUBSTITUTE(P56," ","")&";" -> ;;
A57: BC-04 | B57: P2 Assess & Design | C57: BC | D57: Glamsterdam impact triage (Hoodi 26 Oct; mainnet TBD) | E57: EF repricing checker; transfer/send, hardcoded gas, gasleft branching, presigned fixed-gas txs; Fusaka 2^24 tx gas cap; other Glamsterdam EIPs affecting monitoring/exit SLA (to verify against meta-EIP) | F57: 3 | G57: 3 | H57: =F57+G57-1 -> 5 | J57: =IF(I57="","",SUMPRODUCT(MAX(ISNUMBER(SEARCH(","&$A$7:$A$156&",",","&SUBSTITUTE(I57," ","")&","))*$H$7:$H$156))) | K57: =IF(I57="","OK",IF(F57>J57,"OK","VIOLATION")) -> OK | L57: =IF(H57<=26,"OK","LATE") -> OK | M57: =Overview!$B$4+7*(F57-1) -> 46335 | N57: =Overview!$B$4+7*(H57-1)+4 -> 46353 | O57: BSE | P57: BSC | Q57: EVM gas semantics | R57: Glamsterdam impact report | S57: blog.ethereum.org Glamsterdam posts; EIP-7825 | T57: Not started | U57: Owner BSE - Fri 27 Nov 2026 | V57: =";"&SUBSTITUTE(P57," ","")&";" -> ;BSC;
A58: BC-24 | B58: P2 Assess & Design | C58: BC | D58: Interim on-chain monitoring (self-hosted OpenZeppelin Monitor) | E58: Privileged-role changes, upgrades, Safe/Squads proposals, stake authority changes; route to pager; AGPL review | F58: 3 | G58: 3 | H58: =F58+G58-1 -> 5 | I58: BC-03 | J58: =IF(I58="","",SUMPRODUCT(MAX(ISNUMBER(SEARCH(","&$A$7:$A$156&",",","&SUBSTITUTE(I58," ","")&","))*$H$7:$H$156))) -> 2 | K58: =IF(I58="","OK",IF(F58>J58,"OK","VIOLATION")) -> OK | L58: =IF(H58<=26,"OK","LATE") -> OK | M58: =Overview!$B$4+7*(F58-1) -> 46335 | N58: =Overview!$B$4+7*(H58-1)+4 -> 46353 | O58: BSE | P58: ISE | Q58: On-chain monitoring | R58: Interim monitors live | S58: OpenZeppelin Monitor repo | T58: Not started | V58: =";"&SUBSTITUTE(P58," ","")&";" -> ;ISE;
A59: BC-06 | B59: P2 Assess & Design | C59: BC | D59: Custody vendor assessment (CCSS v9.0, BSSC KMS) | E59: Policy engine (quorum, allowlists, velocity), hot-wallet caps, approver devices, key ceremony evidence, co-signer host, vendor SOC 2, PQ roadmap | F59: 5 | G59: 4 | H59: =F59+G59-1 -> 8 | I59: BC-05, PM-03 | J59: =IF(I59="","",SUMPRODUCT(MAX(ISNUMBER(SEARCH(","&$A$7:$A$156&",",","&SUBSTITUTE(I59," ","")&","))*$H$7:$H$156))) -> 4 | K59: =IF(I59="","OK",IF(F59>J59,"OK","VIOLATION")) -> OK | L59: =IF(H59<=26,"OK","LATE") -> OK | M59: =Overview!$B$4+7*(F59-1) -> 46349 | N59: =Overview!$B$4+7*(H59-1)+4 -> 46374 | O59: CSO | P59: BSE; GRC | Q59: Custody assessment | R59: Custody assessment report | S59: CCSS v9.0; BSSC KMS | T59: Not started | V59: =";"&SUBSTITUTE(P59," ","")&";" -> ;BSE;GRC;
A60: BC-07 | B60: P2 Assess & Design | C60: BC | D60: Staking provider due diligence | E60: SOC report; BSSC NOS v2 attestation; EIP-3076 slashing-protection; client mix post-Alpenglow; Glamsterdam/ePBS readiness; SLA, insurance, exit procedure | F60: 6 | G60: 4 | H60: =F60+G60-1 -> 9 | I60: BC-01, BC-02, PM-03 | J60: =IF(I60="","",SUMPRODUCT(MAX(ISNUMBER(SEARCH(","&$A$7:$A$156&",",","&SUBSTITUTE(I60," ","")&","))*$H$7:$H$156))) -> 2 | K60: =IF(I60="","OK",IF(F60>J60,"OK","VIOLATION")) -> OK | L60: =IF(H60<=26,"OK","LATE") -> OK | M60: =Overview!$B$4+7*(F60-1) -> 46356 | N60: =Overview!$B$4+7*(H60-1)+4 -> 46381 | O60: BSE | P60: CSO | Q60: Staking risk | R60: Staking provider assessment | S60: BSSC NOS v2; EIP-3076; Anza vote-account guide | T60: Not started | V60: =";"&SUBSTITUTE(P60," ","")&";" -> ;CSO;
A61: BC-08 | B61: P2 Assess & Design | C61: BC | D61: Secure SDLC design for Solidity and Rust/Anchor | E61: CI: Slither, Aderyn, Foundry fuzz/invariant, Echidna/Medusa, Halmos; storage layout + _disableInitializers checks; Rust: cargo-audit, clippy, Trident; Solana checks (owner/signer/discriminator, arbitrary CPI, PDA bumps, re-init, closed-account revival, Token-2022 extensions); solana-verify; deploy via multisig | F61: 5 | G61: 3 | H61: =F61+G61-1 -> 7 | I61: BC-05 | J61: =IF(I61="","",SUMPRODUCT(MAX(ISNUMBER(SEARCH(","&$A$7:$A$156&",",","&SUBSTITUTE(I61," ","")&","))*$H$7:$H$156))) -> 4 | K61: =IF(I61="","OK",IF(F61>J61,"OK","VIOLATION")) -> OK | L61: =IF(H61<=26,"OK","LATE") -> OK | M61: =Overview!$B$4+7*(F61-1) -> 46349 | N61: =Overview!$B$4+7*(H61-1)+4 -> 46367 | O61: BSC | P61: BSE; ENG | Q61: Smart-contract security | R61: SSDLC standard | S61: OWASP SC Top 10 2026; BSSC SCS & TIS; NIST SSDF v1.1 | T61: Not started | V61: =";"&SUBSTITUTE(P61," ","")&";" -> ;BSE;ENG;
A62: BC-09 | B62: P2 Assess & Design | C62: BC | D62: On-chain monitoring vendor selection (D-07) | E62: Solana coverage confirmed in writing; Hypernative, Hexagate, OZ Monitor; routing to Splunk/SOAR | F62: 5 | G62: 2 | H62: =F62+G62-1 -> 6 | I62: PM-03, BC-03 | J62: =IF(I62="","",SUMPRODUCT(MAX(ISNUMBER(SEARCH(","&$A$7:$A$156&",",","&SUBSTITUTE(I62," ","")&","))*$H$7:$H$156))) -> 2 | K62: =IF(I62="","OK",IF(F62>J62,"OK","VIOLATION")) -> OK | L62: =IF(H62<=26,"OK","LATE") -> OK | M62: =Overview!$B$4+7*(F62-1) -> 46349 | N62: =Overview!$B$4+7*(H62-1)+4 -> 46360 | O62: BSE | P62: DET | Q62: On-chain monitoring | R62: D-07 decision | S62: Vendor docs (claims confirmed in writing) | T62: Not started | V62: =";"&SUBSTITUTE(P62," ","")&";" -> ;DET;
A63: GC-25 | B63: P2 Assess & Design | C63: GC | D63: Asset and data inventory with data classification | E63: Systems, data stores, wallets, keys, vendors; classification scheme; owners | F63: 4 | G63: 4 | H63: =F63+G63-1 -> 7 | I63: PM-02 | J63: =IF(I63="","",SUMPRODUCT(MAX(ISNUMBER(SEARCH(","&$A$7:$A$156&",",","&SUBSTITUTE(I63," ","")&","))*$H$7:$H$156))) -> 1 | K63: =IF(I63="","OK",IF(F63>J63,"OK","VIOLATION")) -> OK | L63: =IF(H63<=26,"OK","LATE") -> OK | M63: =Overview!$B$4+7*(F63-1) -> 46342 | N63: =Overview!$B$4+7*(H63-1)+4 -> 46367 | O63: GRCC | Q63: Asset management | R63: Asset & data register | S63: CSF 2.0 ID.AM; ISO 27001 A.5.9/A.5.12; SOC 2 CC6.1 | T63: Not started | V63: =";"&SUBSTITUTE(P63," ","")&";" -> ;;
A64: GC-04 | B64: P2 Assess & Design | C64: GC | D64: Policy framework (version-controlled) | E64: Info-sec, access, change, crypto & key mgmt, SSDLC, IR, BC/DR, vendor, HR, acceptable use, data classification, logging; git-based | F64: 5 | G64: 4 | H64: =F64+G64-1 -> 8 | I64: GC-01, GC-02 | J64: =IF(I64="","",SUMPRODUCT(MAX(ISNUMBER(SEARCH(","&$A$7:$A$156&",",","&SUBSTITUTE(I64," ","")&","))*$H$7:$H$156))) -> 4 | K64: =IF(I64="","OK",IF(F64>J64,"OK","VIOLATION")) -> OK | L64: =IF(H64<=26,"OK","LATE") -> OK | M64: =Overview!$B$4+7*(F64-1) -> 46349 | N64: =Overview!$B$4+7*(H64-1)+4 -> 46374 | O64: GRCC | P64: GRC | Q64: Policy authoring | R64: Approved policy set v1.0 | S64: ISO 27001:2022 5.2/A.5.1; SOC 2 CC1-CC5 | T64: Not started | V64: =";"&SUBSTITUTE(P64," ","")&";" -> ;GRC;
A65: GC-07 | B65: P2 Assess & Design | C65: GC | D65: SOC 2 scope, system description and period plan (D-08, D-12) | E65: TSC categories; carve-out vs inclusive for custody/staking providers; CPA consulted only (no design role); Type I as-of date and gap-free Type II start; which pre-period annual controls the CPA accepts | F65: 5 | G65: 3 | H65: =F65+G65-1 -> 7 | I65: GC-01, PM-03 | J65: =IF(I65="","",SUMPRODUCT(MAX(ISNUMBER(SEARCH(","&$A$7:$A$156&",",","&SUBSTITUTE(I65," ","")&","))*$H$7:$H$156))) -> 4 | K65: =IF(I65="","OK",IF(F65>J65,"OK","VIOLATION")) -> OK | L65: =IF(H65<=26,"OK","LATE") -> OK | M65: =Overview!$B$4+7*(F65-1) -> 46349 | N65: =Overview!$B$4+7*(H65-1)+4 -> 46367 | O65: GRC | P65: GRCC; CPA | Q65: SOC 2 | R65: Scope memo + draft system description | S65: AICPA TSC 2017 (2022 PoF); DC 200 (2018, 2022 guidance) | T65: Not started | V65: =";"&SUBSTITUTE(P65," ","")&";" -> ;GRCC;CPA;
A66: GC-06 | B66: P2 Assess & Design | C66: GC | D66: Third-party / ICT risk programme | E66: Tiering; due diligence for custody, staking, RPC, Splunk, CrowdStrike, MDR, auditors; subservice orgs | F66: 6 | G66: 4 | H66: =F66+G66-1 -> 9 | I66: GC-02 | J66: =IF(I66="","",SUMPRODUCT(MAX(ISNUMBER(SEARCH(","&$A$7:$A$156&",",","&SUBSTITUTE(I66," ","")&","))*$H$7:$H$156))) -> 4 | K66: =IF(I66="","OK",IF(F66>J66,"OK","VIOLATION")) -> OK | L66: =IF(H66<=26,"OK","LATE") -> OK | M66: =Overview!$B$4+7*(F66-1) -> 46356 | N66: =Overview!$B$4+7*(H66-1)+4 -> 46381 | O66: GRC | P66: CSO | Q66: TPRM | R66: TPRM procedure + tier-1 assessments | S66: CSF 2.0 GV.SC; ISO 27001 A.5.19-5.22 | T66: Not started | V66: =";"&SUBSTITUTE(P66," ","")&";" -> ;CSO;
A67: GC-12 | B67: P2 Assess & Design | C67: GC | D67: Risk register and exception process (expiry-based) | E67: Risk register (spreadsheet until GRC platform); exceptions max 90 days, one renewal; KRIs | F67: 6 | G67: 2 | H67: =F67+G67-1 -> 7 | I67: PM-04, PM-07 | J67: =IF(I67="","",SUMPRODUCT(MAX(ISNUMBER(SEARCH(","&$A$7:$A$156&",",","&SUBSTITUTE(I67," ","")&","))*$H$7:$H$156))) -> 3 | K67: =IF(I67="","OK",IF(F67>J67,"OK","VIOLATION")) -> OK | L67: =IF(H67<=26,"OK","LATE") -> OK | M67: =Overview!$B$4+7*(F67-1) -> 46356 | N67: =Overview!$B$4+7*(H67-1)+4 -> 46367 | O67: GRC | P67: PL | Q67: Risk mgmt | R67: Risk + exception registers | S67: ISO 27001 6.1/8.2; CSF 2.0 GV.RM; SOC 2 CC3.1 | T67: Not started | V67: =";"&SUBSTITUTE(P67," ","")&";" -> ;PL;
A68: GC-09 | B68: P2 Assess & Design | C68: GC | D68: GRC platform deployment and automated control tests | E68: Integrate AWS, Entra, GitHub, HRIS; tests mapped after GC-05 | F68: 6 | G68: 4 | H68: =F68+G68-1 -> 9 | I68: GC-03 | J68: =IF(I68="","",SUMPRODUCT(MAX(ISNUMBER(SEARCH(","&$A$7:$A$156&",",","&SUBSTITUTE(I68," ","")&","))*$H$7:$H$156))) -> 4 | K68: =IF(I68="","OK",IF(F68>J68,"OK","VIOLATION")) -> OK | L68: =IF(H68<=26,"OK","LATE") -> OK | M68: =Overview!$B$4+7*(F68-1) -> 46356 | N68: =Overview!$B$4+7*(H68-1)+4 -> 46381 | O68: GRCC | Q68: GRC platform | R68: Automated control monitoring live | S68: AICPA TSC 2017 (2022 PoF) | T68: Not started | V68: =";"&SUBSTITUTE(P68," ","")&";" -> ;;
A69: PM-09A | B69: P2 Assess & Design | C69: PM | D69: ARB #1: guardrail, image, identity, telemetry designs | E69: Review HD-04, HD-05, ID-03, ID-04, MR-03; exceptions | F69: 6 | G69: 1 | H69: =F69+G69-1 -> 6 | I69: HD-04, HD-05, ID-03, ID-04, MR-03 | J69: =IF(I69="","",SUMPRODUCT(MAX(ISNUMBER(SEARCH(","&$A$7:$A$156&",",","&SUBSTITUTE(I69," ","")&","))*$H$7:$H$156))) -> 5 | K69: =IF(I69="","OK",IF(F69>J69,"OK","VIOLATION")) -> OK | L69: =IF(H69<=26,"OK","LATE") -> OK | M69: =Overview!$B$4+7*(F69-1) -> 46356 | N69: =Overview!$B$4+7*(H69-1)+4 -> 46360 | O69: PL | P69: CSE; ISE | Q69: Architecture governance | R69: ARB #1 approvals log | S69: ISO 27001 A.8.27 | T69: Not started | V69: =";"&SUBSTITUTE(P69," ","")&";" -> ;CSE;ISE;
A70: GC-17 | B70: P2 Assess & Design | C70: GC | D70: Security and fraud risk assessment | E70: Annual risk assessment and fraud risk assessment (CC3.2/CC3.3); refreshed annually in BAU | F70: 8 | G70: 2 | H70: =F70+G70-1 -> 9 | I70: GC-12, PM-05 | J70: =IF(I70="","",SUMPRODUCT(MAX(ISNUMBER(SEARCH(","&$A$7:$A$156&",",","&SUBSTITUTE(I70," ","")&","))*$H$7:$H$156))) -> 7 | K70: =IF(I70="","OK",IF(F70>J70,"OK","VIOLATION")) -> OK | L70: =IF(H70<=26,"OK","LATE") -> OK | M70: =Overview!$B$4+7*(F70-1) -> 46370 | N70: =Overview!$B$4+7*(H70-1)+4 -> 46381 | O70: GRC | P70: PL | Q70: Risk assessment | R70: Risk assessment report | S70: SOC 2 CC3.2/CC3.3; ISO 27001 8.2 | T70: Not started | V70: =";"&SUBSTITUTE(P70," ","")&";" -> ;PL;
A71: GC-05 | B71: P2 Assess & Design | C71: GC | D71: Unified control matrix | E71: SOC 2 TSC <-> CSF 2.0 <-> ISO 27001 Annex A (93) <-> CIS v8.1 <-> CIS benchmarks <-> BSSC/CCSS/SEAL; owners; tests; denominators for K17 | F71: 8 | G71: 4 | H71: =F71+G71-1 -> 11 | I71: PM-06, GC-07, HD-09 | J71: =IF(I71="","",SUMPRODUCT(MAX(ISNUMBER(SEARCH(","&$A$7:$A$156&",",","&SUBSTITUTE(I71," ","")&","))*$H$7:$H$156))) -> 7 | K71: =IF(I71="","OK",IF(F71>J71,"OK","VIOLATION")) -> OK | L71: =IF(H71<=26,"OK","LATE") -> OK | M71: =Overview!$B$4+7*(F71-1) -> 46370 | N71: =Overview!$B$4+7*(H71-1)+4 -> 46395 | O71: GRCC | P71: GRC | Q71: Control frameworks | R71: Unified control matrix | S71: AICPA TSC 2017 (2022 PoF); CSF 2.0; ISO 27001:2022 | T71: Not started | V71: =";"&SUBSTITUTE(P71," ","")&";" -> ;GRC;
A72: GC-22 | B72: P2 Assess & Design | C72: GC | D72: EU-marketing controls (condition of MiCA no-go) | E72: No EU-targeted ads/influencers/EU-language sites/EU domains; geo-marketing review; evidence | F72: 8 | G72: 3 | H72: =F72+G72-1 -> 10 | I72: GC-01 | J72: =IF(I72="","",SUMPRODUCT(MAX(ISNUMBER(SEARCH(","&$A$7:$A$156&",",","&SUBSTITUTE(I72," ","")&","))*$H$7:$H$156))) -> 4 | K72: =IF(I72="","OK",IF(F72>J72,"OK","VIOLATION")) -> OK | L72: =IF(H72<=26,"OK","LATE") -> OK | M72: =Overview!$B$4+7*(F72-1) -> 46370 | N72: =Overview!$B$4+7*(H72-1)+4 -> 46388 | O72: GRC | P72: LEG | Q72: Marketing compliance | R72: EU marketing control evidence | S72: MiCA Art 61; ESMA reverse-solicitation guidelines | T72: Not started | V72: =";"&SUBSTITUTE(P72," ","")&";" -> ;LEG;
A73: PM-09B | B73: P2 Assess & Design | C73: PM | D73: ARB #2: network, Kubernetes, workload identity, CIAM, DR, SSDLC designs | E73: Review HD-07, HD-08, ID-05, ID-06, MR-06, BC-08; exceptions | F73: 8 | G73: 1 | H73: =F73+G73-1 -> 8 | I73: HD-07, HD-08, ID-05, ID-06, MR-06, BC-08 | J73: =IF(I73="","",SUMPRODUCT(MAX(ISNUMBER(SEARCH(","&$A$7:$A$156&",",","&SUBSTITUTE(I73," ","")&","))*$H$7:$H$156))) -> 7 | K73: =IF(I73="","OK",IF(F73>J73,"OK","VIOLATION")) -> OK | L73: =IF(H73<=26,"OK","LATE") -> OK | M73: =Overview!$B$4+7*(F73-1) -> 46370 | N73: =Overview!$B$4+7*(H73-1)+4 -> 46374 | O73: PL | P73: CSE; ISE | Q73: Architecture governance | R73: ARB #2 approvals log | S73: ISO 27001 A.8.27 | T73: Not started | V73: =";"&SUBSTITUTE(P73," ","")&";" -> ;CSE;ISE;
A74: MR-01B | B74: P3 Build & Harden | C74: MR | D74: GuardDuty Runtime Monitoring agents (after SSM) | E74: Automated agent via SSM on EC2; EKS add-on on EC2 nodes; ECS on EC2 (agent >=1.77.0 / AMI >=2023-09-29); EKS on Fargate unsupported -> HD-25 | F74: 7 | G74: 2 | H74: =F74+G74-1 -> 8 | I74: HD-06, GC-08, MR-01 | J74: =IF(I74="","",SUMPRODUCT(MAX(ISNUMBER(SEARCH(","&$A$7:$A$156&",",","&SUBSTITUTE(I74," ","")&","))*$H$7:$H$156))) -> 6 | K74: =IF(I74="","OK",IF(F74>J74,"OK","VIOLATION")) -> OK | L74: =IF(H74<=26,"OK","LATE") -> OK | M74: =Overview!$B$4+7*(F74-1) -> 46363 | N74: =Overview!$B$4+7*(H74-1)+4 -> 46374 | O74: CPE | P74: CSE | Q74: GuardDuty | R74: Runtime Monitoring coverage report | S74: GuardDuty Runtime Monitoring docs; SH GuardDuty.7/.11/.13 | T74: Not started | V74: =";"&SUBSTITUTE(P74," ","")&";" -> ;CSE;
A75: HD-10 | B75: P3 Build & Harden | C75: HD | D75: Deploy org guardrails (sandbox/non-prod W7-W8; prod from W11) | E75: SCP/RCP/declarative staged with CAB; EBS default encryption all Regions; S3 account BPA; Control Tower controls | F75: 7 | G75: 6 | H75: =F75+G75-1 -> 12 | I75: PM-09A, GC-08 | J75: =IF(I75="","",SUMPRODUCT(MAX(ISNUMBER(SEARCH(","&$A$7:$A$156&",",","&SUBSTITUTE(I75," ","")&","))*$H$7:$H$156))) -> 6 | K75: =IF(I75="","OK",IF(F75>J75,"OK","VIOLATION")) -> OK | L75: =IF(H75<=26,"OK","LATE") -> OK | M75: =Overview!$B$4+7*(F75-1) -> 46363 | N75: =Overview!$B$4+7*(H75-1)+4 -> 46402 | O75: CSE | P75: KHE | Q75: AWS Organizations | R75: Guardrails live in all OUs | S75: SH EC2.7/EC2.8/S3.1/IAM.4 | T75: Not started | V75: =";"&SUBSTITUTE(P75," ","")&";" -> ;KHE;
A76: HD-16A | B76: P3 Build & Harden | C76: HD | D76: EKS node groups AL2 -> AL2023/Bottlerocket at 1.32 (non-prod W6-7, prod W8) | E76: Per D-05; drain/replace node groups; validate workloads; before freeze | F76: 6 | G76: 3 | H76: =F76+G76-1 -> 8 | I76: HD-02, HD-05, HD-24 | J76: =IF(I76="","",SUMPRODUCT(MAX(ISNUMBER(SEARCH(","&$A$7:$A$156&",",","&SUBSTITUTE(I76," ","")&","))*$H$7:$H$156))) -> 5 | K76: =IF(I76="","OK",IF(F76>J76,"OK","VIOLATION")) -> OK | L76: =IF(H76<=26,"OK","LATE") -> OK | M76: =Overview!$B$4+7*(F76-1) -> 46356 | N76: =Overview!$B$4+7*(H76-1)+4 -> 46374 | O76: CPE | P76: CSE; ENG | Q76: EKS node groups | R76: No AL2 EKS nodes | S76: EKS AL2 AMI deprecation FAQ; AL2 FAQ | T76: Not started | V76: =";"&SUBSTITUTE(P76," ","")&";" -> ;CSE;ENG;
A77: HD-23 | B77: P3 Build & Harden | C77: HD | D77: Container hosts on EC2 (ECS/Docker) to AL2023 (non-prod W7-8, prod W11-14) | E77: ECS-optimized AL2023 AMI; cgroup v2 memory checks (JVM); agent versions | F77: 7 | G77: 8 | H77: =F77+G77-1 -> 14 | I77: HD-03, HD-05 | J77: =IF(I77="","",SUMPRODUCT(MAX(ISNUMBER(SEARCH(","&$A$7:$A$156&",",","&SUBSTITUTE(I77," ","")&","))*$H$7:$H$156))) -> 4 | K77: =IF(I77="","OK",IF(F77>J77,"OK","VIOLATION")) -> OK | L77: =IF(H77<=26,"OK","LATE") -> OK | M77: =Overview!$B$4+7*(F77-1) -> 46363 | N77: =Overview!$B$4+7*(H77-1)+4 -> 46416 | O77: KHE | P77: ENG | Q77: ECS, Linux | R77: No AL2 container hosts | S77: ECS AMI docs; AL2 FAQ | T77: Not started | V77: =";"&SUBSTITUTE(P77," ","")&";" -> ;ENG;
A78: HD-11 | B78: P3 Build & Harden | C78: HD | D78: Patch Manager baselines and patch SLA | E78: Baselines per OS; maintenance windows; SLA crit 7d/high 14d | F78: 8 | G78: 3 | H78: =F78+G78-1 -> 10 | I78: HD-06, PM-04 | J78: =IF(I78="","",SUMPRODUCT(MAX(ISNUMBER(SEARCH(","&$A$7:$A$156&",",","&SUBSTITUTE(I78," ","")&","))*$H$7:$H$156))) -> 6 | K78: =IF(I78="","OK",IF(F78>J78,"OK","VIOLATION")) -> OK | L78: =IF(H78<=26,"OK","LATE") -> OK | M78: =Overview!$B$4+7*(F78-1) -> 46370 | N78: =Overview!$B$4+7*(H78-1)+4 -> 46388 | O78: KHE | P78: ENG | Q78: SSM Patch Manager | R78: Patch SLA live | S78: SH SSM.2/SSM.3; CIS Controls 7 | T78: Not started | V78: =";"&SUBSTITUTE(P78," ","")&";" -> ;ENG;
A79: HD-12 | B79: P3 Build & Harden | C79: HD | D79: Inspector CIS scans (AL2023 L1) scheduled | E79: Scheduled scans; baseline score; Graviton/Bottlerocket evidence via HD-26 | F79: 8 | G79: 1 | H79: =F79+G79-1 -> 8 | I79: HD-06, HD-05 | J79: =IF(I79="","",SUMPRODUCT(MAX(ISNUMBER(SEARCH(","&$A$7:$A$156&",",","&SUBSTITUTE(I79," ","")&","))*$H$7:$H$156))) -> 6 | K79: =IF(I79="","OK",IF(F79>J79,"OK","VIOLATION")) -> OK | L79: =IF(H79<=26,"OK","LATE") -> OK | M79: =Overview!$B$4+7*(F79-1) -> 46370 | N79: =Overview!$B$4+7*(H79-1)+4 -> 46374 | O79: KHE | Q79: Amazon Inspector | R79: CIS scan baseline | S79: Inspector CIS scans docs; CIS AL2023 v1.0.0 | T79: Not started | V79: =";"&SUBSTITUTE(P79," ","")&";" -> ;;
A80: HD-13 | B80: P3 Build & Harden | C80: HD | D80: Golden AMI pipeline (EC2 Image Builder) | E80: CIS AL2023 L1 + CrowdStrike sensor + SSM agent; allowed-images policy | F80: 9 | G80: 3 | H80: =F80+G80-1 -> 11 | I80: HD-05, PM-09A | J80: =IF(I80="","",SUMPRODUCT(MAX(ISNUMBER(SEARCH(","&$A$7:$A$156&",",","&SUBSTITUTE(I80," ","")&","))*$H$7:$H$156))) -> 6 | K80: =IF(I80="","OK",IF(F80>J80,"OK","VIOLATION")) -> OK | L80: =IF(H80<=26,"OK","LATE") -> OK | M80: =Overview!$B$4+7*(F80-1) -> 46377 | N80: =Overview!$B$4+7*(H80-1)+4 -> 46395 | O80: KHE | P80: CSE | Q80: Image Builder | R80: Golden AMI v1 | S80: CIS AL2023 v1.0.0; EC2 declarative policies | T80: Not started | V80: =";"&SUBSTITUTE(P80," ","")&";" -> ;CSE;
A81: HD-19 | B81: P3 Build & Harden | C81: HD | D81: Network baseline implementation (prod after freeze) | E81: Network Firewall egress; WAF managed rules + logging; SG cleanup; VPC endpoints; flow logs; DNS Firewall | F81: 9 | G81: 5 | H81: =F81+G81-1 -> 13 | I81: HD-07, PM-09B, GC-08 | J81: =IF(I81="","",SUMPRODUCT(MAX(ISNUMBER(SEARCH(","&$A$7:$A$156&",",","&SUBSTITUTE(I81," ","")&","))*$H$7:$H$156))) -> 8 | K81: =IF(I81="","OK",IF(F81>J81,"OK","VIOLATION")) -> OK | L81: =IF(H81<=26,"OK","LATE") -> OK | M81: =Overview!$B$4+7*(F81-1) -> 46377 | N81: =Overview!$B$4+7*(H81-1)+4 -> 46409 | O81: CSE | P81: KHE; ENG | Q81: AWS networking | R81: Network baseline live | S81: SH EC2.2/EC2.6/ELB.16/WAF.10/WAF.11/NetworkFirewall.2/.4/.5 | T81: Not started | V81: =";"&SUBSTITUTE(P81," ","")&";" -> ;KHE;ENG;
A82: HD-16B | B82: P3 Build & Harden | C82: HD | D82: EKS version hops 1.32 -> 1.36 (before 1.32 extended EOS 23 Mar 2027) | E82: One hop at a time per HD-24 matrix; add-ons; nodes; no reliance on forced auto-upgrade (no notice, no rollback) | F82: 11 | G82: 8 | H82: =F82+G82-1 -> 18 | I82: HD-16A, HD-24, PM-09B | J82: =IF(I82="","",SUMPRODUCT(MAX(ISNUMBER(SEARCH(","&$A$7:$A$156&",",","&SUBSTITUTE(I82," ","")&","))*$H$7:$H$156))) -> 8 | K82: =IF(I82="","OK",IF(F82>J82,"OK","VIOLATION")) -> OK | L82: =IF(H82<=26,"OK","LATE") -> OK | M82: =Overview!$B$4+7*(F82-1) -> 46391 | N82: =Overview!$B$4+7*(H82-1)+4 -> 46444 | O82: CSE | P82: KHE; ENG | Q82: EKS | R82: All clusters on 1.36 | S82: EKS kubernetes-versions page; SH EKS.2/EKS.9 | T82: Not started | U82: Owner CSE - complete by Fri 26 Feb 2027 (hard stop 23 Mar 2027) | V82: =";"&SUBSTITUTE(P82," ","")&";" -> ;KHE;ENG;
A83: HD-17 | B83: P3 Build & Harden | C83: HD | D83: Kubernetes hardening rollout | E83: PSA restricted; admission policies; NetworkPolicies; private endpoints; audit logs; access entries; Pod Identity | F83: 11 | G83: 5 | H83: =F83+G83-1 -> 15 | I83: HD-08, PM-09B, ID-05 | J83: =IF(I83="","",SUMPRODUCT(MAX(ISNUMBER(SEARCH(","&$A$7:$A$156&",",","&SUBSTITUTE(I83," ","")&","))*$H$7:$H$156))) -> 8 | K83: =IF(I83="","OK",IF(F83>J83,"OK","VIOLATION")) -> OK | L83: =IF(H83<=26,"OK","LATE") -> OK | M83: =Overview!$B$4+7*(F83-1) -> 46391 | N83: =Overview!$B$4+7*(H83-1)+4 -> 46423 | O83: KHE | P83: CSE; ENG | Q83: Kubernetes security | R83: K8s baseline enforced | S83: CIS EKS v2.0.0; SH EKS.1/EKS.8 | T83: Not started | V83: =";"&SUBSTITUTE(P83," ","")&";" -> ;CSE;ENG;
A84: HD-14 | B84: P3 Build & Harden | C84: HD | D84: AL2 -> AL2023 migration wave 1 (internet-facing, crypto-adjacent) | E84: Migrate priority workloads using golden AMI; decommission AL2 | F84: 13 | G84: 4 | H84: =F84+G84-1 -> 16 | I84: HD-03, HD-13 | J84: =IF(I84="","",SUMPRODUCT(MAX(ISNUMBER(SEARCH(","&$A$7:$A$156&",",","&SUBSTITUTE(I84," ","")&","))*$H$7:$H$156))) -> 11 | K84: =IF(I84="","OK",IF(F84>J84,"OK","VIOLATION")) -> OK | L84: =IF(H84<=26,"OK","LATE") -> OK | M84: =Overview!$B$4+7*(F84-1) -> 46405 | N84: =Overview!$B$4+7*(H84-1)+4 -> 46430 | O84: CSE | P84: ENG; KHE | Q84: Linux migration | R84: Wave-1 AL2 retired | S84: AL2 FAQ | T84: Not started | V84: =";"&SUBSTITUTE(P84," ","")&";" -> ;ENG;KHE;
A85: HD-21 | B85: P3 Build & Harden | C85: HD | D85: Security Hub CSPM remediation sprints | E85: Burn down FSBP/CIS v5.0.0 failures by severity; suppressions only via exception register | F85: 14 | G85: 6 | H85: =F85+G85-1 -> 19 | I85: HD-10, MR-23 | J85: =IF(I85="","",SUMPRODUCT(MAX(ISNUMBER(SEARCH(","&$A$7:$A$156&",",","&SUBSTITUTE(I85," ","")&","))*$H$7:$H$156))) -> 12 | K85: =IF(I85="","OK",IF(F85>J85,"OK","VIOLATION")) -> OK | L85: =IF(H85<=26,"OK","LATE") -> OK | M85: =Overview!$B$4+7*(F85-1) -> 46412 | N85: =Overview!$B$4+7*(H85-1)+4 -> 46451 | O85: CSE | P85: KHE; ENG | Q85: AWS remediation | R85: Security Hub score >= target | S85: Security Hub CSPM FSBP; CIS AWS v5.0.0 | T85: Not started | V85: =";"&SUBSTITUTE(P85," ","")&";" -> ;KHE;ENG;
A86: HD-15 | B86: P3 Build & Harden | C86: HD | D86: AL2 migration wave 2 (to zero AL2) | E86: Remaining workloads; residual exceptions approved with expiry | F86: 17 | G86: 4 | H86: =F86+G86-1 -> 20 | I86: HD-14 | J86: =IF(I86="","",SUMPRODUCT(MAX(ISNUMBER(SEARCH(","&$A$7:$A$156&",",","&SUBSTITUTE(I86," ","")&","))*$H$7:$H$156))) -> 16 | K86: =IF(I86="","OK",IF(F86>J86,"OK","VIOLATION")) -> OK | L86: =IF(H86<=26,"OK","LATE") -> OK | M86: =Overview!$B$4+7*(F86-1) -> 46433 | N86: =Overview!$B$4+7*(H86-1)+4 -> 46458 | O86: CSE | P86: ENG | Q86: Linux migration | R86: AL2 count = 0 or approved exceptions | S86: AL2 FAQ | T86: Not started | V86: =";"&SUBSTITUTE(P86," ","")&";" -> ;ENG;
A87: HD-25 | B87: P3 Build & Harden | C87: HD | D87: EKS on Fargate runtime-monitoring gap | E87: If Fargate in use: Falcon container sidecar or move workloads to EC2 nodes; IRSA (Pod Identity unsupported) | F87: 15 | G87: 3 | H87: =F87+G87-1 -> 17 | I87: MR-01B, HD-05 | J87: =IF(I87="","",SUMPRODUCT(MAX(ISNUMBER(SEARCH(","&$A$7:$A$156&",",","&SUBSTITUTE(I87," ","")&","))*$H$7:$H$156))) -> 8 | K87: =IF(I87="","OK",IF(F87>J87,"OK","VIOLATION")) -> OK | L87: =IF(H87<=26,"OK","LATE") -> OK | M87: =Overview!$B$4+7*(F87-1) -> 46419 | N87: =Overview!$B$4+7*(H87-1)+4 -> 46437 | O87: KHE | P87: CSE | Q87: EKS Fargate | R87: Fargate coverage decision + implementation | S87: GuardDuty Runtime Monitoring docs; EKS Pod Identity docs | T87: Not started | V87: =";"&SUBSTITUTE(P87," ","")&";" -> ;CSE;
A88: HD-18 | B88: P3 Build & Harden | C88: HD | D88: Container supply chain: signing and verification | E88: ECR managed signing (AWS Signer); tag immutability with exclusions; Inspector ECR; EKS admission verification; ECS: CI/CD signature gate; SBOM | F88: 16 | G88: 4 | H88: =F88+G88-1 -> 19 | I88: HD-17 | J88: =IF(I88="","",SUMPRODUCT(MAX(ISNUMBER(SEARCH(","&$A$7:$A$156&",",","&SUBSTITUTE(I88," ","")&","))*$H$7:$H$156))) -> 15 | K88: =IF(I88="","OK",IF(F88>J88,"OK","VIOLATION")) -> OK | L88: =IF(H88<=26,"OK","LATE") -> OK | M88: =Overview!$B$4+7*(F88-1) -> 46426 | N88: =Overview!$B$4+7*(H88-1)+4 -> 46451 | O88: KHE | P88: ENG | Q88: Supply chain security | R88: Signed-image enforcement | S88: ECR managed signing; SH ECR.1/.2/.3, Inspector.2 | T88: Not started | V88: =";"&SUBSTITUTE(P88," ","")&";" -> ;ENG;
A89: HD-26 | B89: P3 Build & Harden | C89: HD | D89: Bottlerocket CIS evidence (if D-05 selects Bottlerocket) | E89: CIS Bottlerocket v1.0.0 report via Bottlerocket tooling (verify method); evidence to GRC platform | F89: 16 | G89: 3 | H89: =F89+G89-1 -> 18 | I89: HD-05, HD-16A | J89: =IF(I89="","",SUMPRODUCT(MAX(ISNUMBER(SEARCH(","&$A$7:$A$156&",",","&SUBSTITUTE(I89," ","")&","))*$H$7:$H$156))) -> 8 | K89: =IF(I89="","OK",IF(F89>J89,"OK","VIOLATION")) -> OK | L89: =IF(H89<=26,"OK","LATE") -> OK | M89: =Overview!$B$4+7*(F89-1) -> 46426 | N89: =Overview!$B$4+7*(H89-1)+4 -> 46444 | O89: KHE | P89: GRCC | Q89: Bottlerocket | R89: Bottlerocket CIS evidence | S89: CIS Bottlerocket v1.0.0 | T89: Not started | V89: =";"&SUBSTITUTE(P89," ","")&";" -> ;GRCC;
A90: HD-20 | B90: P3 Build & Harden | C90: HD | D90: Data-protection configuration | E90: KMS rotation; Secrets Manager rotation; Aurora encryption/deletion protection; OpenSearch FGAC/audit; SQS/SNS/Kinesis/EFS encryption; ACM | F90: 12 | G90: 4 | H90: =F90+G90-1 -> 15 | I90: PM-09B, ID-05 | J90: =IF(I90="","",SUMPRODUCT(MAX(ISNUMBER(SEARCH(","&$A$7:$A$156&",",","&SUBSTITUTE(I90," ","")&","))*$H$7:$H$156))) -> 8 | K90: =IF(I90="","OK",IF(F90>J90,"OK","VIOLATION")) -> OK | L90: =IF(H90<=26,"OK","LATE") -> OK | M90: =Overview!$B$4+7*(F90-1) -> 46398 | N90: =Overview!$B$4+7*(H90-1)+4 -> 46423 | O90: CPE | P90: ENG | Q90: AWS data services | R90: Data-protection controls passing | S90: SH KMS.4, SecretsManager.1, RDS.2/.3/.7/.8/.27, Opensearch.1/.3/.5/.7, SQS.1, SNS.1, Kinesis.1, EFS.8, ACM.1 | T90: Not started | V90: =";"&SUBSTITUTE(P90," ","")&";" -> ;ENG;
A91: HD-30 | B91: P3 Build & Harden | C91: HD | D91: Macie sensitive-data discovery and data-perimeter validation | E91: Automated discovery on S3; validate RCP data perimeter | F91: 13 | G91: 4 | H91: =F91+G91-1 -> 16 | I91: HD-22, HD-10 | J91: =IF(I91="","",SUMPRODUCT(MAX(ISNUMBER(SEARCH(","&$A$7:$A$156&",",","&SUBSTITUTE(I91," ","")&","))*$H$7:$H$156))) -> 12 | K91: =IF(I91="","OK",IF(F91>J91,"OK","VIOLATION")) -> OK | L91: =IF(H91<=26,"OK","LATE") -> OK | M91: =Overview!$B$4+7*(F91-1) -> 46405 | N91: =Overview!$B$4+7*(H91-1)+4 -> 46430 | O91: CPE | P91: GRCC | Q91: Data security | R91: Sensitive-data findings triaged | S91: Amazon Macie docs; CSF 2.0 ID.AM-07 | T91: Not started | V91: =";"&SUBSTITUTE(P91," ","")&";" -> ;GRCC;
A92: ID-10 | B92: P3 Build & Harden | C92: ID | D92: Enrol device-bound FIDO2 keys for admins | E92: Enrol, attestation enforced, spares, loss procedure (signers use hardware wallets - BC-11) | F92: 9 | G92: 2 | H92: =F92+G92-1 -> 10 | I92: ID-00, ID-03 | J92: =IF(I92="","",SUMPRODUCT(MAX(ISNUMBER(SEARCH(","&$A$7:$A$156&",",","&SUBSTITUTE(I92," ","")&","))*$H$7:$H$156))) -> 5 | K92: =IF(I92="","OK",IF(F92>J92,"OK","VIOLATION")) -> OK | L92: =IF(H92<=26,"OK","LATE") -> OK | M92: =Overview!$B$4+7*(F92-1) -> 46377 | N92: =Overview!$B$4+7*(H92-1)+4 -> 46388 | O92: ISE | Q92: FIDO2 | R92: 100% admins enrolled | S92: Entra passkeys (FIDO2) docs | T92: Not started | V92: =";"&SUBSTITUTE(P92," ","")&";" -> ;;
A93: ID-08 | B93: P3 Build & Harden | C93: ID | D93: Entra Conditional Access baseline in report-only | E93: Block legacy auth; MFA all; phishing-resistant strength for admins; compliant device for admins; break-glass excluded | F93: 7 | G93: 4 | H93: =F93+G93-1 -> 10 | I93: ID-01, ID-03, PM-09A | J93: =IF(I93="","",SUMPRODUCT(MAX(ISNUMBER(SEARCH(","&$A$7:$A$156&",",","&SUBSTITUTE(I93," ","")&","))*$H$7:$H$156))) -> 6 | K93: =IF(I93="","OK",IF(F93>J93,"OK","VIOLATION")) -> OK | L93: =IF(H93<=26,"OK","LATE") -> OK | M93: =Overview!$B$4+7*(F93-1) -> 46363 | N93: =Overview!$B$4+7*(H93-1)+4 -> 46388 | O93: IDC | Q93: Entra CA | R93: Report-only impact analysis | S93: Entra CA docs; CIS Controls 6.3-6.5 | T93: Not started | V93: =";"&SUBSTITUTE(P93," ","")&";" -> ;;
A94: ID-08B | B94: P3 Build & Harden | C94: ID | D94: Enforce Conditional Access baseline (after freeze) | E94: Switch to On in waves; monitor sign-in failures; rollback criteria | F94: 11 | G94: 2 | H94: =F94+G94-1 -> 12 | I94: ID-08, ID-10 | J94: =IF(I94="","",SUMPRODUCT(MAX(ISNUMBER(SEARCH(","&$A$7:$A$156&",",","&SUBSTITUTE(I94," ","")&","))*$H$7:$H$156))) -> 10 | K94: =IF(I94="","OK",IF(F94>J94,"OK","VIOLATION")) -> OK | L94: =IF(H94<=26,"OK","LATE") -> OK | M94: =Overview!$B$4+7*(F94-1) -> 46391 | N94: =Overview!$B$4+7*(H94-1)+4 -> 46402 | O94: IDC | P94: ISE | Q94: Entra CA | R94: CA baseline enforced | S94: Entra CA docs | T94: Not started | V94: =";"&SUBSTITUTE(P94," ","")&";" -> ;ISE;
A95: ID-11 | B95: P3 Build & Harden | C95: ID | D95: AWS IAM Identity Center build-out | E95: SCIM; permission sets; JIT per D-16; remove IAM users/keys; centralized root access (member accounts) | F95: 9 | G95: 4 | H95: =F95+G95-1 -> 12 | I95: ID-04, PM-09A | J95: =IF(I95="","",SUMPRODUCT(MAX(ISNUMBER(SEARCH(","&$A$7:$A$156&",",","&SUBSTITUTE(I95," ","")&","))*$H$7:$H$156))) -> 6 | K95: =IF(I95="","OK",IF(F95>J95,"OK","VIOLATION")) -> OK | L95: =IF(H95<=26,"OK","LATE") -> OK | M95: =Overview!$B$4+7*(F95-1) -> 46377 | N95: =Overview!$B$4+7*(H95-1)+4 -> 46402 | O95: ISE | P95: CSE | Q95: IAM Identity Center | R95: No long-lived human IAM keys | S95: SH IAM.1/.2/.4/.6/.8/.22 | T95: Not started | V95: =";"&SUBSTITUTE(P95," ","")&";" -> ;CSE;
A96: ID-13 | B96: P3 Build & Harden | C96: ID | D96: B2C hardening and step-up MFA on withdrawals | E96: MFA enforcement; step-up on withdrawals and payout-address change with API-side fresh auth_time check; out-of-band confirmation + cool-down; fraud/bot vendor (D-13) | F96: 9 | G96: 5 | H96: =F96+G96-1 -> 13 | I96: ID-06, PM-09B | J96: =IF(I96="","",SUMPRODUCT(MAX(ISNUMBER(SEARCH(","&$A$7:$A$156&",",","&SUBSTITUTE(I96," ","")&","))*$H$7:$H$156))) -> 8 | K96: =IF(I96="","OK",IF(F96>J96,"OK","VIOLATION")) -> OK | L96: =IF(H96<=26,"OK","LATE") -> OK | M96: =Overview!$B$4+7*(F96-1) -> 46377 | N96: =Overview!$B$4+7*(H96-1)+4 -> 46409 | O96: IDC | P96: ISE; ENG | Q96: B2C custom policies | R96: Step-up live; B2C logs in Splunk | S96: B2C claim resolvers; B2C Azure Monitor docs | T96: Not started | V96: =";"&SUBSTITUTE(P96," ","")&";" -> ;ISE;ENG;
A97: ID-12 | B97: P3 Build & Harden | C97: ID | D97: Workload identity rollout | E97: Pod Identity/IRSA; CI/CD OIDC; secret rotation | F97: 12 | G97: 4 | H97: =F97+G97-1 -> 15 | I97: ID-05, PM-09B | J97: =IF(I97="","",SUMPRODUCT(MAX(ISNUMBER(SEARCH(","&$A$7:$A$156&",",","&SUBSTITUTE(I97," ","")&","))*$H$7:$H$156))) -> 8 | K97: =IF(I97="","OK",IF(F97>J97,"OK","VIOLATION")) -> OK | L97: =IF(H97<=26,"OK","LATE") -> OK | M97: =Overview!$B$4+7*(F97-1) -> 46398 | N97: =Overview!$B$4+7*(H97-1)+4 -> 46423 | O97: CPE | P97: ENG | Q97: AWS IAM | R97: No static cloud keys in CI/CD | S97: EKS Pod Identity; SH SecretsManager.1 | T97: Not started | V97: =";"&SUBSTITUTE(P97," ","")&";" -> ;ENG;
A98: ID-09 | B98: P3 Build & Harden | C98: ID | D98: PIM: zero standing privileged access (Entra, Azure, PIM for Groups -> AWS) | E98: Approval + MFA on activation; only break-glass permanent | F98: 13 | G98: 3 | H98: =F98+G98-1 -> 15 | I98: ID-08B, ID-11 | J98: =IF(I98="","",SUMPRODUCT(MAX(ISNUMBER(SEARCH(","&$A$7:$A$156&",",","&SUBSTITUTE(I98," ","")&","))*$H$7:$H$156))) -> 12 | K98: =IF(I98="","OK",IF(F98>J98,"OK","VIOLATION")) -> OK | L98: =IF(H98<=26,"OK","LATE") -> OK | M98: =Overview!$B$4+7*(F98-1) -> 46405 | N98: =Overview!$B$4+7*(H98-1)+4 -> 46423 | O98: ISE | Q98: Entra PIM | R98: Standing admins = break-glass only | S98: Entra PIM; CIS Controls 5.4/6.8 | T98: Not started | V98: =";"&SUBSTITUTE(P98," ","")&";" -> ;;
A99: ID-16 | B99: P3 Build & Harden | C99: ID | D99: Workforce ID Protection: risk-based CA, risky service principals | E99: Per D-02 licensing; user/sign-in risk policies; risky SP review | F99: 13 | G99: 3 | H99: =F99+G99-1 -> 15 | I99: ID-08B | J99: =IF(I99="","",SUMPRODUCT(MAX(ISNUMBER(SEARCH(","&$A$7:$A$156&",",","&SUBSTITUTE(I99," ","")&","))*$H$7:$H$156))) -> 12 | K99: =IF(I99="","OK",IF(F99>J99,"OK","VIOLATION")) -> OK | L99: =IF(H99<=26,"OK","LATE") -> OK | M99: =Overview!$B$4+7*(F99-1) -> 46405 | N99: =Overview!$B$4+7*(H99-1)+4 -> 46423 | O99: IDC | P99: ISE | Q99: Entra ID Protection | R99: Risk-based CA live | S99: Entra ID Protection docs | T99: Not started | V99: =";"&SUBSTITUTE(P99," ","")&";" -> ;ISE;
A100: ID-14 | B100: P3 Build & Harden | C100: ID | D100: Customer identity roadmap: B2C to External ID (D-06) | E100: Gaps (no IEF; no ID Protection in external tenants; passkeys not enforceable by CA); JIT password migration; timeline before May 2030 | F100: 14 | G100: 2 | H100: =F100+G100-1 -> 15 | I100: ID-06 | J100: =IF(I100="","",SUMPRODUCT(MAX(ISNUMBER(SEARCH(","&$A$7:$A$156&",",","&SUBSTITUTE(I100," ","")&","))*$H$7:$H$156))) -> 7 | K100: =IF(I100="","OK",IF(F100>J100,"OK","VIOLATION")) -> OK | L100: =IF(H100<=26,"OK","LATE") -> OK | M100: =Overview!$B$4+7*(F100-1) -> 46412 | N100: =Overview!$B$4+7*(H100-1)+4 -> 46423 | O100: IDC | P100: ISE | Q100: CIAM strategy | R100: D-06 roadmap | S100: External ID migration docs | T100: Not started | V100: =";"&SUBSTITUTE(P100," ","")&";" -> ;ISE;
A101: ID-15 | B101: P3 Build & Harden | C101: ID | D101: Wallet sign-in hardening implementation | E101: Implement verifier, nonce store, EIP-1271; tests; monitoring | F101: 15 | G101: 3 | H101: =F101+G101-1 -> 17 | I101: ID-07 | J101: =IF(I101="","",SUMPRODUCT(MAX(ISNUMBER(SEARCH(","&$A$7:$A$156&",",","&SUBSTITUTE(I101," ","")&","))*$H$7:$H$156))) -> 9 | K101: =IF(I101="","OK",IF(F101>J101,"OK","VIOLATION")) -> OK | L101: =IF(H101<=26,"OK","LATE") -> OK | M101: =Overview!$B$4+7*(F101-1) -> 46419 | N101: =Overview!$B$4+7*(H101-1)+4 -> 46437 | O101: BSC | P101: ENG | Q101: Web3 auth | R101: Hardened wallet sign-in | S101: EIP-4361; EIP-1271 | T101: Not started | V101: =";"&SUBSTITUTE(P101," ","")&";" -> ;ENG;
...

Sheet Roles & Skills
A1: Roles & Skills - live counts from Project Plan; capacity rule: leads <= cap and weighted load (lead 1 + support 0.25) <= 4 x FTE
A2: Partners and business contributors carry 0 program FTE. ENG supports only. Weekly load matrix below.
A4: Role ID | B4: Role | C4: Type | D4: Sourcing | E4: Avg FTE (in window) | F4: Window first wk | G4: Window last wk | H4: Core skills | I4: Certifications / evidence | J4: Lead cap (concurrent) | K4: Tasks led | L4: Tasks supported | M4: First wk led | N4: Last wk led | O4: Peak concurrent leads | P4: Load status | Q4: Peak weighted load | R4: FTE-weeks
A5: PL | B5: Security Program Lead | C5: Internal | D5: Internal (existing) | E5: 1 | F5: 0 | G5: 26 | H5: Program/portfolio management, risk, executive and board comms, budget, vendor management | I5: CISSP or CISM; PMP/PRINCE2 or equivalent delivery record | J5: 3 | K5: =COUNTIF('Project Plan'!$O$7:$O$156,A5) -> 18 | L5: =COUNTIF('Project Plan'!$V$7:$V$156,"*;"&A5&";*") -> 13 | M5: =IF(K5=0,"-",_xlfn.MINIFS('Project Plan'!$F$7:$F$156,'Project Plan'!$O$7:$O$156,A5)) -> 0 | N5: =IF(K5=0,"-",_xlfn.MAXIFS('Project Plan'!$H$7:$H$156,'Project Plan'!$O$7:$O$156,A5)) -> 26 | O5: =MAX(C36:AC36) -> 3 | P5: =IF(OR(O5>J5,AND(E5>0,Q5>4*E5+0.0001)),"OVER","OK") -> OK | Q5: =MAX(C61:AC61) -> 3.75 | R5: =E5*(G5-F5+1) -> 27
A6: CSE | B6: Cloud & Platform Security Engineer | C6: Internal | D6: Internal (existing) | E6: 1 | F6: 0 | G6: 26 | H6: AWS Organizations/Control Tower, SCP/RCP, EKS upgrades, VPC/TGW/Network Firewall, IaC | I6: AWS Certified Security - Specialty; CKS | J6: 3 | K6: =COUNTIF('Project Plan'!$O$7:$O$156,A6) -> 16 | L6: =COUNTIF('Project Plan'!$V$7:$V$156,"*;"&A6&";*") -> 21 | M6: =IF(K6=0,"-",_xlfn.MINIFS('Project Plan'!$F$7:$F$156,'Project Plan'!$O$7:$O$156,A6)) -> 0 | N6: =IF(K6=0,"-",_xlfn.MAXIFS('Project Plan'!$H$7:$H$156,'Project Plan'!$O$7:$O$156,A6)) -> 22 | O6: =MAX(C37:AC37) -> 3 | P6: =IF(OR(O6>J6,AND(E6>0,Q6>4*E6+0.0001)),"OVER","OK") -> OK | Q6: =MAX(C62:AC62) -> 4 | R6: =E6*(G6-F6+1) -> 27
A7: ISE | B7: Identity & Security Operations Engineer (IR Lead) | C7: Internal | D7: Internal (existing) | E7: 1 | F7: 0 | G7: 26 | H7: Entra ID CA/PIM, IAM Identity Center, Splunk ES, incident handling | I7: SC-300; SC-200 or Splunk ES Certified Admin; GCIH | J7: 3 | K7: =COUNTIF('Project Plan'!$O$7:$O$156,A7) -> 15 | L7: =COUNTIF('Project Plan'!$V$7:$V$156,"*;"&A7&";*") -> 34 | M7: =IF(K7=0,"-",_xlfn.MINIFS('Project Plan'!$F$7:$F$156,'Project Plan'!$O$7:$O$156,A7)) -> 0 | N7: =IF(K7=0,"-",_xlfn.MAXIFS('Project Plan'!$H$7:$H$156,'Project Plan'!$O$7:$O$156,A7)) -> 20 | O7: =MAX(C38:AC38) -> 3 | P7: =IF(OR(O7>J7,AND(E7>0,Q7>4*E7+0.0001)),"OVER","OK") -> OK | Q7: =MAX(C63:AC63) -> 4 | R7: =E7*(G7-F7+1) -> 27
A8: GRC | B8: GRC & Risk Lead (2nd line) | C8: Internal | D8: Internal (existing) | E8: 1 | F8: 0 | G8: 26 | H8: SOC 2, NIST CSF 2.0, ISO 27001, TPRM, risk, audit liaison | I8: CISA and/or CRISC; ISO 27001 Lead Implementer | J8: 3 | K8: =COUNTIF('Project Plan'!$O$7:$O$156,A8) -> 13 | L8: =COUNTIF('Project Plan'!$V$7:$V$156,"*;"&A8&";*") -> 21 | M8: =IF(K8=0,"-",_xlfn.MINIFS('Project Plan'!$F$7:$F$156,'Project Plan'!$O$7:$O$156,A8)) -> 0 | N8: =IF(K8=0,"-",_xlfn.MAXIFS('Project Plan'!$H$7:$H$156,'Project Plan'!$O$7:$O$156,A8)) -> 21 | O8: =MAX(C39:AC39) -> 3 | P8: =IF(OR(O8>J8,AND(E8>0,Q8>4*E8+0.0001)),"OVER","OK") -> OK | Q8: =MAX(C64:AC64) -> 4 | R8: =E8*(G8-F8+1) -> 27
A9: BSE | B9: Blockchain Security Engineer | C9: Internal | D9: Internal (existing) | E9: 1 | F9: 0 | G9: 26 | H9: Solidity and Rust/Anchor review, Safe/Squads operations, MPC custody, staking mechanics, on-chain IR | I9: Public audit/contest track record (audit reports, contest placings) | J9: 3 | K9: =COUNTIF('Project Plan'!$O$7:$O$156,A9) -> 20 | L9: =COUNTIF('Project Plan'!$V$7:$V$156,"*;"&A9&";*") -> 25 | M9: =IF(K9=0,"-",_xlfn.MINIFS('Project Plan'!$F$7:$F$156,'Project Plan'!$O$7:$O$156,A9)) -> 0 | N9: =IF(K9=0,"-",_xlfn.MAXIFS('Project Plan'!$H$7:$H$156,'Project Plan'!$O$7:$O$156,A9)) -> 24 | O9: =MAX(C40:AC40) -> 3 | P9: =IF(OR(O9>J9,AND(E9>0,Q9>4*E9+0.0001)),"OVER","OK") -> OK | Q9: =MAX(C65:AC65) -> 4 | R9: =E9*(G9-F9+1) -> 27
A10: KHE | B10: Contract Cloud/K8s Hardening Engineer | C10: Contractor | D10: Contractor (T&M) | E10: 1 | F10: 2 | G10: 22 | H10: CIS benchmarks, SSM, Image Builder, AL2023/Bottlerocket, EKS upgrades, Kubernetes admission policy | I10: CKS; AWS Security Specialty; CIS-CAT experience | J10: 3 | K10: =COUNTIF('Project Plan'!$O$7:$O$156,A10) -> 13 | L10: =COUNTIF('Project Plan'!$V$7:$V$156,"*;"&A10&";*") -> 9 | M10: =IF(K10=0,"-",_xlfn.MINIFS('Project Plan'!$F$7:$F$156,'Project Plan'!$O$7:$O$156,A10)) -> 2 | N10: =IF(K10=0,"-",_xlfn.MAXIFS('Project Plan'!$H$7:$H$156,'Project Plan'!$O$7:$O$156,A10)) -> 19 | O10: =MAX(C41:AC41) -> 3 | P10: =IF(OR(O10>J10,AND(E10>0,Q10>4*E10+0.0001)),"OVER","OK") -> OK | Q10: =MAX(C66:AC66) -> 3.75 | R10: =E10*(G10-F10+1) -> 21
A11: CPE | B11: Contract Cloud Platform Security Engineer | C11: Contractor | D11: Contractor (T&M) | E11: 1 | F11: 3 | G11: 20 | H11: S3 Object Lock/log archive, AWS Backup/Aurora, KMS/Secrets Manager, EKS node groups, CloudFront/DNS | I11: AWS Security Specialty or SA Professional | J11: 3 | K11: =COUNTIF('Project Plan'!$O$7:$O$156,A11) -> 9 | L11: =COUNTIF('Project Plan'!$V$7:$V$156,"*;"&A11&";*") -> 0 | M11: =IF(K11=0,"-",_xlfn.MINIFS('Project Plan'!$F$7:$F$156,'Project Plan'!$O$7:$O$156,A11)) -> 3 | N11: =IF(K11=0,"-",_xlfn.MAXIFS('Project Plan'!$H$7:$H$156,'Project Plan'!$O$7:$O$156,A11)) -> 17 | O11: =MAX(C42:AC42) -> 3 | P11: =IF(OR(O11>J11,AND(E11>0,Q11>4*E11+0.0001)),"OVER","OK") -> OK | Q11: =MAX(C67:AC67) -> 3 | R11: =E11*(G11-F11+1) -> 18
A12: DET | B12: Contract Detection Engineer (Splunk) | C12: Contractor | D12: Contractor (T&M) | E12: 1 | F12: 3 | G12: 24 | H12: SPL, Splunk ES 8 detections, contentctl detection-as-code, Splunk SOAR (Python 3.13) | I12: Splunk Certified Cybersecurity Defense Engineer or ES Admin; GCDA/GCIA | J12: 3 | K12: =COUNTIF('Project Plan'!$O$7:$O$156,A12) -> 9 | L12: =COUNTIF('Project Plan'!$V$7:$V$156,"*;"&A12&";*") -> 4 | M12: =IF(K12=0,"-",_xlfn.MINIFS('Project Plan'!$F$7:$F$156,'Project Plan'!$O$7:$O$156,A12)) -> 6 | N12: =IF(K12=0,"-",_xlfn.MAXIFS('Project Plan'!$H$7:$H$156,'Project Plan'!$O$7:$O$156,A12)) -> 18 | O12: =MAX(C43:AC43) -> 3 | P12: =IF(OR(O12>J12,AND(E12>0,Q12>4*E12+0.0001)),"OVER","OK") -> OK | Q12: =MAX(C68:AC68) -> 3 | R12: =E12*(G12-F12+1) -> 22
A13: IDC | B13: Contract Identity Specialist (Entra/B2C) | C13: Contractor | D13: Contractor (T&M) | E13: 0.5 | F13: 3 | G13: 18 | H13: Entra CA/PIM/auth strengths/ID Protection, Azure AD B2C custom policies (IEF), External ID | I13: SC-300; delivered B2C custom-policy projects | J13: 2 | K13: =COUNTIF('Project Plan'!$O$7:$O$156,A13) -> 9 | L13: =COUNTIF('Project Plan'!$V$7:$V$156,"*;"&A13&";*") -> 0 | M13: =IF(K13=0,"-",_xlfn.MINIFS('Project Plan'!$F$7:$F$156,'Project Plan'!$O$7:$O$156,A13)) -> 3 | N13: =IF(K13=0,"-",_xlfn.MAXIFS('Project Plan'!$H$7:$H$156,'Project Plan'!$O$7:$O$156,A13)) -> 18 | O13: =MAX(C44:AC44) -> 2 | P13: =IF(OR(O13>J13,AND(E13>0,Q13>4*E13+0.0001)),"OVER","OK") -> OK | Q13: =MAX(C69:AC69) -> 2 | R13: =E13*(G13-F13+1) -> 8
A14: CSO | B14: Contract Custody, Staking & Sanctions Specialist | C14: Contractor | D14: Contractor (T&M) | E14: 1 | F14: 3 | G14: 22 | H14: MPC custody policy engines, CCSS v9, Ethereum/Solana staking, OFAC wallet screening | I14: CCSS auditor (CCSSA) or equivalent custody assessment record | J14: 3 | K14: =COUNTIF('Project Plan'!$O$7:$O$156,A14) -> 6 | L14: =COUNTIF('Project Plan'!$V$7:$V$156,"*;"&A14&";*") -> 6 | M14: =IF(K14=0,"-",_xlfn.MINIFS('Project Plan'!$F$7:$F$156,'Project Plan'!$O$7:$O$156,A14)) -> 5 | N14: =IF(K14=0,"-",_xlfn.MAXIFS('Project Plan'!$H$7:$H$156,'Project Plan'!$O$7:$O$156,A14)) -> 19 | O14: =MAX(C45:AC45) -> 3 | P14: =IF(OR(O14>J14,AND(E14>0,Q14>4*E14+0.0001)),"OVER","OK") -> OK | Q14: =MAX(C70:AC70) -> 3.25 | R14: =E14*(G14-F14+1) -> 20
A15: BSC | B15: Contract Smart-Contract Security Engineer | C15: Contractor | D15: Contractor (T&M) | E15: 0.5 | F15: 5 | G15: 22 | H15: Foundry/Slither/Aderyn/Echidna, Anchor 1.x/Trident/solana-verify, SIWE/SIWS | I15: Public audit or contest record on EVM and Solana | J15: 2 | K15: =COUNTIF('Project Plan'!$O$7:$O$156,A15) -> 6 | L15: =COUNTIF('Project Plan'!$V$7:$V$156,"*;"&A15&";*") -> 3 | M15: =IF(K15=0,"-",_xlfn.MINIFS('Project Plan'!$F$7:$F$156,'Project Plan'!$O$7:$O$156,A15)) -> 5 | N15: =IF(K15=0,"-",_xlfn.MAXIFS('Project Plan'!$H$7:$H$156,'Project Plan'!$O$7:$O$156,A15)) -> 18 | O15: =MAX(C46:AC46) -> 2 | P15: =IF(OR(O15>J15,AND(E15>0,Q15>4*E15+0.0001)),"OVER","OK") -> OK | Q15: =MAX(C71:AC71) -> 2 | R15: =E15*(G15-F15+1) -> 9
A16: GRCC | B16: Contract SOC 2 Implementation Consultant | C16: Contractor | D16: Contractor (fixed fee) | E16: 1 | F16: 3 | G16: 24 | H16: Control matrices, policy drafting, GRC platform build, evidence design | I16: CISA; >=3 SOC 2 implementations | J16: 3 | K16: =COUNTIF('Project Plan'!$O$7:$O$156,A16) -> 5 | L16: =COUNTIF('Project Plan'!$V$7:$V$156,"*;"&A16&";*") -> 5 | M16: =IF(K16=0,"-",_xlfn.MINIFS('Project Plan'!$F$7:$F$156,'Project Plan'!$O$7:$O$156,A16)) -> 3 | N16: =IF(K16=0,"-",_xlfn.MAXIFS('Project Plan'!$H$7:$H$156,'Project Plan'!$O$7:$O$156,A16)) -> 11 | O16: =MAX(C47:AC47) -> 3 | P16: =IF(OR(O16>J16,AND(E16>0,Q16>4*E16+0.0001)),"OVER","OK") -> OK | Q16: =MAX(C72:AC72) -> 3.5 | R16: =E16*(G16-F16+1) -> 22
... A26: ENG | B26: Platform & App Engineering teams (change implementers) | C26: Internal-BAU | D26: Internal (outside program FTE) | E26: 0 | F26: 0 | G26: 26 | H26: Workload migration, CI/CD, application changes | I26: n/a - supporting only, never lead | J26: 0 | K26: =COUNTIF('Project Plan'!$O$7:$O$156,A26) -> 0 | L26: =COUNTIF('Project Plan'!$V$7:$V$156,"*;"&A26&";*") -> 34 | M26: =IF(K26=0,"-",_xlfn.MINIFS('Project Plan'!$F$7:$F$156,'Project Plan'!$O$7:$O$156,A26)) -> - | N26: =IF(K26=0,"-",_xlfn.MAXIFS('Project Plan'!$H$7:$H$156,'Project Plan'!$O$7:$O$156,A26)) -> - | O26: =MAX(C57:AC57) -> 0 | P26: =IF(OR(O26>J26,AND(E26>0,Q26>4*E26+0.0001)),"OVER","OK") -> OK | Q26: =MAX(C82:AC82) -> 2.75 | R26: =E26*(G26-F26+1) -> 0
A27: Internal program FTE (total) | E27: =SUMIFS(E5:E26,C5:C26,"Internal") -> 5 | G27: Contractor FTE-weeks | H27: =SUMIFS(R5:R26,C5:C26,"Contractor") -> 133
A28: Contractor FTE (peak concurrent week) | E28: =MAX(C32:AC32) -> 6.5 | G28: Internal FTE-weeks | H28: =SUMIFS(R5:R26,C5:C26,"Internal") -> 135
A29: Partner / firm engagements (count) | E29: =COUNTIF(C5:C26,"Partner") -> 7
A30: Internal within 3-5 FTE range? | E30: =IF(AND(E27>=3,E27<=5),"YES","NO") -> YES
C31: 0 | D31: 1 | E31: 2 | F31: 3 | G31: 4 | H31: 5 | I31: 6 | J31: 7 | K31: 8 | L31: 9 | M31: 10 | N31: 11 | O31: 12 | P31: 13 | Q31: 14 | R31: 15 | S31: 16 | T31: 17 | U31: 18 | V31: 19 | W31: 20 | X31: 21 | Y31: 22 | Z31: 23 | AA31: 24 | AB31: 25 | AC31: 26
A32: Contractor FTE by week | B32: wk -> | C32: =SUMPRODUCT((C5:C26="Contractor")*(F5:F26<=C31)*(G5:G26>=C31)*E5:E26) -> 0 | D32: =SUMPRODUCT((C5:C26="Contractor")*(F5:F26<=D31)*(G5:G26>=D31)*E5:E26) -> 0.5 | E32: =SUMPRODUCT((C5:C26="Contractor")*(F5:F26<=E31)*(G5:G26>=E31)*E5:E26) -> 1.5 | F32: =SUMPRODUCT((C5:C26="Contractor")*(F5:F26<=F31)*(G5:G26>=F31)*E5:E26) -> 6 | G32: =SUMPRODUCT((C5:C26="Contractor")*(F5:F26<=G31)*(G5:G26>=G31)*E5:E26) -> 6 | H32: =SUMPRODUCT((C5:C26="Contractor")*(F5:F26<=H31)*(G5:G26>=H31)*E5:E26) -> 6.5 | I32: =SUMPRODUCT((C5:C26="Contractor")*(F5:F26<=I31)*(G5:G26>=I31)*E5:E26) -> 6.5 | J32: =SUMPRODUCT((C5:C26="Contractor")*(F5:F26<=J31)*(G5:G26>=J31)*E5:E26) -> 6.5 | K32: =SUMPRODUCT((C5:C26="Contractor")*(F5:F26<=K31)*(G5:G26>=K31)*E5:E26) -> 6.5 | L32: =SUMPRODUCT((C5:C26="Contractor")*(F5:F26<=L31)*(G5:G26>=L31)*E5:E26) -> 6.5 | M32: =SUMPRODUCT((C5:C26="Contractor")*(F5:F26<=M31)*(G5:G26>=M31)*E5:E26) -> 6.5 | N32: =SUMPRODUCT((C5:C26="Contractor")*(F5:F26<=N31)*(G5:G26>=N31)*E5:E26) -> 6.5 | O32: =SUMPRODUCT((C5:C26="Contractor")*(F5:F26<=O31)*(G5:G26>=O31)*E5:E26) -> 6.5 | P32: =SUMPRODUCT((C5:C26="Contractor")*(F5:F26<=P31)*(G5:G26>=P31)*E5:E26) -> 6.5 | Q32: =SUMPRODUCT((C5:C26="Contractor")*(F5:F26<=Q31)*(G5:G26>=Q31)*E5:E26) -> 6.5 | R32: =SUMPRODUCT((C5:C26="Contractor")*(F5:F26<=R31)*(G5:G26>=R31)*E5:E26) -> 6.5 | S32: =SUMPRODUCT((C5:C26="Contractor")*(F5:F26<=S31)*(G5:G26>=S31)*E5:E26) -> 6.5 | T32: =SUMPRODUCT((C5:C26="Contractor")*(F5:F26<=T31)*(G5:G26>=T31)*E5:E26) -> 6.5 | U32: =SUMPRODUCT((C5:C26="Contractor")*(F5:F26<=U31)*(G5:G26>=U31)*E5:E26) -> 6.5 | V32: =SUMPRODUCT((C5:C26="Contractor")*(F5:F26<=V31)*(G5:G26>=V31)*E5:E26) -> 6 | W32: =SUMPRODUCT((C5:C26="Contractor")*(F5:F26<=W31)*(G5:G26>=W31)*E5:E26) -> 6 | X32: =SUMPRODUCT((C5:C26="Contractor")*(F5:F26<=X31)*(G5:G26>=X31)*E5:E26) -> 5 | Y32: =SUMPRODUCT((C5:C26="Contractor")*(F5:F26<=Y31)*(G5:G26>=Y31)*E5:E26) -> 5 | Z32: =SUMPRODUCT((C5:C26="Contractor")*(F5:F26<=Z31)*(G5:G26>=Z31)*E5:E26) -> 2.5 | AA32: =SUMPRODUCT((C5:C26="Contractor")*(F5:F26<=AA31)*(G5:G26>=AA31)*E5:E26) -> 2.5 | AB32: =SUMPRODUCT((C5:C26="Contractor")*(F5:F26<=AB31)*(G5:G26>=AB31)*E5:E26) -> 0.5 | AC32: =SUMPRODUCT((C5:C26="Contractor")*(F5:F26<=AC31)*(G5:G26>=AC31)*E5:E26) -> 0.5
A34: Concurrent LEAD tasks per role per week
A35: Role | B35: Cap | C35: 0 | D35: 1 | E35: 2 | F35: 3 | G35: 4 | H35: 5 | I35: 6 | J35: 7 | K35: 8 | L35: 9 | M35: 10 | N35: 11 | O35: 12 | P35: 13 | Q35: 14 | R35: 15 | S35: 16 | T35: 17 | U35: 18 | V35: 19 | W35: 20 | X35: 21 | Y35: 22 | Z35: 23 | AA35: 24 | AB35: 25 | AC35: 26
A36: =A5 -> PL | B36: =J5 -> 3 | C36: =COUNTIFS('Project Plan'!$O$7:$O$156,$A36,'Project Plan'!$F$7:$F$156,"<="&C$35,'Project Plan'!$H$7:$H$156,">="&C$35) -> 3 | D36: =COUNTIFS('Project Plan'!$O$7:$O$156,$A36,'Project Plan'!$F$7:$F$156,"<="&D$35,'Project Plan'!$H$7:$H$156,">="&D$35) -> 2 | E36: =COUNTIFS('Project Plan'!$O$7:$O$156,$A36,'Project Plan'!$F$7:$F$156,"<="&E$35,'Project Plan'!$H$7:$H$156,">="&E$35) -> 2 | F36: =COUNTIFS('Project Plan'!$O$7:$O$156,$A36,'Project Plan'!$F$7:$F$156,"<="&F$35,'Project Plan'!$H$7:$H$156,">="&F$35) -> 3 | G36: =COUNTIFS('Project Plan'!$O$7:$O$156,$A36,'Project Plan'!$F$7:$F$156,"<="&G$35,'Project Plan'!$H$7:$H$156,">="&G$35) -> 2 | H36: =COUNTIFS('Project Plan'!$O$7:$O$156,$A36,'Project Plan'!$F$7:$F$156,"<="&H$35,'Project Plan'!$H$7:$H$156,">="&H$35) -> 2 | I36: =COUNTIFS('Project Plan'!$O$7:$O$156,$A36,'Project Plan'!$F$7:$F$156,"<="&I$35,'Project Plan'!$H$7:$H$156,">="&I$35) -> 3 | J36: =COUNTIFS('Project Plan'!$O$7:$O$156,$A36,'Project Plan'!$F$7:$F$156,"<="&J$35,'Project Plan'!$H$7:$H$156,">="&J$35) -> 1 | ... AC36: =COUNTIFS('Project Plan'!$O$7:$O$156,$A36,'Project Plan'!$F$7:$F$156,"<="&AC$35,'Project Plan'!$H$7:$H$156,">="&AC$35) -> 1
A37: =A6 -> CSE | B37: =J6 -> 3 | C37: =COUNTIFS('Project Plan'!$O$7:$O$156,$A37,'Project Plan'!$F$7:$F$156,"<="&C$35,'Project Plan'!$H$7:$H$156,">="&C$35) -> 3 | D37: =COUNTIFS('Project Plan'!$O$7:$O$156,$A37,'Project Plan'!$F$7:$F$156,"<="&D$35,'Project Plan'!$H$7:$H$156,">="&D$35) -> 3 | E37: =COUNTIFS('Project Plan'!$O$7:$O$156,$A37,'Project Plan'!$F$7:$F$156,"<="&E$35,'Project Plan'!$H$7:$H$156,">="&E$35) -> 2 | F37: =COUNTIFS('Project Plan'!$O$7:$O$156,$A37,'Project Plan'!$F$7:$F$156,"<="&F$35,'Project Plan'!$H$7:$H$156,">="&F$35) -> 3 | G37: =COUNTIFS('Project Plan'!$O$7:$O$156,$A37,'Project Plan'!$F$7:$F$156,"<="&G$35,'Project Plan'!$H$7:$H$156,">="&G$35) -> 2 | H37: =COUNTIFS('Project Plan'!$O$7:$O$156,$A37,'Project Plan'!$F$7:$F$156,"<="&H$35,'Project Plan'!$H$7:$H$156,">="&H$35) -> 3 | I37: =COUNTIFS('Project Plan'!$O$7:$O$156,$A37,'Project Plan'!$F$7:$F$156,"<="&I$35,'Project Plan'!$H$7:$H$156,">="&I$35) -> 3 | J37: =COUNTIFS('Project Plan'!$O$7:$O$156,$A37,'Project Plan'!$F$7:$F$156,"<="&J$35,'Project Plan'!$H$7:$H$156,">="&J$35) -> 3 | ... AC37: =COUNTIFS('Project Plan'!$O$7:$O$156,$A37,'Project Plan'!$F$7:$F$156,"<="&AC$35,'Project Plan'!$H$7:$H$156,">="&AC$35) -> 0
A38: =A7 -> ISE | B38: =J7 -> 3 | C38: =COUNTIFS('Project Plan'!$O$7:$O$156,$A38,'Project Plan'!$F$7:$F$156,"<="&C$35,'Project Plan'!$H$7:$H$156,">="&C$35) -> 3 | D38: =COUNTIFS('Project Plan'!$O$7:$O$156,$A38,'Project Plan'!$F$7:$F$156,"<="&D$35,'Project Plan'!$H$7:$H$156,">="&D$35) -> 3 | E38: =COUNTIFS('Project Plan'!$O$7:$O$156,$A38,'Project Plan'!$F$7:$F$156,"<="&E$35,'Project Plan'!$H$7:$H$156,">="&E$35) -> 1 | F38: =COUNTIFS('Project Plan'!$O$7:$O$156,$A38,'Project Plan'!$F$7:$F$156,"<="&F$35,'Project Plan'!$H$7:$H$156,">="&F$35) -> 3 | G38: =COUNTIFS('Project Plan'!$O$7:$O$156,$A38,'Project Plan'!$F$7:$F$156,"<="&G$35,'Project Plan'!$H$7:$H$156,">="&G$35) -> 3 | H38: =COUNTIFS('Project Plan'!$O$7:$O$156,$A38,'Project Plan'!$F$7:$F$156,"<="&H$35,'Project Plan'!$H$7:$H$156,">="&H$35) -> 2 | I38: =COUNTIFS('Project Plan'!$O$7:$O$156,$A38,'Project Plan'!$F$7:$F$156,"<="&I$35,'Project Plan'!$H$7:$H$156,">="&I$35) -> 3 | J38: =COUNTIFS('Project Plan'!$O$7:$O$156,$A38,'Project Plan'!$F$7:$F$156,"<="&J$35,'Project Plan'!$H$7:$H$156,">="&J$35) -> 3 | ... AC38: =COUNTIFS('Project Plan'!$O$7:$O$156,$A38,'Project Plan'!$F$7:$F$156,"<="&AC$35,'Project Plan'!$H$7:$H$156,">="&AC$35) -> 0
A39: =A8 -> GRC | B39: =J8 -> 3 | C39: =COUNTIFS('Project Plan'!$O$7:$O$156,$A39,'Project Plan'!$F$7:$F$156,"<="&C$35,'Project Plan'!$H$7:$H$156,">="&C$35) -> 1 | D39: =COUNTIFS('Project Plan'!$O$7:$O$156,$A39,'Project Plan'!$F$7:$F$156,"<="&D$35,'Project Plan'!$H$7:$H$156,">="&D$35) -> 1 | E39: =COUNTIFS('Project Plan'!$O$7:$O$156,$A39,'Project Plan'!$F$7:$F$156,"<="&E$35,'Project Plan'!$H$7:$H$156,">="&E$35) -> 1 | F39: =COUNTIFS('Project Plan'!$O$7:$O$156,$A39,'Project Plan'!$F$7:$F$156,"<="&F$35,'Project Plan'!$H$7:$H$156,">="&F$35) -> 2 | G39: =COUNTIFS('Project Plan'!$O$7:$O$156,$A39,'Project Plan'!$F$7:$F$156,"<="&G$35,'Project Plan'!$H$7:$H$156,">="&G$35) -> 3 | H39: =COUNTIFS('Project Plan'!$O$7:$O$156,$A39,'Project Plan'!$F$7:$F$156,"<="&H$35,'Project Plan'!$H$7:$H$156,">="&H$35) -> 3 | I39: =COUNTIFS('Project Plan'!$O$7:$O$156,$A39,'Project Plan'!$F$7:$F$156,"<="&I$35,'Project Plan'!$H$7:$H$156,">="&I$35) -> 3 | J39: =COUNTIFS('Project Plan'!$O$7:$O$156,$A39,'Project Plan'!$F$7:$F$156,"<="&J$35,'Project Plan'!$H$7:$H$156,">="&J$35) -> 3 | ... AC39: =COUNTIFS('Project Plan'!$O$7:$O$156,$A39,'Project Plan'!$F$7:$F$156,"<="&AC$35,'Project Plan'!$H$7:$H$156,">="&AC$35) -> 0
A40: =A9 -> BSE | B40: =J9 -> 3 | C40: =COUNTIFS('Project Plan'!$O$7:$O$156,$A40,'Project Plan'!$F$7:$F$156,"<="&C$35,'Project Plan'!$H$7:$H$156,">="&C$35) -> 3 | D40: =COUNTIFS('Project Plan'!$O$7:$O$156,$A40,'Project Plan'!$F$7:$F$156,"<="&D$35,'Project Plan'!$H$7:$H$156,">="&D$35) -> 3 | E40: =COUNTIFS('Project Plan'!$O$7:$O$156,$A40,'Project Plan'!$F$7:$F$156,"<="&E$35,'Project Plan'!$H$7:$H$156,">="&E$35) -> 3 | F40: =COUNTIFS('Project Plan'!$O$7:$O$156,$A40,'Project Plan'!$F$7:$F$156,"<="&F$35,'Project Plan'!$H$7:$H$156,">="&F$35) -> 3 | G40: =COUNTIFS('Project Plan'!$O$7:$O$156,$A40,'Project Plan'!$F$7:$F$156,"<="&G$35,'Project Plan'!$H$7:$H$156,">="&G$35) -> 3 | H40: =COUNTIFS('Project Plan'!$O$7:$O$156,$A40,'Project Plan'!$F$7:$F$156,"<="&H$35,'Project Plan'!$H$7:$H$156,">="&H$35) -> 3 | I40: =COUNTIFS('Project Plan'!$O$7:$O$156,$A40,'Project Plan'!$F$7:$F$156,"<="&I$35,'Project Plan'!$H$7:$H$156,">="&I$35) -> 2 | J40: =COUNTIFS('Project Plan'!$O$7:$O$156,$A40,'Project Plan'!$F$7:$F$156,"<="&J$35,'Project Plan'!$H$7:$H$156,">="&J$35) -> 2 | ... AC40: =COUNTIFS('Project Plan'!$O$7:$O$156,$A40,'Project Plan'!$F$7:$F$156,"<="&AC$35,'Project Plan'!$H$7:$H$156,">="&AC$35) -> 0
A41: =A10 -> KHE | B41: =J10 -> 3 | C41: =COUNTIFS('Project Plan'!$O$7:$O$156,$A41,'Project Plan'!$F$7:$F$156,"<="&C$35,'Project Plan'!$H$7:$H$156,">="&C$35) -> 0 | D41: =COUNTIFS('Project Plan'!$O$7:$O$156,$A41,'Project Plan'!$F$7:$F$156,"<="&D$35,'Project Plan'!$H$7:$H$156,">="&D$35) -> 0 | E41: =COUNTIFS('Project Plan'!$O$7:$O$156,$A41,'Project Plan'!$F$7:$F$156,"<="&E$35,'Project Plan'!$H$7:$H$156,">="&E$35) -> 3 | F41: =COUNTIFS('Project Plan'!$O$7:$O$156,$A41,'Project Plan'!$F$7:$F$156,"<="&F$35,'Project Plan'!$H$7:$H$156,">="&F$35) -> 3 | G41: =COUNTIFS('Project Plan'!$O$7:$O$156,$A41,'Project Plan'!$F$7:$F$156,"<="&G$35,'Project Plan'!$H$7:$H$156,">="&G$35) -> 3 | H41: =COUNTIFS('Project Plan'!$O$7:$O$156,$A41,'Project Plan'!$F$7:$F$156,"<="&H$35,'Project Plan'!$H$7:$H$156,">="&H$35) -> 1 | I41: =COUNTIFS('Project Plan'!$O$7:$O$156,$A41,'Project Plan'!$F$7:$F$156,"<="&I$35,'Project Plan'!$H$7:$H$156,">="&I$35) -> 3 | J41: =COUNTIFS('Project Plan'!$O$7:$O$156,$A41,'Project Plan'!$F$7:$F$156,"<="&J$35,'Project Plan'!$H$7:$H$156,">="&J$35) -> 3 | ... AC41: =COUNTIFS('Project Plan'!$O$7:$O$156,$A41,'Project Plan'!$F$7:$F$156,"<="&AC$35,'Project Plan'!$H$7:$H$156,">="&AC$35) -> 0
A42: =A11 -> CPE | B42: =J11 -> 3 | C42: =COUNTIFS('Project Plan'!$O$7:$O$156,$A42,'Project Plan'!$F$7:$F$156,"<="&C$35,'Project Plan'!$H$7:$H$156,">="&C$35) -> 0 | D42: =COUNTIFS('Project Plan'!$O$7:$O$156,$A42,'Project Plan'!$F$7:$F$156,"<="&D$35,'Project Plan'!$H$7:$H$156,">="&D$35) -> 0 | E42: =COUNTIFS('Project Plan'!$O$7:$O$156,$A42,'Project Plan'!$F$7:$F$156,"<="&E$35,'Project Plan'!$H$7:$H$156,">="&E$35) -> 0 | F42: =COUNTIFS('Project Plan'!$O$7:$O$156,$A42,'Project Plan'!$F$7:$F$156,"<="&F$35,'Project Plan'!$H$7:$H$156,">="&F$35) -> 1 | G42: =COUNTIFS('Project Plan'!$O$7:$O$156,$A42,'Project Plan'!$F$7:$F$156,"<="&G$35,'Project Plan'!$H$7:$H$156,">="&G$35) -> 2 | H42: =COUNTIFS('Project Plan'!$O$7:$O$156,$A42,'Project Plan'!$F$7:$F$156,"<="&H$35,'Project Plan'!$H$7:$H$156,">="&H$35) -> 2 | I42: =COUNTIFS('Project Plan'!$O$7:$O$156,$A42,'Project Plan'!$F$7:$F$156,"<="&I$35,'Project Plan'!$H$7:$H$156,">="&I$35) -> 2 | J42: =COUNTIFS('Project Plan'!$O$7:$O$156,$A42,'Project Plan'!$F$7:$F$156,"<="&J$35,'Project Plan'!$H$7:$H$156,">="&J$35) -> 3 | ... AC42: =COUNTIFS('Project Plan'!$O$7:$O$156,$A42,'Project Plan'!$F$7:$F$156,"<="&AC$35,'Project Plan'!$H$7:$H$156,">="&AC$35) -> 0
A43: =A12 -> DET | B43: =J12 -> 3 | C43: =COUNTIFS('Project Plan'!$O$7:$O$156,$A43,'Project Plan'!$F$7:$F$156,"<="&C$35,'Project Plan'!$H$7:$H$156,">="&C$35) -> 0 | D43: =COUNTIFS('Project Plan'!$O$7:$O$156,$A43,'Project Plan'!$F$7:$F$156,"<="&D$35,'Project Plan'!$H$7:$H$156,">="&D$35) -> 0 | E43: =COUNTIFS('Project Plan'!$O$7:$O$156,$A43,'Project Plan'!$F$7:$F$156,"<="&E$35,'Project Plan'!$H$7:$H$156,">="&E$35) -> 0 | F43: =COUNTIFS('Project Plan'!$O$7:$O$156,$A43,'Project Plan'!$F$7:$F$156,"<="&F$35,'Project Plan'!$H$7:$H$156,">="&F$35) -> 0 | G43: =COUNTIFS('Project Plan'!$O$7:$O$156,$A43,'Project Plan'!$F$7:$F$156,"<="&G$35,'Project Plan'!$H$7:$H$156,">="&G$35) -> 0 | H43: =COUNTIFS('Project Plan'!$O$7:$O$156,$A43,'Project Plan'!$F$7:$F$156,"<="&H$35,'Project Plan'!$H$7:$H$156,">="&H$35) -> 0 | I43: =COUNTIFS('Project Plan'!$O$7:$O$156,$A43,'Project Plan'!$F$7:$F$156,"<="&I$35,'Project Plan'!$H$7:$H$156,">="&I$35) -> 1 | J43: =COUNTIFS('Project Plan'!$O$7:$O$156,$A43,'Project Plan'!$F$7:$F$156,"<="&J$35,'Project Plan'!$H$7:$H$156,">="&J$35) -> 2 | ... AC43: =COUNTIFS('Project Plan'!$O$7:$O$156,$A43,'Project Plan'!$F$7:$F$156,"<="&AC$35,'Project Plan'!$H$7:$H$156,">="&AC$35) -> 0
A44: =A13 -> IDC | B44: =J13 -> 2 | C44: =COUNTIFS('Project Plan'!$O$7:$O$156,$A44,'Project Plan'!$F$7:$F$156,"<="&C$35,'Project Plan'!$H$7:$H$156,">="&C$35) -> 0 | D44: =COUNTIFS('Project Plan'!$O$7:$O$156,$A44,'Project Plan'!$F$7:$F$156,"<="&D$35,'Project Plan'!$H$7:$H$156,">="&D$35) -> 0 | E44: =COUNTIFS('Project Plan'!$O$7:$O$156,$A44,'Project Plan'!$F$7:$F$156,"<="&E$35,'Project Plan'!$H$7:$H$156,">="&E$35) -> 0 | F44: =COUNTIFS('Project Plan'!$O$7:$O$156,$A44,'Project Plan'!$F$7:$F$156,"<="&F$35,'Project Plan'!$H$7:$H$156,">="&F$35) -> 1 | G44: =COUNTIFS('Project Plan'!$O$7:$O$156,$A44,'Project Plan'!$F$7:$F$156,"<="&G$35,'Project Plan'!$H$7:$H$156,">="&G$35) -> 2 | H44: =COUNTIFS('Project Plan'!$O$7:$O$156,$A44,'Project Plan'!$F$7:$F$156,"<="&H$35,'Project Plan'!$H$7:$H$156,">="&H$35) -> 2 | I44: =COUNTIFS('Project Plan'!$O$7:$O$156,$A44,'Project Plan'!$F$7:$F$156,"<="&I$35,'Project Plan'!$H$7:$H$156,">="&I$35) -> 1 | J44: =COUNTIFS('Project Plan'!$O$7:$O$156,$A44,'Project Plan'!$F$7:$F$156,"<="&J$35,'Project Plan'!$H$7:$H$156,">="&J$35) -> 2 | ... AC44: =COUNTIFS('Project Plan'!$O$7:$O$156,$A44,'Project Plan'!$F$7:$F$156,"<="&AC$35,'Project Plan'!$H$7:$H$156,">="&AC$35) -> 0
A45: =A14 -> CSO | B45: =J14 -> 3 | C45: =COUNTIFS('Project Plan'!$O$7:$O$156,$A45,'Project Plan'!$F$7:$F$156,"<="&C$35,'Project Plan'!$H$7:$H$156,">="&C$35) -> 0 | D45: =COUNTIFS('Project Plan'!$O$7:$O$156,$A45,'Project Plan'!$F$7:$F$156,"<="&D$35,'Project Plan'!$H$7:$H$156,">="&D$35) -> 0 | E45: =COUNTIFS('Project Plan'!$O$7:$O$156,$A45,'Project Plan'!$F$7:$F$156,"<="&E$35,'Project Plan'!$H$7:$H$156,">="&E$35) -> 0 | F45: =COUNTIFS('Project Plan'!$O$7:$O$156,$A45,'Project Plan'!$F$7:$F$156,"<="&F$35,'Project Plan'!$H$7:$H$156,">="&F$35) -> 0 | G45: =COUNTIFS('Project Plan'!$O$7:$O$156,$A45,'Project Plan'!$F$7:$F$156,"<="&G$35,'Project Plan'!$H$7:$H$156,">="&G$35) -> 0 | H45: =COUNTIFS('Project Plan'!$O$7:$O$156,$A45,'Project Plan'!$F$7:$F$156,"<="&H$35,'Project Plan'!$H$7:$H$156,">="&H$35) -> 1 | I45: =COUNTIFS('Project Plan'!$O$7:$O$156,$A45,'Project Plan'!$F$7:$F$156,"<="&I$35,'Project Plan'!$H$7:$H$156,">="&I$35) -> 2 | J45: =COUNTIFS('Project Plan'!$O$7:$O$156,$A45,'Project Plan'!$F$7:$F$156,"<="&J$35,'Project Plan'!$H$7:$H$156,">="&J$35) -> 2 | ... AC45: =COUNTIFS('Project Plan'!$O$7:$O$156,$A45,'Project Plan'!$F$7:$F$156,"<="&AC$35,'Project Plan'!$H$7:$H$156,">="&AC$35) -> 0
A46: =A15 -> BSC | B46: =J15 -> 2 | C46: =COUNTIFS('Project Plan'!$O$7:$O$156,$A46,'Project Plan'!$F$7:$F$156,"<="&C$35,'Project Plan'!$H$7:$H$156,">="&C$35) -> 0 | D46: =COUNTIFS('Project Plan'!$O$7:$O$156,$A46,'Project Plan'!$F$7:$F$156,"<="&D$35,'Project Plan'!$H$7:$H$156,">="&D$35) -> 0 | E46: =COUNTIFS('Project Plan'!$O$7:$O$156,$A46,'Project Plan'!$F$7:$F$156,"<="&E$35,'Project Plan'!$H$7:$H$156,">="&E$35) -> 0 | F46: =COUNTIFS('Project Plan'!$O$7:$O$156,$A46,'Project Plan'!$F$7:$F$156,"<="&F$35,'Project Plan'!$H$7:$H$156,">="&F$35) -> 0 | G46: =COUNTIFS('Project Plan'!$O$7:$O$156,$A46,'Project Plan'!$F$7:$F$156,"<="&G$35,'Project Plan'!$H$7:$H$156,">="&G$35) -> 0 | H46: =COUNTIFS('Project Plan'!$O$7:$O$156,$A46,'Project Plan'!$F$7:$F$156,"<="&H$35,'Project Plan'!$H$7:$H$156,">="&H$35) -> 1 | I46: =COUNTIFS('Project Plan'!$O$7:$O$156,$A46,'Project Plan'!$F$7:$F$156,"<="&I$35,'Project Plan'!$H$7:$H$156,">="&I$35) -> 2 | J46: =COUNTIFS('Project Plan'!$O$7:$O$156,$A46,'Project Plan'!$F$7:$F$156,"<="&J$35,'Project Plan'!$H$7:$H$156,">="&J$35) -> 2 | ... AC46: =COUNTIFS('Project Plan'!$O$7:$O$156,$A46,'Project Plan'!$F$7:$F$156,"<="&AC$35,'Project Plan'!$H$7:$H$156,">="&AC$35) -> 0
A47: =A16 -> GRCC | B47: =J16 -> 3 | C47: =COUNTIFS('Project Plan'!$O$7:$O$156,$A47,'Project Plan'!$F$7:$F$156,"<="&C$35,'Project Plan'!$H$7:$H$156,">="&C$35) -> 0 | D47: =COUNTIFS('Project Plan'!$O$7:$O$156,$A47,'Project Plan'!$F$7:$F$156,"<="&D$35,'Project Plan'!$H$7:$H$156,">="&D$35) -> 0 | E47: =COUNTIFS('Project Plan'!$O$7:$O$156,$A47,'Project Plan'!$F$7:$F$156,"<="&E$35,'Project Plan'!$H$7:$H$156,">="&E$35) -> 0 | F47: =COUNTIFS('Project Plan'!$O$7:$O$156,$A47,'Project Plan'!$F$7:$F$156,"<="&F$35,'Project Plan'!$H$7:$H$156,">="&F$35) -> 1 | G47: =COUNTIFS('Project Plan'!$O$7:$O$156,$A47,'Project Plan'!$F$7:$F$156,"<="&G$35,'Project Plan'!$H$7:$H$156,">="&G$35) -> 2 | H47: =COUNTIFS('Project Plan'!$O$7:$O$156,$A47,'Project Plan'!$F$7:$F$156,"<="&H$35,'Project Plan'!$H$7:$H$156,">="&H$35) -> 2 | I47: =COUNTIFS('Project Plan'!$O$7:$O$156,$A47,'Project Plan'!$F$7:$F$156,"<="&I$35,'Project Plan'!$H$7:$H$156,">="&I$35) -> 3 | J47: =COUNTIFS('Project Plan'!$O$7:$O$156,$A47,'Project Plan'!$F$7:$F$156,"<="&J$35,'Project Plan'!$H$7:$H$156,">="&J$35) -> 3 | ... AC47: =COUNTIFS('Project Plan'!$O$7:$O$156,$A47,'Project Plan'!$F$7:$F$156,"<="&AC$35,'Project Plan'!$H$7:$H$156,">="&AC$35) -> 0
... A57: =A26 -> ENG | B57: =J26 -> 0 | C57: =COUNTIFS('Project Plan'!$O$7:$O$156,$A57,'Project Plan'!$F$7:$F$156,"<="&C$35,'Project Plan'!$H$7:$H$156,">="&C$35) -> 0 | D57: =COUNTIFS('Project Plan'!$O$7:$O$156,$A57,'Project Plan'!$F$7:$F$156,"<="&D$35,'Project Plan'!$H$7:$H$156,">="&D$35) -> 0 | E57: =COUNTIFS('Project Plan'!$O$7:$O$156,$A57,'Project Plan'!$F$7:$F$156,"<="&E$35,'Project Plan'!$H$7:$H$156,">="&E$35) -> 0 | F57: =COUNTIFS('Project Plan'!$O$7:$O$156,$A57,'Project Plan'!$F$7:$F$156,"<="&F$35,'Project Plan'!$H$7:$H$156,">="&F$35) -> 0 | G57: =COUNTIFS('Project Plan'!$O$7:$O$156,$A57,'Project Plan'!$F$7:$F$156,"<="&G$35,'Project Plan'!$H$7:$H$156,">="&G$35) -> 0 | H57: =COUNTIFS('Project Plan'!$O$7:$O$156,$A57,'Project Plan'!$F$7:$F$156,"<="&H$35,'Project Plan'!$H$7:$H$156,">="&H$35) -> 0 | I57: =COUNTIFS('Project Plan'!$O$7:$O$156,$A57,'Project Plan'!$F$7:$F$156,"<="&I$35,'Project Plan'!$H$7:$H$156,">="&I$35) -> 0 | J57: =COUNTIFS('Project Plan'!$O$7:$O$156,$A57,'Project Plan'!$F$7:$F$156,"<="&J$35,'Project Plan'!$H$7:$H$156,">="&J$35) -> 0 | ... AC57: =COUNTIFS('Project Plan'!$O$7:$O$156,$A57,'Project Plan'!$F$7:$F$156,"<="&AC$35,'Project Plan'!$H$7:$H$156,">="&AC$35) -> 0
A59: Weighted load per role per week (lead 1.0 + support 0.25); limit 4 x FTE
A60: Role | B60: Limit | C60: 0 | D60: 1 | E60: 2 | F60: 3 | G60: 4 | H60: 5 | I60: 6 | J60: 7 | K60: 8 | L60: 9 | M60: 10 | N60: 11 | O60: 12 | P60: 13 | Q60: 14 | R60: 15 | S60: 16 | T60: 17 | U60: 18 | V60: 19 | W60: 20 | X60: 21 | Y60: 22 | Z60: 23 | AA60: 24 | AB60: 25 | AC60: 26
A61: =A5 -> PL | B61: =4*E5 -> 4 | C61: =COUNTIFS('Project Plan'!$O$7:$O$156,$A61,'Project Plan'!$F$7:$F$156,"<="&C$60,'Project Plan'!$H$7:$H$156,">="&C$60)+0.25*COUNTIFS('Project Plan'!$V$7:$V$156,"*;"&$A61&";*",'Project Plan'!$O$7:$O$156,"<>"&$A61,'Project Plan'!$F$7:$F$156,"<="&C$60,'Project Plan'!$H$7:$H$156,">="&C$60) -> 3.25 | D61: =COUNTIFS('Project Plan'!$O$7:$O$156,$A61,'Project Plan'!$F$7:$F$156,"<="&D$60,'Project Plan'!$H$7:$H$156,">="&D$60)+0.25*COUNTIFS('Project Plan'!$V$7:$V$156,"*;"&$A61&";*",'Project Plan'!$O$7:$O$156,"<>"&$A61,'Project Plan'!$F$7:$F$156,"<="&D$60,'Project Plan'!$H$7:$H$156,">="&D$60) -> 2.25 | E61: =COUNTIFS('Project Plan'!$O$7:$O$156,$A61,'Project Plan'!$F$7:$F$156,"<="&E$60,'Project Plan'!$H$7:$H$156,">="&E$60)+0.25*COUNTIFS('Project Plan'!$V$7:$V$156,"*;"&$A61&";*",'Project Plan'!$O$7:$O$156,"<>"&$A61,'Project Plan'!$F$7:$F$156,"<="&E$60,'Project Plan'!$H$7:$H$156,">="&E$60) -> 2.5 | F61: =COUNTIFS('Project Plan'!$O$7:$O$156,$A61,'Project Plan'!$F$7:$F$156,"<="&F$60,'Project Plan'!$H$7:$H$156,">="&F$60)+0.25*COUNTIFS('Project Plan'!$V$7:$V$156,"*;"&$A61&";*",'Project Plan'!$O$7:$O$156,"<>"&$A61,'Project Plan'!$F$7:$F$156,"<="&F$60,'Project Plan'!$H$7:$H$156,">="&F$60) -> 3.5 | G61: =COUNTIFS('Project Plan'!$O$7:$O$156,$A61,'Project Plan'!$F$7:$F$156,"<="&G$60,'Project Plan'!$H$7:$H$156,">="&G$60)+0.25*COUNTIFS('Project Plan'!$V$7:$V$156,"*;"&$A61&";*",'Project Plan'!$O$7:$O$156,"<>"&$A61,'Project Plan'!$F$7:$F$156,"<="&G$60,'Project Plan'!$H$7:$H$156,">="&G$60) -> 2.75 | H61: =COUNTIFS('Project Plan'!$O$7:$O$156,$A61,'Project Plan'!$F$7:$F$156,"<="&H$60,'Project Plan'!$H$7:$H$156,">="&H$60)+0.25*COUNTIFS('Project Plan'!$V$7:$V$156,"*;"&$A61&";*",'Project Plan'!$O$7:$O$156,"<>"&$A61,'Project Plan'!$F$7:$F$156,"<="&H$60,'Project Plan'!$H$7:$H$156,">="&H$60) -> 2.5 | I61: =COUNTIFS('Project Plan'!$O$7:$O$156,$A61,'Project Plan'!$F$7:$F$156,"<="&I$60,'Project Plan'!$H$7:$H$156,">="&I$60)+0.25*COUNTIFS('Project Plan'!$V$7:$V$156,"*;"&$A61&";*",'Project Plan'!$O$7:$O$156,"<>"&$A61,'Project Plan'!$F$7:$F$156,"<="&I$60,'Project Plan'!$H$7:$H$156,">="&I$60) -> 3.75 | J61: =COUNTIFS('Project Plan'!$O$7:$O$156,$A61,'Project Plan'!$F$7:$F$156,"<="&J$60,'Project Plan'!$H$7:$H$156,">="&J$60)+0.25*COUNTIFS('Project Plan'!$V$7:$V$156,"*;"&$A61&";*",'Project Plan'!$O$7:$O$156,"<>"&$A61,'Project Plan'!$F$7:$F$156,"<="&J$60,'Project Plan'!$H$7:$H$156,">="&J$60) -> 1.5 | ... AC61: =COUNTIFS('Project Plan'!$O$7:$O$156,$A61,'Project Plan'!$F$7:$F$156,"<="&AC$60,'Project Plan'!$H$7:$H$156,">="&AC$60)+0.25*COUNTIFS('Project Plan'!$V$7:$V$156,"*;"&$A61&";*",'Project Plan'!$O$7:$O$156,"<>"&$A61,'Project Plan'!$F$7:$F$156,"<="&AC$60,'Project Plan'!$H$7:$H$156,">="&AC$60) -> 1
A62: =A6 -> CSE | B62: =4*E6 -> 4 | C62: =COUNTIFS('Project Plan'!$O$7:$O$156,$A62,'Project Plan'!$F$7:$F$156,"<="&C$60,'Project Plan'!$H$7:$H$156,">="&C$60)+0.25*COUNTIFS('Project Plan'!$V$7:$V$156,"*;"&$A62&";*",'Project Plan'!$O$7:$O$156,"<>"&$A62,'Project Plan'!$F$7:$F$156,"<="&C$60,'Project Plan'!$H$7:$H$156,">="&C$60) -> 3.25 | D62: =COUNTIFS('Project Plan'!$O$7:$O$156,$A62,'Project Plan'!$F$7:$F$156,"<="&D$60,'Project Plan'!$H$7:$H$156,">="&D$60)+0.25*COUNTIFS('Project Plan'!$V$7:$V$156,"*;"&$A62&";*",'Project Plan'!$O$7:$O$156,"<>"&$A62,'Project Plan'!$F$7:$F$156,"<="&D$60,'Project Plan'!$H$7:$H$156,">="&D$60) -> 3 | E62: =COUNTIFS('Project Plan'!$O$7:$O$156,$A62,'Project Plan'!$F$7:$F$156,"<="&E$60,'Project Plan'!$H$7:$H$156,">="&E$60)+0.25*COUNTIFS('Project Plan'!$V$7:$V$156,"*;"&$A62&";*",'Project Plan'!$O$7:$O$156,"<>"&$A62,'Project Plan'!$F$7:$F$156,"<="&E$60,'Project Plan'!$H$7:$H$156,">="&E$60) -> 2.25 | F62: =COUNTIFS('Project Plan'!$O$7:$O$156,$A62,'Project Plan'!$F$7:$F$156,"<="&F$60,'Project Plan'!$H$7:$H$156,">="&F$60)+0.25*COUNTIFS('Project Plan'!$V$7:$V$156,"*;"&$A62&";*",'Project Plan'!$O$7:$O$156,"<>"&$A62,'Project Plan'!$F$7:$F$156,"<="&F$60,'Project Plan'!$H$7:$H$156,">="&F$60) -> 3.75 | G62: =COUNTIFS('Project Plan'!$O$7:$O$156,$A62,'Project Plan'!$F$7:$F$156,"<="&G$60,'Project Plan'!$H$7:$H$156,">="&G$60)+0.25*COUNTIFS('Project Plan'!$V$7:$V$156,"*;"&$A62&";*",'Project Plan'!$O$7:$O$156,"<>"&$A62,'Project Plan'!$F$7:$F$156,"<="&G$60,'Project Plan'!$H$7:$H$156,">="&G$60) -> 3 | H62: =COUNTIFS('Project Plan'!$O$7:$O$156,$A62,'Project Plan'!$F$7:$F$156,"<="&H$60,'Project Plan'!$H$7:$H$156,">="&H$60)+0.25*COUNTIFS('Project Plan'!$V$7:$V$156,"*;"&$A62&";*",'Project Plan'!$O$7:$O$156,"<>"&$A62,'Project Plan'!$F$7:$F$156,"<="&H$60,'Project Plan'!$H$7:$H$156,">="&H$60) -> 3.75 | I62: =COUNTIFS('Project Plan'!$O$7:$O$156,$A62,'Project Plan'!$F$7:$F$156,"<="&I$60,'Project Plan'!$H$7:$H$156,">="&I$60)+0.25*COUNTIFS('Project Plan'!$V$7:$V$156,"*;"&$A62&";*",'Project Plan'!$O$7:$O$156,"<>"&$A62,'Project Plan'!$F$7:$F$156,"<="&I$60,'Project Plan'!$H$7:$H$156,">="&I$60) -> 4 | J62: =COUNTIFS('Project Plan'!$O$7:$O$156,$A62,'Project Plan'!$F$7:$F$156,"<="&J$60,'Project Plan'!$H$7:$H$156,">="&J$60)+0.25*COUNTIFS('Project Plan'!$V$7:$V$156,"*;"&$A62&";*",'Project Plan'!$O$7:$O$156,"<>"&$A62,'Project Plan'!$F$7:$F$156,"<="&J$60,'Project Plan'!$H$7:$H$156,">="&J$60) -> 4 | ... AC62: =COUNTIFS('Project Plan'!$O$7:$O$156,$A62,'Project Plan'!$F$7:$F$156,"<="&AC$60,'Project Plan'!$H$7:$H$156,">="&AC$60)+0.25*COUNTIFS('Project Plan'!$V$7:$V$156,"*;"&$A62&";*",'Project Plan'!$O$7:$O$156,"<>"&$A62,'Project Plan'!$F$7:$F$156,"<="&AC$60,'Project Plan'!$H$7:$H$156,">="&AC$60) -> 0
A63: =A7 -> ISE | B63: =4*E7 -> 4 | C63: =COUNTIFS('Project Plan'!$O$7:$O$156,$A63,'Project Plan'!$F$7:$F$156,"<="&C$60,'Project Plan'!$H$7:$H$156,">="&C$60)+0.25*COUNTIFS('Project Plan'!$V$7:$V$156,"*;"&$A63&";*",'Project Plan'!$O$7:$O$156,"<>"&$A63,'Project Plan'!$F$7:$F$156,"<="&C$60,'Project Plan'!$H$7:$H$156,">="&C$60) -> 4 | D63: =COUNTIFS('Project Plan'!$O$7:$O$156,$A63,'Project Plan'!$F$7:$F$156,"<="&D$60,'Project Plan'!$H$7:$H$156,">="&D$60)+0.25*COUNTIFS('Project Plan'!$V$7:$V$156,"*;"&$A63&";*",'Project Plan'!$O$7:$O$156,"<>"&$A63,'Project Plan'!$F$7:$F$156,"<="&D$60,'Project Plan'!$H$7:$H$156,">="&D$60) -> 3.75 | E63: =COUNTIFS('Project Plan'!$O$7:$O$156,$A63,'Project Plan'!$F$7:$F$156,"<="&E$60,'Project Plan'!$H$7:$H$156,">="&E$60)+0.25*COUNTIFS('Project Plan'!$V$7:$V$156,"*;"&$A63&";*",'Project Plan'!$O$7:$O$156,"<>"&$A63,'Project Plan'!$F$7:$F$156,"<="&E$60,'Project Plan'!$H$7:$H$156,">="&E$60) -> 1.25 | F63: =COUNTIFS('Project Plan'!$O$7:$O$156,$A63,'Project Plan'!$F$7:$F$156,"<="&F$60,'Project Plan'!$H$7:$H$156,">="&F$60)+0.25*COUNTIFS('Project Plan'!$V$7:$V$156,"*;"&$A63&";*",'Project Plan'!$O$7:$O$156,"<>"&$A63,'Project Plan'!$F$7:$F$156,"<="&F$60,'Project Plan'!$H$7:$H$156,">="&F$60) -> 3.75 | G63: =COUNTIFS('Project Plan'!$O$7:$O$156,$A63,'Project Plan'!$F$7:$F$156,"<="&G$60,'Project Plan'!$H$7:$H$156,">="&G$60)+0.25*COUNTIFS('Project Plan'!$V$7:$V$156,"*;"&$A63&";*",'Project Plan'!$O$7:$O$156,"<>"&$A63,'Project Plan'!$F$7:$F$156,"<="&G$60,'Project Plan'!$H$7:$H$156,">="&G$60) -> 4 | H63: =COUNTIFS('Project Plan'!$O$7:$O$156,$A63,'Project Plan'!$F$7:$F$156,"<="&H$60,'Project Plan'!$H$7:$H$156,">="&H$60)+0.25*COUNTIFS('Project Plan'!$V$7:$V$156,"*;"&$A63&";*",'Project Plan'!$O$7:$O$156,"<>"&$A63,'Project Plan'!$F$7:$F$156,"<="&H$60,'Project Plan'!$H$7:$H$156,">="&H$60) -> 3.25 | I63: =COUNTIFS('Project Plan'!$O$7:$O$156,$A63,'Project Plan'!$F$7:$F$156,"<="&I$60,'Project Plan'!$H$7:$H$156,">="&I$60)+0.25*COUNTIFS('Project Plan'!$V$7:$V$156,"*;"&$A63&";*",'Project Plan'!$O$7:$O$156,"<>"&$A63,'Project Plan'!$F$7:$F$156,"<="&I$60,'Project Plan'!$H$7:$H$156,">="&I$60) -> 4 | J63: =COUNTIFS('Project Plan'!$O$7:$O$156,$A63,'Project Plan'!$F$7:$F$156,"<="&J$60,'Project Plan'!$H$7:$H$156,">="&J$60)+0.25*COUNTIFS('Project Plan'!$V$7:$V$156,"*;"&$A63&";*",'Project Plan'!$O$7:$O$156,"<>"&$A63,'Project Plan'!$F$7:$F$156,"<="&J$60,'Project Plan'!$H$7:$H$156,">="&J$60) -> 4 | ... AC63: =COUNTIFS('Project Plan'!$O$7:$O$156,$A63,'Project Plan'!$F$7:$F$156,"<="&AC$60,'Project Plan'!$H$7:$H$156,">="&AC$60)+0.25*COUNTIFS('Project Plan'!$V$7:$V$156,"*;"&$A63&";*",'Project Plan'!$O$7:$O$156,"<>"&$A63,'Project Plan'!$F$7:$F$156,"<="&AC$60,'Project Plan'!$H$7:$H$156,">="&AC$60) -> 0
A64: =A8 -> GRC | B64: =4*E8 -> 4 | C64: =COUNTIFS('Project Plan'!$O$7:$O$156,$A64,'Project Plan'!$F$7:$F$156,"<="&C$60,'Project Plan'!$H$7:$H$156,">="&C$60)+0.25*COUNTIFS('Project Plan'!$V$7:$V$156,"*;"&$A64&";*",'Project Plan'!$O$7:$O$156,"<>"&$A64,'Project Plan'!$F$7:$F$156,"<="&C$60,'Project Plan'!$H$7:$H$156,">="&C$60) -> 1.25 | D64: =COUNTIFS('Project Plan'!$O$7:$O$156,$A64,'Project Plan'!$F$7:$F$156,"<="&D$60,'Project Plan'!$H$7:$H$156,">="&D$60)+0.25*COUNTIFS('Project Plan'!$V$7:$V$156,"*;"&$A64&";*",'Project Plan'!$O$7:$O$156,"<>"&$A64,'Project Plan'!$F$7:$F$156,"<="&D$60,'Project Plan'!$H$7:$H$156,">="&D$60) -> 1.5 | E64: =COUNTIFS('Project Plan'!$O$7:$O$156,$A64,'Project Plan'!$F$7:$F$156,"<="&E$60,'Project Plan'!$H$7:$H$156,">="&E$60)+0.25*COUNTIFS('Project Plan'!$V$7:$V$156,"*;"&$A64&";*",'Project Plan'!$O$7:$O$156,"<>"&$A64,'Project Plan'!$F$7:$F$156,"<="&E$60,'Project Plan'!$H$7:$H$156,">="&E$60) -> 1.5 | F64: =COUNTIFS('Project Plan'!$O$7:$O$156,$A64,'Project Plan'!$F$7:$F$156,"<="&F$60,'Project Plan'!$H$7:$H$156,">="&F$60)+0.25*COUNTIFS('Project Plan'!$V$7:$V$156,"*;"&$A64&";*",'Project Plan'!$O$7:$O$156,"<>"&$A64,'Project Plan'!$F$7:$F$156,"<="&F$60,'Project Plan'!$H$7:$H$156,">="&F$60) -> 2.75 | G64: =COUNTIFS('Project Plan'!$O$7:$O$156,$A64,'Project Plan'!$F$7:$F$156,"<="&G$60,'Project Plan'!$H$7:$H$156,">="&G$60)+0.25*COUNTIFS('Project Plan'!$V$7:$V$156,"*;"&$A64&";*",'Project Plan'!$O$7:$O$156,"<>"&$A64,'Project Plan'!$F$7:$F$156,"<="&G$60,'Project Plan'!$H$7:$H$156,">="&G$60) -> 3.5 | H64: =COUNTIFS('Project Plan'!$O$7:$O$156,$A64,'Project Plan'!$F$7:$F$156,"<="&H$60,'Project Plan'!$H$7:$H$156,">="&H$60)+0.25*COUNTIFS('Project Plan'!$V$7:$V$156,"*;"&$A64&";*",'Project Plan'!$O$7:$O$156,"<>"&$A64,'Project Plan'!$F$7:$F$156,"<="&H$60,'Project Plan'!$H$7:$H$156,">="&H$60) -> 3.75 | I64: =COUNTIFS('Project Plan'!$O$7:$O$156,$A64,'Project Plan'!$F$7:$F$156,"<="&I$60,'Project Plan'!$H$7:$H$156,">="&I$60)+0.25*COUNTIFS('Project Plan'!$V$7:$V$156,"*;"&$A64&";*",'Project Plan'!$O$7:$O$156,"<>"&$A64,'Project Plan'!$F$7:$F$156,"<="&I$60,'Project Plan'!$H$7:$H$156,">="&I$60) -> 4 | J64: =COUNTIFS('Project Plan'!$O$7:$O$156,$A64,'Project Plan'!$F$7:$F$156,"<="&J$60,'Project Plan'!$H$7:$H$156,">="&J$60)+0.25*COUNTIFS('Project Plan'!$V$7:$V$156,"*;"&$A64&";*",'Project Plan'!$O$7:$O$156,"<>"&$A64,'Project Plan'!$F$7:$F$156,"<="&J$60,'Project Plan'!$H$7:$H$156,">="&J$60) -> 3.75 | ... AC64: =COUNTIFS('Project Plan'!$O$7:$O$156,$A64,'Project Plan'!$F$7:$F$156,"<="&AC$60,'Project Plan'!$H$7:$H$156,">="&AC$60)+0.25*COUNTIFS('Project Plan'!$V$7:$V$156,"*;"&$A64&";*",'Project Plan'!$O$7:$O$156,"<>"&$A64,'Project Plan'!$F$7:$F$156,"<="&AC$60,'Project Plan'!$H$7:$H$156,">="&AC$60) -> 0
A65: =A9 -> BSE | B65: =4*E9 -> 4 | C65: =COUNTIFS('Project Plan'!$O$7:$O$156,$A65,'Project Plan'!$F$7:$F$156,"<="&C$60,'Project Plan'!$H$7:$H$156,">="&C$60)+0.25*COUNTIFS('Project Plan'!$V$7:$V$156,"*;"&$A65&";*",'Project Plan'!$O$7:$O$156,"<>"&$A65,'Project Plan'!$F$7:$F$156,"<="&C$60,'Project Plan'!$H$7:$H$156,">="&C$60) -> 3.75 | D65: =COUNTIFS('Project Plan'!$O$7:$O$156,$A65,'Project Plan'!$F$7:$F$156,"<="&D$60,'Project Plan'!$H$7:$H$156,">="&D$60)+0.25*COUNTIFS('Project Plan'!$V$7:$V$156,"*;"&$A65&";*",'Project Plan'!$O$7:$O$156,"<>"&$A65,'Project Plan'!$F$7:$F$156,"<="&D$60,'Project Plan'!$H$7:$H$156,">="&D$60) -> 3.5 | E65: =COUNTIFS('Project Plan'!$O$7:$O$156,$A65,'Project Plan'!$F$7:$F$156,"<="&E$60,'Project Plan'!$H$7:$H$156,">="&E$60)+0.25*COUNTIFS('Project Plan'!$V$7:$V$156,"*;"&$A65&";*",'Project Plan'!$O$7:$O$156,"<>"&$A65,'Project Plan'!$F$7:$F$156,"<="&E$60,'Project Plan'!$H$7:$H$156,">="&E$60) -> 3.5 | F65: =COUNTIFS('Project Plan'!$O$7:$O$156,$A65,'Project Plan'!$F$7:$F$156,"<="&F$60,'Project Plan'!$H$7:$H$156,">="&F$60)+0.25*COUNTIFS('Project Plan'!$V$7:$V$156,"*;"&$A65&";*",'Project Plan'!$O$7:$O$156,"<>"&$A65,'Project Plan'!$F$7:$F$156,"<="&F$60,'Project Plan'!$H$7:$H$156,">="&F$60) -> 3.5 | G65: =COUNTIFS('Project Plan'!$O$7:$O$156,$A65,'Project Plan'!$F$7:$F$156,"<="&G$60,'Project Plan'!$H$7:$H$156,">="&G$60)+0.25*COUNTIFS('Project Plan'!$V$7:$V$156,"*;"&$A65&";*",'Project Plan'!$O$7:$O$156,"<>"&$A65,'Project Plan'!$F$7:$F$156,"<="&G$60,'Project Plan'!$H$7:$H$156,">="&G$60) -> 3.5 | H65: =COUNTIFS('Project Plan'!$O$7:$O$156,$A65,'Project Plan'!$F$7:$F$156,"<="&H$60,'Project Plan'!$H$7:$H$156,">="&H$60)+0.25*COUNTIFS('Project Plan'!$V$7:$V$156,"*;"&$A65&";*",'Project Plan'!$O$7:$O$156,"<>"&$A65,'Project Plan'!$F$7:$F$156,"<="&H$60,'Project Plan'!$H$7:$H$156,">="&H$60) -> 4 | I65: =COUNTIFS('Project Plan'!$O$7:$O$156,$A65,'Project Plan'!$F$7:$F$156,"<="&I$60,'Project Plan'!$H$7:$H$156,">="&I$60)+0.25*COUNTIFS('Project Plan'!$V$7:$V$156,"*;"&$A65&";*",'Project Plan'!$O$7:$O$156,"<>"&$A65,'Project Plan'!$F$7:$F$156,"<="&I$60,'Project Plan'!$H$7:$H$156,">="&I$60) -> 3.25 | J65: =COUNTIFS('Project Plan'!$O$7:$O$156,$A65,'Project Plan'!$F$7:$F$156,"<="&J$60,'Project Plan'!$H$7:$H$156,">="&J$60)+0.25*COUNTIFS('Project Plan'!$V$7:$V$156,"*;"&$A65&";*",'Project Plan'!$O$7:$O$156,"<>"&$A65,'Project Plan'!$F$7:$F$156,"<="&J$60,'Project Plan'!$H$7:$H$156,">="&J$60) -> 3.25 | ... AC65: =COUNTIFS('Project Plan'!$O$7:$O$156,$A65,'Project Plan'!$F$7:$F$156,"<="&AC$60,'Project Plan'!$H$7:$H$156,">="&AC$60)+0.25*COUNTIFS('Project Plan'!$V$7:$V$156,"*;"&$A65&";*",'Project Plan'!$O$7:$O$156,"<>"&$A65,'Project Plan'!$F$7:$F$156,"<="&AC$60,'Project Plan'!$H$7:$H$156,">="&AC$60) -> 0
A66: =A10 -> KHE | B66: =4*E10 -> 4 | C66: =COUNTIFS('Project Plan'!$O$7:$O$156,$A66,'Project Plan'!$F$7:$F$156,"<="&C$60,'Project Plan'!$H$7:$H$156,">="&C$60)+0.25*COUNTIFS('Project Plan'!$V$7:$V$156,"*;"&$A66&";*",'Project Plan'!$O$7:$O$156,"<>"&$A66,'Project Plan'!$F$7:$F$156,"<="&C$60,'Project Plan'!$H$7:$H$156,">="&C$60) -> 0 | D66: =COUNTIFS('Project Plan'!$O$7:$O$156,$A66,'Project Plan'!$F$7:$F$156,"<="&D$60,'Project Plan'!$H$7:$H$156,">="&D$60)+0.25*COUNTIFS('Project Plan'!$V$7:$V$156,"*;"&$A66&";*",'Project Plan'!$O$7:$O$156,"<>"&$A66,'Project Plan'!$F$7:$F$156,"<="&D$60,'Project Plan'!$H$7:$H$156,">="&D$60) -> 0 | E66: =COUNTIFS('Project Plan'!$O$7:$O$156,$A66,'Project Plan'!$F$7:$F$156,"<="&E$60,'Project Plan'!$H$7:$H$156,">="&E$60)+0.25*COUNTIFS('Project Plan'!$V$7:$V$156,"*;"&$A66&";*",'Project Plan'!$O$7:$O$156,"<>"&$A66,'Project Plan'!$F$7:$F$156,"<="&E$60,'Project Plan'!$H$7:$H$156,">="&E$60) -> 3.25 | F66: =COUNTIFS('Project Plan'!$O$7:$O$156,$A66,'Project Plan'!$F$7:$F$156,"<="&F$60,'Project Plan'!$H$7:$H$156,">="&F$60)+0.25*COUNTIFS('Project Plan'!$V$7:$V$156,"*;"&$A66&";*",'Project Plan'!$O$7:$O$156,"<>"&$A66,'Project Plan'!$F$7:$F$156,"<="&F$60,'Project Plan'!$H$7:$H$156,">="&F$60) -> 3.5 | G66: =COUNTIFS('Project Plan'!$O$7:$O$156,$A66,'Project Plan'!$F$7:$F$156,"<="&G$60,'Project Plan'!$H$7:$H$156,">="&G$60)+0.25*COUNTIFS('Project Plan'!$V$7:$V$156,"*;"&$A66&";*",'Project Plan'!$O$7:$O$156,"<>"&$A66,'Project Plan'!$F$7:$F$156,"<="&G$60,'Project Plan'!$H$7:$H$156,">="&G$60) -> 3.5 | H66: =COUNTIFS('Project Plan'!$O$7:$O$156,$A66,'Project Plan'!$F$7:$F$156,"<="&H$60,'Project Plan'!$H$7:$H$156,">="&H$60)+0.25*COUNTIFS('Project Plan'!$V$7:$V$156,"*;"&$A66&";*",'Project Plan'!$O$7:$O$156,"<>"&$A66,'Project Plan'!$F$7:$F$156,"<="&H$60,'Project Plan'!$H$7:$H$156,">="&H$60) -> 1.75 | I66: =COUNTIFS('Project Plan'!$O$7:$O$156,$A66,'Project Plan'!$F$7:$F$156,"<="&I$60,'Project Plan'!$H$7:$H$156,">="&I$60)+0.25*COUNTIFS('Project Plan'!$V$7:$V$156,"*;"&$A66&";*",'Project Plan'!$O$7:$O$156,"<>"&$A66,'Project Plan'!$F$7:$F$156,"<="&I$60,'Project Plan'!$H$7:$H$156,">="&I$60) -> 3.5 | J66: =COUNTIFS('Project Plan'!$O$7:$O$156,$A66,'Project Plan'!$F$7:$F$156,"<="&J$60,'Project Plan'!$H$7:$H$156,">="&J$60)+0.25*COUNTIFS('Project Plan'!$V$7:$V$156,"*;"&$A66&";*",'Project Plan'!$O$7:$O$156,"<>"&$A66,'Project Plan'!$F$7:$F$156,"<="&J$60,'Project Plan'!$H$7:$H$156,">="&J$60) -> 3.5 | ... AC66: =COUNTIFS('Project Plan'!$O$7:$O$156,$A66,'Project Plan'!$F$7:$F$156,"<="&AC$60,'Project Plan'!$H$7:$H$156,">="&AC$60)+0.25*COUNTIFS('Project Plan'!$V$7:$V$156,"*;"&$A66&";*",'Project Plan'!$O$7:$O$156,"<>"&$A66,'Project Plan'!$F$7:$F$156,"<="&AC$60,'Project Plan'!$H$7:$H$156,">="&AC$60) -> 0
A67: =A11 -> CPE | B67: =4*E11 -> 4 | C67: =COUNTIFS('Project Plan'!$O$7:$O$156,$A67,'Project Plan'!$F$7:$F$156,"<="&C$60,'Project Plan'!$H$7:$H$156,">="&C$60)+0.25*COUNTIFS('Project Plan'!$V$7:$V$156,"*;"&$A67&";*",'Project Plan'!$O$7:$O$156,"<>"&$A67,'Project Plan'!$F$7:$F$156,"<="&C$60,'Project Plan'!$H$7:$H$156,">="&C$60) -> 0 | D67: =COUNTIFS('Project Plan'!$O$7:$O$156,$A67,'Project Plan'!$F$7:$F$156,"<="&D$60,'Project Plan'!$H$7:$H$156,">="&D$60)+0.25*COUNTIFS('Project Plan'!$V$7:$V$156,"*;"&$A67&";*",'Project Plan'!$O$7:$O$156,"<>"&$A67,'Project Plan'!$F$7:$F$156,"<="&D$60,'Project Plan'!$H$7:$H$156,">="&D$60) -> 0 | E67: =COUNTIFS('Project Plan'!$O$7:$O$156,$A67,'Project Plan'!$F$7:$F$156,"<="&E$60,'Project Plan'!$H$7:$H$156,">="&E$60)+0.25*COUNTIFS('Project Plan'!$V$7:$V$156,"*;"&$A67&";*",'Project Plan'!$O$7:$O$156,"<>"&$A67,'Project Plan'!$F$7:$F$156,"<="&E$60,'Project Plan'!$H$7:$H$156,">="&E$60) -> 0 | F67: =COUNTIFS('Project Plan'!$O$7:$O$156,$A67,'Project Plan'!$F$7:$F$156,"<="&F$60,'Project Plan'!$H$7:$H$156,">="&F$60)+0.25*COUNTIFS('Project Plan'!$V$7:$V$156,"*;"&$A67&";*",'Project Plan'!$O$7:$O$156,"<>"&$A67,'Project Plan'!$F$7:$F$156,"<="&F$60,'Project Plan'!$H$7:$H$156,">="&F$60) -> 1 | G67: =COUNTIFS('Project Plan'!$O$7:$O$156,$A67,'Project Plan'!$F$7:$F$156,"<="&G$60,'Project Plan'!$H$7:$H$156,">="&G$60)+0.25*COUNTIFS('Project Plan'!$V$7:$V$156,"*;"&$A67&";*",'Project Plan'!$O$7:$O$156,"<>"&$A67,'Project Plan'!$F$7:$F$156,"<="&G$60,'Project Plan'!$H$7:$H$156,">="&G$60) -> 2 | H67: =COUNTIFS('Project Plan'!$O$7:$O$156,$A67,'Project Plan'!$F$7:$F$156,"<="&H$60,'Project Plan'!$H$7:$H$156,">="&H$60)+0.25*COUNTIFS('Project Plan'!$V$7:$V$156,"*;"&$A67&";*",'Project Plan'!$O$7:$O$156,"<>"&$A67,'Project Plan'!$F$7:$F$156,"<="&H$60,'Project Plan'!$H$7:$H$156,">="&H$60) -> 2 | I67: =COUNTIFS('Project Plan'!$O$7:$O$156,$A67,'Project Plan'!$F$7:$F$156,"<="&I$60,'Project Plan'!$H$7:$H$156,">="&I$60)+0.25*COUNTIFS('Project Plan'!$V$7:$V$156,"*;"&$A67&";*",'Project Plan'!$O$7:$O$156,"<>"&$A67,'Project Plan'!$F$7:$F$156,"<="&I$60,'Project Plan'!$H$7:$H$156,">="&I$60) -> 2 | J67: =COUNTIFS('Project Plan'!$O$7:$O$156,$A67,'Project Plan'!$F$7:$F$156,"<="&J$60,'Project Plan'!$H$7:$H$156,">="&J$60)+0.25*COUNTIFS('Project Plan'!$V$7:$V$156,"*;"&$A67&";*",'Project Plan'!$O$7:$O$156,"<>"&$A67,'Project Plan'!$F$7:$F$156,"<="&J$60,'Project Plan'!$H$7:$H$156,">="&J$60) -> 3 | ... AC67: =COUNTIFS('Project Plan'!$O$7:$O$156,$A67,'Project Plan'!$F$7:$F$156,"<="&AC$60,'Project Plan'!$H$7:$H$156,">="&AC$60)+0.25*COUNTIFS('Project Plan'!$V$7:$V$156,"*;"&$A67&";*",'Project Plan'!$O$7:$O$156,"<>"&$A67,'Project Plan'!$F$7:$F$156,"<="&AC$60,'Project Plan'!$H$7:$H$156,">="&AC$60) -> 0
A68: =A12 -> DET | B68: =4*E12 -> 4 | C68: =COUNTIFS('Project Plan'!$O$7:$O$156,$A68,'Project Plan'!$F$7:$F$156,"<="&C$60,'Project Plan'!$H$7:$H$156,">="&C$60)+0.25*COUNTIFS('Project Plan'!$V$7:$V$156,"*;"&$A68&";*",'Project Plan'!$O$7:$O$156,"<>"&$A68,'Project Plan'!$F$7:$F$156,"<="&C$60,'Project Plan'!$H$7:$H$156,">="&C$60) -> 0 | D68: =COUNTIFS('Project Plan'!$O$7:$O$156,$A68,'Project Plan'!$F$7:$F$156,"<="&D$60,'Project Plan'!$H$7:$H$156,">="&D$60)+0.25*COUNTIFS('Project Plan'!$V$7:$V$156,"*;"&$A68&";*",'Project Plan'!$O$7:$O$156,"<>"&$A68,'Project Plan'!$F$7:$F$156,"<="&D$60,'Project Plan'!$H$7:$H$156,">="&D$60) -> 0 | E68: =COUNTIFS('Project Plan'!$O$7:$O$156,$A68,'Project Plan'!$F$7:$F$156,"<="&E$60,'Project Plan'!$H$7:$H$156,">="&E$60)+0.25*COUNTIFS('Project Plan'!$V$7:$V$156,"*;"&$A68&";*",'Project Plan'!$O$7:$O$156,"<>"&$A68,'Project Plan'!$F$7:$F$156,"<="&E$60,'Project Plan'!$H$7:$H$156,">="&E$60) -> 0 | F68: =COUNTIFS('Project Plan'!$O$7:$O$156,$A68,'Project Plan'!$F$7:$F$156,"<="&F$60,'Project Plan'!$H$7:$H$156,">="&F$60)+0.25*COUNTIFS('Project Plan'!$V$7:$V$156,"*;"&$A68&";*",'Project Plan'!$O$7:$O$156,"<>"&$A68,'Project Plan'!$F$7:$F$156,"<="&F$60,'Project Plan'!$H$7:$H$156,">="&F$60) -> 0.25 | G68: =COUNTIFS('Project Plan'!$O$7:$O$156,$A68,'Project Plan'!$F$7:$F$156,"<="&G$60,'Project Plan'!$H$7:$H$156,">="&G$60)+0.25*COUNTIFS('Project Plan'!$V$7:$V$156,"*;"&$A68&";*",'Project Plan'!$O$7:$O$156,"<>"&$A68,'Project Plan'!$F$7:$F$156,"<="&G$60,'Project Plan'!$H$7:$H$156,">="&G$60) -> 0.25 | H68: =COUNTIFS('Project Plan'!$O$7:$O$156,$A68,'Project Plan'!$F$7:$F$156,"<="&H$60,'Project Plan'!$H$7:$H$156,">="&H$60)+0.25*COUNTIFS('Project Plan'!$V$7:$V$156,"*;"&$A68&";*",'Project Plan'!$O$7:$O$156,"<>"&$A68,'Project Plan'!$F$7:$F$156,"<="&H$60,'Project Plan'!$H$7:$H$156,">="&H$60) -> 0.5 | I68: =COUNTIFS('Project Plan'!$O$7:$O$156,$A68,'Project Plan'!$F$7:$F$156,"<="&I$60,'Project Plan'!$H$7:$H$156,">="&I$60)+0.25*COUNTIFS('Project Plan'!$V$7:$V$156,"*;"&$A68&";*",'Project Plan'!$O$7:$O$156,"<>"&$A68,'Project Plan'!$F$7:$F$156,"<="&I$60,'Project Plan'!$H$7:$H$156,">="&I$60) -> 1.25 | J68: =COUNTIFS('Project Plan'!$O$7:$O$156,$A68,'Project Plan'!$F$7:$F$156,"<="&J$60,'Project Plan'!$H$7:$H$156,">="&J$60)+0.25*COUNTIFS('Project Plan'!$V$7:$V$156,"*;"&$A68&";*",'Project Plan'!$O$7:$O$156,"<>"&$A68,'Project Plan'!$F$7:$F$156,"<="&J$60,'Project Plan'!$H$7:$H$156,">="&J$60) -> 2.25 | ... AC68: =COUNTIFS('Project Plan'!$O$7:$O$156,$A68,'Project Plan'!$F$7:$F$156,"<="&AC$60,'Project Plan'!$H$7:$H$156,">="&AC$60)+0.25*COUNTIFS('Project Plan'!$V$7:$V$156,"*;"&$A68&";*",'Project Plan'!$O$7:$O$156,"<>"&$A68,'Project Plan'!$F$7:$F$156,"<="&AC$60,'Project Plan'!$H$7:$H$156,">="&AC$60) -> 0
A69: =A13 -> IDC | B69: =4*E13 -> 2 | C69: =COUNTIFS('Project Plan'!$O$7:$O$156,$A69,'Project Plan'!$F$7:$F$156,"<="&C$60,'Project Plan'!$H$7:$H$156,">="&C$60)+0.25*COUNTIFS('Project Plan'!$V$7:$V$156,"*;"&$A69&";*",'Project Plan'!$O$7:$O$156,"<>"&$A69,'Project Plan'!$F$7:$F$156,"<="&C$60,'Project Plan'!$H$7:$H$156,">="&C$60) -> 0 | D69: =COUNTIFS('Project Plan'!$O$7:$O$156,$A69,'Project Plan'!$F$7:$F$156,"<="&D$60,'Project Plan'!$H$7:$H$156,">="&D$60)+0.25*COUNTIFS('Project Plan'!$V$7:$V$156,"*;"&$A69&";*",'Project Plan'!$O$7:$O$156,"<>"&$A69,'Project Plan'!$F$7:$F$156,"<="&D$60,'Project Plan'!$H$7:$H$156,">="&D$60) -> 0 | E69: =COUNTIFS('Project Plan'!$O$7:$O$156,$A69,'Project Plan'!$F$7:$F$156,"<="&E$60,'Project Plan'!$H$7:$H$156,">="&E$60)+0.25*COUNTIFS('Project Plan'!$V$7:$V$156,"*;"&$A69&";*",'Project Plan'!$O$7:$O$156,"<>"&$A69,'Project Plan'!$F$7:$F$156,"<="&E$60,'Project Plan'!$H$7:$H$156,">="&E$60) -> 0 | F69: =COUNTIFS('Project Plan'!$O$7:$O$156,$A69,'Project Plan'!$F$7:$F$156,"<="&F$60,'Project Plan'!$H$7:$H$156,">="&F$60)+0.25*COUNTIFS('Project Plan'!$V$7:$V$156,"*;"&$A69&";*",'Project Plan'!$O$7:$O$156,"<>"&$A69,'Project Plan'!$F$7:$F$156,"<="&F$60,'Project Plan'!$H$7:$H$156,">="&F$60) -> 1 | G69: =COUNTIFS('Project Plan'!$O$7:$O$156,$A69,'Project Plan'!$F$7:$F$156,"<="&G$60,'Project Plan'!$H$7:$H$156,">="&G$60)+0.25*COUNTIFS('Project Plan'!$V$7:$V$156,"*;"&$A69&";*",'Project Plan'!$O$7:$O$156,"<>"&$A69,'Project Plan'!$F$7:$F$156,"<="&G$60,'Project Plan'!$H$7:$H$156,">="&G$60) -> 2 | H69: =COUNTIFS('Project Plan'!$O$7:$O$156,$A69,'Project Plan'!$F$7:$F$156,"<="&H$60,'Project Plan'!$H$7:$H$156,">="&H$60)+0.25*COUNTIFS('Project Plan'!$V$7:$V$156,"*;"&$A69&";*",'Project Plan'!$O$7:$O$156,"<>"&$A69,'Project Plan'!$F$7:$F$156,"<="&H$60,'Project Plan'!$H$7:$H$156,">="&H$60) -> 2 | I69: =COUNTIFS('Project Plan'!$O$7:$O$156,$A69,'Project Plan'!$F$7:$F$156,"<="&I$60,'Project Plan'!$H$7:$H$156,">="&I$60)+0.25*COUNTIFS('Project Plan'!$V$7:$V$156,"*;"&$A69&";*",'Project Plan'!$O$7:$O$156,"<>"&$A69,'Project Plan'!$F$7:$F$156,"<="&I$60,'Project Plan'!$H$7:$H$156,">="&I$60) -> 1 | J69: =COUNTIFS('Project Plan'!$O$7:$O$156,$A69,'Project Plan'!$F$7:$F$156,"<="&J$60,'Project Plan'!$H$7:$H$156,">="&J$60)+0.25*COUNTIFS('Project Plan'!$V$7:$V$156,"*;"&$A69&";*",'Project Plan'!$O$7:$O$156,"<>"&$A69,'Project Plan'!$F$7:$F$156,"<="&J$60,'Project Plan'!$H$7:$H$156,">="&J$60) -> 2 | ... AC69: =COUNTIFS('Project Plan'!$O$7:$O$156,$A69,'Project Plan'!$F$7:$F$156,"<="&AC$60,'Project Plan'!$H$7:$H$156,">="&AC$60)+0.25*COUNTIFS('Project Plan'!$V$7:$V$156,"*;"&$A69&";*",'Project Plan'!$O$7:$O$156,"<>"&$A69,'Project Plan'!$F$7:$F$156,"<="&AC$60,'Project Plan'!$H$7:$H$156,">="&AC$60) -> 0
A70: =A14 -> CSO | B70: =4*E14 -> 4 | C70: =COUNTIFS('Project Plan'!$O$7:$O$156,$A70,'Project Plan'!$F$7:$F$156,"<="&C$60,'Project Plan'!$H$7:$H$156,">="&C$60)+0.25*COUNTIFS('Project Plan'!$V$7:$V$156,"*;"&$A70&";*",'Project Plan'!$O$7:$O$156,"<>"&$A70,'Project Plan'!$F$7:$F$156,"<="&C$60,'Project Plan'!$H$7:$H$156,">="&C$60) -> 0.5 | D70: =COUNTIFS('Project Plan'!$O$7:$O$156,$A70,'Project Plan'!$F$7:$F$156,"<="&D$60,'Project Plan'!$H$7:$H$156,">="&D$60)+0.25*COUNTIFS('Project Plan'!$V$7:$V$156,"*;"&$A70&";*",'Project Plan'!$O$7:$O$156,"<>"&$A70,'Project Plan'!$F$7:$F$156,"<="&D$60,'Project Plan'!$H$7:$H$156,">="&D$60) -> 0.5 | E70: =COUNTIFS('Project Plan'!$O$7:$O$156,$A70,'Project Plan'!$F$7:$F$156,"<="&E$60,'Project Plan'!$H$7:$H$156,">="&E$60)+0.25*COUNTIFS('Project Plan'!$V$7:$V$156,"*;"&$A70&";*",'Project Plan'!$O$7:$O$156,"<>"&$A70,'Project Plan'!$F$7:$F$156,"<="&E$60,'Project Plan'!$H$7:$H$156,">="&E$60) -> 0.25 | F70: =COUNTIFS('Project Plan'!$O$7:$O$156,$A70,'Project Plan'!$F$7:$F$156,"<="&F$60,'Project Plan'!$H$7:$H$156,">="&F$60)+0.25*COUNTIFS('Project Plan'!$V$7:$V$156,"*;"&$A70&";*",'Project Plan'!$O$7:$O$156,"<>"&$A70,'Project Plan'!$F$7:$F$156,"<="&F$60,'Project Plan'!$H$7:$H$156,">="&F$60) -> 0 | G70: =COUNTIFS('Project Plan'!$O$7:$O$156,$A70,'Project Plan'!$F$7:$F$156,"<="&G$60,'Project Plan'!$H$7:$H$156,">="&G$60)+0.25*COUNTIFS('Project Plan'!$V$7:$V$156,"*;"&$A70&";*",'Project Plan'!$O$7:$O$156,"<>"&$A70,'Project Plan'!$F$7:$F$156,"<="&G$60,'Project Plan'!$H$7:$H$156,">="&G$60) -> 0 | H70: =COUNTIFS('Project Plan'!$O$7:$O$156,$A70,'Project Plan'!$F$7:$F$156,"<="&H$60,'Project Plan'!$H$7:$H$156,">="&H$60)+0.25*COUNTIFS('Project Plan'!$V$7:$V$156,"*;"&$A70&";*",'Project Plan'!$O$7:$O$156,"<>"&$A70,'Project Plan'!$F$7:$F$156,"<="&H$60,'Project Plan'!$H$7:$H$156,">="&H$60) -> 1 | I70: =COUNTIFS('Project Plan'!$O$7:$O$156,$A70,'Project Plan'!$F$7:$F$156,"<="&I$60,'Project Plan'!$H$7:$H$156,">="&I$60)+0.25*COUNTIFS('Project Plan'!$V$7:$V$156,"*;"&$A70&";*",'Project Plan'!$O$7:$O$156,"<>"&$A70,'Project Plan'!$F$7:$F$156,"<="&I$60,'Project Plan'!$H$7:$H$156,">="&I$60) -> 2.5 | J70: =COUNTIFS('Project Plan'!$O$7:$O$156,$A70,'Project Plan'!$F$7:$F$156,"<="&J$60,'Project Plan'!$H$7:$H$156,">="&J$60)+0.25*COUNTIFS('Project Plan'!$V$7:$V$156,"*;"&$A70&";*",'Project Plan'!$O$7:$O$156,"<>"&$A70,'Project Plan'!$F$7:$F$156,"<="&J$60,'Project Plan'!$H$7:$H$156,">="&J$60) -> 2.5 | ... AC70: =COUNTIFS('Project Plan'!$O$7:$O$156,$A70,'Project Plan'!$F$7:$F$156,"<="&AC$60,'Project Plan'!$H$7:$H$156,">="&AC$60)+0.25*COUNTIFS('Project Plan'!$V$7:$V$156,"*;"&$A70&";*",'Project Plan'!$O$7:$O$156,"<>"&$A70,'Project Plan'!$F$7:$F$156,"<="&AC$60,'Project Plan'!$H$7:$H$156,">="&AC$60) -> 0
A71: =A15 -> BSC | B71: =4*E15 -> 2 | C71: =COUNTIFS('Project Plan'!$O$7:$O$156,$A71,'Project Plan'!$F$7:$F$156,"<="&C$60,'Project Plan'!$H$7:$H$156,">="&C$60)+0.25*COUNTIFS('Project Plan'!$V$7:$V$156,"*;"&$A71&";*",'Project Plan'!$O$7:$O$156,"<>"&$A71,'Project Plan'!$F$7:$F$156,"<="&C$60,'Project Plan'!$H$7:$H$156,">="&C$60) -> 0 | D71: =COUNTIFS('Project Plan'!$O$7:$O$156,$A71,'Project Plan'!$F$7:$F$156,"<="&D$60,'Project Plan'!$H$7:$H$156,">="&D$60)+0.25*COUNTIFS('Project Plan'!$V$7:$V$156,"*;"&$A71&";*",'Project Plan'!$O$7:$O$156,"<>"&$A71,'Project Plan'!$F$7:$F$156,"<="&D$60,'Project Plan'!$H$7:$H$156,">="&D$60) -> 0 | E71: =COUNTIFS('Project Plan'!$O$7:$O$156,$A71,'Project Plan'!$F$7:$F$156,"<="&E$60,'Project Plan'!$H$7:$H$156,">="&E$60)+0.25*COUNTIFS('Project Plan'!$V$7:$V$156,"*;"&$A71&";*",'Project Plan'!$O$7:$O$156,"<>"&$A71,'Project Plan'!$F$7:$F$156,"<="&E$60,'Project Plan'!$H$7:$H$156,">="&E$60) -> 0 | F71: =COUNTIFS('Project Plan'!$O$7:$O$156,$A71,'Project Plan'!$F$7:$F$156,"<="&F$60,'Project Plan'!$H$7:$H$156,">="&F$60)+0.25*COUNTIFS('Project Plan'!$V$7:$V$156,"*;"&$A71&";*",'Project Plan'!$O$7:$O$156,"<>"&$A71,'Project Plan'!$F$7:$F$156,"<="&F$60,'Project Plan'!$H$7:$H$156,">="&F$60) -> 0.25 | G71: =COUNTIFS('Project Plan'!$O$7:$O$156,$A71,'Project Plan'!$F$7:$F$156,"<="&G$60,'Project Plan'!$H$7:$H$156,">="&G$60)+0.25*COUNTIFS('Project Plan'!$V$7:$V$156,"*;"&$A71&";*",'Project Plan'!$O$7:$O$156,"<>"&$A71,'Project Plan'!$F$7:$F$156,"<="&G$60,'Project Plan'!$H$7:$H$156,">="&G$60) -> 0.25 | H71: =COUNTIFS('Project Plan'!$O$7:$O$156,$A71,'Project Plan'!$F$7:$F$156,"<="&H$60,'Project Plan'!$H$7:$H$156,">="&H$60)+0.25*COUNTIFS('Project Plan'!$V$7:$V$156,"*;"&$A71&";*",'Project Plan'!$O$7:$O$156,"<>"&$A71,'Project Plan'!$F$7:$F$156,"<="&H$60,'Project Plan'!$H$7:$H$156,">="&H$60) -> 1.25 | I71: =COUNTIFS('Project Plan'!$O$7:$O$156,$A71,'Project Plan'!$F$7:$F$156,"<="&I$60,'Project Plan'!$H$7:$H$156,">="&I$60)+0.25*COUNTIFS('Project Plan'!$V$7:$V$156,"*;"&$A71&";*",'Project Plan'!$O$7:$O$156,"<>"&$A71,'Project Plan'!$F$7:$F$156,"<="&I$60,'Project Plan'!$H$7:$H$156,">="&I$60) -> 2 | J71: =COUNTIFS('Project Plan'!$O$7:$O$156,$A71,'Project Plan'!$F$7:$F$156,"<="&J$60,'Project Plan'!$H$7:$H$156,">="&J$60)+0.25*COUNTIFS('Project Plan'!$V$7:$V$156,"*;"&$A71&";*",'Project Plan'!$O$7:$O$156,"<>"&$A71,'Project Plan'!$F$7:$F$156,"<="&J$60,'Project Plan'!$H$7:$H$156,">="&J$60) -> 2 | ... AC71: =COUNTIFS('Project Plan'!$O$7:$O$156,$A71,'Project Plan'!$F$7:$F$156,"<="&AC$60,'Project Plan'!$H$7:$H$156,">="&AC$60)+0.25*COUNTIFS('Project Plan'!$V$7:$V$156,"*;"&$A71&";*",'Project Plan'!$O$7:$O$156,"<>"&$A71,'Project Plan'!$F$7:$F$156,"<="&AC$60,'Project Plan'!$H$7:$H$156,">="&AC$60) -> 0
A72: =A16 -> GRCC | B72: =4*E16 -> 4 | C72: =COUNTIFS('Project Plan'!$O$7:$O$156,$A72,'Project Plan'!$F$7:$F$156,"<="&C$60,'Project Plan'!$H$7:$H$156,">="&C$60)+0.25*COUNTIFS('Project Plan'!$V$7:$V$156,"*;"&$A72&";*",'Project Plan'!$O$7:$O$156,"<>"&$A72,'Project Plan'!$F$7:$F$156,"<="&C$60,'Project Plan'!$H$7:$H$156,">="&C$60) -> 0 | D72: =COUNTIFS('Project Plan'!$O$7:$O$156,$A72,'Project Plan'!$F$7:$F$156,"<="&D$60,'Project Plan'!$H$7:$H$156,">="&D$60)+0.25*COUNTIFS('Project Plan'!$V$7:$V$156,"*;"&$A72&";*",'Project Plan'!$O$7:$O$156,"<>"&$A72,'Project Plan'!$F$7:$F$156,"<="&D$60,'Project Plan'!$H$7:$H$156,">="&D$60) -> 0 | E72: =COUNTIFS('Project Plan'!$O$7:$O$156,$A72,'Project Plan'!$F$7:$F$156,"<="&E$60,'Project Plan'!$H$7:$H$156,">="&E$60)+0.25*COUNTIFS('Project Plan'!$V$7:$V$156,"*;"&$A72&";*",'Project Plan'!$O$7:$O$156,"<>"&$A72,'Project Plan'!$F$7:$F$156,"<="&E$60,'Project Plan'!$H$7:$H$156,">="&E$60) -> 0 | F72: =COUNTIFS('Project Plan'!$O$7:$O$156,$A72,'Project Plan'!$F$7:$F$156,"<="&F$60,'Project Plan'!$H$7:$H$156,">="&F$60)+0.25*COUNTIFS('Project Plan'!$V$7:$V$156,"*;"&$A72&";*",'Project Plan'!$O$7:$O$156,"<>"&$A72,'Project Plan'!$F$7:$F$156,"<="&F$60,'Project Plan'!$H$7:$H$156,">="&F$60) -> 1 | G72: =COUNTIFS('Project Plan'!$O$7:$O$156,$A72,'Project Plan'!$F$7:$F$156,"<="&G$60,'Project Plan'!$H$7:$H$156,">="&G$60)+0.25*COUNTIFS('Project Plan'!$V$7:$V$156,"*;"&$A72&";*",'Project Plan'!$O$7:$O$156,"<>"&$A72,'Project Plan'!$F$7:$F$156,"<="&G$60,'Project Plan'!$H$7:$H$156,">="&G$60) -> 2 | H72: =COUNTIFS('Project Plan'!$O$7:$O$156,$A72,'Project Plan'!$F$7:$F$156,"<="&H$60,'Project Plan'!$H$7:$H$156,">="&H$60)+0.25*COUNTIFS('Project Plan'!$V$7:$V$156,"*;"&$A72&";*",'Project Plan'!$O$7:$O$156,"<>"&$A72,'Project Plan'!$F$7:$F$156,"<="&H$60,'Project Plan'!$H$7:$H$156,">="&H$60) -> 2.25 | I72: =COUNTIFS('Project Plan'!$O$7:$O$156,$A72,'Project Plan'!$F$7:$F$156,"<="&I$60,'Project Plan'!$H$7:$H$156,">="&I$60)+0.25*COUNTIFS('Project Plan'!$V$7:$V$156,"*;"&$A72&";*",'Project Plan'!$O$7:$O$156,"<>"&$A72,'Project Plan'!$F$7:$F$156,"<="&I$60,'Project Plan'!$H$7:$H$156,">="&I$60) -> 3.5 | J72: =COUNTIFS('Project Plan'!$O$7:$O$156,$A72,'Project Plan'!$F$7:$F$156,"<="&J$60,'Project Plan'!$H$7:$H$156,">="&J$60)+0.25*COUNTIFS('Project Plan'!$V$7:$V$156,"*;"&$A72&";*",'Project Plan'!$O$7:$O$156,"<>"&$A72,'Project Plan'!$F$7:$F$156,"<="&J$60,'Project Plan'!$H$7:$H$156,">="&J$60) -> 3.5 | ... AC72: =COUNTIFS('Project Plan'!$O$7:$O$156,$A72,'Project Plan'!$F$7:$F$156,"<="&AC$60,'Project Plan'!$H$7:$H$156,">="&AC$60)+0.25*COUNTIFS('Project Plan'!$V$7:$V$156,"*;"&$A72&";*",'Project Plan'!$O$7:$O$156,"<>"&$A72,'Project Plan'!$F$7:$F$156,"<="&AC$60,'Project Plan'!$H$7:$H$156,">="&AC$60) -> 0
... A82: =A26 -> ENG | B82: =4*E26 -> 0 | C82: =COUNTIFS('Project Plan'!$O$7:$O$156,$A82,'Project Plan'!$F$7:$F$156,"<="&C$60,'Project Plan'!$H$7:$H$156,">="&C$60)+0.25*COUNTIFS('Project Plan'!$V$7:$V$156,"*;"&$A82&";*",'Project Plan'!$O$7:$O$156,"<>"&$A82,'Project Plan'!$F$7:$F$156,"<="&C$60,'Project Plan'!$H$7:$H$156,">="&C$60) -> 0.5 | D82: =COUNTIFS('Project Plan'!$O$7:$O$156,$A82,'Project Plan'!$F$7:$F$156,"<="&D$60,'Project Plan'!$H$7:$H$156,">="&D$60)+0.25*COUNTIFS('Project Plan'!$V$7:$V$156,"*;"&$A82&";*",'Project Plan'!$O$7:$O$156,"<>"&$A82,'Project Plan'!$F$7:$F$156,"<="&D$60,'Project Plan'!$H$7:$H$156,">="&D$60) -> 0.5 | E82: =COUNTIFS('Project Plan'!$O$7:$O$156,$A82,'Project Plan'!$F$7:$F$156,"<="&E$60,'Project Plan'!$H$7:$H$156,">="&E$60)+0.25*COUNTIFS('Project Plan'!$V$7:$V$156,"*;"&$A82&";*",'Project Plan'!$O$7:$O$156,"<>"&$A82,'Project Plan'!$F$7:$F$156,"<="&E$60,'Project Plan'!$H$7:$H$156,">="&E$60) -> 1.25 | F82: =COUNTIFS('Project Plan'!$O$7:$O$156,$A82,'Project Plan'!$F$7:$F$156,"<="&F$60,'Project Plan'!$H$7:$H$156,">="&F$60)+0.25*COUNTIFS('Project Plan'!$V$7:$V$156,"*;"&$A82&";*",'Project Plan'!$O$7:$O$156,"<>"&$A82,'Project Plan'!$F$7:$F$156,"<="&F$60,'Project Plan'!$H$7:$H$156,">="&F$60) -> 1 | G82: =COUNTIFS('Project Plan'!$O$7:$O$156,$A82,'Project Plan'!$F$7:$F$156,"<="&G$60,'Project Plan'!$H$7:$H$156,">="&G$60)+0.25*COUNTIFS('Project Plan'!$V$7:$V$156,"*;"&$A82&";*",'Project Plan'!$O$7:$O$156,"<>"&$A82,'Project Plan'!$F$7:$F$156,"<="&G$60,'Project Plan'!$H$7:$H$156,">="&G$60) -> 1 | H82: =COUNTIFS('Project Plan'!$O$7:$O$156,$A82,'Project Plan'!$F$7:$F$156,"<="&H$60,'Project Plan'!$H$7:$H$156,">="&H$60)+0.25*COUNTIFS('Project Plan'!$V$7:$V$156,"*;"&$A82&";*",'Project Plan'!$O$7:$O$156,"<>"&$A82,'Project Plan'!$F$7:$F$156,"<="&H$60,'Project Plan'!$H$7:$H$156,">="&H$60) -> 1 | I82: =COUNTIFS('Project Plan'!$O$7:$O$156,$A82,'Project Plan'!$F$7:$F$156,"<="&I$60,'Project Plan'!$H$7:$H$156,">="&I$60)+0.25*COUNTIFS('Project Plan'!$V$7:$V$156,"*;"&$A82&";*",'Project Plan'!$O$7:$O$156,"<>"&$A82,'Project Plan'!$F$7:$F$156,"<="&I$60,'Project Plan'!$H$7:$H$156,">="&I$60) -> 2 | J82: =COUNTIFS('Project Plan'!$O$7:$O$156,$A82,'Project Plan'!$F$7:$F$156,"<="&J$60,'Project Plan'!$H$7:$H$156,">="&J$60)+0.25*COUNTIFS('Project Plan'!$V$7:$V$156,"*;"&$A82&";*",'Project Plan'!$O$7:$O$156,"<>"&$A82,'Project Plan'!$F$7:$F$156,"<="&J$60,'Project Plan'!$H$7:$H$156,">="&J$60) -> 2 | ... AC82: =COUNTIFS('Project Plan'!$O$7:$O$156,$A82,'Project Plan'!$F$7:$F$156,"<="&AC$60,'Project Plan'!$H$7:$H$156,">="&AC$60)+0.25*COUNTIFS('Project Plan'!$V$7:$V$156,"*;"&$A82&";*",'Project Plan'!$O$7:$O$156,"<>"&$A82,'Project Plan'!$F$7:$F$156,"<="&AC$60,'Project Plan'!$H$7:$H$156,">="&AC$60) -> 0

Sheet RACI
A1: RACI - workstream x role (R Responsible, A Accountable, C Consulted, I Informed, - none)
A2: Exactly one A per workstream. Executive sponsor (CEO/COO) chairs Steering and is accountable for the program overall.
A4: WS | B4: Workstream | C4: PL | D4: CSE | E4: ISE | F4: GRC | G4: BSE | H4: KHE | I4: CPE | J4: DET | K4: IDC | L4: CSO | M4: BSC | N4: GRCC | O4: PMC | P4: SCA | Q4: MDR | R4: PEN | S4: RDA | T4: CPA | U4: LEG | V4: IA | W4: HRB | X4: ENG | Y4: # of A (must be 1)
A5: HD | B5: OS & Container Hardening (org guardrails, network, EOL) | C5: I | D5: A | E5: C | F5: C | G5: I | H5: R | I5: R | J5: I | K5: - | L5: - | M5: - | N5: I | O5: I | P5: - | Q5: I | R5: C | S5: - | T5: - | U5: - | V5: - | W5: - | X5: R | Y5: =COUNTIF(C5:X5,"A") -> 1
A6: ID | B6: Identity Hardening (workforce, customer, workload, wallet sign-in) | C6: I | D6: C | E6: A | F6: C | G6: R | H6: - | I6: R | J6: C | K6: R | L6: - | M6: R | N6: I | O6: I | P6: - | Q6: I | R6: C | S6: - | T6: - | U6: - | V6: - | W6: C | X6: R | Y6: =COUNTIF(C6:X6,"A") -> 1
A7: MR | B7: Security Monitoring, Response & Resilience | C7: C | D7: R | E7: A | F7: C | G7: R | H7: C | I7: R | J7: R | K7: C | L7: R | M7: - | N7: I | O7: I | P7: - | Q7: R | R7: R | S7: - | T7: - | U7: C | V7: - | W7: - | X7: C | Y7: =COUNTIF(C7:X7,"A") -> 1
A8: BC | B8: Blockchain Security | C8: C | D8: C | E8: C | F8: C | G8: A | H8: - | I8: - | J8: C | K8: - | L8: R | M8: R | N8: I | O8: I | P8: R | Q8: I | R8: C | S8: - | T8: - | U8: C | V8: - | W8: - | X8: R | Y8: =COUNTIF(C8:X8,"A") -> 1
A9: GC | B9: Governance & Compliance | C9: C | D9: C | E9: C | F9: A | G9: C | H9: - | I9: - | J9: - | K9: - | L9: R | M9: - | N9: R | O9: R | P9: - | Q9: - | R9: - | S9: R | T9: R | U9: R | V9: R | W9: R | X9: I | Y9: =COUNTIF(C9:X9,"A") -> 1
A10: PM | B10: Program Management & Sustainment | C10: A | D10: R | E10: R | F10: R | G10: R | H10: I | I10: I | J10: I | K10: I | L10: I | M10: I | N10: I | O10: R | P10: I | Q10: I | R10: I | S10: I | T10: I | U10: I | V10: I | W10: I | X10: I | Y10: =COUNTIF(C10:X10,"A") -> 1
A12: Role key
A13: PL | B13: Security Program Lead
A14: CSE | B14: Cloud & Platform Security Engineer
A15: ISE | B15: Identity & Security Operations Engineer (IR Lead)
A16: GRC | B16: GRC & Risk Lead (2nd line)
A17: BSE | B17: Blockchain Security Engineer
A18: KHE | B18: Contract Cloud/K8s Hardening Engineer
A19: CPE | B19: Contract Cloud Platform Security Engineer
A20: DET | B20: Contract Detection Engineer (Splunk)
A21: IDC | B21: Contract Identity Specialist (Entra/B2C)
A22: CSO | B22: Contract Custody, Staking & Sanctions Specialist
A23: BSC | B23: Contract Smart-Contract Security Engineer
A24: GRCC | B24: Contract SOC 2 Implementation Consultant
... A34: ENG | B34: Platform & App Engineering teams (change implementers)

Sheet Governance Model
A1: Governance Model - forums, three lines, policy lifecycle, evergreen loop, operating calendar, triggers
A4: Forum | B4: Cadence | C4: Membership | D4: Decision rights | E4: Inputs | F4: Outputs
A5: Security Steering Committee (incl. Risk & Compliance review) | B5: Monthly (60 min) + at gates W6/W15/W20/W26 | C5: CEO or COO (chair), CTO, CFO, Security Program Lead, GRC Lead; IA attends quarterly; reports quarterly to the Board | D5: Scope, budget, gate pass/fail, risk acceptance above appetite, policy approval, regulatory go/no-go | E5: KPI/KRI pack, risk register, exceptions due, decision log, gate evidence | F5: Signed minutes, decisions, risk acceptances
A6: Architecture Review Board | B6: Fortnightly (first 30 min of the weekly CAB slot); monthly in BAU | C6: Head of Platform (chair), Cloud & Platform Sec Eng, Identity & SecOps Eng, Blockchain Sec Eng, Program Lead | D6: Approve designs/standards; grant time-boxed exceptions (max 90 days) to standards | E6: Design packs, threat model deltas, benchmark changes | F6: Approvals log, exception records
A7: Contract Upgrade & Key Committee (CUKC) | B7: Fortnightly (30 min) + ad hoc within 4h for emergencies | C7: Head of Blockchain Engineering (internal chair), Blockchain Sec Eng (security veto), Custody Ops lead, Program Lead, Legal on call | D7: Approve contract/program deploys and upgrades, signer/threshold/timelock changes, custody policy-engine changes, staking authority/consolidation actions | E7: Audit/diff reports, verified-build hashes, simulation results, monitoring updates | F7: Signed change record; on-chain tx hashes
A8: Change Advisory Board | B8: Weekly; emergency CAB within 2h | C8: Head of Platform/SRE (chair), service owners, Cloud & Platform Sec Eng | D8: Approve production changes (standard/normal/emergency); enforce freeze windows | E8: Change requests with rollback plans | F8: Approved change calendar
A9: Incident Response forum | B9: 24/7: interim internal on-call W0-W12, MDR from W13 (phased from W5); monthly IR review; post-incident review within 5 business days | C9: IR Lead (Identity & SecOps Eng), MDR, Blockchain Sec Eng for on-chain, Program Lead, Legal/Comms | D9: Declare/close incidents, contain, notify (per D-01 matrix), invoke CUKC emergency pause | E9: Alerts, MDR escalations, on-chain monitor alerts | F9: Incident records, PIR actions
A10: Independent assurance | B10: Annual internal-audit cycle (first review W22-W24) + annual SOC 2 by CPA | C10: Outsourced internal audit reporting directly to the Board/Audit Committee; SOC 2 CPA firm; independent readiness assessor | D10: Independently test 1st- and 2nd-line controls; report findings directly to Steering/Board | E10: Control matrix, evidence, risk register | F10: IA report; SOC 2 report
A12: Three lines model
A13: Line | B13: Who | C13: Responsibilities
A14: 1st line - own and operate controls | B14: Cloud & Platform Sec Eng, Identity & SecOps Eng, Blockchain Sec Eng, Platform/App engineering, Custody Ops | C14: Implement and run controls; self-assess; raise exceptions
A15: 2nd line - oversee and challenge | B15: GRC & Risk Lead (with SOC 2 readiness consultant during program) | C15: Policies, risk register, control monitoring in GRC platform, TPRM, exception expiry; never tests controls it operates
A16: 3rd line - independent assurance | B16: Outsourced internal audit (reports to Board/Audit Committee); SOC 2 CPA firm; independent readiness assessor | C16: Independent testing of 1st- and 2nd-line controls; the implementation consultant (GRCC), readiness assessor (RDA) and CPA are three different firms
A18: Policy lifecycle (version-controlled in git)
A19: Stage | B19: What happens | C19: Owner
A20: 1 Draft | B20: Author opens a pull request in the policy git repo (markdown, semantic version) | C20: Policy owner
A21: 2 Review | B21: GRC review against control matrix; SME review; legal where needed | C21: GRC Lead
A22: 3 Approve | B22: Policies: Steering; standards/procedures: ARB or owning forum | C22: Steering / ARB
A23: 4 Publish & attest | B23: Tagged release; staff acknowledgement tracked in GRC platform | C23: GRC Lead
A24: 5 Operate & monitor | B24: Mapped controls tested automatically where possible; exceptions time-boxed | C24: Control owners
A25: 6 Review | B25: Annually, or within 30 days of a trigger event | C25: Policy owner
A26: 7 Retire | B26: Superseded versions archived; mapping updated | C26: GRC Lead
A28: Evergreen loop
A29: Step | B29: Mechanism | C29: Owner
A30: 1 Monitor | B30: Automated control health (Security Hub CSPM, Inspector, GRC platform tests, Splunk silent-source alerts, on-chain monitors) | C30: Control owners (1st line)
A31: 2 Measure | B31: KPI/KRI pack refreshed weekly; exceptions and expiry tracked | C31: PMC -> GRC in BAU
A32: 3 Review | B32: Monthly Steering + risk & compliance review; ARB/CUKC/CAB on changes; quarterly board report | C32: Steering
A33: 4 Improve | B33: Corrective-action log; design changes via ARB; threat-model and benchmark refresh on triggers | C33: Workstream leads
A34: 5 Assure | B34: Independent assurance (IA annually; SOC 2 Type II annually; readiness assessor separate from CPA) | C34: 3rd line
A36: Operating calendar
A37: Cadence | B37: Activities
A38: Weekly | B38: Audit-evidence calendar check; vulnerability & patch SLA review; Security Hub score delta; detection tuning; CAB; CUKC; on-chain/validator alert review; KPI auto-refresh
A39: Monthly | B39: Steering + risk & compliance review; KPI/KRI pack; exception expiry sweep; privileged access review; phishing simulation; staking provider performance report; EOL register update
A40: Quarterly | B40: Full access reviews (Entra, AWS, custody approvers, multisig signers); tabletop exercise; automated tier-1 restore tests; signer key-ceremony drill; board cyber report; benchmark/version check (CIS, EKS, Agave/Firedancer, Safe/Squads); threat-model refresh; SCIM/secret expiry check
A41: Semi-annual | B41: Policy review tranche; pause/guardian drill; staking & custody vendor reassessment; on-chain monitoring coverage review; IR plan update
A42: Annual | B42: SOC 2 Type II examination; penetration test (plus after major change); full DR test; security and fraud risk assessment & risk appetite refresh; management review; cyber insurance renewal; vendor exit-plan test; policy re-approval; internal audit; training refresh; crypto-agility/PQ roadmap review; CSF 2.0 profile re-baseline
A44: Event triggers that force re-assessment
A45: Trigger | B45: Required response
A46: Contract deploy or upgrade | B46: CUKC approval; audit or diff review; verified build; monitor rules updated before execution; timelock respected
A47: Hard fork or client release (e.g. Glamsterdam mainnet, Agave/Firedancer majors) | B47: Fork runbook; provider written readiness; testnet regression; heightened monitoring 72h
A48: New benchmark or vendor version (CIS, EKS EOS, Splunk/Security Hub change) | B48: Gap mapping within 30 days; ARB decision; KPI targets adjusted
A49: Major incident (internal or industry, e.g. multisig/UI compromise) | B49: Post-incident review; threat model update; control changes via ARB/CUKC
A50: New vendor or material vendor change | B50: TPRM tiering and due diligence before contract; SOC report review
A51: Regulatory change or new market (e.g. EU marketing, US market-structure law) | B51: Counsel review; D-01 refresh; re-plan if in scope
A52: Signer, admin or key-person change | B52: Signer rotation; access revocation within 24h; contractor-dependency KRI update
A53: EOL announcement (OS, Kubernetes, tooling) | B53: EOL register entry with owner/date; exception if needed
A54: Exception reaching expiry | B54: Remediate or one renewal max (Steering approval); second expiry escalates as a risk acceptance
A55: Contractor exit or contract change | B55: Knowledge-transfer check; access revoked within 24h; contractor-dependency KRI recalculated
A57: Framework mapping by workstream
A58: WS | B58: NIST CSF 2.0 | C58: ISO 27001:2022 Annex A / clauses | D58: CIS Controls v8.1 | E58: Benchmarks / standards | F58: SOC 2 TSC | G58: Security Hub CSPM control IDs
A59: HD | B59: PR.PS, PR.IR, ID.AM | C59: A.8.8, A.8.9, A.8.20-8.22, A.8.25-8.28 | D59: 1, 2, 4, 7, 12, 13 | E59: CIS AWS Foundations v5.0.0 (automated) / v7.1.0 (manual delta); CIS AL2023 v1.0.0; CIS EKS v2.0.0; CIS EKS Auto Mode v1.0.0; CIS Kubernetes v2.1.0; CIS Bottlerocket v1.0.0 | F59: CC6.1, CC6.6, CC6.8, CC7.1, CC8.1 | G59: EC2.2/.6/.7/.8/.9/.170, SSM.1-.3, EKS.1/.2/.8/.9, ECR.1-.3, S3.1/.5, KMS.3/.4, RDS.2/.3/.7/.8/.27, ELB.1/.4/.5/.16, WAF.10/.11, NetworkFirewall.2/.4/.5, Opensearch.1/.3/.5/.7, EFS.8, SQS.1, SNS.1, Kinesis.1, ACM.1, Inspector.1-.4
A60: ID | B60: PR.AA, GV.RR | C60: A.5.15-5.18, A.8.2, A.8.5 | D60: 5, 6 | E60: Microsoft Entra guidance; OWASP ASVS (customer auth); EIP-4361 (Final); EIP-1271 | F60: CC6.1-CC6.3 | G60: IAM.1/.2/.4/.6/.8/.22, SecretsManager.1/.3
A61: MR | B61: DE.CM, DE.AE, RS.*, RC.* | C61: A.5.24-5.28, A.8.13-8.16, A.5.29-5.30 | D61: 8, 10, 11, 13, 17, 18 | E61: NIST SP 800-61r3; MITRE ATT&CK; SEAL Incident Mgmt/Monitoring | F61: CC7.2-CC7.5, A1.2-A1.3 | G61: GuardDuty.1/.5/.7/.8/.10/.11, CloudTrail.1/.2/.4, Config.1, Backup.1, RDS.11/.14
A62: BC | B62: PR.DS, PR.PS, GV.SC, ID.RA | C62: A.8.24, A.8.25-8.29, A.5.19-5.22 | D62: 3, 16 | E62: BSSC SCS, KMS, NOS v2, TIS, GSP; CCSS v9.0; OWASP SC Top 10 2026 / SCSVS; SEAL Frameworks | F62: CC6.1, CC6.7, CC8.1, CC9.2 | G62: n/a (off-AWS)
A63: GC | B63: GV.OC, GV.RM, GV.RR, GV.PO, GV.OV, GV.SC | C63: Clauses 4-10; A.5.1-5.37; A.6.1-6.8 | D63: 14, 15 | E63: AICPA TSC 2017 (2022 PoF); NIST CSF 2.0; ISO/IEC 27001:2022; CIS Controls v8.1; MiCA/DORA/PCI (go/no-go) | F63: CC1-CC5, CC9 | G63: Account.1
A64: PM | B64: GV.OV, ID.IM | C64: Clauses 6, 9, 10 | D64: - | E64: Program governance | F64: CC3, CC4 | G64: -

Sheet KPIs
A1: KPIs and KRIs - fill 'Current value' and 'Named owner' (yellow); RAG is manual
A2: Example row format for Current value: '87%' or '3'. Owner role is the proposed accountable role.
A4: ID | B4: KPI | C4: Definition | D4: Target | E4: Data source | F4: Frequency | G4: Owner role (proposed) | H4: Current value | I4: Named owner | J4: RAG
A5: K01 | B5: CIS AL2023 Level 1 pass rate (EC2 fleet) | C5: Passed L1 checks / total applicable L1 checks across scanned AL2023 instances | D5: >=90% by W20 | E5: Amazon Inspector CIS scans | F5: Weekly | G5: CSE
A6: K02 | B6: Amazon Linux 2 / EOL OS instance count | C6: Running instances and node groups on AL2 or other EOL OS | D6: 0 (or approved exceptions with expiry) by W20 | E6: AWS Config / SSM inventory | F6: Weekly | G6: CSE
A7: K03 | B7: EKS clusters on a standard-support version | C7: Clusters on a version in standard support / all clusters | D7: 100% by W18 | E7: EKS API; Security Hub EKS.2/EKS.9 | F7: Weekly | G7: CSE
A8: K04 | B8: Patch SLA compliance (critical <=7d, high <=14d) | C8: Findings remediated within SLA / findings due in period | D8: >=95% from W12 | E8: SSM Patch Manager; Inspector | F8: Weekly | G8: KHE -> CSE
A9: K05 | B9: IMDSv2 coverage | C9: Instances requiring IMDSv2 / all instances | D9: 100% of instances by W12 | E9: Security Hub EC2.8 / EC2.170 | F9: Weekly | G9: CSE
A10: K06 | B10: Security Hub CSPM security score (FSBP + CIS v5.0.0) | C10: Security Hub CSPM score as reported | D10: >=90% by W20 | E10: Security Hub CSPM | F10: Weekly | G10: CSE
A11: K07 | B11: Production workloads running signed images | C11: Prod pods/tasks from signed images / all prod pods/tasks | D11: 100% by W19 | E11: ECR signing + admission/CI logs | F11: Weekly | G11: KHE -> CSE
A12: K08 | B12: Admins using phishing-resistant (device-bound FIDO2) MFA | C12: Privileged-role holders with enforced FIDO2 strength / all privileged-role holders | D12: 100% by W12 | E12: Entra authentication-methods report | F12: Weekly | G12: ISE
A13: K09 | B13: Standing privileged admins (excl. 2 break-glass) | C13: Permanent privileged assignments other than break-glass | D13: 0 by W15 | E13: Entra PIM; IAM Identity Center | F13: Weekly | G13: ISE
A14: K10 | B14: Customer withdrawals / payout-address changes protected by step-up MFA | C14: Withdrawal/payout-change requests with fresh step-up (auth_time <=5 min) / all such requests | D14: 100% of flows by W13 | E14: B2C logs + withdrawal API logs in Splunk | F14: Monthly | G14: ISE
A15: K11 | B15: MTTD - identity high-severity events | C15: Event _time to notable/MDR ticket creation | D15: Median <=15 min; p90 <=60 min from W14 | E15: Splunk ES / MDR tickets | F15: Monthly | G15: ISE
A16: K12 | B16: MTTD - on-chain privileged events | C16: Block timestamp to alert delivered to pager | D16: Median <=5 min; p90 <=15 min from W13 | E16: On-chain monitor + Splunk | F16: Monthly | G16: BSE
... A29: K25 | B29: Tier-1 vendor reviews current | C29: Tier-1 vendors with in-date review / tier-1 vendors | D29: 100% | E29: TPRM register | F29: Quarterly | G29: GRC
A31: Key risk indicators
A32: ID | B32: KRI | C32: Threshold | D32: Data source | E32: Frequency | F32: Owner role | G32: Current value | H32: Named owner
A33: KRI-1 | B33: Contractor dependency: critical runbooks without a trained internal owner | C33: 0 by W24 | D33: Handover tracker | E33: Monthly | F33: PL
A34: KRI-2 | B34: Lead tasks held by contractors after W24 | C34: 0 | D34: Project Plan | E34: Monthly | F34: PL
A35: KRI-3 | B35: Days of telemetry gap on any tier-1 log source | C35: 0 per month | D35: Splunk silent-source alerts | E35: Monthly | F35: ISE

Sheet Risks and Decisions
A1: Risk register (rating = likelihood x impact, 1-5 scales) and decision log (alignment checked by formula)
A4: ID | B4: Risk | C4: Likelihood (1-5) | D4: Impact (1-5) | E4: Rating | F4: Level | G4: Mitigation | H4: Owner
A5: R01 | B5: AL2 workloads cannot migrate on time (app dependencies) | C5: 4 | D5: 4 | E5: =C5*D5 -> 16 | F5: =IF(E5>=15,"High",IF(E5>=8,"Medium","Low")) -> High | G5: Containment (HD-03), two migration waves, time-boxed exceptions with expiry, CrowdStrike prevention | H5: CSE
A6: R02 | B6: EKS forced upgrade after 26 Nov 2026 breaks workloads | C6: 3 | D6: 4 | E6: =C6*D6 -> 12 | F6: =IF(E6>=15,"High",IF(E6>=8,"Medium","Low")) -> Medium | G6: HD-02 controlled 1.31->1.32 upgrade by W4; add-on testing; rollback | H6: CSE
A7: R03 | B7: Staking provider mishandles Alpenglow/Glamsterdam -> missed rewards or slashing | C7: 3 | D7: 3 | E7: =C7*D7 -> 9 | F7: =IF(E7>=15,"High",IF(E7>=8,"Medium","Low")) -> Medium | G7: BC-01 written confirmation; MR-14 monitoring; contract amendments BC-19 | H7: BSE
A8: R04 | B8: Signer-UI compromise or multisig social engineering (Bybit/Drift patterns) | C8: 3 | D8: 5 | E8: =C8*D8 -> 15 | F8: =IF(E8>=15,"High",IF(E8>=8,"Medium","Low")) -> High | G8: BC-10 timelocks/thresholds/delegatecall guard/durable-nonce ban; BC-11 clear signing and independent hash check; MR-13 alerts | H8: BSE
A9: R05 | B9: Smart-contract audit slot slips | C9: 3 | D9: 4 | E9: =C9*D9 -> 12 | F9: =IF(E9>=15,"High",IF(E9>=8,"Medium","Low")) -> Medium | G9: Book in W1-2 (PM-03) sized by nSLOC; code freeze W15; parallel EVM/Solana teams; backup auditor shortlisted | H9: PL
A10: R06 | B10: Small team overload / key-person dependency | C10: 4 | D10: 4 | E10: =C10*D10 -> 16 | F10: =IF(E10>=15,"High",IF(E10>=8,"Medium","Low")) -> High | G10: Capacity rule enforced (<=3 leads and weighted <=4.0 per FTE); 8 contractors for build peaks; deputies named in RACI | H10: PL
A11: R07 | B11: Contractor dependency persists after handover | C11: 3 | D11: 3 | E11: =C11*D11 -> 9 | F11: =IF(E11>=15,"High",IF(E11>=8,"Medium","Low")) -> Medium | G11: K20 KRI; handover PM-12 with internal owners; contractor access revoked at exit | H11: PL
A12: R08 | B12: Splunk ingest/licence overrun (Entra non-interactive logs 5-10x; OCSF volumes) | C12: 4 | D12: 3 | E12: =C12*D12 -> 12 | F12: =IF(E12>=15,"High",IF(E12>=8,"Medium","Low")) -> Medium | G12: Volume sizing in MR-03; filtering at Event Hub/HEC; tiered retention | H12: ISE
A13: R09 | B13: Customer account takeover on withdrawals (B2C has no risk-based protection after P2 retirement) | C13: 3 | D13: 4 | E13: =C13*D13 -> 12 | F13: =IF(E13>=15,"High",IF(E13>=8,"Medium","Low")) -> Medium | G13: Step-up MFA (ID-13); fraud/bot vendor (D-13); detections | H13: ISE
A14: R10 | B14: Regulatory scope changes (EU solicitation found; US market-structure law) | C14: 2 | D14: 5 | E14: =C14*D14 -> 10 | F14: =IF(E14>=15,"High",IF(E14>=8,"Medium","Low")) -> Medium | G14: D-01 with counsel; regulatory-change trigger; quarterly watch | H14: GRC
A15: R11 | B15: Unverified vendor claims (Solana monitoring coverage; CrowdStrike AL2023/Bottlerocket support) | C15: 3 | D15: 3 | E15: =C15*D15 -> 9 | F15: =IF(E15>=15,"High",IF(E15>=8,"Medium","Low")) -> Medium | G15: Written confirmation as contract condition (BC-09, HD-13) | H15: BSE
A16: R12 | B16: Holiday period W9-W10 reduces capacity | C16: 4 | D16: 2 | E16: =C16*D16 -> 8 | F16: =IF(E16>=15,"High",IF(E16>=8,"Medium","Low")) -> Medium | G16: Freeze prod changes; schedule design/non-prod work; no gates in W9-W10 | H16: PL
... A26: R22 | B26: Internal roles run at the capacity limit (3 leads, weighted 4.0) in several weeks | C26: 3 | D26: 3 | E26: =C26*D26 -> 9 | F26: =IF(E26>=15,"High",IF(E26>=8,"Medium","Low")) -> Medium | G26: PMO coordinator; weekly load review; Steering can descope low-priority tasks (e.g. HD-26/HD-30) | H26: PL
A28: Decision log
A29: ID | B29: Decision | C29: Options | D29: Owning task | E29: Due week | F29: Due date (Fri) | G29: Needed by (task IDs) | H29: Owning task end wk | I29: Earliest consumer start wk | J29: Alignment | K29: Decision taken / date
A30: D-01 | B30: Regulatory scope: MiCA/DORA/PCI no-go conditions; custodial/MSB/state licensing/Safeguards Rule; OFAC | C30: Out of scope with conditions / in scope (re-plan at G1) / partial | D30: GC-01 | E30: 4 | F30: =Overview!$B$4+7*(E30-1)+4 -> 46346 | G30: GC-04, MR-05, GC-07, GC-22, GC-23 | H30: =INDEX('Project Plan'!$H$7:$H$156,MATCH(D30,'Project Plan'!$A$7:$A$156,0)) -> 4 | I30: =SUMPRODUCT(MIN('Project Plan'!$F$7:$F$156+999*(1-ISNUMBER(SEARCH(","&'Project Plan'!$A$7:$A$156&",",","&SUBSTITUTE(G30," ","")&","))))) -> 5 | J30: =IF(AND(H30<=E30,I30>=E30),"ALIGNED","MISALIGNED") -> ALIGNED
A31: D-02 | B31: Entra licensing (admins, access-review population, workforce risk CA, workload identities) | C31: P2 / ID Governance / Entra Suite / Workload ID Premium | D31: ID-03 | E31: 5 | F31: =Overview!$B$4+7*(E31-1)+4 -> 46353 | G31: ID-08, ID-09, ID-16 | H31: =INDEX('Project Plan'!$H$7:$H$156,MATCH(D31,'Project Plan'!$A$7:$A$156,0)) -> 5 | I31: =SUMPRODUCT(MIN('Project Plan'!$F$7:$F$156+999*(1-ISNUMBER(SEARCH(","&'Project Plan'!$A$7:$A$156&",",","&SUBSTITUTE(G31," ","")&","))))) -> 7 | J31: =IF(AND(H31<=E31,I31>=E31),"ALIGNED","MISALIGNED") -> ALIGNED
A32: D-03 | B32: MDR provider and 24/7 owner per alert source | C32: Falcon Complete Next-Gen MDR / Splunk-integrated MDR / other | D32: MR-02 | E32: 4 | F32: =Overview!$B$4+7*(E32-1)+4 -> 46346 | G32: MR-11 | H32: =INDEX('Project Plan'!$H$7:$H$156,MATCH(D32,'Project Plan'!$A$7:$A$156,0)) -> 4 | I32: =SUMPRODUCT(MIN('Project Plan'!$F$7:$F$156+999*(1-ISNUMBER(SEARCH(","&'Project Plan'!$A$7:$A$156&",",","&SUBSTITUTE(G32," ","")&","))))) -> 5 | J32: =IF(AND(H32<=E32,I32>=E32),"ALIGNED","MISALIGNED") -> ALIGNED
A33: D-04 | B33: GRC platform | C33: Vanta / Drata / Secureframe | D33: GC-03 | E33: 4 | F33: =Overview!$B$4+7*(E33-1)+4 -> 46346 | G33: GC-09 | H33: =INDEX('Project Plan'!$H$7:$H$156,MATCH(D33,'Project Plan'!$A$7:$A$156,0)) -> 4 | I33: =SUMPRODUCT(MIN('Project Plan'!$F$7:$F$156+999*(1-ISNUMBER(SEARCH(","&'Project Plan'!$A$7:$A$156&",",","&SUBSTITUTE(G33," ","")&","))))) -> 6 | J33: =IF(AND(H33<=E33,I33>=E33),"ALIGNED","MISALIGNED") -> ALIGNED
A34: D-05 | B34: EKS node OS | C34: AL2023 managed nodes / Bottlerocket / EKS Auto Mode | D34: HD-05 | E34: 4 | F34: =Overview!$B$4+7*(E34-1)+4 -> 46346 | G34: HD-08, HD-13, HD-16A, HD-23, HD-26 | H34: =INDEX('Project Plan'!$H$7:$H$156,MATCH(D34,'Project Plan'!$A$7:$A$156,0)) -> 4 | I34: =SUMPRODUCT(MIN('Project Plan'!$F$7:$F$156+999*(1-ISNUMBER(SEARCH(","&'Project Plan'!$A$7:$A$156&",",","&SUBSTITUTE(G34," ","")&","))))) -> 5 | J34: =IF(AND(H34<=E34,I34>=E34),"ALIGNED","MISALIGNED") -> ALIGNED
A35: D-06 | B35: Customer identity strategy | C35: Stay on B2C to 2029 / migrate to External ID FY27 / other CIAM | D35: ID-14 | E35: 15 | F35: =Overview!$B$4+7*(E35-1)+4 -> 46423 | G35: PM-15 | H35: =INDEX('Project Plan'!$H$7:$H$156,MATCH(D35,'Project Plan'!$A$7:$A$156,0)) -> 15 | I35: =SUMPRODUCT(MIN('Project Plan'!$F$7:$F$156+999*(1-ISNUMBER(SEARCH(","&'Project Plan'!$A$7:$A$156&",",","&SUBSTITUTE(G35," ","")&","))))) -> 25 | J35: =IF(AND(H35<=E35,I35>=E35),"ALIGNED","MISALIGNED") -> ALIGNED
A36: D-07 | B36: On-chain monitoring vendor | C36: Hypernative / Hexagate / OZ Monitor self-hosted / combination | D36: BC-09 | E36: 6 | F36: =Overview!$B$4+7*(E36-1)+4 -> 46360 | G36: MR-13 | H36: =INDEX('Project Plan'!$H$7:$H$156,MATCH(D36,'Project Plan'!$A$7:$A$156,0)) -> 6 | I36: =SUMPRODUCT(MIN('Project Plan'!$F$7:$F$156+999*(1-ISNUMBER(SEARCH(","&'Project Plan'!$A$7:$A$156&",",","&SUBSTITUTE(G36," ","")&","))))) -> 7 | J36: =IF(AND(H36<=E36,I36>=E36),"ALIGNED","MISALIGNED") -> ALIGNED
A37: D-08 | B37: SOC 2 TSC scope and subservice treatment | C37: Security only / +Availability / +Confidentiality; carve-out vs inclusive | D37: GC-07 | E37: 7 | F37: =Overview!$B$4+7*(E37-1)+4 -> 46367 | G37: GC-05, GC-13 | H37: =INDEX('Project Plan'!$H$7:$H$156,MATCH(D37,'Project Plan'!$A$7:$A$156,0)) -> 7 | I37: =SUMPRODUCT(MIN('Project Plan'!$F$7:$F$156+999*(1-ISNUMBER(SEARCH(","&'Project Plan'!$A$7:$A$156&",",","&SUBSTITUTE(G37," ","")&","))))) -> 8 | J37: =IF(AND(H37<=E37,I37>=E37),"ALIGNED","MISALIGNED") -> ALIGNED
A38: D-09 | B38: Bug bounty platform and SEAL Safe Harbor | C38: Immunefi / other; adopt Safe Harbor yes/no | D38: BC-18 | E38: 24 | F38: =Overview!$B$4+7*(E38-1)+4 -> 46486 | G38: PM-16 | H38: =INDEX('Project Plan'!$H$7:$H$156,MATCH(D38,'Project Plan'!$A$7:$A$156,0)) -> 24 | I38: =SUMPRODUCT(MIN('Project Plan'!$F$7:$F$156+999*(1-ISNUMBER(SEARCH(","&'Project Plan'!$A$7:$A$156&",",","&SUBSTITUTE(G38," ","")&","))))) -> 26 | J38: =IF(AND(H38<=E38,I38>=E38),"ALIGNED","MISALIGNED") -> ALIGNED
A39: D-10 | B39: EKS 1.34 clusters and upgradePolicy | C39: Upgrade to 1.35 before 2 Dec / EXTENDED at $0.60 per cluster-hr | D39: HD-01 | E39: 2 | F39: =Overview!$B$4+7*(E39-1)+4 -> 46332 | G39: HD-02 | H39: =INDEX('Project Plan'!$H$7:$H$156,MATCH(D39,'Project Plan'!$A$7:$A$156,0)) -> 1 | I39: =SUMPRODUCT(MIN('Project Plan'!$F$7:$F$156+999*(1-ISNUMBER(SEARCH(","&'Project Plan'!$A$7:$A$156&",",","&SUBSTITUTE(G39," ","")&","))))) -> 2 | J39: =IF(AND(H39<=E39,I39>=E39),"ALIGNED","MISALIGNED") -> ALIGNED
A40: D-11 | B40: Admission policy engine and image-signature verifier | C40: ValidatingAdmissionPolicy / Kyverno; verifier for ECR signatures | D40: HD-08 | E40: 6 | F40: =Overview!$B$4+7*(E40-1)+4 -> 46360 | G40: HD-17, HD-18 | H40: =INDEX('Project Plan'!$H$7:$H$156,MATCH(D40,'Project Plan'!$A$7:$A$156,0)) -> 6 | I40: =SUMPRODUCT(MIN('Project Plan'!$F$7:$F$156+999*(1-ISNUMBER(SEARCH(","&'Project Plan'!$A$7:$A$156&",",","&SUBSTITUTE(G40," ","")&","))))) -> 11 | J40: =IF(AND(H40<=E40,I40>=E40),"ALIGNED","MISALIGNED") -> ALIGNED
A41: D-12 | B41: SOC 2 Type I first vs straight to Type II | C41: Type I as-of 21 Mar 2027 + gap-free Type II / Type II only | D41: GC-07 | E41: 7 | F41: =Overview!$B$4+7*(E41-1)+4 -> 46367 | G41: GC-15 | H41: =INDEX('Project Plan'!$H$7:$H$156,MATCH(D41,'Project Plan'!$A$7:$A$156,0)) -> 7 | I41: =SUMPRODUCT(MIN('Project Plan'!$F$7:$F$156+999*(1-ISNUMBER(SEARCH(","&'Project Plan'!$A$7:$A$156&",",","&SUBSTITUTE(G41," ","")&","))))) -> 22 | J41: =IF(AND(H41<=E41,I41>=E41),"ALIGNED","MISALIGNED") -> ALIGNED
... A46: D-16 | B46: AWS just-in-time elevation approach | C46: PIM for Groups via SCIM / alternative tool (verify maintenance) | D46: ID-04 | E46: 5 | F46: =Overview!$B$4+7*(E46-1)+4 -> 46353 | G46: ID-11, ID-09 | H46: =INDEX('Project Plan'!$H$7:$H$156,MATCH(D46,'Project Plan'!$A$7:$A$156,0)) -> 5 | I46: =SUMPRODUCT(MIN('Project Plan'!$F$7:$F$156+999*(1-ISNUMBER(SEARCH(","&'Project Plan'!$A$7:$A$156&",",","&SUBSTITUTE(G46," ","")&","))))) -> 9 | J46: =IF(AND(H46<=E46,I46>=E46),"ALIGNED","MISALIGNED") -> ALIGNED

Sheet Review Log
A1: Independent review log (v1 -> v2): four adversarial reviewers + lead re-verification
A2: Status 'Deferred' or 'UNVERIFIED' items carry a named validation task.
A4: ID | B4: Reviewer | C4: Task ID(s) | D4: Severity | E4: Finding | F4: Resolution in v2 | G4: Status
A5: RV-01 | B5: Cloud/OS & container | C5: MR-01 | D5: Critical | E5: GuardDuty Runtime Monitoring agents need SSM (HD-06 W2-6), SCP allowance for guardduty:SendSecurityTelemetry, ECS agent >=1.77.0; EKS on Fargate unsupported. | F5: Split: MR-01 agentless services W0-1; new MR-01B runtime agents W7-8 after HD-06 + CAB; SCP allowance added to HD-04; Fargate gap HD-25; Gate 1 criterion reworded. | G5: Fixed
A6: RV-02 | B6: Cloud/OS & container | C6: HD-06 | D6: High | E6: Default Host Management Configuration needs IMDSv2 and can't attach the Inspector CIS policy; existing instance profiles take precedence. | F6: Instance profiles as primary path; DHMC only where no profile; per-instance IMDSv2 conversion; extended to W2-W6. | G6: Fixed
A7: RV-03 | B7: Cloud/OS & container | C7: HD-16 | D7: Critical | E7: Node OS migration too late (AL2 EOS 30 Jun 2026); 4 version hops in 8 weeks; started in freeze; binding deadline is 1.32 end of extended support 23 Mar 2027 (W22), not 27 Mar. | F7: Split into HD-16A (node groups to AL2023/Bottlerocket at 1.32, W6-W8 before freeze) and HD-16B (hops to 1.36, W11-W18); new HD-24 upgrade-readiness matrix W2-W4; D-05 moved to W4. | G7: Fixed
A8: RV-04 | B8: Cloud/OS & container | C8: HD-02 / D-10 | D8: High | E8: No task executed the 1.34 decision; upgradePolicy (STANDARD auto-upgrades at end of standard support) not inventoried; extended-support cost not costed. | F8: HD-01 records upgradePolicy; D-10 due W2 (owner HD-01); HD-02 W2-W5 covers 1.31 and 1.34; cost into D-15/R20. | G8: Fixed
A9: RV-05 | B9: Cloud/OS & container | C9: HD-04 / HD-10 | D9: Medium | E9: IMDSv2 hop limit per workload type; VPC BPA exclusions; allowed-images audit mode; prod steps in freeze. | F9: Added to HD-04 activities; HD-10 prod from W11; freeze rule in Overview. | G9: Fixed
A10: RV-06 | B10: Cloud/OS & container | C10: HD-12 / HD-05 | D10: Medium | E10: Inspector CIS is x86_64-oriented; Bottlerocket excluded; alternate method undefined. | F10: Noted in HD-05/HD-12; new HD-26 Bottlerocket CIS evidence (method to verify). | G10: Fixed (method UNVERIFIED)
A11: RV-07 | B11: Cloud/OS & container | C11: MR-06 | D11: Medium | E11: Only some resource types back up directly to the air-gapped vault; Aurora backtrack is MySQL-only; no EKS backup design. | F11: MR-06 activities corrected; EKS backup approach added (verify AWS Backup EKS support). | G11: Fixed (EKS support UNVERIFIED)
A12: RV-08 | B12: Cloud/OS & container | C12: Cost | D12: Low | E12: Security Hub per-resource pricing decision needed before trial ends (~W4). | F12: New MR-23 + D-15 due W4. | G12: Fixed
A13: RV-09 | B13: Cloud/OS & container | C13: HD-18 | D13: Low | E13: ECS has no admission control for signatures. | F13: HD-18: CI/CD signature gate for ECS. | G13: Fixed
A14: RV-10 | B14: Cloud/OS & container | C14: HD-09 | D14: Low | E14: CIS v7.1.0 delta should precede control matrix. | F14: HD-09 moved to W6-7; GC-05 depends on it. | G14: Fixed
A15: RV-11 | B15: Cloud/OS & container | C15: Missing | D15: High | E15: Missing: immutable log archive, ECS-on-EC2 AL2 migration, EKS readiness matrix, Fargate gap, Bottlerocket CIS, Control Tower drift, root credential removal, DNS/registrar/CloudFront, Macie. | F15: Added HD-22, HD-23, HD-24, HD-25, HD-26, HD-27, HD-30; root removal in ID-01/ID-11; DNS/registrar in BC-25. | G15: Fixed
... A66: RV-62 | B66: Lead re-verification | C66: Deferred | D66: Low | E66: Items not verifiable from public primary sources: CrowdStrike AL2023/Bottlerocket support (login-gated), Hexagate/Tenderly Solana coverage, SOC 2 minimum Type II period (AICPA FAQ login-gated), FIPS 206 status, Bottlerocket CIS reporting method, AWS Backup EKS support. | F66: Kept as UNVERIFIED with written-confirmation or validation tasks (HD-05, BC-09, GC-07, HD-26, MR-06). | G66: Deferred - validation tasks assigned
A68: Summary
A69: Critical | B69: =COUNTIF(D5:D66,"Critical") -> 7 | D69: Cloud/OS & container | E69: =COUNTIF(B5:B66,D69) -> 11
A70: High | B70: =COUNTIF(D5:D66,"High") -> 26 | D70: Identity & monitoring | E70: =COUNTIF(B5:B66,D70) -> 16
A71: Medium | B71: =COUNTIF(D5:D66,"Medium") -> 22 | D71: Blockchain | E71: =COUNTIF(B5:B66,D71) -> 15
A72: Low | B72: =COUNTIF(D5:D66,"Low") -> 7 | D72: Governance/PMO | E72: =COUNTIF(B5:B66,D72) -> 16
D73: Lead re-verification | E73: =COUNTIF(B5:B66,D73) -> 4
A74: Not fully fixed | B74: =COUNTA(G5:G66)-COUNTIF(G5:G66,"Fixed")-COUNTIF(G5:G66,"Verified") -> 7

Sheet Sources
A1: Sources - primary sources checked 19 Oct 2026 (status: Verified / Partial / Secondary / Vendor claim / UNVERIFIED)
A4: # | B4: Topic | C4: Fact | D4: Status | E4: URL | F4: Checked
A5: 1 | B5: AWS - CIS | C5: Latest CIS AWS Foundations Benchmark v7.1.0 | D5: Verified | E5: https://www.cisecurity.org/benchmark/amazon_web_services | F5: 2026-10-19
A6: 2 | B6: AWS - CIS | C6: Security Hub CSPM automates CIS AWS Foundations v1.2.0, v1.4.0, v3.0.0, v5.0.0 | D6: Verified | E6: https://docs.aws.amazon.com/securityhub/latest/userguide/cis-aws-foundations-benchmark.html | F6: 2026-10-19
A7: 3 | B7: AWS - CIS | C7: CIS Amazon Linux 2023 v1.0.0; CIS Amazon Linux 2 v4.0.0 | D7: Verified | E7: https://www.cisecurity.org/benchmark/amazon_linux | F7: 2026-10-19
A8: 4 | B8: AWS - CIS | C8: CIS Kubernetes v2.1.0; CIS Amazon EKS v2.0.0; CIS EKS Auto Mode v1.0.0 | D8: Verified | E8: https://www.cisecurity.org/benchmark/kubernetes | F8: 2026-10-19
A9: 5 | B9: AWS - CIS | C9: CIS Bottlerocket v1.0.0 | D9: Verified | E9: https://www.cisecurity.org/benchmark/bottlerocket | F9: 2026-10-19
A10: 6 | B10: Frameworks | C10: CIS Controls v8.1 (Jun 2024) with governance function | D10: Verified | E10: https://www.cisecurity.org/controls | F10: 2026-10-19
A11: 7 | B11: AWS - lifecycle | C11: Amazon Linux 2 end of support 2026-06-30; AL2023 supported to Jun 2029 | D11: Verified | E11: https://aws.amazon.com/amazon-linux-2/faqs/ | F11: 2026-10-19
A12: 8 | B12: AWS - lifecycle | C12: EKS stopped publishing AL2 AMIs 2025-11-26; 1.32 is last version with AL2 AMIs | D12: Verified | E12: https://docs.aws.amazon.com/eks/latest/userguide/eks-ami-deprecation-faqs.html | F12: 2026-10-19
A13: 9 | B13: AWS - lifecycle | C13: EKS version calendar (1.31 ext. EOS 2026-11-26; 1.32 ext. EOS 2027-03-23; 1.34 std. EOS 2026-12-02; 1.35 std. EOS 2027-03-27); auto-upgrade behaviour; upgradePolicy | D13: Verified (lead re-check) | E13: https://docs.aws.amazon.com/eks/latest/userguide/kubernetes-versions.html | F13: 2026-10-19
A14: 10 | B14: AWS - lifecycle | C14: EKS pricing: standard $0.10, extended $0.60 per cluster-hour | D14: Verified | E14: https://aws.amazon.com/eks/pricing/ | F14: 2026-10-19
A15: 11 | B15: AWS - services | C15: New AWS Security Hub GA 2025-12-02 (correlation, exposure, OCSF) | D15: Verified | E15: https://aws.amazon.com/blogs/aws/aws-security-hub-now-generally-available-with-near-real-time-analytics-and-risk-prioritization/ | F15: 2026-10-19
A16: 12 | B16: AWS - services | C16: Security Hub CSPM posture checks (FSBP, CIS, PCI, NIST) | D16: Verified | E16: https://docs.aws.amazon.com/securityhub/latest/userguide/what-is-securityhub.html | F16: 2026-10-19
... A116: 112 | B116: GRC tooling | C116: Secureframe Entra ID integration | D116: Vendor | E116: https://support.secureframe.com/hc/en-us/articles/20710013602963-Microsoft-Entra-ID | F116: 2026-10-19
