Workbook

Sheet README
A1: Unified Blockchain Security Control Register
A2: Prepared 2026-10-20 · Blockchain Security Architecture (drafted with Claude) · Scope: exchanges/custodians, protocol/dApp/token teams, node/validator operators, enterprise baseline.
A4: What this is
A5: One register of 386 controls. The backbone is every normative BSSC requirement (NOS, TIS, KMS, SCS, GSP = 325 controls). 61 supplementary controls close gaps BSSC does not explicitly require, drawn from OWASP SC Top 10:2026, OWASP SCSVS, OWASP Web3 Top 15, SEAL Frameworks, CCSS v9.0, CIS Controls v8.1, DORA, MiCA and FATF.
A6: Every control is cross-referenced to all applicable frameworks (grey-blue header columns M–W). 'Applicable Frameworks' lists them in one cell for filtering.
A8: Columns
A9: Primary Source Framework / Ref ID: the framework the control was derived from. Reference Standard: citation text. Requirement Level: BSSC RFC 2119 keyword, or 'Recommended (supplementary)'.
A10: Overlap Flag / Reference (same convention as the Azure CIS register in this project): Duplicate = two source requirements ask the same party for the same thing – implement once, evidence both. Related = overlapping scope, or mirror requirements for different parties (e.g., TIS integrator check vs SCS issuer obligation). Each reference is tagged [Duplicate] or [Related]; the flag shows the strongest.
A11: Implementation Status, Control Owner, Notes (yellow) are for you to complete; Summary updates automatically.
A12: Example: UCR row for NOS req-limit-consensus-power → Status = Implemented, Owner = Head of Staking, Notes = 'Stake share 18% on Ethereum as of Q3'.
A14: Verification performed
A15: • BSSC requirement anchors re-checked against live specs (NOS 53, SCS 69, GSP 56); TIS/KMS heading-level.
... A23: • Source defects noted in BSSC specs: SCS version link points to gsp/v2.html; SCS references undefined #req-trigger-automated-response; NOS changelog uses #req-use-testnets; GSP anchor typo req-use-seecure-comms; KMS mixes FIPS 140-2/140-3.

Sheet Summary
A1: Unified Blockchain Control Register — Summary
A2: All figures are live formulas over the 'Control Register' tab.
A3: Controls by domain and priority
A4: Domain | B4: Critical | C4: High | D4: Medium | E4: Low | F4: Total | G4: Implemented | H4: % Implemented (excl. N/A & risk accepted)
A5: 01 Governance, Risk & Compliance | B5: =COUNTIFS('Control Register'!$C$2:$C$387,$A5,'Control Register'!$J$2:$J$387,"Critical") -> 2 | C5: =COUNTIFS('Control Register'!$C$2:$C$387,$A5,'Control Register'!$J$2:$J$387,"High") -> 15 | D5: =COUNTIFS('Control Register'!$C$2:$C$387,$A5,'Control Register'!$J$2:$J$387,"Medium") -> 7 | E5: =COUNTIFS('Control Register'!$C$2:$C$387,$A5,'Control Register'!$J$2:$J$387,"Low") -> 2 | F5: =SUM(B5:E5) -> 26 | G5: =COUNTIFS('Control Register'!$C$2:$C$387,$A5,'Control Register'!$AB$2:$AB$387,"Implemented") -> 0 | H5: =IF((F5-(COUNTIFS('Control Register'!$C$2:$C$387,$A5,'Control Register'!$AB$2:$AB$387,"Not applicable")+COUNTIFS('Control Register'!$C$2:$C$387,$A5,'Control Register'!$AB$2:$AB$387,"Risk accepted")))=0,0,G5/(F5-(COUNTIFS('Control Register'!$C$2:$C$387,$A5,'Control Register'!$AB$2:$AB$387,"Not applicable")+COUNTIFS('Control Register'!$C$2:$C$387,$A5,'Control Register'!$AB$2:$AB$387,"Risk accepted")))) -> 0
A6: 02 Key & Wallet Management | B6: =COUNTIFS('Control Register'!$C$2:$C$387,$A6,'Control Register'!$J$2:$J$387,"Critical") -> 32 | C6: =COUNTIFS('Control Register'!$C$2:$C$387,$A6,'Control Register'!$J$2:$J$387,"High") -> 32 | D6: =COUNTIFS('Control Register'!$C$2:$C$387,$A6,'Control Register'!$J$2:$J$387,"Medium") -> 11 | E6: =COUNTIFS('Control Register'!$C$2:$C$387,$A6,'Control Register'!$J$2:$J$387,"Low") -> 3 | F6: =SUM(B6:E6) -> 78 | G6: =COUNTIFS('Control Register'!$C$2:$C$387,$A6,'Control Register'!$AB$2:$AB$387,"Implemented") -> 0 | H6: =IF((F6-(COUNTIFS('Control Register'!$C$2:$C$387,$A6,'Control Register'!$AB$2:$AB$387,"Not applicable")+COUNTIFS('Control Register'!$C$2:$C$387,$A6,'Control Register'!$AB$2:$AB$387,"Risk accepted")))=0,0,G6/(F6-(COUNTIFS('Control Register'!$C$2:$C$387,$A6,'Control Register'!$AB$2:$AB$387,"Not applicable")+COUNTIFS('Control Register'!$C$2:$C$387,$A6,'Control Register'!$AB$2:$AB$387,"Risk accepted")))) -> 0
A7: 03 Smart Contract Development & Assurance | B7: =COUNTIFS('Control Register'!$C$2:$C$387,$A7,'Control Register'!$J$2:$J$387,"Critical") -> 10 | C7: =COUNTIFS('Control Register'!$C$2:$C$387,$A7,'Control Register'!$J$2:$J$387,"High") -> 23 | D7: =COUNTIFS('Control Register'!$C$2:$C$387,$A7,'Control Register'!$J$2:$J$387,"Medium") -> 21 | E7: =COUNTIFS('Control Register'!$C$2:$C$387,$A7,'Control Register'!$J$2:$J$387,"Low") -> 9 | F7: =SUM(B7:E7) -> 63 | G7: =COUNTIFS('Control Register'!$C$2:$C$387,$A7,'Control Register'!$AB$2:$AB$387,"Implemented") -> 0 | H7: =IF((F7-(COUNTIFS('Control Register'!$C$2:$C$387,$A7,'Control Register'!$AB$2:$AB$387,"Not applicable")+COUNTIFS('Control Register'!$C$2:$C$387,$A7,'Control Register'!$AB$2:$AB$387,"Risk accepted")))=0,0,G7/(F7-(COUNTIFS('Control Register'!$C$2:$C$387,$A7,'Control Register'!$AB$2:$AB$387,"Not applicable")+COUNTIFS('Control Register'!$C$2:$C$387,$A7,'Control Register'!$AB$2:$AB$387,"Risk accepted")))) -> 0
A8: 04 Token Integration & Listing | B8: =COUNTIFS('Control Register'!$C$2:$C$387,$A8,'Control Register'!$J$2:$J$387,"Critical") -> 5 | C8: =COUNTIFS('Control Register'!$C$2:$C$387,$A8,'Control Register'!$J$2:$J$387,"High") -> 20 | D8: =COUNTIFS('Control Register'!$C$2:$C$387,$A8,'Control Register'!$J$2:$J$387,"Medium") -> 18 | E8: =COUNTIFS('Control Register'!$C$2:$C$387,$A8,'Control Register'!$J$2:$J$387,"Low") -> 7 | F8: =SUM(B8:E8) -> 50 | G8: =COUNTIFS('Control Register'!$C$2:$C$387,$A8,'Control Register'!$AB$2:$AB$387,"Implemented") -> 0 | H8: =IF((F8-(COUNTIFS('Control Register'!$C$2:$C$387,$A8,'Control Register'!$AB$2:$AB$387,"Not applicable")+COUNTIFS('Control Register'!$C$2:$C$387,$A8,'Control Register'!$AB$2:$AB$387,"Risk accepted")))=0,0,G8/(F8-(COUNTIFS('Control Register'!$C$2:$C$387,$A8,'Control Register'!$AB$2:$AB$387,"Not applicable")+COUNTIFS('Control Register'!$C$2:$C$387,$A8,'Control Register'!$AB$2:$AB$387,"Risk accepted")))) -> 0
A9: 05 Node & Network Operations | B9: =COUNTIFS('Control Register'!$C$2:$C$387,$A9,'Control Register'!$J$2:$J$387,"Critical") -> 2 | C9: =COUNTIFS('Control Register'!$C$2:$C$387,$A9,'Control Register'!$J$2:$J$387,"High") -> 10 | D9: =COUNTIFS('Control Register'!$C$2:$C$387,$A9,'Control Register'!$J$2:$J$387,"Medium") -> 11 | E9: =COUNTIFS('Control Register'!$C$2:$C$387,$A9,'Control Register'!$J$2:$J$387,"Low") -> 2 | F9: =SUM(B9:E9) -> 25 | G9: =COUNTIFS('Control Register'!$C$2:$C$387,$A9,'Control Register'!$AB$2:$AB$387,"Implemented") -> 0 | H9: =IF((F9-(COUNTIFS('Control Register'!$C$2:$C$387,$A9,'Control Register'!$AB$2:$AB$387,"Not applicable")+COUNTIFS('Control Register'!$C$2:$C$387,$A9,'Control Register'!$AB$2:$AB$387,"Risk accepted")))=0,0,G9/(F9-(COUNTIFS('Control Register'!$C$2:$C$387,$A9,'Control Register'!$AB$2:$AB$387,"Not applicable")+COUNTIFS('Control Register'!$C$2:$C$387,$A9,'Control Register'!$AB$2:$AB$387,"Risk accepted")))) -> 0
A10: 06 Identity & Access Management | B10: =COUNTIFS('Control Register'!$C$2:$C$387,$A10,'Control Register'!$J$2:$J$387,"Critical") -> 3 | C10: =COUNTIFS('Control Register'!$C$2:$C$387,$A10,'Control Register'!$J$2:$J$387,"High") -> 8 | D10: =COUNTIFS('Control Register'!$C$2:$C$387,$A10,'Control Register'!$J$2:$J$387,"Medium") -> 1 | E10: =COUNTIFS('Control Register'!$C$2:$C$387,$A10,'Control Register'!$J$2:$J$387,"Low") -> 0 | F10: =SUM(B10:E10) -> 12 | G10: =COUNTIFS('Control Register'!$C$2:$C$387,$A10,'Control Register'!$AB$2:$AB$387,"Implemented") -> 0 | H10: =IF((F10-(COUNTIFS('Control Register'!$C$2:$C$387,$A10,'Control Register'!$AB$2:$AB$387,"Not applicable")+COUNTIFS('Control Register'!$C$2:$C$387,$A10,'Control Register'!$AB$2:$AB$387,"Risk accepted")))=0,0,G10/(F10-(COUNTIFS('Control Register'!$C$2:$C$387,$A10,'Control Register'!$AB$2:$AB$387,"Not applicable")+COUNTIFS('Control Register'!$C$2:$C$387,$A10,'Control Register'!$AB$2:$AB$387,"Risk accepted")))) -> 0
A11: 07 Logging, Monitoring & Detection | B11: =COUNTIFS('Control Register'!$C$2:$C$387,$A11,'Control Register'!$J$2:$J$387,"Critical") -> 4 | C11: =COUNTIFS('Control Register'!$C$2:$C$387,$A11,'Control Register'!$J$2:$J$387,"High") -> 11 | D11: =COUNTIFS('Control Register'!$C$2:$C$387,$A11,'Control Register'!$J$2:$J$387,"Medium") -> 3 | E11: =COUNTIFS('Control Register'!$C$2:$C$387,$A11,'Control Register'!$J$2:$J$387,"Low") -> 0 | F11: =SUM(B11:E11) -> 18 | G11: =COUNTIFS('Control Register'!$C$2:$C$387,$A11,'Control Register'!$AB$2:$AB$387,"Implemented") -> 0 | H11: =IF((F11-(COUNTIFS('Control Register'!$C$2:$C$387,$A11,'Control Register'!$AB$2:$AB$387,"Not applicable")+COUNTIFS('Control Register'!$C$2:$C$387,$A11,'Control Register'!$AB$2:$AB$387,"Risk accepted")))=0,0,G11/(F11-(COUNTIFS('Control Register'!$C$2:$C$387,$A11,'Control Register'!$AB$2:$AB$387,"Not applicable")+COUNTIFS('Control Register'!$C$2:$C$387,$A11,'Control Register'!$AB$2:$AB$387,"Risk accepted")))) -> 0
A12: 08 Incident Response & Resilience | B12: =COUNTIFS('Control Register'!$C$2:$C$387,$A12,'Control Register'!$J$2:$J$387,"Critical") -> 3 | C12: =COUNTIFS('Control Register'!$C$2:$C$387,$A12,'Control Register'!$J$2:$J$387,"High") -> 24 | D12: =COUNTIFS('Control Register'!$C$2:$C$387,$A12,'Control Register'!$J$2:$J$387,"Medium") -> 8 | E12: =COUNTIFS('Control Register'!$C$2:$C$387,$A12,'Control Register'!$J$2:$J$387,"Low") -> 0 | F12: =SUM(B12:E12) -> 35 | G12: =COUNTIFS('Control Register'!$C$2:$C$387,$A12,'Control Register'!$AB$2:$AB$387,"Implemented") -> 0 | H12: =IF((F12-(COUNTIFS('Control Register'!$C$2:$C$387,$A12,'Control Register'!$AB$2:$AB$387,"Not applicable")+COUNTIFS('Control Register'!$C$2:$C$387,$A12,'Control Register'!$AB$2:$AB$387,"Risk accepted")))=0,0,G12/(F12-(COUNTIFS('Control Register'!$C$2:$C$387,$A12,'Control Register'!$AB$2:$AB$387,"Not applicable")+COUNTIFS('Control Register'!$C$2:$C$387,$A12,'Control Register'!$AB$2:$AB$387,"Risk accepted")))) -> 0
A13: 09 Infrastructure & Endpoint Security | B13: =COUNTIFS('Control Register'!$C$2:$C$387,$A13,'Control Register'!$J$2:$J$387,"Critical") -> 2 | C13: =COUNTIFS('Control Register'!$C$2:$C$387,$A13,'Control Register'!$J$2:$J$387,"High") -> 10 | D13: =COUNTIFS('Control Register'!$C$2:$C$387,$A13,'Control Register'!$J$2:$J$387,"Medium") -> 4 | E13: =COUNTIFS('Control Register'!$C$2:$C$387,$A13,'Control Register'!$J$2:$J$387,"Low") -> 0 | F13: =SUM(B13:E13) -> 16 | G13: =COUNTIFS('Control Register'!$C$2:$C$387,$A13,'Control Register'!$AB$2:$AB$387,"Implemented") -> 0 | H13: =IF((F13-(COUNTIFS('Control Register'!$C$2:$C$387,$A13,'Control Register'!$AB$2:$AB$387,"Not applicable")+COUNTIFS('Control Register'!$C$2:$C$387,$A13,'Control Register'!$AB$2:$AB$387,"Risk accepted")))=0,0,G13/(F13-(COUNTIFS('Control Register'!$C$2:$C$387,$A13,'Control Register'!$AB$2:$AB$387,"Not applicable")+COUNTIFS('Control Register'!$C$2:$C$387,$A13,'Control Register'!$AB$2:$AB$387,"Risk accepted")))) -> 0
A14: 10 Supply Chain & Third Parties | B14: =COUNTIFS('Control Register'!$C$2:$C$387,$A14,'Control Register'!$J$2:$J$387,"Critical") -> 3 | C14: =COUNTIFS('Control Register'!$C$2:$C$387,$A14,'Control Register'!$J$2:$J$387,"High") -> 8 | D14: =COUNTIFS('Control Register'!$C$2:$C$387,$A14,'Control Register'!$J$2:$J$387,"Medium") -> 2 | E14: =COUNTIFS('Control Register'!$C$2:$C$387,$A14,'Control Register'!$J$2:$J$387,"Low") -> 0 | F14: =SUM(B14:E14) -> 13 | G14: =COUNTIFS('Control Register'!$C$2:$C$387,$A14,'Control Register'!$AB$2:$AB$387,"Implemented") -> 0 | H14: =IF((F14-(COUNTIFS('Control Register'!$C$2:$C$387,$A14,'Control Register'!$AB$2:$AB$387,"Not applicable")+COUNTIFS('Control Register'!$C$2:$C$387,$A14,'Control Register'!$AB$2:$AB$387,"Risk accepted")))=0,0,G14/(F14-(COUNTIFS('Control Register'!$C$2:$C$387,$A14,'Control Register'!$AB$2:$AB$387,"Not applicable")+COUNTIFS('Control Register'!$C$2:$C$387,$A14,'Control Register'!$AB$2:$AB$387,"Risk accepted")))) -> 0
A15: 11 Data Protection & Privacy | B15: =COUNTIFS('Control Register'!$C$2:$C$387,$A15,'Control Register'!$J$2:$J$387,"Critical") -> 0 | C15: =COUNTIFS('Control Register'!$C$2:$C$387,$A15,'Control Register'!$J$2:$J$387,"High") -> 5 | D15: =COUNTIFS('Control Register'!$C$2:$C$387,$A15,'Control Register'!$J$2:$J$387,"Medium") -> 7 | E15: =COUNTIFS('Control Register'!$C$2:$C$387,$A15,'Control Register'!$J$2:$J$387,"Low") -> 0 | F15: =SUM(B15:E15) -> 12 | G15: =COUNTIFS('Control Register'!$C$2:$C$387,$A15,'Control Register'!$AB$2:$AB$387,"Implemented") -> 0 | H15: =IF((F15-(COUNTIFS('Control Register'!$C$2:$C$387,$A15,'Control Register'!$AB$2:$AB$387,"Not applicable")+COUNTIFS('Control Register'!$C$2:$C$387,$A15,'Control Register'!$AB$2:$AB$387,"Risk accepted")))=0,0,G15/(F15-(COUNTIFS('Control Register'!$C$2:$C$387,$A15,'Control Register'!$AB$2:$AB$387,"Not applicable")+COUNTIFS('Control Register'!$C$2:$C$387,$A15,'Control Register'!$AB$2:$AB$387,"Risk accepted")))) -> 0
A16: 12 People & Physical Security | B16: =COUNTIFS('Control Register'!$C$2:$C$387,$A16,'Control Register'!$J$2:$J$387,"Critical") -> 3 | C16: =COUNTIFS('Control Register'!$C$2:$C$387,$A16,'Control Register'!$J$2:$J$387,"High") -> 4 | D16: =COUNTIFS('Control Register'!$C$2:$C$387,$A16,'Control Register'!$J$2:$J$387,"Medium") -> 2 | E16: =COUNTIFS('Control Register'!$C$2:$C$387,$A16,'Control Register'!$J$2:$J$387,"Low") -> 0 | F16: =SUM(B16:E16) -> 9 | G16: =COUNTIFS('Control Register'!$C$2:$C$387,$A16,'Control Register'!$AB$2:$AB$387,"Implemented") -> 0 | H16: =IF((F16-(COUNTIFS('Control Register'!$C$2:$C$387,$A16,'Control Register'!$AB$2:$AB$387,"Not applicable")+COUNTIFS('Control Register'!$C$2:$C$387,$A16,'Control Register'!$AB$2:$AB$387,"Risk accepted")))=0,0,G16/(F16-(COUNTIFS('Control Register'!$C$2:$C$387,$A16,'Control Register'!$AB$2:$AB$387,"Not applicable")+COUNTIFS('Control Register'!$C$2:$C$387,$A16,'Control Register'!$AB$2:$AB$387,"Risk accepted")))) -> 0
... A18: 14 Protocol Governance & Upgrades | B18: =COUNTIFS('Control Register'!$C$2:$C$387,$A18,'Control Register'!$J$2:$J$387,"Critical") -> 5 | C18: =COUNTIFS('Control Register'!$C$2:$C$387,$A18,'Control Register'!$J$2:$J$387,"High") -> 6 | D18: =COUNTIFS('Control Register'!$C$2:$C$387,$A18,'Control Register'!$J$2:$J$387,"Medium") -> 7 | E18: =COUNTIFS('Control Register'!$C$2:$C$387,$A18,'Control Register'!$J$2:$J$387,"Low") -> 4 | F18: =SUM(B18:E18) -> 22 | G18: =COUNTIFS('Control Register'!$C$2:$C$387,$A18,'Control Register'!$AB$2:$AB$387,"Implemented") -> 0 | H18: =IF((F18-(COUNTIFS('Control Register'!$C$2:$C$387,$A18,'Control Register'!$AB$2:$AB$387,"Not applicable")+COUNTIFS('Control Register'!$C$2:$C$387,$A18,'Control Register'!$AB$2:$AB$387,"Risk accepted")))=0,0,G18/(F18-(COUNTIFS('Control Register'!$C$2:$C$387,$A18,'Control Register'!$AB$2:$AB$387,"Not applicable")+COUNTIFS('Control Register'!$C$2:$C$387,$A18,'Control Register'!$AB$2:$AB$387,"Risk accepted")))) -> 0
A19: Total | B19: =SUM(B5:B18) -> 77 | C19: =SUM(C5:C18) -> 178 | D19: =SUM(D5:D18) -> 104 | E19: =SUM(E5:E18) -> 27 | F19: =SUM(F5:F18) -> 386 | G19: =SUM(G5:G18) -> 0 | H19: =IF((F19-COUNTIF('Control Register'!$AB$2:$AB$387,"Not applicable")-COUNTIF('Control Register'!$AB$2:$AB$387,"Risk accepted"))=0,0,G19/(F19-COUNTIF('Control Register'!$AB$2:$AB$387,"Not applicable")-COUNTIF('Control Register'!$AB$2:$AB$387,"Risk accepted"))) -> 0
A20: Check: total equals register row count | F20: =IF(F19=COUNTA('Control Register'!$B$2:$B$387),"OK","MISMATCH") -> OK
A22: Controls by primary source framework
A23: Primary Source Framework | B23: Controls
A24: BSSC NOS v2 | B24: =COUNTIF('Control Register'!$F$2:$F$387,$A24) -> 54
A25: BSSC TIS v1 | B25: =COUNTIF('Control Register'!$F$2:$F$387,$A25) -> 50
A26: BSSC KMS v1 | B26: =COUNTIF('Control Register'!$F$2:$F$387,$A26) -> 96
A27: BSSC SCS v1 | B27: =COUNTIF('Control Register'!$F$2:$F$387,$A27) -> 69
A28: BSSC GSP v2 | B28: =COUNTIF('Control Register'!$F$2:$F$387,$A28) -> 56
A29: OWASP SC Top 10:2026 | B29: =COUNTIF('Control Register'!$F$2:$F$387,$A29) -> 13
A30: OWASP SCSVS | B30: =COUNTIF('Control Register'!$F$2:$F$387,$A30) -> 8
A31: OWASP Web3 Top 15 | B31: =COUNTIF('Control Register'!$F$2:$F$387,$A31) -> 6
A32: SEAL Frameworks | B32: =COUNTIF('Control Register'!$F$2:$F$387,$A32) -> 22
A33: CCSS v9.0 | B33: =COUNTIF('Control Register'!$F$2:$F$387,$A33) -> 3
A34: CIS Controls v8.1 | B34: =COUNTIF('Control Register'!$F$2:$F$387,$A34) -> 4
A35: DORA (EU 2022/2554) | B35: =COUNTIF('Control Register'!$F$2:$F$387,$A35) -> 3
... A37: FATF Recommendations | B37: =COUNTIF('Control Register'!$F$2:$F$387,$A37) -> 1
A38: Total | B38: =SUM(B24:B37) -> 386
A40: Framework coverage (controls mapped to each item; 0 = gap)
A41: Framework | B41: Item | C41: Mapped controls | D41: Covered?
A42: OWASP SC Top 10:2026 | B42: SC01 | C42: =COUNTIF('Control Register'!$O$2:$O$387,"*SC01*") -> 13 | D42: =IF(C42>0,"Yes","GAP") -> Yes
A43: OWASP SC Top 10:2026 | B43: SC02 | C43: =COUNTIF('Control Register'!$O$2:$O$387,"*SC02*") -> 12 | D43: =IF(C43>0,"Yes","GAP") -> Yes
A44: OWASP SC Top 10:2026 | B44: SC03 | C44: =COUNTIF('Control Register'!$O$2:$O$387,"*SC03*") -> 6 | D44: =IF(C44>0,"Yes","GAP") -> Yes
A45: OWASP SC Top 10:2026 | B45: SC04 | C45: =COUNTIF('Control Register'!$O$2:$O$387,"*SC04*") -> 2 | D45: =IF(C45>0,"Yes","GAP") -> Yes
A46: OWASP SC Top 10:2026 | B46: SC05 | C46: =COUNTIF('Control Register'!$O$2:$O$387,"*SC05*") -> 3 | D46: =IF(C46>0,"Yes","GAP") -> Yes
A47: OWASP SC Top 10:2026 | B47: SC06 | C47: =COUNTIF('Control Register'!$O$2:$O$387,"*SC06*") -> 1 | D47: =IF(C47>0,"Yes","GAP") -> Yes
A48: OWASP SC Top 10:2026 | B48: SC07 | C48: =COUNTIF('Control Register'!$O$2:$O$387,"*SC07*") -> 5 | D48: =IF(C48>0,"Yes","GAP") -> Yes
A49: OWASP SC Top 10:2026 | B49: SC08 | C49: =COUNTIF('Control Register'!$O$2:$O$387,"*SC08*") -> 4 | D49: =IF(C49>0,"Yes","GAP") -> Yes
A50: OWASP SC Top 10:2026 | B50: SC09 | C50: =COUNTIF('Control Register'!$O$2:$O$387,"*SC09*") -> 5 | D50: =IF(C50>0,"Yes","GAP") -> Yes
A51: OWASP SC Top 10:2026 | B51: SC10 | C51: =COUNTIF('Control Register'!$O$2:$O$387,"*SC10*") -> 21 | D51: =IF(C51>0,"Yes","GAP") -> Yes
A52: OWASP Web3 Top 15 | B52: WA01 | C52: =COUNTIF('Control Register'!$P$2:$P$387,"*WA01*") -> 17 | D52: =IF(C52>0,"Yes","GAP") -> Yes
A53: OWASP Web3 Top 15 | B53: WA02 | C53: =COUNTIF('Control Register'!$P$2:$P$387,"*WA02*") -> 11 | D53: =IF(C53>0,"Yes","GAP") -> Yes
A54: OWASP Web3 Top 15 | B54: WA03 | C54: =COUNTIF('Control Register'!$P$2:$P$387,"*WA03*") -> 55 | D54: =IF(C54>0,"Yes","GAP") -> Yes
A55: OWASP Web3 Top 15 | B55: WA04 | C55: =COUNTIF('Control Register'!$P$2:$P$387,"*WA04*") -> 2 | D55: =IF(C55>0,"Yes","GAP") -> Yes
A56: OWASP Web3 Top 15 | B56: WA05 | C56: =COUNTIF('Control Register'!$P$2:$P$387,"*WA05*") -> 2 | D56: =IF(C56>0,"Yes","GAP") -> Yes
A57: OWASP Web3 Top 15 | B57: WA06 | C57: =COUNTIF('Control Register'!$P$2:$P$387,"*WA06*") -> 5 | D57: =IF(C57>0,"Yes","GAP") -> Yes
A58: OWASP Web3 Top 15 | B58: WA07 | C58: =COUNTIF('Control Register'!$P$2:$P$387,"*WA07*") -> 8 | D58: =IF(C58>0,"Yes","GAP") -> Yes
A59: OWASP Web3 Top 15 | B59: WA08 | C59: =COUNTIF('Control Register'!$P$2:$P$387,"*WA08*") -> 5 | D59: =IF(C59>0,"Yes","GAP") -> Yes
A60: OWASP Web3 Top 15 | B60: WA09 | C60: =COUNTIF('Control Register'!$P$2:$P$387,"*WA09*") -> 1 | D60: =IF(C60>0,"Yes","GAP") -> Yes
A61: OWASP Web3 Top 15 | B61: WA10 | C61: =COUNTIF('Control Register'!$P$2:$P$387,"*WA10*") -> 13 | D61: =IF(C61>0,"Yes","GAP") -> Yes
A62: OWASP Web3 Top 15 | B62: WA11 | C62: =COUNTIF('Control Register'!$P$2:$P$387,"*WA11*") -> 3 | D62: =IF(C62>0,"Yes","GAP") -> Yes
A63: OWASP Web3 Top 15 | B63: WA12 | C63: =COUNTIF('Control Register'!$P$2:$P$387,"*WA12*") -> 13 | D63: =IF(C63>0,"Yes","GAP") -> Yes
A64: OWASP Web3 Top 15 | B64: WA13 | C64: =COUNTIF('Control Register'!$P$2:$P$387,"*WA13*") -> 3 | D64: =IF(C64>0,"Yes","GAP") -> Yes
A65: OWASP Web3 Top 15 | B65: WA14 | C65: =COUNTIF('Control Register'!$P$2:$P$387,"*WA14*") -> 5 | D65: =IF(C65>0,"Yes","GAP") -> Yes
A66: OWASP Web3 Top 15 | B66: WA15 | C66: =COUNTIF('Control Register'!$P$2:$P$387,"*WA15*") -> 2 | D66: =IF(C66>0,"Yes","GAP") -> Yes
A67: OWASP SCSVS | B67: SCSVS-ARCH | C67: =COUNTIF('Control Register'!$N$2:$N$387,"*SCSVS-ARCH*") -> 25 | D67: =IF(C67>0,"Yes","GAP") -> Yes
A68: OWASP SCSVS | B68: SCSVS-CODE | C68: =COUNTIF('Control Register'!$N$2:$N$387,"*SCSVS-CODE*") -> 38 | D68: =IF(C68>0,"Yes","GAP") -> Yes
A69: OWASP SCSVS | B69: SCSVS-GOV | C69: =COUNTIF('Control Register'!$N$2:$N$387,"*SCSVS-GOV*") -> 7 | D69: =IF(C69>0,"Yes","GAP") -> Yes
A70: OWASP SCSVS | B70: SCSVS-AUTH | C70: =COUNTIF('Control Register'!$N$2:$N$387,"*SCSVS-AUTH*") -> 15 | D70: =IF(C70>0,"Yes","GAP") -> Yes
A71: OWASP SCSVS | B71: SCSVS-COMM | C71: =COUNTIF('Control Register'!$N$2:$N$387,"*SCSVS-COMM*") -> 11 | D71: =IF(C71>0,"Yes","GAP") -> Yes
A72: OWASP SCSVS | B72: SCSVS-CRYPTO | C72: =COUNTIF('Control Register'!$N$2:$N$387,"*SCSVS-CRYPTO*") -> 7 | D72: =IF(C72>0,"Yes","GAP") -> Yes
A73: OWASP SCSVS | B73: SCSVS-ORACLE | C73: =COUNTIF('Control Register'!$N$2:$N$387,"*SCSVS-ORACLE*") -> 6 | D73: =IF(C73>0,"Yes","GAP") -> Yes
A74: OWASP SCSVS | B74: SCSVS-BLOCK | C74: =COUNTIF('Control Register'!$N$2:$N$387,"*SCSVS-BLOCK*") -> 1 | D74: =IF(C74>0,"Yes","GAP") -> Yes
A75: OWASP SCSVS | B75: SCSVS-BRIDGE | C75: =COUNTIF('Control Register'!$N$2:$N$387,"*SCSVS-BRIDGE*") -> 1 | D75: =IF(C75>0,"Yes","GAP") -> Yes
A76: OWASP SCSVS | B76: SCSVS-DEFI | C76: =COUNTIF('Control Register'!$N$2:$N$387,"*SCSVS-DEFI*") -> 2 | D76: =IF(C76>0,"Yes","GAP") -> Yes
A77: OWASP SCSVS | B77: SCSVS-COMP | C77: =COUNTIF('Control Register'!$N$2:$N$387,"*SCSVS-COMP*") -> 13 | D77: =IF(C77>0,"Yes","GAP") -> Yes
A78: SEAL Frameworks | B78: AI Security | C78: =COUNTIF('Control Register'!$R$2:$R$387,"*AI Security*") -> 2 | D78: =IF(C78>0,"Yes","GAP") -> Yes
A79: SEAL Frameworks | B79: Awareness | C79: =COUNTIF('Control Register'!$R$2:$R$387,"*Awareness*") -> 5 | D79: =IF(C79>0,"Yes","GAP") -> Yes
A80: SEAL Frameworks | B80: Community Management | C80: =COUNTIF('Control Register'!$R$2:$R$387,"*Community Management*") -> 2 | D80: =IF(C80>0,"Yes","GAP") -> Yes
A81: SEAL Frameworks | B81: DevSecOps | C81: =COUNTIF('Control Register'!$R$2:$R$387,"*DevSecOps*") -> 25 | D81: =IF(C81>0,"Yes","GAP") -> Yes
A82: SEAL Frameworks | B82: Insider Threats (DPRK IT Workers) | C82: =COUNTIF('Control Register'!$R$2:$R$387,"*Insider Threats (DPRK IT Workers)*") -> 2 | D82: =IF(C82>0,"Yes","GAP") -> Yes
A83: SEAL Frameworks | B83: ENS | C83: =COUNTIF('Control Register'!$R$2:$R$387,"*ENS*") -> 1 | D83: =IF(C83>0,"Yes","GAP") -> Yes
A84: SEAL Frameworks | B84: External Security Reviews | C84: =COUNTIF('Control Register'!$R$2:$R$387,"*External Security Reviews*") -> 10 | D84: =IF(C84>0,"Yes","GAP") -> Yes
A85: SEAL Frameworks | B85: Incident Management | C85: =COUNTIF('Control Register'!$R$2:$R$387,"*Incident Management*") -> 32 | D85: =IF(C85>0,"Yes","GAP") -> Yes
A86: SEAL Frameworks | B86: Infrastructure | C86: =COUNTIF('Control Register'!$R$2:$R$387,"*Infrastructure*") -> 26 | D86: =IF(C86>0,"Yes","GAP") -> Yes
A87: SEAL Frameworks | B87: Monitoring | C87: =COUNTIF('Control Register'!$R$2:$R$387,"*Monitoring*") -> 34 | D87: =IF(C87>0,"Yes","GAP") -> Yes
A88: SEAL Frameworks | B88: Multisig for Protocols | C88: =COUNTIF('Control Register'!$R$2:$R$387,"*Multisig for Protocols*") -> 25 | D88: =IF(C88>0,"Yes","GAP") -> Yes
A89: SEAL Frameworks | B89: OpSec | C89: =COUNTIF('Control Register'!$R$2:$R$387,"*OpSec*") -> 23 | D89: =IF(C89>0,"Yes","GAP") -> Yes
A90: SEAL Frameworks | B90: Physical Security | C90: =COUNTIF('Control Register'!$R$2:$R$387,"*Physical Security*") -> 3 | D90: =IF(C90>0,"Yes","GAP") -> Yes
A91: SEAL Frameworks | B91: Privacy | C91: =COUNTIF('Control Register'!$R$2:$R$387,"*Privacy*") -> 8 | D91: =IF(C91>0,"Yes","GAP") -> Yes
A92: SEAL Frameworks | B92: Safe Harbor | C92: =COUNTIF('Control Register'!$R$2:$R$387,"*Safe Harbor*") -> 6 | D92: =IF(C92>0,"Yes","GAP") -> Yes
A93: SEAL Frameworks | B93: Security Testing | C93: =COUNTIF('Control Register'!$R$2:$R$387,"*Security Testing*") -> 21 | D93: =IF(C93>0,"Yes","GAP") -> Yes
A94: SEAL Frameworks | B94: Supply Chain | C94: =COUNTIF('Control Register'!$R$2:$R$387,"*Supply Chain*") -> 14 | D94: =IF(C94>0,"Yes","GAP") -> Yes
A95: SEAL Frameworks | B95: Treasury Operations | C95: =COUNTIF('Control Register'!$R$2:$R$387,"*Treasury Operations*") -> 11 | D95: =IF(C95>0,"Yes","GAP") -> Yes
A96: SEAL Frameworks | B96: Wallet Security | C96: =COUNTIF('Control Register'!$R$2:$R$387,"*Wallet Security*") -> 73 | D96: =IF(C96>0,"Yes","GAP") -> Yes
A97: SEAL Frameworks | B97: SEAL Certifications | C97: =COUNTIF('Control Register'!$R$2:$R$387,"*SEAL Certifications*") -> 1 | D97: =IF(C97>0,"Yes","GAP") -> Yes
A98: CCSS v9.0 | B98: 1.01 Key Material Generation | C98: =COUNTIF('Control Register'!$S$2:$S$387,"*1.01 Key Material Generation*") -> 9 | D98: =IF(C98>0,"Yes","GAP") -> Yes
A99: CCSS v9.0 | B99: 1.02 Wallet Creation | C99: =COUNTIF('Control Register'!$S$2:$S$387,"*1.02 Wallet Creation*") -> 6 | D99: =IF(C99>0,"Yes","GAP") -> Yes
A100: CCSS v9.0 | B100: 1.03 Key Storage | C100: =COUNTIF('Control Register'!$S$2:$S$387,"*1.03 Key Storage*") -> 24 | D100: =IF(C100>0,"Yes","GAP") -> Yes
A101: CCSS v9.0 | B101: 1.04 Key Material Access | C101: =COUNTIF('Control Register'!$S$2:$S$387,"*1.04 Key Material Access*") -> 16 | D101: =IF(C101>0,"Yes","GAP") -> Yes
A102: CCSS v9.0 | B102: 1.05 Key Usage | C102: =COUNTIF('Control Register'!$S$2:$S$387,"*1.05 Key Usage*") -> 19 | D102: =IF(C102>0,"Yes","GAP") -> Yes
A103: CCSS v9.0 | B103: 1.06 Key Compromise Protocol | C103: =COUNTIF('Control Register'!$S$2:$S$387,"*1.06 Key Compromise Protocol*") -> 12 | D103: =IF(C103>0,"Yes","GAP") -> Yes
A104: CCSS v9.0 | B104: 2.01 Security Audits | C104: =COUNTIF('Control Register'!$S$2:$S$387,"*2.01 Security Audits*") -> 6 | D104: =IF(C104>0,"Yes","GAP") -> Yes
...

Sheet Control Register
A1: # | B1: Control ID | C1: Domain | D1: Area | E1: Recommended Control | F1: Primary Source Framework | G1: Primary Source Ref ID | H1: Reference Standard | I1: Requirement Level | J1: Priority | K1: Applies To | L1: Applicable Frameworks | M1: BSSC (ID · req) | N1: OWASP SCSVS | O1: OWASP SC Top 10:2026 | P1: OWASP Web3 Top 15 | Q1: EthTrust | R1: SEAL Frameworks | S1: CCSS v9.0 | T1: CIS Controls v8.1 | U1: NIST CSF 2.0 | V1: ISO/IEC 27001:2022 | W1: Regulatory | X1: Overlap Flag | Y1: Overlap Reference | Z1: Verification Method / Evidence | AA1: Source Link | AB1: Implementation Status | AC1: Control Owner | AD1: Notes
A2: 1 | B2: UCR-001 | C2: 01 Governance, Risk & Compliance | D2: Baseline security program | E2: Implement the BSSC General Security & Privacy Guidelines (or ISO 27001 / SOC 2 equivalent) as the baseline security program for node operations. | F2: BSSC NOS v2 | G2: req-implement-basic-security | H2: BSSC NOS v2 — 0. Basic Security | I2: MUST | J2: High | K2: Node/validator operator; Exchange/Custodian running nodes | L2: BSSC NOS; SEAL; CIS v8.1; NIST CSF 2.0; ISO 27001:2022; DORA | M2: NOS-002 · req-implement-basic-security | R2: OpSec | T2: CIS 1–18 (IG1 baseline) | U2: GV.PO-01 | V2: A.5.1 | W2: DORA Art. 5–6 | X2: Related | Y2: UCR-320 [Related] (CIS Controls v8.1 CIS 4.1) | Z2: Review GSP gap assessment or ISO/SOC 2 report scope covering node infrastructure. | AA2: Open source | AB2: Not started
A3: 2 | B3: UCR-002 | C3: 01 Governance, Risk & Compliance | D3: Risk assessment | E3: Run a documented protocol selection and risk analysis (consensus, economics, client maturity, slashing exposure) before onboarding any new network. | F3: BSSC NOS v2 | G3: req-document-protocol-analysis | H3: BSSC NOS v2 — 1. Protocol Onboarding | I3: MUST | J3: High | K3: Node/validator operator; Exchange/Custodian running nodes | L3: BSSC NOS; SEAL; NIST CSF 2.0; ISO 27001:2022; DORA | M3: NOS-003 · req-document-protocol-analysis | R3: OpSec | U3: ID.RA-01; GV.RM-03 | V3: A.5.8 | W3: DORA Art. 6, 8 | X3: None | Z3: Inspect onboarding risk assessments and approval sign-off for each supported protocol. | AA3: Open source | AB3: Not started
A4: 3 | B4: UCR-003 | C4: 01 Governance, Risk & Compliance | D4: Risk assessment | E4: Continuously monitor protocol forks, upgrades and governance changes (release feeds, EIPs/BIPs, dev calls) and refresh the protocol risk assessment on each material change. | F4: BSSC NOS v2 | G4: req-monitor-protocol-changes | H4: BSSC NOS v2 — 1. Protocol Onboarding | I4: MUST | J4: High | K4: Node/validator operator; Exchange/Custodian running nodes | L4: BSSC NOS; SEAL; NIST CSF 2.0; ISO 27001:2022; DORA | M4: NOS-004 · req-monitor-protocol-changes | R4: OpSec | U4: ID.RA-03; ID.RA-07 | V4: A.5.7 | W4: DORA Art. 6, 8 | X4: None | Z4: Show change-tracking log, subscriptions, and risk-assessment revision history. | AA4: Open source | AB4: Not started
A5: 4 | B5: UCR-004 | C5: 01 Governance, Risk & Compliance | D5: Compliance | E5: Screen counterparties and addresses against applicable AML/sanctions blacklists (e.g., OFAC SDN) where required; document jurisdictional obligations. | F5: BSSC NOS v2 | G5: req-follow-relevant-regulation | H5: BSSC NOS v2 — 1. Protocol Onboarding | I5: MUST | J5: Critical | K5: Node/validator operator; Exchange/Custodian running nodes | L5: BSSC NOS; NIST CSF 2.0; ISO 27001:2022; FATF | M5: NOS-011 · req-follow-relevant-regulation | U5: GV.OC-03 | V5: A.5.31 | W5: FATF R.6/R.7 (sanctions), R.15; EU TFR 2023/1113; EU AMLR 2024/1624 | X5: Related | Y5: UCR-018 [Related] (BSSC GSP v2 req-monitor-regulation) | Z5: Test screening tooling against known sanctioned addresses; review compliance register. | AA5: Open source | AB5: Not started
A6: 5 | B6: UCR-005 | C6: 01 Governance, Risk & Compliance | D6: Transparency | E6: Disclose scope and terms of insurance covering slashing, downtime and compromise, or state clearly that none exists. | F6: BSSC NOS v2 | G6: req-document-insurance | H6: BSSC NOS v2 — 5. Transparency | I6: MUST | J6: Medium | K6: Node/validator operator; Exchange/Custodian running nodes | L6: BSSC NOS; NIST CSF 2.0 | M6: NOS-050 · req-document-insurance | U6: GV.OC-02 | X6: None | Z6: Review published insurance disclosure. | AA6: Open source | AB6: Not started
A7: 6 | B7: UCR-006 | C7: 01 Governance, Risk & Compliance | D7: Transparency | E7: Document exit triggers, notification timelines, stored-transaction handling, unbonding/withdrawal penalties and delay conditions. | F7: BSSC NOS v2 | G7: req-document-exit-procedures | H7: BSSC NOS v2 — 5. Transparency | I7: MUST | J7: Medium | K7: Node/validator operator; Exchange/Custodian running nodes | L7: BSSC NOS; NIST CSF 2.0; ISO 27001:2022 | M7: NOS-052 · req-document-exit-procedures | U7: GV.OC-02 | V7: A.5.37 | X7: None | Z7: Review client-facing exit documentation. | AA7: Open source | AB7: Not started
A8: 7 | B8: UCR-007 | C8: 01 Governance, Risk & Compliance | D8: Transparency | E8: Use only industry-standard encrypted communication methods with clients and partners. | F8: BSSC NOS v2 | G8: req-communicate-securely | H8: BSSC NOS v2 — 5. Transparency | I8: MUST | J8: High | K8: Node/validator operator; Exchange/Custodian running nodes | L8: BSSC NOS; SEAL; CIS v8.1; NIST CSF 2.0; ISO 27001:2022 | M8: NOS-053 · req-communicate-securely | R8: OpSec | T8: CIS 3.10 | U8: PR.DS-02 | V8: A.5.14 | X8: Related | Y8: UCR-314 [Related] (BSSC GSP v2 req-use-seecure-comms) | Z8: Review approved communications channels list. | AA8: Open source | AB8: Not started
A9: 8 | B9: UCR-008 | C9: 01 Governance, Risk & Compliance | D9: Threat modelling | E9: Maintain a threat model covering online and offline key components. | F9: BSSC KMS v1 | G9: KMS-GEN-15 | H9: BSSC KMS v1 — §5 General Requirements | I9: SHOULD | J9: High | K9: All key holders (Custodian/Exchange, Node operator, Protocol/admin keys) | L9: BSSC KMS; SEAL; CIS v8.1; NIST CSF 2.0; ISO 27001:2022 | M9: KMS-015 · KMS-GEN-15 | R9: OpSec | T9: CIS 16.14 | U9: ID.RA-03 | V9: A.5.7; A.8.27 | X9: None | Z9: Review threat model currency. | AA9: Open source | AB9: Not started
A10: 9 | B10: UCR-009 | C10: 01 Governance, Risk & Compliance | D10: Threat modelling | E10: Ensure the threat model identifies threats and vulnerabilities. | F10: BSSC KMS v1 | G10: KMS-GEN-16 | H10: BSSC KMS v1 — §5 General Requirements | I10: MUST | J10: High | K10: All key holders (Custodian/Exchange, Node operator, Protocol/admin keys) | L10: BSSC KMS; SEAL; CIS v8.1; NIST CSF 2.0; ISO 27001:2022 | M10: KMS-016 · KMS-GEN-16 | R10: OpSec | T10: CIS 16.14 | U10: ID.RA-03 | V10: A.8.27 | X10: None | Z10: Threat model content review. | AA10: Open source | AB10: Not started
A11: 10 | B11: UCR-010 | C11: 01 Governance, Risk & Compliance | D11: Threat modelling | E11: Ensure the threat model recommends controls and tracks implementation status. | F11: BSSC KMS v1 | G11: KMS-GEN-17 | H11: BSSC KMS v1 — §5 General Requirements | I11: MUST | J11: Medium | K11: All key holders (Custodian/Exchange, Node operator, Protocol/admin keys) | L11: BSSC KMS; SEAL; CIS v8.1; NIST CSF 2.0; ISO 27001:2022 | M11: KMS-017 · KMS-GEN-17 | R11: OpSec | T11: CIS 16.14 | U11: ID.RA-06 | V11: A.8.27 | X11: None | Z11: Trace threats to control status. | AA11: Open source | AB11: Not started
A12: 11 | B12: UCR-011 | C12: 01 Governance, Risk & Compliance | D12: Threat modelling | E12: Periodically test threats and controls via audits and penetration tests. | F12: BSSC KMS v1 | G12: KMS-GEN-18 | H12: BSSC KMS v1 — §5 General Requirements | I12: SHOULD | J12: High | K12: All key holders (Custodian/Exchange, Node operator, Protocol/admin keys) | L12: BSSC KMS; SEAL; CCSS v9.0; CIS v8.1; NIST CSF 2.0; ISO 27001:2022 | M12: KMS-018 · KMS-GEN-18 | R12: Security Testing | S12: 2.01 Security Audits | T12: CIS 18.1 | U12: ID.IM-02 | V12: A.8.8 | X12: Related | Y12: UCR-317 [Related] (BSSC GSP v2 req-test-penetration) | Z12: Review pentest/audit reports. | AA12: Open source | AB12: Not started
A13: 12 | B13: UCR-012 | C13: 01 Governance, Risk & Compliance | D13: Risk assessment & monitoring | E13: Document a risk assessment at least annually. | F13: BSSC SCS v1 | G13: req-assess-risk-regularly | H13: BSSC SCS v1 — 4. Operations | I13: MUST | J13: High | K13: Protocol/dApp/token developer; Exchange/Custodian (own contracts) | L13: BSSC SCS; SEAL; NIST CSF 2.0; ISO 27001:2022; DORA | M13: SCS-048 · req-assess-risk-regularly | R13: OpSec | U13: ID.RA-01 | V13: Cl. 8.2; A.5.7 | W13: DORA Art. 6, 8 | X13: Duplicate | Y13: UCR-020 [Duplicate] (BSSC GSP v2 req-assess-risks) | Z13: Latest annual risk assessment. | AA13: Open source | AB13: Not started
A14: 13 | B14: UCR-013 | C14: 01 Governance, Risk & Compliance | D14: Security knowledge | E14: Document how new security information (exploit post-mortems, advisories) is integrated. | F14: BSSC SCS v1 | G14: req-update-security-process | H14: BSSC SCS v1 — 4. Operations | I14: MUST | J14: Medium | K14: Protocol/dApp/token developer; Exchange/Custodian (own contracts) | L14: BSSC SCS; SEAL; NIST CSF 2.0; ISO 27001:2022 | M14: SCS-052 · req-update-security-process | R14: Awareness | U14: ID.IM-01 | V14: A.5.7 | X14: None | Z14: Process doc and examples. | AA14: Open source | AB14: Not started
A15: 14 | B15: UCR-014 | C15: 01 Governance, Risk & Compliance | D15: Risk management | E15: Include blockchain-specific risks (key loss, smart contract, chain, bridge) in enterprise risk management. | F15: BSSC GSP v2 | G15: req-treat-blockchain-risk | H15: BSSC GSP v2 — 1. Govern | I15: SHOULD | J15: High | K15: All blockchain participants | L15: BSSC GSP; SEAL; NIST CSF 2.0; ISO 27001:2022; DORA | M15: GSP-001 · req-treat-blockchain-risk | R15: OpSec | U15: GV.RM-01; GV.RM-03 | V15: Cl. 6.1; A.5.1 | W15: DORA Art. 5–6 | X15: None | Z15: ERM register shows blockchain risk category. | AA15: Open source | AB15: Not started
A16: 15 | B16: UCR-015 | C16: 01 Governance, Risk & Compliance | D16: Risk management | E16: Maintain a risk governance framework and risk register reviewed with stakeholders. | F16: BSSC GSP v2 | G16: req-risk-register | H16: BSSC GSP v2 — 1. Govern | I16: SHOULD | J16: High | K16: All blockchain participants | L16: BSSC GSP; SEAL; NIST CSF 2.0; ISO 27001:2022; DORA | M16: GSP-002 · req-risk-register | R16: OpSec | U16: GV.RM-01; ID.RA-06 | V16: Cl. 6.1.2; Cl. 8.2 | W16: DORA Art. 5–6 | X16: None | Z16: Register and review minutes. | AA16: Open source | AB16: Not started
A17: 16 | B17: UCR-016 | C17: 01 Governance, Risk & Compliance | D17: Governance resources | E17: Assign dedicated resources and owners for security governance and compliance. | F17: BSSC GSP v2 | G17: req-assign-governance | H17: BSSC GSP v2 — 1. Govern | I17: SHOULD | J17: Medium | K17: All blockchain participants | L17: BSSC GSP; SEAL; NIST CSF 2.0; ISO 27001:2022; DORA | M17: GSP-003 · req-assign-governance | R17: OpSec | U17: GV.RR-03 | V17: Cl. 5.3; A.5.2 | W17: DORA Art. 5 | X17: None | Z17: Org chart / RACI. | AA17: Open source | AB17: Not started
A18: 17 | B18: UCR-017 | C18: 01 Governance, Risk & Compliance | D18: Public compliance | E18: Publish a trust centre with compliance documentation and privacy policy. | F18: BSSC GSP v2 | G18: req-publish-trust-info | H18: BSSC GSP v2 — 1. Govern | I18: SHOULD | J18: Low | K18: All blockchain participants | L18: BSSC GSP; NIST CSF 2.0; ISO 27001:2022 | M18: GSP-005 · req-publish-trust-info | U18: GV.OC-02 | V18: A.5.34 | X18: None | Z18: Trust centre review. | AA18: Open source | AB18: Not started
A19: 18 | B19: UCR-018 | C19: 01 Governance, Risk & Compliance | D19: Regulatory monitoring | E19: Track and adapt to evolving regulation (MiCA, Travel Rule, local VASP rules). | F19: BSSC GSP v2 | G19: req-monitor-regulation | H19: BSSC GSP v2 — 1. Govern | I19: SHOULD | J19: High | K19: All blockchain participants | L19: BSSC GSP; NIST CSF 2.0; ISO 27001:2022; DORA; MiCA; FATF | M19: GSP-006 · req-monitor-regulation | U19: GV.OC-03 | V19: A.5.31 | W19: MiCA; DORA; FATF | X19: Related | Y19: UCR-004 [Related] (BSSC NOS v2 req-follow-relevant-regulation) | Z19: Regulatory watch log. | AA19: Open source | AB19: Not started
A20: 19 | B20: UCR-019 | C20: 01 Governance, Risk & Compliance | D20: Crypto standards | E20: Track cryptographic standards incl. post-quantum guidance in risk management. | F20: BSSC GSP v2 | G20: req-monitor-crypto | H20: BSSC GSP v2 — 1. Govern | I20: SHOULD | J20: Medium | K20: All blockchain participants | L20: BSSC GSP; NIST CSF 2.0; ISO 27001:2022 | M20: GSP-008 · req-monitor-crypto | U20: ID.RA-03 | V20: A.8.24 | X20: Related | Y20: UCR-221 [Related] (BSSC NOS v2 req-evaluate-protocol-pqc-plan); UCR-126 [Related] (BSSC SCS v1 req-assess-cryptography-risk) | Z20: Crypto watch entries in risk register. | AA20: Open source | AB20: Not started
A21: 20 | B21: UCR-020 | C21: 01 Governance, Risk & Compliance | D21: Risk assessment | E21: Conduct regular blockchain-specific risk assessments. | F21: BSSC GSP v2 | G21: req-assess-risks | H21: BSSC GSP v2 — 2. Identify | I21: SHOULD | J21: High | K21: All blockchain participants | L21: BSSC GSP; SEAL; NIST CSF 2.0; ISO 27001:2022; DORA | M21: GSP-009 · req-assess-risks | R21: OpSec | U21: ID.RA-01 | V21: Cl. 8.2 | W21: DORA Art. 6, 8 | X21: Duplicate | Y21: UCR-012 [Duplicate] (BSSC SCS v1 req-assess-risk-regularly) | Z21: Assessment reports. | AA21: Open source | AB21: Not started
A22: 21 | B22: UCR-021 | C22: 01 Governance, Risk & Compliance | D22: Customer funds | E22: Document risks to customer funds and keep accessible. | F22: BSSC GSP v2 | G22: req-document-funds-risks | H22: BSSC GSP v2 — 2. Identify | I22: SHOULD | J22: Critical | K22: Custodian/Exchange; Protocol holding user funds | L22: BSSC GSP; SEAL; CCSS v9.0; NIST CSF 2.0; ISO 27001:2022; MiCA | M22: GSP-010 · req-document-funds-risks | R22: Treasury Operations | S22: 2.03 Proof of Reserve | U22: ID.RA-04 | V22: Cl. 6.1.2 | W22: MiCA Art. 70 | X22: Related | Y22: UCR-025 [Related] (CCSS v9.0 2.03 Proof of Reserve); UCR-104 [Related] (MiCA (EU 2023/1114) Art. 70; 75) | Z22: Customer-funds risk document. | AA22: Open source | AB22: Not started
A23: 22 | B23: UCR-022 | C23: 01 Governance, Risk & Compliance | D23: Ecosystem risk | E23: Assess ecosystem/external risks (bridges, L1 health, counterparties, stablecoin depegs). | F23: BSSC GSP v2 | G23: req-assess-ecosystem-risk | H23: BSSC GSP v2 — 2. Identify | I23: SHOULD | J23: High | K23: All blockchain participants | L23: BSSC GSP; NIST CSF 2.0; ISO 27001:2022 | M23: GSP-011 · req-assess-ecosystem-risk | U23: ID.RA-03; GV.SC-07 | V23: A.5.7 | X23: Related | Y23: UCR-160 [Related] (OWASP SC Top 10:2026 SC03) | Z23: Ecosystem risk assessment. | AA23: Open source | AB23: Not started
A24: 23 | B24: UCR-023 | C24: 01 Governance, Risk & Compliance | D24: Cryptographic security | E24: Maintain a cryptographic inventory and migration plan for timely transitions incl. post-quantum. | F24: BSSC GSP v2 | G24: req-crypto-agility | H24: BSSC GSP v2 — 3. Protect | I24: SHOULD | J24: Medium | K24: All blockchain participants | L24: BSSC GSP; NIST CSF 2.0; ISO 27001:2022 | M24: GSP-037 · req-crypto-agility | U24: ID.AM-08; ID.IM-04 | V24: A.8.24 | X24: Related | Y24: UCR-220 [Related] (BSSC NOS v2 req-document-protocol-crypto); UCR-124 [Related] (BSSC SCS v1 req-document-cryptography) | Z24: Crypto inventory and plan. | AA24: Open source | AB24: Not started
A25: 24 | B25: UCR-024 | C25: 01 Governance, Risk & Compliance | D25: Independent security certification | E25: Pursue an independent certification (e.g., SEAL certification, CCSS audit, SOC 2/ISO 27001) appropriate to the business line. | F25: SEAL Frameworks | G25: SEAL Certifications | H25: SEAL Frameworks — SEAL Certifications | I25: Recommended (supplementary) | J25: Low | K25: All blockchain participants | L25: SEAL; CCSS v9.0; NIST CSF 2.0; ISO 27001:2022 | R25: SEAL Certifications | S25: 2.01 Security Audits | U25: GV.OV-01 | V25: A.5.35 | X25: None | Z25: Certificate/report. | AA25: Open source | AB25: Not started
A26: 25 | B26: UCR-025 | C26: 01 Governance, Risk & Compliance | D26: Proof of reserve | E26: Perform periodic, independently attested proof-of-reserve (assets ≥ liabilities) and publish results. | F26: CCSS v9.0 | G26: 2.03 Proof of Reserve | H26: CCSS v9.0 — 2.03 Proof of Reserve | I26: Recommended (supplementary) | J26: High | K26: Custodian/Exchange | L26: OWASP Web3 Top 15; SEAL; CCSS v9.0; NIST CSF 2.0; ISO 27001:2022; MiCA | P26: WA07 | R26: Treasury Operations | S26: 2.03 Proof of Reserve | U26: GV.OC-02 | V26: A.5.35 | W26: MiCA Art. 70 | X26: Related | Y26: UCR-021 [Related] (BSSC GSP v2 req-document-funds-risks) | Z26: Latest PoR attestation. | AA26: Open source | AB26: Not started
A27: 26 | B27: UCR-026 | C27: 01 Governance, Risk & Compliance | D27: Travel Rule | E27: Collect and transmit originator/beneficiary information for qualifying virtual-asset transfers and screen counterparties (VASP due diligence). | F27: FATF Recommendations | G27: R.15; R.16 | H27: FATF Recommendations — R.15; R.16 | I27: Recommended (supplementary) | J27: High | K27: Custodian/Exchange | L27: NIST CSF 2.0; ISO 27001:2022; FATF | U27: GV.OC-03 | V27: A.5.31 | W27: FATF R.15/R.16; EU TFR 2023/1113 | X27: None | Z27: Travel-rule solution logs; sample transfers. | AA27: Open source | AB27: Not started
A28: 27 | B28: UCR-027 | C28: 02 Key & Wallet Management | D28: Key security | E28: Manage all node, validator, withdrawal and signing keys under the BSSC Key Management Standard (or a documented equivalent); maintain a KMS conformance mapping. | F28: BSSC NOS v2 | G28: req-manage-key-security | H28: BSSC NOS v2 — 0. Basic Security | I28: MUST | J28: Critical | K28: Node/validator operator; Exchange/Custodian running nodes | L28: BSSC NOS; OWASP Web3 Top 15; SEAL; CCSS v9.0; CIS v8.1; NIST CSF 2.0; ISO 27001:2022 | M28: NOS-001 · req-manage-key-security | P28: WA03 | R28: Wallet Security | S28: 1.01–1.06 (Section 1, key lifecycle) | T28: CIS 3.11 | U28: PR.AA-01; PR.DS-01 | V28: A.8.24 | X28: Duplicate | Y28: UCR-094 [Duplicate] (BSSC GSP v2 req-protect-keys) | Z28: Review KMS conformance matrix; sample key lifecycle records; interview key custodians. | AA28: Open source | AB28: Not started
A29: 28 | B29: UCR-028 | C29: 02 Key & Wallet Management | D29: Access control | E29: Use remote signers/HSM-backed signing so key material is not on network-connected nodes; isolate the signer network. | F29: BSSC NOS v2 | G29: req-use-remote-signers | H29: BSSC NOS v2 — 4. Security and Access Control | I29: SHOULD | J29: Critical | K29: Node/validator operator; Exchange/Custodian running nodes | L29: BSSC NOS; OWASP Web3 Top 15; SEAL; CCSS v9.0; CIS v8.1; NIST CSF 2.0; ISO 27001:2022 | M29: NOS-037 · req-use-remote-signers | P29: WA03 | R29: Wallet Security | S29: 1.03 Key Storage; 1.05 Key Usage | T29: CIS 3.11; CIS 12.2 | U29: PR.AA-05; PR.DS-01 | V29: A.8.24; A.8.22 | X29: Related | Y29: UCR-322 [Related] (CIS Controls v8.1 CIS 12.2; 13.4) | Z29: Verify no keystores on beacon/validator hosts; review signer network segmentation. | AA29: Open source | AB29: Not started
A30: 29 | B30: UCR-029 | C30: 02 Key & Wallet Management | D30: Access control | E30: Where remote signers are unsupported, apply compensating key protections (encrypted keystores, TEEs, host hardening, strict access). | F30: BSSC NOS v2 | G30: req-remote-signer-alternatives | H30: BSSC NOS v2 — 4. Security and Access Control | I30: MUST | J30: Critical | K30: Node/validator operator; Exchange/Custodian running nodes | L30: BSSC NOS; OWASP Web3 Top 15; SEAL; CCSS v9.0; CIS v8.1; NIST CSF 2.0; ISO 27001:2022 | M30: NOS-038 · req-remote-signer-alternatives | P30: WA03 | R30: Wallet Security | S30: 1.03 Key Storage | T30: CIS 3.11 | U30: PR.DS-01; PR.PS-01 | V30: A.8.24 | X30: None | Z30: Review compensating controls and risk acceptance for each protocol lacking remote signing. | AA30: Open source | AB30: Not started
A31: 30 | B31: UCR-030 | C31: 02 Key & Wallet Management | D31: Transparency | E31: Deliver pre-signed exit transactions to clients only through cryptographically secure, confidential channels. | F31: BSSC NOS v2 | G31: req-deliver-exit-transactions-securely | H31: BSSC NOS v2 — 5. Transparency | I31: MUST | J31: Critical | K31: Node/validator operator; Exchange/Custodian running nodes | L31: BSSC NOS; SEAL; CCSS v9.0; CIS v8.1; NIST CSF 2.0; ISO 27001:2022 | M31: NOS-051 · req-deliver-exit-transactions-securely | R31: Wallet Security | S31: 1.05 Key Usage | T31: CIS 3.10 | U31: PR.DS-02 | V31: A.5.14 | X31: None | Z31: Inspect delivery mechanism (encrypted, authenticated); sample delivery logs. | AA31: Open source | AB31: Not started
A32: 31 | B32: UCR-031 | C32: 02 Key & Wallet Management | D32: Change management | E32: Enforce a formal change management process for every key management component (HSMs, MPC nodes, policy engines, signing services). | F32: BSSC KMS v1 | G32: KMS-GEN-01 | H32: BSSC KMS v1 — §5 General Requirements | I32: MUST | J32: High | K32: All key holders (Custodian/Exchange, Node operator, Protocol/admin keys) | L32: BSSC KMS; OWASP Web3 Top 15; SEAL; CCSS v9.0; CIS v8.1; NIST CSF 2.0; ISO 27001:2022; DORA | M32: KMS-001 · KMS-GEN-01 | P32: WA12 | R32: DevSecOps | S32: 1.04 Key Material Access | T32: CIS 4.1 | U32: PR.PS-01; ID.RA-07 | V32: A.8.32 | W32: DORA Art. 9(4)(e) | X32: None | Z32: Sample changes: ticket, approval, test evidence. | AA32: Open source | AB32: Not started
A33: 32 | B33: UCR-032 | C33: 02 Key & Wallet Management | D33: Change management | E33: Keep an audit trail of every change naming proposer and approver(s). | F33: BSSC KMS v1 | G33: KMS-GEN-02 | H33: BSSC KMS v1 — §5 General Requirements | I33: MUST | J33: High | K33: All key holders (Custodian/Exchange, Node operator, Protocol/admin keys) | L33: BSSC KMS; OWASP Web3 Top 15; SEAL; CCSS v9.0; CIS v8.1; NIST CSF 2.0; ISO 27001:2022; DORA | M33: KMS-002 · KMS-GEN-02 | P33: WA12 | R33: DevSecOps | S33: 2.04 Audit Logs | T33: CIS 4.1 | U33: PR.PS-04 | V33: A.8.32; A.8.15 | W33: DORA Art. 9(4)(e) | X33: None | Z33: Inspect change records for proposer/approver identity. | AA33: Open source | AB33: Not started
A34: 33 | B34: UCR-033 | C34: 02 Key & Wallet Management | D34: Change management | E34: Require at least one proposer and one distinct approver for every change (four-eyes). | F34: BSSC KMS v1 | G34: KMS-GEN-03 | H34: BSSC KMS v1 — §5 General Requirements | I34: MUST | J34: Critical | K34: All key holders (Custodian/Exchange, Node operator, Protocol/admin keys) | L34: BSSC KMS; OWASP Web3 Top 15; SEAL; CCSS v9.0; CIS v8.1; NIST CSF 2.0; ISO 27001:2022; DORA | M34: KMS-003 · KMS-GEN-03 | P34: WA12 | R34: DevSecOps | S34: 1.04 Key Material Access | T34: CIS 4.1 | U34: PR.AA-05 | V34: A.5.3 | W34: DORA Art. 9(4)(e) | X34: None | Z34: Verify tooling blocks self-approval. | AA34: Open source | AB34: Not started
A35: 34 | B35: UCR-034 | C35: 02 Key & Wallet Management | D35: Separation of duties | E35: Technically enforce that no single individual can cause key misuse or destruction (quorum, MPC thresholds, policy engines). | F35: BSSC KMS v1 | G35: KMS-GEN-04 | H35: BSSC KMS v1 — §5 General Requirements | I35: SHOULD | J35: Critical | K35: All key holders (Custodian/Exchange, Node operator, Protocol/admin keys) | L35: BSSC KMS; OWASP Web3 Top 15; SEAL; CCSS v9.0; CIS v8.1; NIST CSF 2.0; ISO 27001:2022 | M35: KMS-004 · KMS-GEN-04 | P35: WA12 | R35: Multisig for Protocols | S35: 1.05 Key Usage; 1.04 Key Material Access | T35: CIS 6.8 | U35: PR.AA-05 | V35: A.5.3 | X35: None | Z35: Attempt single-actor critical action in test; review threshold configs. | AA35: Open source | AB35: Not started
A36: 35 | B36: UCR-035 | C36: 02 Key & Wallet Management | D36: Change management | E36: Test all changes in a non-production environment before activation. | F36: BSSC KMS v1 | G36: KMS-GEN-05 | H36: BSSC KMS v1 — §5 General Requirements | I36: MUST | J36: High | K36: All key holders (Custodian/Exchange, Node operator, Protocol/admin keys) | L36: BSSC KMS; OWASP Web3 Top 15; SEAL; CIS v8.1; NIST CSF 2.0; ISO 27001:2022; DORA | M36: KMS-005 · KMS-GEN-05 | P36: WA12 | R36: DevSecOps | T36: CIS 4.1 | U36: PR.PS-06 | V36: A.8.31; A.8.32 | W36: DORA Art. 9(4)(e) | X36: None | Z36: Trace changes to test evidence. | AA36: Open source | AB36: Not started
A37: 36 | B37: UCR-036 | C37: 02 Key & Wallet Management | D37: Procedures | E37: Document non-digital (ceremony, physical) processes as transparent, repeatable procedures. | F37: BSSC KMS v1 | G37: KMS-GEN-09 | H37: BSSC KMS v1 — §5 General Requirements | I37: MUST | J37: Medium | K37: All key holders (Custodian/Exchange, Node operator, Protocol/admin keys) | L37: BSSC KMS; SEAL; CCSS v9.0; NIST CSF 2.0; ISO 27001:2022 | M37: KMS-009 · KMS-GEN-09 | R37: Treasury Operations | S37: 1.01 Key Material Generation | U37: GV.PO-01 | V37: A.5.37 | X37: None | Z37: Review ceremony scripts. | AA37: Open source | AB37: Not started
A38: 37 | B38: UCR-037 | C38: 02 Key & Wallet Management | D38: Compromise handling | E38: Immediately remove suspected/known compromised keys from active use. | F38: BSSC KMS v1 | G38: KMS-GEN-24 | H38: BSSC KMS v1 — §5 General Requirements | I38: MUST | J38: Critical | K38: All key holders (Custodian/Exchange, Node operator, Protocol/admin keys) | L38: BSSC KMS; OWASP Web3 Top 15; SEAL; CCSS v9.0; CIS v8.1; NIST CSF 2.0; ISO 27001:2022 | M38: KMS-024 · KMS-GEN-24 | P38: WA03 | R38: Incident Management | S38: 1.06 Key Compromise Protocol | T38: CIS 17.4 | U38: RS.MI-01 | V38: A.5.26 | X38: None | Z38: Review compromise procedure; drill evidence. | AA38: Open source | AB38: Not started
A39: 38 | B39: UCR-038 | C39: 02 Key & Wallet Management | D39: Compromise handling | E39: Promptly retire suspected/known compromised keys (sweep funds, revoke roles). | F39: BSSC KMS v1 | G39: KMS-GEN-25 | H39: BSSC KMS v1 — §5 General Requirements | I39: MUST | J39: Critical | K39: All key holders (Custodian/Exchange, Node operator, Protocol/admin keys) | L39: BSSC KMS; OWASP Web3 Top 15; SEAL; CCSS v9.0; CIS v8.1; NIST CSF 2.0; ISO 27001:2022 | M39: KMS-025 · KMS-GEN-25 | P39: WA03 | R39: Incident Management | S39: 1.06 Key Compromise Protocol | T39: CIS 17.4 | U39: RS.MI-02 | V39: A.5.26 | X39: None | Z39: Review sweep/rotation runbook. | AA39: Open source | AB39: Not started
A40: 39 | B40: UCR-039 | C40: 02 Key & Wallet Management | D40: Compromise handling | E40: Promptly retire keys at increased risk of compromise. | F40: BSSC KMS v1 | G40: KMS-GEN-26 | H40: BSSC KMS v1 — §5 General Requirements | I40: SHOULD | J40: High | K40: All key holders (Custodian/Exchange, Node operator, Protocol/admin keys) | L40: BSSC KMS; OWASP Web3 Top 15; SEAL; CCSS v9.0; CIS v8.1; NIST CSF 2.0; ISO 27001:2022 | M40: KMS-026 · KMS-GEN-26 | P40: WA03 | R40: Incident Management | S40: 1.06 Key Compromise Protocol | T40: CIS 17.4 | U40: RS.MI-02 | V40: A.8.24 | X40: None | Z40: Review risk-triggered retirements. | AA40: Open source | AB40: Not started
A41: 40 | B41: UCR-040 | C41: 02 Key & Wallet Management | D41: Backup & recovery | E41: Implement and regularly test a key backup and recovery strategy. | F41: BSSC KMS v1 | G41: KMS-GEN-27 | H41: BSSC KMS v1 — §5 General Requirements | I41: SHOULD | J41: Critical | K41: All key holders (Custodian/Exchange, Node operator, Protocol/admin keys) | L41: BSSC KMS; SEAL; CCSS v9.0; CIS v8.1; NIST CSF 2.0; ISO 27001:2022 | M41: KMS-027 · KMS-GEN-27 | R41: Wallet Security | S41: 1.03 Key Storage | T41: CIS 11.1; CIS 11.3 | U41: PR.DS-11; RC.RP-03 | V41: A.8.13 | X41: Related | Y41: UCR-304 [Related] (BSSC GSP v2 req-test-recovery-plans); UCR-101 [Related] (SEAL Frameworks Multisig for Protocols) | Z41: Witness recovery test from backup. | AA41: Open source | AB41: Not started
A42: 41 | B42: UCR-041 | C42: 02 Key & Wallet Management | D42: Backup & recovery | E42: Document backup and recovery procedures. | F42: BSSC KMS v1 | G42: KMS-GEN-28 | H42: BSSC KMS v1 — §5 General Requirements | I42: MUST | J42: High | K42: All key holders (Custodian/Exchange, Node operator, Protocol/admin keys) | L42: BSSC KMS; SEAL; CCSS v9.0; CIS v8.1; NIST CSF 2.0; ISO 27001:2022 | M42: KMS-028 · KMS-GEN-28 | R42: Wallet Security | S42: 1.03 Key Storage | T42: CIS 11.1; CIS 11.3 | U42: PR.DS-11 | V42: A.8.13 | X42: None | Z42: Review procedures. | AA42: Open source | AB42: Not started
A43: 42 | B43: UCR-042 | C43: 02 Key & Wallet Management | D43: Backup & recovery | E43: Keep backup/recovery systems separate from primary systems. | F43: BSSC KMS v1 | G43: KMS-GEN-29 | H43: BSSC KMS v1 — §5 General Requirements | I43: MUST | J43: High | K43: All key holders (Custodian/Exchange, Node operator, Protocol/admin keys) | L43: BSSC KMS; SEAL; CCSS v9.0; CIS v8.1; NIST CSF 2.0; ISO 27001:2022 | M43: KMS-029 · KMS-GEN-29 | R43: Wallet Security | S43: 1.03 Key Storage | T43: CIS 11.1; CIS 11.3 | U43: PR.DS-11 | V43: A.8.13 | X43: None | Z43: Architecture review. | AA43: Open source | AB43: Not started
A44: 43 | B44: UCR-043 | C44: 02 Key & Wallet Management | D44: Backup & recovery | E44: Protect backups to the same security standard as primary systems (encryption, access, physical). | F44: BSSC KMS v1 | G44: KMS-GEN-30 | H44: BSSC KMS v1 — §5 General Requirements | I44: MUST | J44: Critical | K44: All key holders (Custodian/Exchange, Node operator, Protocol/admin keys) | L44: BSSC KMS; SEAL; CCSS v9.0; CIS v8.1; NIST CSF 2.0; ISO 27001:2022 | M44: KMS-030 · KMS-GEN-30 | R44: Wallet Security | S44: 1.03 Key Storage | T44: CIS 11.1; CIS 11.3 | U44: PR.DS-11 | V44: A.8.13 | X44: None | Z44: Inspect backup storage controls. | AA44: Open source | AB44: Not started
A45: 44 | B45: UCR-044 | C45: 02 Key & Wallet Management | D45: Backup & recovery | E45: Use 3-2-1 style backups with geographically separate, access-controlled locations. | F45: BSSC KMS v1 | G45: KMS-GEN-31 | H45: BSSC KMS v1 — §5 General Requirements | I45: SHOULD | J45: High | K45: All key holders (Custodian/Exchange, Node operator, Protocol/admin keys) | L45: BSSC KMS; SEAL; CCSS v9.0; CIS v8.1; NIST CSF 2.0; ISO 27001:2022 | M45: KMS-031 · KMS-GEN-31 | R45: Wallet Security | S45: 1.03 Key Storage | T45: CIS 11.1; CIS 11.3 | U45: PR.DS-11 | V45: A.8.13; A.7.8 | X45: None | Z45: Review backup location inventory. | AA45: Open source | AB45: Not started
A46: 45 | B46: UCR-045 | C46: 02 Key & Wallet Management | D46: Separation of duties | E46: Ensure keys controlling Critical Actions cannot be accessed unilaterally by one person. | F46: BSSC KMS v1 | G46: KMS-GEN-44 | H46: BSSC KMS v1 — §5 General Requirements | I46: SHOULD | J46: Critical | K46: All key holders (Custodian/Exchange, Node operator, Protocol/admin keys) | L46: BSSC KMS; OWASP Web3 Top 15; SEAL; CCSS v9.0; CIS v8.1; NIST CSF 2.0; ISO 27001:2022 | M46: KMS-044 · KMS-GEN-44 | P46: WA12 | R46: Multisig for Protocols | S46: 1.05 Key Usage | T46: CIS 6.8 | U46: PR.AA-05 | V46: A.5.3 | X46: Related | Y46: UCR-356 [Related] (SEAL Frameworks Physical Security) | Z46: Review M-of-N / MPC policies. | AA46: Open source | AB46: Not started
A47: 46 | B47: UCR-046 | C47: 02 Key & Wallet Management | D47: Key material | E47: Protect Private Key Material (shares, seeds) to the same standard as full private keys. | F47: BSSC KMS v1 | G47: KMS-GEN-45 | H47: BSSC KMS v1 — §5 General Requirements | I47: SHOULD | J47: Critical | K47: All key holders (Custodian/Exchange, Node operator, Protocol/admin keys) | L47: BSSC KMS; OWASP Web3 Top 15; SEAL; CCSS v9.0; CIS v8.1; NIST CSF 2.0; ISO 27001:2022 | M47: KMS-045 · KMS-GEN-45 | P47: WA03 | R47: Wallet Security | S47: 1.03 Key Storage | T47: CIS 3.11 | U47: PR.DS-01 | V47: A.8.24 | X47: None | Z47: Inspect share storage controls. | AA47: Open source | AB47: Not started
A48: 47 | B48: UCR-047 | C48: 02 Key & Wallet Management | D48: Generation ceremony | E48: Conduct key generation ceremonies (automated, manual or mixed) with future key users and auditors present as appropriate. | F48: BSSC KMS v1 | G48: KMS-KG-01 | H48: BSSC KMS v1 — §6 Key Generation | I48: MAY | J48: Low | K48: All key holders (Custodian/Exchange, Node operator, Protocol/admin keys) | L48: BSSC KMS; OWASP Web3 Top 15; SEAL; CCSS v9.0; NIST CSF 2.0; ISO 27001:2022 | M48: KMS-046 · KMS-KG-01 | P48: WA03 | R48: Wallet Security | S48: 1.01 Key Material Generation; 1.02 Wallet Creation | U48: PR.AA-01 | V48: A.8.24 | X48: None | Z48: Review ceremony attendance records. | AA48: Open source | AB48: Not started
A49: 48 | B49: UCR-048 | C49: 02 Key & Wallet Management | D49: Secure generation | E49: Generate keys only in secure environments (HSM, air-gapped, attested enclave). | F49: BSSC KMS v1 | G49: KMS-KG-02 | H49: BSSC KMS v1 — §6 Key Generation | I49: MUST | J49: Critical | K49: All key holders (Custodian/Exchange, Node operator, Protocol/admin keys) | L49: BSSC KMS; OWASP Web3 Top 15; SEAL; CCSS v9.0; NIST CSF 2.0; ISO 27001:2022 | M49: KMS-047 · KMS-KG-02 | P49: WA03 | R49: Wallet Security | S49: 1.01 Key Material Generation | U49: PR.DS-01 | V49: A.8.24 | X49: None | Z49: Ceremony evidence; environment attestation. | AA49: Open source | AB49: Not started
A50: 49 | B50: UCR-049 | C50: 02 Key & Wallet Management | D50: Secure generation | E50: Use secure algorithms, appropriate key sizes and strong RNGs. | F50: BSSC KMS v1 | G50: KMS-KG-03 | H50: BSSC KMS v1 — §6 Key Generation | I50: MUST | J50: Critical | K50: All key holders (Custodian/Exchange, Node operator, Protocol/admin keys) | L50: BSSC KMS; OWASP Web3 Top 15; SEAL; CCSS v9.0; NIST CSF 2.0; ISO 27001:2022 | M50: KMS-048 · KMS-KG-03 | P50: WA03 | R50: Wallet Security | S50: 1.01 Key Material Generation | U50: PR.DS-01 | V50: A.8.24 | X50: None | Z50: Crypto config review. | AA50: Open source | AB50: Not started
A51: 50 | B51: UCR-050 | C51: 02 Key & Wallet Management | D51: Entropy | E51: Ensure randomness sources provide sufficient entropy (outputs indistinguishable from random). | F51: BSSC KMS v1 | G51: KMS-KG-04 | H51: BSSC KMS v1 — §6 Key Generation | I51: MUST | J51: Critical | K51: All key holders (Custodian/Exchange, Node operator, Protocol/admin keys) | L51: BSSC KMS; OWASP Web3 Top 15; SEAL; CCSS v9.0; NIST CSF 2.0; ISO 27001:2022 | M51: KMS-049 · KMS-KG-04 | P51: WA03 | R51: Wallet Security | S51: 1.01 Key Material Generation | U51: PR.DS-01 | V51: A.8.24 | X51: None | Z51: RNG validation (e.g., NIST SP 800-90B evidence). | AA51: Open source | AB51: Not started
A52: 51 | B52: UCR-051 | C52: 02 Key & Wallet Management | D52: Entropy | E52: Use hardware RNGs as entropy sources. | F52: BSSC KMS v1 | G52: KMS-KG-05 | H52: BSSC KMS v1 — §6 Key Generation | I52: SHOULD | J52: High | K52: All key holders (Custodian/Exchange, Node operator, Protocol/admin keys) | L52: BSSC KMS; OWASP Web3 Top 15; SEAL; CCSS v9.0; NIST CSF 2.0; ISO 27001:2022 | M52: KMS-050 · KMS-KG-05 | P52: WA03 | R52: Wallet Security | S52: 1.01 Key Material Generation | U52: PR.DS-01 | V52: A.8.24 | X52: None | Z52: HSM/TRNG specification review. | AA52: Open source | AB52: Not started
A53: 52 | B53: UCR-052 | C53: 02 Key & Wallet Management | D53: Distributed generation | E53: Hold every participant in multisig/MPC/DKG generation to the same generation standards. | F53: BSSC KMS v1 | G53: KMS-KG-06 | H53: BSSC KMS v1 — §6 Key Generation | I53: MUST | J53: High | K53: All key holders (Custodian/Exchange, Node operator, Protocol/admin keys) | L53: BSSC KMS; OWASP Web3 Top 15; SEAL; CCSS v9.0; NIST CSF 2.0; ISO 27001:2022 | M53: KMS-051 · KMS-KG-06 | P53: WA03 | R53: Wallet Security | S53: 1.01 Key Material Generation; 1.02 Wallet Creation | U53: PR.DS-01; GV.SC-05 | V53: A.8.24 | X53: None | Z53: Review participant environments. | AA53: Open source | AB53: Not started
A54: 53 | B54: UCR-053 | C54: 02 Key & Wallet Management | D54: Password-based derivation | E54: Use a well-established KDF (Argon2id, scrypt, PBKDF2) for password-derived keys. | F54: BSSC KMS v1 | G54: KMS-KD-01 | H54: BSSC KMS v1 — §6 Key Derivation | I54: MUST | J54: High | K54: All key holders (Custodian/Exchange, Node operator, Protocol/admin keys) | L54: BSSC KMS; OWASP Web3 Top 15; SEAL; CCSS v9.0; NIST CSF 2.0; ISO 27001:2022 | M54: KMS-052 · KMS-KD-01 | P54: WA03 | R54: Wallet Security | S54: 1.01 Key Material Generation | U54: PR.DS-01 | V54: A.8.24 | X54: None | Z54: Config/code review. | AA54: Open source | AB54: Not started
A55: 54 | B55: UCR-054 | C55: 02 Key & Wallet Management | D55: HD wallets | E55: Derive HD child keys per applicable standards (BIP-32/39/44). | F55: BSSC KMS v1 | G55: KMS-KD-02 | H55: BSSC KMS v1 — §6 Key Derivation | I55: MUST | J55: High | K55: All key holders (Custodian/Exchange, Node operator, Protocol/admin keys) | L55: BSSC KMS; OWASP Web3 Top 15; SEAL; CCSS v9.0; NIST CSF 2.0; ISO 27001:2022 | M55: KMS-053 · KMS-KD-02 | P55: WA03 | R55: Wallet Security | S55: 1.02 Wallet Creation | U55: PR.DS-01 | V55: A.8.24 | X55: Related | Y55: UCR-103 [Related] (CCSS v9.0 1.02 Wallet Creation) | Z55: Derivation path test vectors. | AA55: Open source | AB55: Not started
A56: 55 | B56: UCR-055 | C56: 02 Key & Wallet Management | D56: HD wallets | E56: Use hardened derivation where appropriate. | F56: BSSC KMS v1 | G56: KMS-KD-03 | H56: BSSC KMS v1 — §6 Key Derivation | I56: SHOULD | J56: Medium | K56: All key holders (Custodian/Exchange, Node operator, Protocol/admin keys) | L56: BSSC KMS; OWASP Web3 Top 15; SEAL; CCSS v9.0; NIST CSF 2.0; ISO 27001:2022 | M56: KMS-054 · KMS-KD-03 | P56: WA03 | R56: Wallet Security | S56: 1.02 Wallet Creation | U56: PR.DS-01 | V56: A.8.24 | X56: None | Z56: Path review. | AA56: Open source | AB56: Not started
A57: 56 | B57: UCR-056 | C57: 02 Key & Wallet Management | D57: Salting | E57: Use unique salts where source secret entropy is below derived-key requirements. | F57: BSSC KMS v1 | G57: KMS-KD-04 | H57: BSSC KMS v1 — §6 Key Derivation | I57: MUST | J57: High | K57: All key holders (Custodian/Exchange, Node operator, Protocol/admin keys) | L57: BSSC KMS; OWASP Web3 Top 15; SEAL; NIST CSF 2.0; ISO 27001:2022 | M57: KMS-055 · KMS-KD-04 | P57: WA03 | R57: Wallet Security | U57: PR.DS-01 | V57: A.8.24 | X57: None | Z57: Code review. | AA57: Open source | AB57: Not started
A58: 57 | B58: UCR-057 | C58: 02 Key & Wallet Management | D58: Entropy | E58: Ensure passwords/shared secrets carry at least the derived key's entropy. | F58: BSSC KMS v1 | G58: KMS-KD-05 | H58: BSSC KMS v1 — §6 Key Derivation | I58: SHOULD | J58: Medium | K58: All key holders (Custodian/Exchange, Node operator, Protocol/admin keys) | L58: BSSC KMS; OWASP Web3 Top 15; SEAL; NIST CSF 2.0; ISO 27001:2022 | M58: KMS-056 · KMS-KD-05 | P58: WA03 | R58: Wallet Security | U58: PR.DS-01 | V58: A.8.24; A.5.17 | X58: None | Z58: Policy review. | AA58: Open source | AB58: Not started
A59: 58 | B59: UCR-058 | C59: 02 Key & Wallet Management | D59: Entropy | E59: Mandate full entropy for any secret that can cause a blockchain state change. | F59: BSSC KMS v1 | G59: KMS-KD-06 | H59: BSSC KMS v1 — §6 Key Derivation | I59: MUST | J59: Critical | K59: All key holders (Custodian/Exchange, Node operator, Protocol/admin keys) | L59: BSSC KMS; OWASP Web3 Top 15; SEAL; CCSS v9.0; NIST CSF 2.0; ISO 27001:2022 | M59: KMS-057 · KMS-KD-06 | P59: WA03 | R59: Wallet Security | S59: 1.01 Key Material Generation | U59: PR.DS-01 | V59: A.8.24 | X59: None | Z59: Policy and generation review. | AA59: Open source | AB59: Not started
A60: 59 | B60: UCR-059 | C60: 02 Key & Wallet Management | D60: Domain separation | E60: Use context labels when deriving multiple keys from one secret. | F60: BSSC KMS v1 | G60: KMS-KD-07 | H60: BSSC KMS v1 — §6 Key Derivation | I60: SHOULD | J60: Medium | K60: All key holders (Custodian/Exchange, Node operator, Protocol/admin keys) | L60: BSSC KMS; OWASP Web3 Top 15; SEAL; NIST CSF 2.0; ISO 27001:2022 | M60: KMS-058 · KMS-KD-07 | P60: WA03 | R60: Wallet Security | U60: PR.DS-01 | V60: A.8.24 | X60: None | Z60: Code review. | AA60: Open source | AB60: Not started
A61: 60 | B61: UCR-060 | C61: 02 Key & Wallet Management | D61: KDF selection | E61: Follow NIST SP 800-108 for KDF selection and use. | F61: BSSC KMS v1 | G61: KMS-KD-08 | H61: BSSC KMS v1 — §6 Key Derivation | I61: SHOULD | J61: Low | K61: All key holders (Custodian/Exchange, Node operator, Protocol/admin keys) | L61: BSSC KMS; OWASP Web3 Top 15; SEAL; NIST CSF 2.0; ISO 27001:2022 | M61: KMS-059 · KMS-KD-08 | P61: WA03 | R61: Wallet Security | U61: PR.DS-01 | V61: A.8.24 | X61: None | Z61: Design review. | AA61: Open source | AB61: Not started
A62: 61 | B62: UCR-061 | C62: 02 Key & Wallet Management | D62: Encryption at rest | E62: Store all keys encrypted at rest. | F62: BSSC KMS v1 | G62: KMS-KS-01 | H62: BSSC KMS v1 — §6 Key Storage | I62: MUST | J62: Critical | K62: All key holders (Custodian/Exchange, Node operator, Protocol/admin keys) | L62: BSSC KMS; OWASP Web3 Top 15; SEAL; CCSS v9.0; CIS v8.1; NIST CSF 2.0; ISO 27001:2022 | M62: KMS-060 · KMS-KS-01 | P62: WA03 | R62: Wallet Security | S62: 1.03 Key Storage | T62: CIS 3.11 | U62: PR.DS-01 | V62: A.8.24 | X62: None | Z62: Storage inspection. | AA62: Open source | AB62: Not started
A63: 62 | B63: UCR-062 | C63: 02 Key & Wallet Management | D63: Secure hardware | E63: Store keys in FIPS 140 L3 / CC EAL4+ HSMs or secure elements, or strongly access-controlled encrypted databases. | F63: BSSC KMS v1 | G63: KMS-KS-02 | H63: BSSC KMS v1 — §6 Key Storage | I63: SHOULD | J63: Critical | K63: All key holders (Custodian/Exchange, Node operator, Protocol/admin keys) | L63: BSSC KMS; OWASP Web3 Top 15; SEAL; CCSS v9.0; CIS v8.1; NIST CSF 2.0; ISO 27001:2022 | M63: KMS-061 · KMS-KS-02 | P63: WA03 | R63: Wallet Security | S63: 1.03 Key Storage | T63: CIS 3.11 | U63: PR.DS-01 | V63: A.8.24 | X63: None | Z63: Certificate review. | AA63: Open source | AB63: Not started
A64: 63 | B64: UCR-063 | C64: 02 Key & Wallet Management | D64: Secure hardware | E64: Use HSMs for secure storage where suitable. | F64: BSSC KMS v1 | G64: KMS-KS-04 | H64: BSSC KMS v1 — §6 Key Storage | I64: MAY | J64: Low | K64: All key holders (Custodian/Exchange, Node operator, Protocol/admin keys) | L64: BSSC KMS; OWASP Web3 Top 15; SEAL; CCSS v9.0; CIS v8.1; NIST CSF 2.0; ISO 27001:2022 | M64: KMS-063 · KMS-KS-04 | P64: WA03 | R64: Wallet Security | S64: 1.03 Key Storage | T64: CIS 3.11 | U64: PR.DS-01 | V64: A.8.24 | X64: None | Z64: Architecture review. | AA64: Open source | AB64: Not started
A65: 64 | B65: UCR-064 | C65: 02 Key & Wallet Management | D65: Secure hardware | E65: Use HSMs certified FIPS 140 Level 3 or better. | F65: BSSC KMS v1 | G65: KMS-KS-05 | H65: BSSC KMS v1 — §6 Key Storage | I65: SHOULD | J65: High | K65: All key holders (Custodian/Exchange, Node operator, Protocol/admin keys) | L65: BSSC KMS; OWASP Web3 Top 15; SEAL; CCSS v9.0; CIS v8.1; NIST CSF 2.0; ISO 27001:2022 | M65: KMS-064 · KMS-KS-05 | P65: WA03 | R65: Wallet Security | S65: 1.03 Key Storage | T65: CIS 3.11 | U65: PR.DS-01 | V65: A.8.24 | X65: None | Z65: CMVP certificate check. | AA65: Open source | AB65: Not started
A66: 65 | B66: UCR-065 | C66: 02 Key & Wallet Management | D66: Isolation | E66: Disconnect HSMs from other systems when not in active use (cold storage). | F66: BSSC KMS v1 | G66: KMS-KS-07 | H66: BSSC KMS v1 — §6 Key Storage | I66: SHOULD | J66: High | K66: Custodian/Exchange; Node operator | L66: BSSC KMS; OWASP Web3 Top 15; SEAL; CCSS v9.0; CIS v8.1; NIST CSF 2.0; ISO 27001:2022 | M66: KMS-066 · KMS-KS-07 | P66: WA03 | R66: Wallet Security | S66: 1.03 Key Storage | T66: CIS 12.2 | U66: PR.IR-01 | V66: A.8.22 | X66: Related | Y66: UCR-102 [Related] (SEAL Frameworks Treasury Operations) | Z66: Network isolation review. | AA66: Open source | AB66: Not started
A67: 66 | B67: UCR-066 | C67: 02 Key & Wallet Management | D67: Transport encryption | E67: Encrypt key material for the entire duration of online distribution (key wrapping). | F67: BSSC KMS v1 | G67: KMS-KDI-01 | H67: BSSC KMS v1 — §6 Key Distribution | I67: MUST | J67: Critical | K67: All key holders (Custodian/Exchange, Node operator, Protocol/admin keys) | L67: BSSC KMS; OWASP Web3 Top 15; SEAL; CCSS v9.0; CIS v8.1; NIST CSF 2.0; ISO 27001:2022 | M67: KMS-067 · KMS-KDI-01 | P67: WA03 | R67: Wallet Security | S67: 1.03 Key Storage | T67: CIS 3.10 | U67: PR.DS-02 | V67: A.8.24 | X67: None | Z67: Transport protocol review. | AA67: Open source | AB67: Not started
A68: 67 | B68: UCR-067 | C68: 02 Key & Wallet Management | D68: Out-of-band secrets | E68: Send decryption passwords over a channel separate from the key transport. | F68: BSSC KMS v1 | G68: KMS-KDI-02 | H68: BSSC KMS v1 — §6 Key Distribution | I68: MUST | J68: High | K68: All key holders (Custodian/Exchange, Node operator, Protocol/admin keys) | L68: BSSC KMS; OWASP Web3 Top 15; SEAL; CIS v8.1; NIST CSF 2.0; ISO 27001:2022 | M68: KMS-068 · KMS-KDI-02 | P68: WA03 | R68: Wallet Security | T68: CIS 3.10 | U68: PR.DS-02 | V68: A.5.14 | X68: None | Z68: Procedure review. | AA68: Open source | AB68: Not started
A69: 68 | B69: UCR-068 | C69: 02 Key & Wallet Management | D69: Integrity | E69: Authenticate keys at destination (signatures/MACs, fingerprints). | F69: BSSC KMS v1 | G69: KMS-KDI-03 | H69: BSSC KMS v1 — §6 Key Distribution | I69: MUST | J69: High | K69: All key holders (Custodian/Exchange, Node operator, Protocol/admin keys) | L69: BSSC KMS; OWASP Web3 Top 15; SEAL; CIS v8.1; NIST CSF 2.0; ISO 27001:2022 | M69: KMS-069 · KMS-KDI-03 | P69: WA03 | R69: Wallet Security | T69: CIS 3.10 | U69: PR.DS-02 | V69: A.8.24 | X69: None | Z69: Test import verification. | AA69: Open source | AB69: Not started
A70: 69 | B70: UCR-069 | C70: 02 Key & Wallet Management | D70: Physical transport | E70: Use tamper-evident, access-controlled physical transport (sealed bags, dual courier). | F70: BSSC KMS v1 | G70: KMS-KDI-04 | H70: BSSC KMS v1 — §6 Key Distribution | I70: MUST | J70: High | K70: All key holders (Custodian/Exchange, Node operator, Protocol/admin keys) | L70: BSSC KMS; OWASP Web3 Top 15; SEAL; CCSS v9.0; NIST CSF 2.0; ISO 27001:2022 | M70: KMS-070 · KMS-KDI-04 | P70: WA03 | R70: Wallet Security | S70: 1.03 Key Storage | U70: PR.DS-02 | V70: A.7.10 | X70: None | Z70: Chain-of-custody records. | AA70: Open source | AB70: Not started
A71: 70 | B71: UCR-070 | C71: 02 Key & Wallet Management | D71: KEK access | E71: Limit Key Encryption Key access to the minimum individuals/systems. | F71: BSSC KMS v1 | G71: KMS-KDI-05 | H71: BSSC KMS v1 — §6 Key Distribution | I71: SHOULD | J71: High | K71: All key holders (Custodian/Exchange, Node operator, Protocol/admin keys) | L71: BSSC KMS; OWASP Web3 Top 15; SEAL; CCSS v9.0; CIS v8.1; NIST CSF 2.0; ISO 27001:2022 | M71: KMS-071 · KMS-KDI-05 | P71: WA03 | R71: Wallet Security | S71: 1.04 Key Material Access | T71: CIS 6.8 | U71: PR.AA-05 | V71: A.8.2 | X71: None | Z71: Access list review. | AA71: Open source | AB71: Not started
A72: 71 | B72: UCR-071 | C72: 02 Key & Wallet Management | D72: DEK distribution | E72: Distribute Data Encryption Keys only to systems needing immediate access. | F72: BSSC KMS v1 | G72: KMS-KDI-06 | H72: BSSC KMS v1 — §6 Key Distribution | I72: SHOULD | J72: Medium | K72: All key holders (Custodian/Exchange, Node operator, Protocol/admin keys) | L72: BSSC KMS; OWASP Web3 Top 15; SEAL; CIS v8.1; NIST CSF 2.0; ISO 27001:2022 | M72: KMS-072 · KMS-KDI-06 | P72: WA03 | R72: Wallet Security | T72: CIS 6.8 | U72: PR.AA-05 | V72: A.8.24 | X72: None | Z72: Distribution inventory. | AA72: Open source | AB72: Not started
A73: 72 | B73: UCR-072 | C73: 02 Key & Wallet Management | D73: Out-of-band distribution | E73: Distribute keys/shares out-of-band from encrypted data channels. | F73: BSSC KMS v1 | G73: KMS-KDI-07 | H73: BSSC KMS v1 — §6 Key Distribution | I73: SHOULD | J73: Medium | K73: All key holders (Custodian/Exchange, Node operator, Protocol/admin keys) | L73: BSSC KMS; OWASP Web3 Top 15; SEAL; CIS v8.1; NIST CSF 2.0; ISO 27001:2022 | M73: KMS-073 · KMS-KDI-07 | P73: WA03 | R73: Wallet Security | T73: CIS 3.10 | U73: PR.DS-02 | V73: A.5.14 | X73: None | Z73: Procedure review. | AA73: Open source | AB73: Not started
A74: 73 | B74: UCR-073 | C74: 02 Key & Wallet Management | D74: Authorisation | E74: Restrict authority to request signatures/use keys to explicitly authorised individuals or systems. | F74: BSSC KMS v1 | G74: KMS-KU-01 | H74: BSSC KMS v1 — §6 Key Usage | I74: MUST | J74: Critical | K74: All key holders (Custodian/Exchange, Node operator, Protocol/admin keys) | L74: BSSC KMS; OWASP Web3 Top 15; SEAL; CCSS v9.0; CIS v8.1; NIST CSF 2.0; ISO 27001:2022 | M74: KMS-074 · KMS-KU-01 | P74: WA01 | R74: Treasury Operations | S74: 1.05 Key Usage | T74: CIS 6.8 | U74: PR.AA-05 | V74: A.5.15 | X74: None | Z74: Signing policy review. | AA74: Open source | AB74: Not started
A75: 74 | B75: UCR-074 | C75: 02 Key & Wallet Management | D75: Authorisation | E75: Define, review and adjust the authorisation set regularly. | F75: BSSC KMS v1 | G75: KMS-KU-02 | H75: BSSC KMS v1 — §6 Key Usage | I75: SHOULD | J75: High | K75: All key holders (Custodian/Exchange, Node operator, Protocol/admin keys) | L75: BSSC KMS; OWASP Web3 Top 15; SEAL; CCSS v9.0; CIS v8.1; NIST CSF 2.0; ISO 27001:2022 | M75: KMS-075 · KMS-KU-02 | P75: WA01 | R75: Treasury Operations | S75: 1.04 Key Material Access | T75: CIS 6.8 | U75: PR.AA-05 | V75: A.5.18 | X75: None | Z75: Review records. | AA75: Open source | AB75: Not started
A76: 75 | B76: UCR-075 | C76: 02 Key & Wallet Management | D76: Quorum controls | E76: Require proportionate controls (quorum, approval groups, two-person ceremonies) for critical operations. | F76: BSSC KMS v1 | G76: KMS-KU-05 | H76: BSSC KMS v1 — §6 Key Usage | I76: MUST | J76: Critical | K76: All key holders (Custodian/Exchange, Node operator, Protocol/admin keys) | L76: BSSC KMS; OWASP Web3 Top 15; SEAL; CCSS v9.0; CIS v8.1; NIST CSF 2.0; ISO 27001:2022 | M76: KMS-078 · KMS-KU-05 | P76: WA01 | R76: Multisig for Protocols; Treasury Operations | S76: 1.05 Key Usage | T76: CIS 6.8 | U76: PR.AA-05 | V76: A.5.3 | X76: Related | Y76: UCR-098 [Related] (SEAL Frameworks Treasury Operations) | Z76: Policy-engine configuration review. | AA76: Open source | AB76: Not started
A77: 76 | B77: UCR-076 | C77: 02 Key & Wallet Management | D77: Owner approval | E77: For keys managed on behalf of owners, require explicit owner involvement/approval for use. | F77: BSSC KMS v1 | G77: KMS-KU-06 | H77: BSSC KMS v1 — §6 Key Usage | I77: SHOULD | J77: High | K77: Custodian/Exchange; Node operator | L77: BSSC KMS; OWASP Web3 Top 15; SEAL; CCSS v9.0; CIS v8.1; NIST CSF 2.0; ISO 27001:2022; MiCA | M77: KMS-079 · KMS-KU-06 | P77: WA03 | R77: Wallet Security | S77: 1.05 Key Usage | T77: CIS 6.8 | U77: PR.AA-05 | V77: A.5.15 | W77: MiCA Art. 75 | X77: None | Z77: Workflow review. | AA77: Open source | AB77: Not started
A78: 77 | B78: UCR-077 | C78: 02 Key & Wallet Management | D78: Plaintext exposure | E78: Make plaintext key access time-limited and access-controlled. | F78: BSSC KMS v1 | G78: KMS-KU-07 | H78: BSSC KMS v1 — §6 Key Usage | I78: MUST | J78: Critical | K78: All key holders (Custodian/Exchange, Node operator, Protocol/admin keys) | L78: BSSC KMS; OWASP Web3 Top 15; SEAL; CCSS v9.0; NIST CSF 2.0; ISO 27001:2022 | M78: KMS-080 · KMS-KU-07 | P78: WA03 | R78: Wallet Security | S78: 1.05 Key Usage | U78: PR.DS-10 | V78: A.8.24 | X78: None | Z78: Review in-memory handling design. | AA78: Open source | AB78: Not started
A79: 78 | B79: UCR-078 | C79: 02 Key & Wallet Management | D79: Plaintext exposure | E79: Wipe plaintext copies as soon as practical after use (zeroise memory). | F79: BSSC KMS v1 | G79: KMS-KU-08 | H79: BSSC KMS v1 — §6 Key Usage | I79: MUST | J79: Critical | K79: All key holders (Custodian/Exchange, Node operator, Protocol/admin keys) | L79: BSSC KMS; OWASP Web3 Top 15; SEAL; CCSS v9.0; NIST CSF 2.0; ISO 27001:2022 | M79: KMS-081 · KMS-KU-08 | P79: WA03 | R79: Wallet Security | S79: 2.02 Data Sanitization | U79: PR.DS-10 | V79: A.8.24; A.8.10 | X79: None | Z79: Code review for zeroisation. | AA79: Open source | AB79: Not started
A80: 79 | B80: UCR-079 | C80: 02 Key & Wallet Management | D80: Share rotation | E80: If key shards/shares are rotated, rotate on defined triggers or schedule. | F80: BSSC KMS v1 | G80: KMS-KU-09 | H80: BSSC KMS v1 — §6 Key Usage | I80: MUST | J80: High | K80: All key holders (Custodian/Exchange, Node operator, Protocol/admin keys) | L80: BSSC KMS; OWASP Web3 Top 15; SEAL; CCSS v9.0; NIST CSF 2.0; ISO 27001:2022 | M80: KMS-082 · KMS-KU-09 | P80: WA03 | R80: Wallet Security | S80: 1.05 Key Usage | U80: PR.DS-01 | V80: A.8.24 | X80: None | Z80: Rotation log review. | AA80: Open source | AB80: Not started
A81: 80 | B81: UCR-080 | C81: 02 Key & Wallet Management | D81: Share rotation | E81: Automate rotation where possible. | F81: BSSC KMS v1 | G81: KMS-KU-10 | H81: BSSC KMS v1 — §6 Key Usage | I81: MUST | J81: Medium | K81: All key holders (Custodian/Exchange, Node operator, Protocol/admin keys) | L81: BSSC KMS; OWASP Web3 Top 15; SEAL; NIST CSF 2.0; ISO 27001:2022 | M81: KMS-083 · KMS-KU-10 | P81: WA03 | R81: Wallet Security | U81: PR.DS-01 | V81: A.8.24 | X81: None | Z81: Automation review. | AA81: Open source | AB81: Not started
A82: 81 | B82: UCR-081 | C82: 02 Key & Wallet Management | D82: Share rotation | E82: Validate post-rotation that private key access is preserved (test signing). | F82: BSSC KMS v1 | G82: KMS-KU-11 | H82: BSSC KMS v1 — §6 Key Usage | I82: MUST | J82: Critical | K82: All key holders (Custodian/Exchange, Node operator, Protocol/admin keys) | L82: BSSC KMS; OWASP Web3 Top 15; SEAL; NIST CSF 2.0; ISO 27001:2022 | M82: KMS-084 · KMS-KU-11 | P82: WA03 | R82: Wallet Security | U82: PR.DS-11 | V82: A.8.24 | X82: None | Z82: Rotation validation evidence. | AA82: Open source | AB82: Not started
A83: 82 | B83: UCR-082 | C83: 02 Key & Wallet Management | D83: Purpose limitation | E83: Use keys strictly for their intended purpose. | F83: BSSC KMS v1 | G83: KMS-KU-12 | H83: BSSC KMS v1 — §6 Key Usage | I83: MUST | J83: High | K83: All key holders (Custodian/Exchange, Node operator, Protocol/admin keys) | L83: BSSC KMS; OWASP Web3 Top 15; SEAL; CCSS v9.0; CIS v8.1; NIST CSF 2.0; ISO 27001:2022 | M83: KMS-085 · KMS-KU-12 | P83: WA03 | R83: Wallet Security | S83: 1.05 Key Usage | T83: CIS 6.8 | U83: PR.DS-01 | V83: A.8.24 | X83: None | Z83: Key inventory with purpose tags. | AA83: Open source | AB83: Not started
A84: 83 | B84: UCR-083 | C84: 02 Key & Wallet Management | D84: Purpose limitation | E84: Enforce Key Usage Policies technically (policy engine). | F84: BSSC KMS v1 | G84: KMS-KU-13 | H84: BSSC KMS v1 — §6 Key Usage | I84: SHOULD | J84: High | K84: All key holders (Custodian/Exchange, Node operator, Protocol/admin keys) | L84: BSSC KMS; OWASP Web3 Top 15; SEAL; CCSS v9.0; CIS v8.1; NIST CSF 2.0; ISO 27001:2022 | M84: KMS-086 · KMS-KU-13 | P84: WA03 | R84: Wallet Security | S84: 1.05 Key Usage | T84: CIS 6.8 | U84: PR.AA-05 | V84: A.8.24 | X84: None | Z84: Policy-engine test. | AA84: Open source | AB84: Not started
A85: 84 | B85: UCR-084 | C85: 02 Key & Wallet Management | D85: Purpose limitation | E85: Prefer single-purpose keys. | F85: BSSC KMS v1 | G85: KMS-KU-14 | H85: BSSC KMS v1 — §6 Key Usage | I85: SHOULD | J85: Medium | K85: All key holders (Custodian/Exchange, Node operator, Protocol/admin keys) | L85: BSSC KMS; OWASP Web3 Top 15; SEAL; CIS v8.1; NIST CSF 2.0; ISO 27001:2022 | M85: KMS-087 · KMS-KU-14 | P85: WA03 | R85: Wallet Security | T85: CIS 6.8 | U85: PR.DS-01 | V85: A.8.24 | X85: None | Z85: Key inventory review. | AA85: Open source | AB85: Not started
A86: 85 | B86: UCR-085 | C86: 02 Key & Wallet Management | D86: Purpose limitation | E86: For multi-purpose keys, enforce strong access controls and usage policies restricted to intended environments. | F86: BSSC KMS v1 | G86: KMS-KU-15 | H86: BSSC KMS v1 — §6 Key Usage | I86: MUST | J86: High | K86: All key holders (Custodian/Exchange, Node operator, Protocol/admin keys) | L86: BSSC KMS; OWASP Web3 Top 15; SEAL; CCSS v9.0; CIS v8.1; NIST CSF 2.0; ISO 27001:2022 | M86: KMS-088 · KMS-KU-15 | P86: WA03 | R86: Wallet Security | S86: 1.05 Key Usage | T86: CIS 6.8 | U86: PR.AA-05 | V86: A.8.24 | X86: None | Z86: Policy review. | AA86: Open source | AB86: Not started
A87: 86 | B87: UCR-086 | C87: 02 Key & Wallet Management | D87: Retirement | E87: Remove all value and privileges from keys before retirement. | F87: BSSC KMS v1 | G87: KMS-KR-01 | H87: BSSC KMS v1 — §6 Key Retirement | I87: SHOULD | J87: High | K87: All key holders (Custodian/Exchange, Node operator, Protocol/admin keys) | L87: BSSC KMS; SEAL; CIS v8.1; NIST CSF 2.0; ISO 27001:2022 | M87: KMS-089 · KMS-KR-01 | R87: Wallet Security | T87: CIS 6.2 | U87: PR.AA-05 | V87: A.8.24 | X87: None | Z87: Verify zero balance/roles on-chain. | AA87: Open source | AB87: Not started
A88: 87 | B88: UCR-087 | C88: 02 Key & Wallet Management | D88: Retirement | E88: Keep retired keys offline when not regularly needed. | F88: BSSC KMS v1 | G88: KMS-KR-02 | H88: BSSC KMS v1 — §6 Key Retirement | I88: SHOULD | J88: Medium | K88: All key holders (Custodian/Exchange, Node operator, Protocol/admin keys) | L88: BSSC KMS; SEAL; CCSS v9.0; CIS v8.1; NIST CSF 2.0; ISO 27001:2022 | M88: KMS-090 · KMS-KR-02 | R88: Wallet Security | S88: 1.03 Key Storage | T88: CIS 3.11 | U88: PR.DS-01 | V88: A.8.24 | X88: None | Z88: Storage review. | AA88: Open source | AB88: Not started
A89: 88 | B89: UCR-088 | C89: 02 Key & Wallet Management | D89: Retirement | E89: Securely destroy redundant non-backup copies (zeroisation or hardware destruction). | F89: BSSC KMS v1 | G89: KMS-KR-03 | H89: BSSC KMS v1 — §6 Key Retirement | I89: MUST | J89: High | K89: All key holders (Custodian/Exchange, Node operator, Protocol/admin keys) | L89: BSSC KMS; SEAL; CCSS v9.0; CIS v8.1; NIST CSF 2.0; ISO 27001:2022 | M89: KMS-091 · KMS-KR-03 | R89: Wallet Security | S89: 2.02 Data Sanitization | T89: CIS 3.5 | U89: PR.DS-01 | V89: A.8.10; A.7.14 | X89: None | Z89: Destruction certificates. | AA89: Open source | AB89: Not started
A90: 89 | B90: UCR-089 | C90: 02 Key & Wallet Management | D90: Retirement | E90: Keep retired keys under full storage controls (access control, encryption at rest). | F90: BSSC KMS v1 | G90: KMS-KR-04 | H90: BSSC KMS v1 — §6 Key Retirement | I90: SHOULD | J90: Medium | K90: All key holders (Custodian/Exchange, Node operator, Protocol/admin keys) | L90: BSSC KMS; SEAL; CCSS v9.0; CIS v8.1; NIST CSF 2.0; ISO 27001:2022 | M90: KMS-092 · KMS-KR-04 | R90: Wallet Security | S90: 1.03 Key Storage | T90: CIS 3.11 | U90: PR.DS-01 | V90: A.8.24 | X90: None | Z90: Storage review. | AA90: Open source | AB90: Not started
A91: 90 | B91: UCR-090 | C91: 02 Key & Wallet Management | D91: Destruction | E91: Do not destroy keys used for blockchain state changes (addresses may later receive funds); archive instead. | F91: BSSC KMS v1 | G91: KMS-KX-01 | H91: BSSC KMS v1 — §6 Key Destruction | I91: SHOULD NOT | J91: High | K91: All key holders (Custodian/Exchange, Node operator, Protocol/admin keys) | L91: BSSC KMS; SEAL; CCSS v9.0; CIS v8.1; NIST CSF 2.0; ISO 27001:2022 | M91: KMS-093 · KMS-KX-01 | R91: Wallet Security | S91: 2.02 Data Sanitization | T91: CIS 3.5 | U91: PR.DS-11 | V91: A.8.24 | X91: None | Z91: Destruction approvals reference this check. | AA91: Open source | AB91: Not started
A92: 91 | B92: UCR-091 | C92: 02 Key & Wallet Management | D92: Destruction | E92: When destroying an owner's key as agent, provide the key to the owner first. | F92: BSSC KMS v1 | G92: KMS-KX-02 | H92: BSSC KMS v1 — §6 Key Destruction | I92: SHOULD | J92: Medium | K92: Custodian/Exchange; Node operator | L92: BSSC KMS; SEAL; CCSS v9.0; CIS v8.1; NIST CSF 2.0; ISO 27001:2022; MiCA | M92: KMS-094 · KMS-KX-02 | R92: Wallet Security | S92: 2.02 Data Sanitization | T92: CIS 3.5 | U92: PR.DS-11 | V92: A.8.24 | W92: MiCA Art. 75 | X92: None | Z92: Handover records. | AA92: Open source | AB92: Not started
A93: 92 | B93: UCR-092 | C93: 02 Key & Wallet Management | D93: Destruction | E93: Document destruction processes and make them auditable. | F93: BSSC KMS v1 | G93: KMS-KX-03 | H93: BSSC KMS v1 — §6 Key Destruction | I93: MUST | J93: High | K93: All key holders (Custodian/Exchange, Node operator, Protocol/admin keys) | L93: BSSC KMS; SEAL; CCSS v9.0; CIS v8.1; NIST CSF 2.0; ISO 27001:2022 | M93: KMS-095 · KMS-KX-03 | R93: Wallet Security | S93: 2.02 Data Sanitization | T93: CIS 3.5 | U93: PR.PS-04 | V93: A.8.10 | X93: None | Z93: Destruction logs/witness records. | AA93: Open source | AB93: Not started
A94: 93 | B94: UCR-093 | C94: 02 Key & Wallet Management | D94: Destruction | E94: Use irreversible destruction (zeroisation, physical hardware destruction). | F94: BSSC KMS v1 | G94: KMS-KX-04 | H94: BSSC KMS v1 — §6 Key Destruction | I94: MUST | J94: High | K94: All key holders (Custodian/Exchange, Node operator, Protocol/admin keys) | L94: BSSC KMS; SEAL; CCSS v9.0; CIS v8.1; NIST CSF 2.0; ISO 27001:2022 | M94: KMS-096 · KMS-KX-04 | R94: Wallet Security | S94: 2.02 Data Sanitization | T94: CIS 3.5 | U94: PR.DS-01 | V94: A.8.10; A.7.14 | X94: Related | Y94: UCR-348 [Related] (CCSS v9.0 2.02 Data Sanitization) | Z94: Destruction certificates. | AA94: Open source | AB94: Not started
A95: 94 | B95: UCR-094 | C95: 02 Key & Wallet Management | D95: Infrastructure security | E95: Implement the BSSC Key Management Standard or equivalent. | F95: BSSC GSP v2 | G95: req-protect-keys | H95: BSSC GSP v2 — 3. Protect | I95: SHOULD | J95: Critical | K95: All blockchain participants | L95: BSSC GSP; OWASP Web3 Top 15; SEAL; CCSS v9.0; CIS v8.1; NIST CSF 2.0; ISO 27001:2022 | M95: GSP-029 · req-protect-keys | P95: WA03 | R95: Wallet Security | S95: 1.01–1.06 (key lifecycle); 2.04 Audit Logs | T95: CIS 3.11 | U95: PR.DS-01 | V95: A.8.24 | X95: Duplicate | Y95: UCR-027 [Duplicate] (BSSC NOS v2 req-manage-key-security) | Z95: KMS conformance matrix. | AA95: Open source | AB95: Not started
A96: 95 | B96: UCR-095 | C96: 02 Key & Wallet Management | D96: Deposit finality & reorg handling | E96: Credit deposits only after chain-specific finality/confirmation depth; monitor for reorgs and 51% attacks and raise thresholds or halt deposits for affected chains. | F96: OWASP SCSVS | G96: SCSVS-DEFI-1 (S10.1.B1) | H96: OWASP SCSVS — SCSVS-DEFI-1 (S10.1.B1) | I96: Recommended (supplementary) | J96: Critical | K96: Custodian/Exchange | L96: OWASP SCSVS; OWASP Web3 Top 15; SEAL; NIST CSF 2.0; ISO 27001:2022 | N96: SCSVS-DEFI | P96: WA07 | R96: Monitoring; Treasury Operations | U96: DE.CM-09 | V96: A.8.16 | X96: Related | Y96: UCR-223 [Related] (BSSC NOS v2 req-follow-protocol-consensus) | Z96: Confirmation policy per chain; reorg alert test. | AA96: Open source | AB96: Not started
A97: 96 | B97: UCR-096 | C97: 02 Key & Wallet Management | D97: Multisig signer security | E97: Require multisig signers to use dedicated hardware wallets on dedicated devices, independently decode and verify calldata and safe-tx hashes before signing, and never sign blind. | F97: SEAL Frameworks | G97: Multisig for Protocols | H97: SEAL Frameworks — Multisig for Protocols | I97: Recommended (supplementary) | J97: Critical | K97: Protocol/dApp/token developer; Custodian/Exchange | L97: OWASP SCSVS; OWASP SC Top 10:2026; OWASP Web3 Top 15; SEAL; CCSS v9.0; CIS v8.1; NIST CSF 2.0; ISO 27001:2022 | N97: SCSVS-AUTH | O97: SC01 | P97: WA01; WA06 | R97: Multisig for Protocols; Wallet Security | S97: 1.05 Key Usage | T97: CIS 6.5 | U97: PR.AA-05 | V97: A.5.3 | X97: Related | Y97: UCR-381 [Related] (BSSC SCS v1 req-decentralize-privileged-roles) | Z97: Signer checklist; observe a signing ceremony. | AA97: Open source | AB97: Not started
A98: 97 | B98: UCR-097 | C98: 02 Key & Wallet Management | D98: Multisig configuration | E98: Set thresholds proportional to value at risk (no 1-of-N), use geographically and organisationally independent signers, maintain signer rotation/offboarding, and alert on owner/threshold changes. | F98: SEAL Frameworks | G98: Multisig for Protocols | H98: SEAL Frameworks — Multisig for Protocols | I98: Recommended (supplementary) | J98: Critical | K98: Protocol/dApp/token developer; Custodian/Exchange | L98: OWASP SCSVS; OWASP SC Top 10:2026; OWASP Web3 Top 15; SEAL; CCSS v9.0; CIS v8.1; NIST CSF 2.0; ISO 27001:2022 | N98: SCSVS-AUTH | O98: SC01 | P98: WA01; WA12 | R98: Multisig for Protocols | S98: 1.02 Wallet Creation | T98: CIS 6.2 | U98: PR.AA-05 | V98: A.5.3 | X98: Related | Y98: UCR-183 [Related] (BSSC TIS v1 Document Multisig) | Z98: On-chain threshold check; signer register. | AA98: Open source | AB98: Not started
A99: 98 | B99: UCR-098 | C99: 02 Key & Wallet Management | D99: Treasury transfer controls | E99: Enforce destination allowlists, per-transfer and velocity limits, out-of-band address verification and test transactions for large transfers. | F99: SEAL Frameworks | G99: Treasury Operations | H99: SEAL Frameworks — Treasury Operations | I99: Recommended (supplementary) | J99: Critical | K99: Custodian/Exchange; Protocol treasury | L99: OWASP Web3 Top 15; SEAL; CCSS v9.0; CIS v8.1; NIST CSF 2.0; ISO 27001:2022; MiCA | P99: WA01; WA06 | R99: Treasury Operations | S99: 1.05 Key Usage | T99: CIS 6.8 | U99: PR.AA-05 | V99: A.5.15 | W99: MiCA Art. 70 | X99: Related | Y99: UCR-075 [Related] (BSSC KMS v1 KMS-KU-05) | Z99: Policy-engine rules; sample large transfers. | AA99: Open source | AB99: Not started
A100: 99 | B100: UCR-099 | C100: 02 Key & Wallet Management | D100: Approved wallet software | E100: Maintain an approved list of wallet software/extensions and hardware models; verify downloads and firmware; prohibit unapproved browser wallet extensions on privileged devices. | F100: SEAL Frameworks | G100: Wallet Security | H100: SEAL Frameworks — Wallet Security | I100: Recommended (supplementary) | J100: High | K100: All blockchain participants | L100: OWASP Web3 Top 15; SEAL; CCSS v9.0; CIS v8.1; NIST CSF 2.0; ISO 27001:2022 | P100: WA14 | R100: Wallet Security | S100: 1.03 Key Storage | T100: CIS 2.5; CIS 9.4 | U100: PR.PS-02 | V100: A.8.19 | X100: None | Z100: Endpoint software inventory vs allowlist. | AA100: Open source | AB100: Not started
...

Sheet Framework Sources
A1: Framework | B1: Version used | C1: Source | D1: How used in register | E1: Verification note
A2: BSSC Node Operation Standard (NOS) | B2: v2, 2026-05-14 | C2: https://specs.blockchainssc.org/nos/ | D2: Backbone (1 control per requirement) | E2: 53 req- anchors verified against live spec
A3: BSSC Token Integration Standard (TIS) | B3: v1, 2025-05-13 | C3: https://specs.blockchainssc.org/tis/ | D3: Backbone | E3: Headings verified; only 1 req- anchor in source
A4: BSSC Key Management Standard (KMS) | B4: v1, 2025-05-13 | C4: https://specs.blockchainssc.org/kms/ | D4: Backbone | E4: No IDs in source; KMS-xx IDs assigned in document order
A5: BSSC Smart Contract Security Standard (SCS) | B5: v1, 2026-05-14 | C5: https://specs.blockchainssc.org/scs/ | D5: Backbone | E5: 69 req- anchors verified
A6: BSSC General Security & Privacy Guidelines (GSP) | B6: v2, 2026-05-14 | C6: https://specs.blockchainssc.org/gsp/ | D6: Backbone | E6: 56 req- anchors verified
A7: OWASP Smart Contract Top 10 | B7: 2026 edition | C7: https://scs.owasp.org/sctop10 | D7: Mapping + supplementary controls | E7: SC01–SC10 names verified
A8: OWASP Smart Contract Security Verification Standard (SCSVS) | B8: Current (2024 refactor; no version label) | C8: https://scs.owasp.org/SCSVS/ | D8: Mapped at area level (SCSVS-ARCH … SCSVS-COMP) | E8: 11 areas / 35 controls verified. Note: area codes do not always match area titles (e.g., SCSVS-ORACLE = 'Arithmetic and Logic Security')
A9: OWASP Alternate Top 15: Web3 Attack Vectors | B9: 2026 | C9: https://scs.owasp.org/sctop10/Web3-Attack-Vectors-Top15/ | D9: Mapping + supplementary controls | E9: WA01–WA15 names verified
A10: EthTrust Security Levels | B10: Latest published spec (EEA; maintained by W3C EthTrust CG since Apr 2026) | C10: https://github.com/w3c-cg/EthTrust | D10: Mapped by level [S]/[M]/[Q] and named requirements cited by BSSC TIS | E10: Version number not stated on CG pages – confirm before certification use
A11: SEAL Frameworks (Security Alliance) | B11: Living document | C11: https://frameworks.securityalliance.org/ | D11: Mapping + supplementary controls | E11: 20 framework names verified
A12: CryptoCurrency Security Standard (CCSS) | B12: v9.0 (Dec 2024) | C12: https://cryptoconsortium.org/ | D12: Mapping (aspect level) + supplementary | E12: 10 aspects verified; prior BSSC workbook used legacy numbering – corrected here
... A18: FATF Recommendations 15 & 16 / EU TFR 2023/1113 | B18: Current | C18: https://www.fatf-gafi.org/ | D18: Supplementary | E18: Travel Rule
